Workbook
Name Discount: 'Quarter Effect Worksheet'!$A$36:$A$41

Sheet Proforma _Summary
B2: 2017-2022 Proforma
B6: Projected Financial Performance (in US$) | E6: 2017 | F6: 2018 | G6: 2019 | H6: 2020 | I6: 2021 | J6: 2022
C8: Total number of Customers (Registered Users) | E8: 0 | F8: ='Assumptions & Sensitivity'!L13+'Assumptions & Sensitivity'!L30 -> 0 | G8: =SUM('Assumptions & Sensitivity'!P13)+SUM('Assumptions & Sensitivity'!P30) -> 236340 | H8: =SUM('Assumptions & Sensitivity'!T13)+SUM('Assumptions & Sensitivity'!T30) -> 1055661 | I8: =SUM('Assumptions & Sensitivity'!X13)+SUM('Assumptions & Sensitivity'!X30) -> 3536128 | J8: =SUM('Assumptions & Sensitivity'!AB13)+SUM('Assumptions & Sensitivity'!AB30) -> 7943561
C9: Total number of orders assisted | E9: 0 | F9: =SUM('Assumptions & Sensitivity'!I17:L17)+SUM('Assumptions & Sensitivity'!I34:L34) -> 0 | G9: =SUM('Assumptions & Sensitivity'!M17:P17)+SUM('Assumptions & Sensitivity'!M34:P34) -> 223447 | H9: =SUM('Assumptions & Sensitivity'!Q17:T17)+SUM('Assumptions & Sensitivity'!Q34:T34) -> 1066967 | I9: =SUM('Assumptions & Sensitivity'!U17:X17)+SUM('Assumptions & Sensitivity'!U34:X34) -> 3983256 | J9: =SUM('Assumptions & Sensitivity'!Y17:AB17)+SUM('Assumptions & Sensitivity'!Y34:AB34) -> 9870612
C10: Projected GMV generated(in US$) | E10: 0 | F10: =SUM('Assumptions & Sensitivity'!I19:L19)+SUM('Assumptions & Sensitivity'!I36:L36) -> 0 | G10: =SUM('Assumptions & Sensitivity'!M19:P19)+SUM('Assumptions & Sensitivity'!M36:P36) -> 21674359 | H10: =SUM('Assumptions & Sensitivity'!Q19:T19)+SUM('Assumptions & Sensitivity'!Q36:T36) -> 103495799 | I10: =SUM('Assumptions & Sensitivity'!U19:X19)+SUM('Assumptions & Sensitivity'!U36:X36) -> 386375832 | J10: =SUM('Assumptions & Sensitivity'!Y19:AB19)+SUM('Assumptions & Sensitivity'!Y36:AB36) -> 984354507
C12: Net Revenue | E12: 0 | F12: ='P&L'!N3 -> 0 | G12: ='P&L'!S3 -> 1265714.2 | H12: ='P&L'!X3 -> 6043829.4 | I12: ='P&L'!AC3 -> 22563136 | J12: ='P&L'!AH3 -> 57483213
C13: Cost of Goods Sold (Tech Expenses) | E13: =SUM('Assumptions & Sensitivity'!E57:H57) -> 12788.22 | F13: =SUM('Assumptions & Sensitivity'!I57:L57) -> 58722.5 | G13: =SUM('Assumptions & Sensitivity'!M57:P57) -> 235642.1 | H13: =SUM('Assumptions & Sensitivity'!Q57:T57) -> 771210.24 | I13: =SUM('Assumptions & Sensitivity'!U57:X57) -> 2233425.6 | J13: =SUM('Assumptions & Sensitivity'!Y57:AB57) -> 5074707.7 | K13: =J13/$J$12 -> 0.088281561
C14: Gross Margin | E14: =E12-E13 -> -12788.22 | F14: =F12-F13 -> -58722.5 | G14: =G12-G13 -> 1030072.1 | H14: =H12-H13 -> 5272619.2 | I14: =I12-I13 -> 20329710 | J14: =J12-J13 -> 52408505
C16: Operating Expenses
D17: Compensation (ex.Marketing) | E17: =SUM(E18:E19) -> 38000 | F17: =SUM(F18:F19) -> 387000 | G17: =SUM(G18:G19) -> 561825 | H17: =SUM(H18:H19) -> 1373557.5 | I17: =SUM(I18:I19) -> 2355424.9 | J17: =SUM(J18:J19) -> 2494157 | K17: =J17/$J$12 -> 0.043389312
D18: Comp Tech | E18: =SUM('Hiring Plan'!D105:G105) -> 38000 | F18: =SUM('Hiring Plan'!H105:K105) -> 337000 | G18: =SUM('Hiring Plan'!L108:O108) -> 201825 | H18: =SUM('Hiring Plan'!P105:S105) -> 890857.5 | I18: =SUM('Hiring Plan'!T105:W105) -> 1533634 | J18: =SUM('Hiring Plan'!X105:AA105) -> 1533634 | K18: =J18/$J$12 -> 0.026679685
D19: Comp Other | E19: =SUM('Hiring Plan'!D101:G101)+SUM('Hiring Plan'!D129:G129)+SUM('Hiring Plan'!D132:G132)+SUM('Hiring Plan'!D135:G136)+SUM('Hiring Plan'!D141:G141) -> 0 | F19: =SUM('Hiring Plan'!H101:K101)+SUM('Hiring Plan'!H129:K129)+SUM('Hiring Plan'!H132:K132)+SUM('Hiring Plan'!H135:K136)+SUM('Hiring Plan'!H141:K141) -> 50000 | G19: =SUM('Hiring Plan'!L101:O101)+SUM('Hiring Plan'!L129:O129)+SUM('Hiring Plan'!L132:O132)+SUM('Hiring Plan'!L135:O136)+SUM('Hiring Plan'!L141:O141) -> 360000 | H19: =SUM('Hiring Plan'!P101:S101)+SUM('Hiring Plan'!P129:S129)+SUM('Hiring Plan'!P132:S132)+SUM('Hiring Plan'!P135:S136)+SUM('Hiring Plan'!P141:S141) -> 482700 | I19: =SUM('Hiring Plan'!T101:W101)+SUM('Hiring Plan'!T129:W129)+SUM('Hiring Plan'!T132:W132)+SUM('Hiring Plan'!T135:W136)+SUM('Hiring Plan'!T141:W141) -> 821790.88 | J19: =SUM('Hiring Plan'!X101:AA101)+SUM('Hiring Plan'!X129:AA129)+SUM('Hiring Plan'!X132:AA132)+SUM('Hiring Plan'!X135:AA136)+SUM('Hiring Plan'!X141:AA141) -> 960523 | K19: =J19/$J$12 -> 0.016709626
D20: Outsourcing - Contractors | E20: =SUM('Assumptions & Sensitivity'!E49:H49) -> 33049.37 | F20: =SUM('Assumptions & Sensitivity'!I49:L49) -> 95203.125 | G20: =SUM('Assumptions & Sensitivity'!M49:P49) -> 52792.5 | H20: =SUM('Assumptions & Sensitivity'!Q49:T49) -> 53444.55 | I20: =SUM('Assumptions & Sensitivity'!U49:X49) -> 34162.5 | J20: =SUM('Assumptions & Sensitivity'!Y49:AB49) -> 34162.5 | K20: =J20/$J$12 -> 0.00059430394
D21: Office Rent, Utilities & Maintenance | E21: =SUM('Assumptions & Sensitivity'!E50:H50) -> 3683.95 | F21: =SUM('Assumptions & Sensitivity'!I50:L50) -> 57120 | G21: =SUM('Assumptions & Sensitivity'!M50:P50) -> 117096 | H21: =SUM('Assumptions & Sensitivity'!Q50:T50) -> 184426.2 | I21: =SUM('Assumptions & Sensitivity'!U50:X50) -> 193647.51 | J21: =SUM('Assumptions & Sensitivity'!Y50:AB50) -> 198535.93 | K21: =J21/$J$12 -> 0.0034538071
D22: AI Training | E22: =SUM('Assumptions & Sensitivity'!E67:H67) -> 0 | F22: =SUM('Assumptions & Sensitivity'!I67:L67) -> 272987.5 | G22: =SUM('Assumptions & Sensitivity'!M67:P67) -> 266719.5 | H22: =SUM('Assumptions & Sensitivity'!Q67:T67) -> 275955.88 | I22: =SUM('Assumptions & Sensitivity'!U67:X67) -> 154755.88 | J22: =SUM('Assumptions & Sensitivity'!Y67:AB67) -> 270832.79 | K22: =J22/$J$12 -> 0.0047115109
D23: Software Subscriptions | E23: =SUM('Assumptions & Sensitivity'!E71:H71) -> 1902.54 | F23: =SUM('Assumptions & Sensitivity'!I71:L71) -> 5200 | G23: =SUM('Assumptions & Sensitivity'!M71:P71) -> 8550 | H23: =SUM('Assumptions & Sensitivity'!Q71:T71) -> 15300 | I23: =SUM('Assumptions & Sensitivity'!U71:X71) -> 25842 | J23: =SUM('Assumptions & Sensitivity'!Y71:AB71) -> 27642 | K23: =J23/$J$12 -> 0.00048087083
D24: Equipment Lease (computers, desks) | E24: =SUM('Assumptions & Sensitivity'!E72:H72) -> 0 | F24: =SUM('Assumptions & Sensitivity'!I72:L72) -> 1800 | G24: =SUM('Assumptions & Sensitivity'!M72:P72) -> 5600 | H24: =SUM('Assumptions & Sensitivity'!Q72:T72) -> 8500 | I24: =SUM('Assumptions & Sensitivity'!U72:X72) -> 15821 | J24: =SUM('Assumptions & Sensitivity'!Y72:AB72) -> 18428 | K24: =J24/$J$12 -> 0.00032058055
D25: Legal Fees | E25: =SUM('Assumptions & Sensitivity'!E73:H73) -> 64404.04 | F25: =SUM('Assumptions & Sensitivity'!I73:L73) -> 50000 | G25: =SUM('Assumptions & Sensitivity'!M73:P73) -> 60000 | H25: =SUM('Assumptions & Sensitivity'!Q73:T73) -> 100000 | I25: =SUM('Assumptions & Sensitivity'!U73:X73) -> 120000 | J25: =SUM('Assumptions & Sensitivity'!Y73:AB73) -> 120010 | K25: =J25/$J$12 -> 0.00208774
D26: Marketing Expenses (inc. Comp) | E26: =SUM('Assumptions & Sensitivity'!E74:H74)+E27 -> 129.99 | F26: =SUM('Assumptions & Sensitivity'!I74:L74)+F27 -> 125000 | G26: =SUM('Assumptions & Sensitivity'!M74:P74)+G27 -> 500000 | H26: =SUM('Assumptions & Sensitivity'!Q74:T74)+H27 -> 2053648.8 | I26: =SUM('Assumptions & Sensitivity'!U74:X74)+I27 -> 7324030.3 | J26: =SUM('Assumptions & Sensitivity'!Y74:AB74)+J27 -> 17900053 | K26: =J26/$J$12 -> 0.31139619
D27: Comp Marketing | E27: =SUM('Hiring Plan'!D118:G118) -> 0 | F27: =SUM('Hiring Plan'!H118:K118) -> 50000 | G27: =SUM('Hiring Plan'!L118:O118) -> 100000 | H27: =SUM('Hiring Plan'!P118:S118) -> 240500 | I27: =SUM('Hiring Plan'!T118:W118) -> 555089.5 | J27: =SUM('Hiring Plan'!X118:AA118) -> 655089.5 | K27: =J27/$J$12 -> 0.011396188
D28: Travel & Entertainment | E28: =SUM('Assumptions & Sensitivity'!E75:H75) -> 20603.74 | F28: =SUM('Assumptions & Sensitivity'!I75:L75) -> 22000 | G28: =SUM('Assumptions & Sensitivity'!M75:P75) -> 40000 | H28: =SUM('Assumptions & Sensitivity'!Q75:T75) -> 130000 | I28: =SUM('Assumptions & Sensitivity'!U75:X75) -> 200000 | J28: =SUM('Assumptions & Sensitivity'!Y75:AB75) -> 200010 | K28: =J28/$J$12 -> 0.0034794506
D29: Misc. Expenses | E29: =SUM('Assumptions & Sensitivity'!E76:H76) -> 19011.65 | F29: =SUM('Assumptions & Sensitivity'!I76:L76) -> 20000 | G29: =SUM('Assumptions & Sensitivity'!M76:P76) -> 12657.142 | H29: =SUM('Assumptions & Sensitivity'!Q76:T76) -> 60438.294 | I29: =SUM('Assumptions & Sensitivity'!U76:X76) -> 225631.36 | J29: =SUM('Assumptions & Sensitivity'!Y76:AB76) -> 574832.13 | K29: =J29/$J$12 -> 0.01
E30: =E17+SUM(E20:E26)+E28+E29 -> 180785.28 | F30: =F17+SUM(F20:F26)+F28+F29 -> 1036310.6 | G30: =G17+SUM(G20:G26)+G28+G29 -> 1625240.1 | H30: =H17+SUM(H20:H26)+H28+H29 -> 4255271.3 | I30: =I17+SUM(I20:I26)+I28+I29 -> 10649315 | J30: =J17+SUM(J20:J26)+J28+J29 -> 21838664
C32: Operating Income (Loss) | E32: =E14-E30 -> -193573.5 | F32: =F14-F30 -> -1095033.1 | G32: =G14-G30 -> -595168.04 | H32: =H14-H30 -> 1017347.9 | I32: =I14-I30 -> 9680395 | J32: =J14-J30 -> 30569841 | K32: =J32/$J$12 -> 0.53180468
C34: Operating Ratios as a percent of Sales
D35: Total Expenses | E35: NA | F35: NA | G35: =G30/G12 -> 1.2840499 | H35: =H30/H12 -> 0.70406872 | I35: =I30/I12 -> 0.47197852 | J35: =J30/J12 -> 0.37991376
D36: Marketing Expenses | E36: NA | F36: NA | G36: =G26/G12 -> 0.39503389 | H36: =H26/H12 -> 0.33979265 | I36: =I26/I12 -> 0.32460161 | J36: =J26/J12 -> 0.31139619
D37: Gross Margin | E37: NA | F37: NA | G37: =G14/G12 -> 0.81382677 | H37: =H14/H12 -> 0.87239709 | I37: =I14/I12 -> 0.9010144 | J37: =J14/J12 -> 0.91171844
D38: Operating Margin | E38: NA | F38: NA | G38: =G32/G12 -> -0.47022309 | H38: =H32/H12 -> 0.16832837 | I38: =I32/I12 -> 0.42903588 | J38: =J32/J12 -> 0.53180468
B42: Use of Funds
D44: 18 months
D45: Tech Hires | E45: =SUM('Hiring Plan'!J105:O105) -> 813025 | F45: =E45/$E$54 -> 0.25817568
D46: Non-Tech Hires | E46: =SUM('Hiring Plan'!J144:O144)-SUM('Hiring Plan'!J105:O105)-SUM('Hiring Plan'!J118:O118) -> 410000 | F46: =E46/$E$54 -> 0.13019529
D47: Marketing | E47: =SUM('Assumptions & Sensitivity'!K74:P74)+SUM('Hiring Plan'!J118:O118) -> 625000 | F47: =E47/$E$54 -> 0.19846844
D48: Technology | E48: =SUM('Assumptions & Sensitivity'!K57:P57)+SUM('Assumptions & Sensitivity'!K71:P72) -> 304514.6 | F48: =E48/$E$54 -> 0.096698458
D49: G & A | E49: =SUM('Assumptions & Sensitivity'!K78:P78) -> 338873.14 | F49: =E49/$E$54 -> 0.107609
D50: AI Training | E50: =SUM('Assumptions & Sensitivity'!K69:P69) -> 334237.5 | F50: =E50/$E$54 -> 0.10613695 | G50: =E50/SUM($E$50:$E$53) -> 0.5081894
D51: Rent & Equipment | E51: =SUM('Assumptions & Sensitivity'!K68:P68)+SUM('Assumptions & Sensitivity'!K70:P70) -> 205469.5 | F51: =E51/$E$54 -> 0.065246736 | G51: =E51/SUM($E$50:$E$53) -> 0.31240487
D52: Labor 1 | E52: =SUM('Hiring Plan'!J152:O153)+SUM('Hiring Plan'!J156:O156) -> 89730 | F52: =E52/$E$54 -> 0.028493716 | G52: =E52/SUM($E$50:$E$53) -> 0.13642944
D53: Labor 2 | E53: =SUM('Hiring Plan'!J154:O155) -> 28265.625 | F53: =E53/$E$54 -> 0.008975735 | G53: =E53/SUM($E$50:$E$53) -> 0.0429763
D54: Total | E54: =SUM(E45:E53) -> 3149115.4 | F54: =E54/$E$54 -> 1
D57: Check | E57: =SUM('Assumptions & Sensitivity'!K77:P77)-E54 -> 0
D69: Unit Economic Assumptions
D70: Average Order Value | F70: ='Assumptions & Sensitivity'!$M$18 -> 97
D71: Commission % | F71: ='Assumptions & Sensitivity'!$M$20 -> 0.06
D72: Revenue | F72: =F70*F71 -> 5.82
D74: Unit Economics | E74: % of Revenue | F74: Per Order
D75: Profit | E75: =K32 -> 0.53180468 | F75: =$F$72*E75 -> 3.0951032
D76: Tech Expense | E76: =K13 -> 0.088281561 | F76: =$F$72*E76 -> 0.51379869
D77: Engineers | E77: =K18 -> 0.026679685 | F77: =$F$72*E77 -> 0.15527577
D78: Marketing | E78: =K26 -> 0.31139619 | F78: =$F$72*E78 -> 1.8123258
D79: Other | E79: =K19+SUM(K20:K25)+K28+K29 -> 0.04183789 | F79: =$F$72*E79 -> 0.24349652
D80: Total | E80: 1 | F80: =SUM(F75:F79) -> 5.82

Sheet Assumptions & Sensitivity
A1: Assumptions | E1: Q1-17 | F1: Q2-17 | G1: Q3-17 | H1: Q4-17 | I1: Q1-18 | J1: Q2-18 | K1: Q3-18 | L1: Q4-18 | M1: Q1-19 | N1: Q2-19 | O1: Q3-19 | P1: Q4-19 | Q1: Q1-20 | R1: Q2-20 | S1: Q3-20 | T1: Q4-20 | U1: Q1-21 | V1: Q2-21 | W1: Q3-21 | X1: Q4-21 | Y1: Q1-22 | Z1: Q2-22 | AA1: Q3-22 | AB1: Q4-22
B3: Revenue Assumptions
B5: Revenue Stream 1 - Affiliate Marketing
C6: Women: 18-38 years
C7: Population 18 - 29 | K7: =SUM('U.S. Population'!V100:AG100) -> 26459763 | L7: =K7+(O7-K7)/4 -> 26487561 | M7: =K7+2*(O7-K7)/4 -> 26515359 | N7: =K7+3*(O7-K7)/4 -> 26543157 | O7: =SUM('U.S. Population'!V101:AG101) -> 26570955 | P7: =O7+(S7-O7)/4 -> 26577470 | Q7: =O7+2*(S7-O7)/4 -> 26583984 | R7: =O7+3*(S7-O7)/4 -> 26590499 | S7: =SUM('U.S. Population'!V102:AG102) -> 26597014 | T7: =S7+(W7-S7)/4 -> 26566608 | U7: =S7+2*(W7-S7)/4 -> 26536202 | V7: =S7+3*(W7-S7)/4 -> 26505797 | W7: =SUM('U.S. Population'!V103:AG103) -> 26475391 | X7: =W7+45000 -> 26520391 | Y7: =X7+45000 -> 26565391 | Z7: =Y7+45000 -> 26610391 | AA7: =Z7+45000 -> 26655391 | AB7: =AA7+45000 -> 26700391
C8: Population 30 - 38 | K8: =SUM('U.S. Population'!AH100:AP100) -> 19454990 | L8: =K8+(O8-K8)/4 -> 19454990 | M8: =K8+2*(O8-K8)/4 -> 19454990 | N8: =K8+3*(O8-K8)/4 -> 19454990 | O8: =SUM('U.S. Population'!AH100:AP100) -> 19454990 | P8: =O8+(S8-O8)/4 -> 19557784 | Q8: =O8+2*(S8-O8)/4 -> 19660577 | R8: =O8+3*(S8-O8)/4 -> 19763370 | S8: =SUM('U.S. Population'!AH102:AP102) -> 19866164 | T8: =S8+(W8-S8)/4 -> 19866164 | U8: =S8+2*(W8-S8)/4 -> 19866164 | V8: =S8+3*(W8-S8)/4 -> 19866164 | W8: =SUM('U.S. Population'!AH102:AP102) -> 19866164 | X8: =W8+45000 -> 19911164 | Y8: =X8+45000 -> 19956164 | Z8: =Y8+45000 -> 20001164 | AA8: =Z8+45000 -> 20046164 | AB8: =AA8+45000 -> 20091164
C9: Use Instagram or Pinterest 18 - 29 | D9: 0.6 | K9: =K7*$D$9 -> 15875858 | L9: =L7*$D$9 -> 15892537 | M9: =M7*$D$9 -> 15909215 | N9: =N7*$D$9 -> 15925894 | O9: =O7*$D$9 -> 15942573 | P9: =P7*$D$9 -> 15946482 | Q9: =Q7*$D$9 -> 15950391 | R9: =R7*$D$9 -> 15954300 | ... AB9: =AB7*$D$9 -> 16020235
C10: Use Instagram or Pinterest 30 - 38 | D10: 0.41 | K10: =K8*$D$10 -> 7976545.9 | L10: =L8*$D$10 -> 7976545.9 | M10: =M8*$D$10 -> 7976545.9 | N10: =N8*$D$10 -> 7976545.9 | O10: =O8*$D$10 -> 7976545.9 | P10: =P8*$D$10 -> 8018691.2 | Q10: =Q8*$D$10 -> 8060836.6 | R10: =R8*$D$10 -> 8102981.9 | ... AB10: =AB8*$D$10 -> 8237377.2
C11: Total User Base | K11: =K9+K10 -> 23852404 | L11: =L9+L10 -> 23869082 | M11: =M9+M10 -> 23885761 | N11: =N9+N10 -> 23902440 | O11: =O9+O10 -> 23919119 | P11: =P9+P10 -> 23965173 | Q11: =Q9+Q10 -> 24011227 | R11: =R9+R10 -> 24057281 | ... AB11: =AB9+AB10 -> 24257612
C12: Our reach | M12: 0.002 | N12: =N13/N7 -> 0.0032722181 | O12: =O13/O7 -> 0.0051176557 | P12: =P13/P7 -> 0.007466926 | Q12: =Q13/Q7 -> 0.010866392 | R12: =R13/R7 -> 0.016023618 | S12: =S13/S7 -> 0.024003296 | T12: =T13/T7 -> 0.033366134 | U12: =U13/U7 -> 0.050930272 | ... AB12: =AB13/AB7 -> 0.24981275
C13: Total number of Customers (Registered Users) | M13: =M11*M12 -> 47771.523 | N13: =ROUNDUP(M13*(1+M14),0) -> 86855 | O13: =ROUNDUP(N13*(1+N14),0) -> 135981 | P13: =ROUNDUP(O13*(1+O14),0) -> 198452 | Q13: =ROUNDUP(P13*(1+P14),0) -> 288872 | R13: =ROUNDUP(Q13*(1+Q14),0) -> 426076 | S13: =ROUNDUP(R13*(1+R14),0) -> 638416 | T13: =ROUNDUP(S13*(1+S14),0) -> 886425 | U13: =ROUNDUP(T13*(1+T14),0) -> 1351496 | ... AB13: =ROUNDUP(AA13*(1+AA14),0) -> 6670098
C14: Growth Rate (Customer Acquisition) | M14: 0.818125 | N14: 0.56560096 | O14: 0.45940318 | P14: 0.455625 | Q14: 0.47496429 | R14: 0.49836111 | S14: 0.38847527 | T14: 0.5246586 | U14: 0.3 | V14: 0.3 | W14: 0.3 | X14: 0.3 | Y14: 0.2 | Z14: 0.2 | AA14: 0.2 | AB14: 0
C15: Avg. shopping instances | D15: 4 | E15: per quarter per Woman | R15: =R13/N13-1 -> 3.9056013 | V15: =V13/R13-1 -> 3.1235484
C16: Avg. orders assisted (in %) | M16: 0.1 | N16: 0.1 | O16: 0.1 | P16: 0.1 | Q16: 0.1 | R16: 0.1 | S16: 0.1 | T16: 0.1 | U16: 0.1 | V16: 0.1 | W16: 0.1 | X16: 0.1 | Y16: 0.1 | Z16: 0.1 | AA16: 0.1 | AB16: 0.1
C17: Total number of orders assisted | M17: =ROUNDUP(M13*($D$15*M16),0) -> 19109 | N17: =ROUNDUP(N13*($D$15*N16),0) -> 34742 | O17: =ROUNDUP(O13*($D$15*O16),0) -> 54393 | P17: =ROUNDUP(P13*($D$15*P16),0) -> 79381 | Q17: =ROUNDUP(Q13*($D$15*Q16),0) -> 115549 | R17: =ROUNDUP(R13*($D$15*R16),0) -> 170431 | S17: =ROUNDUP(S13*($D$15*S16),0) -> 255367 | T17: =ROUNDUP(T13*($D$15*T16),0) -> 354570 | ... AB17: =ROUNDUP(AB13*($D$15*AB16),0) -> 2668040
C18: Average Order Value, AOV (in US$) | M18: 97 | N18: 97 | O18: 97 | P18: 97 | Q18: 97 | R18: 97 | S18: 97 | T18: 97 | U18: 97 | V18: 97 | W18: 97 | X18: 97 | Y18: 98 | Z18: 99 | AA18: 100 | AB18: 101
C19: Projected GMV generated(in US$) | M19: =M18*M17 -> 1853573 | N19: =N18*N17 -> 3369974 | O19: =O18*O17 -> 5276121 | P19: =P18*P17 -> 7699957 | Q19: =Q18*Q17 -> 11208253 | R19: =R18*R17 -> 16531807 | S19: =S18*S17 -> 24770599 | T19: =T18*T17 -> 34393290 | ... AB19: =AB18*AB17 -> 269472040
C20: Average Commission Rate (%) | M20: 0.06 | N20: 0.06 | O20: 0.06 | P20: 0.06 | Q20: 0.06 | R20: 0.06 | S20: 0.06 | T20: 0.06 | U20: 0.06 | V20: 0.06 | W20: 0.06 | X20: 0.06 | Y20: 0.06 | Z20: 0.06 | AA20: 0.06 | AB20: 0.06
C21: Revenue - Women | M21: =M20*M19 -> 111214.38 | N21: =N20*N19 -> 202198.44 | O21: =O20*O19 -> 316567.26 | P21: =P20*P19 -> 461997.42 | Q21: =Q20*Q19 -> 672495.18 | R21: =R20*R19 -> 991908.42 | S21: =S20*S19 -> 1486235.9 | T21: =T20*T19 -> 2063597.4 | ... AB21: =AB20*AB19 -> 16168322
C23: Men: 18-38 years
C24: Population 18 - 29 | K24: =SUM('U.S. Population'!V53:AG53) -> 27756248 | L24: =K24+(O24-K24)/4 -> 27789971 | M24: =K24+2*(O24-K24)/4 -> 27823694 | N24: =K24+3*(O24-K24)/4 -> 27857416 | O24: =SUM('U.S. Population'!V54:AG54) -> 27891139 | P24: =O24+(S24-O24)/4 -> 27899573 | Q24: =O24+2*(S24-O24)/4 -> 27908008 | R24: =O24+3*(S24-O24)/4 -> 27916442 | S24: =SUM('U.S. Population'!V55:AG55) -> 27924876 | T24: =S24+(W24-S24)/4 -> 27894138 | U24: =S24+2*(W24-S24)/4 -> 27863400 | V24: =S24+3*(W24-S24)/4 -> 27832662 | W24: =SUM('U.S. Population'!V56:AG56) -> 27801924 | X24: =W24+(48744844-W24)/4 -> 33037654 | Y24: =X24+(48744844-X24)/4 -> 36964452 | Z24: =Y24+(48744844-Y24)/4 -> 39909550 | AA24: =Z24+(48744844-Z24)/4 -> 42118373 | AB24: =AA24+(48744844-AA24)/4 -> 43774991
C25: Population 30 - 38 | K25: =SUM('U.S. Population'!AH55:AP55) -> 20314925 | L25: =K25+(O25-K25)/4 -> 20314925 | M25: =K25+2*(O25-K25)/4 -> 20314925 | N25: =K25+3*(O25-K25)/4 -> 20314925 | O25: =SUM('U.S. Population'!AH55:AP55) -> 20314925 | P25: =O25+(S25-O25)/4 -> 20410855 | Q25: =O25+2*(S25-O25)/4 -> 20506786 | R25: =O25+3*(S25-O25)/4 -> 20602716 | S25: =SUM('U.S. Population'!AH56:AP56) -> 20698646 | T25: =S25+(W25-S25)/4 -> 20792462 | U25: =S25+2*(W25-S25)/4 -> 20886278 | V25: =S25+3*(W25-S25)/4 -> 20980093 | W25: =SUM('U.S. Population'!AH57:AP57) -> 21073909 | X25: =W25+(SUM('U.S. Population'!AH57:AP57)-W25)/4 -> 21073909 | Y25: =X25+(SUM('U.S. Population'!AI57:AQ57)-X25)/4 -> 20997930 | Z25: =Y25+(SUM('U.S. Population'!AJ57:AR57)-Y25)/4 -> 20860768 | AA25: =Z25+(SUM('U.S. Population'!AK57:AS57)-Z25)/4 -> 20713811 | AB25: =AA25+(SUM('U.S. Population'!AL57:AT57)-AA25)/4 -> 20538811
C26: Use Instagram or Pinterest 18 - 29 | D26: 0.4 | L26: =L24*$D$26 -> 11115988 | M26: =M24*$D$26 -> 11129477 | N26: =N24*$D$26 -> 11142966 | O26: =O24*$D$26 -> 11156456 | P26: =P24*$D$26 -> 11159829 | Q26: =Q24*$D$26 -> 11163203 | R26: =R24*$D$26 -> 11166577 | S26: =S24*$D$26 -> 11169950 | ... AB26: =AB24*$D$26 -> 17509996
C27: Use Instagram or Pinterest 30 - 38 | D27: 0.35 | L27: =L25*$D$27 -> 7110223.8 | M27: =M25*$D$27 -> 7110223.8 | N27: =N25*$D$27 -> 7110223.8 | O27: =O25*$D$27 -> 7110223.8 | P27: =P25*$D$27 -> 7143799.3 | Q27: =Q25*$D$27 -> 7177374.9 | R27: =R25*$D$27 -> 7210950.5 | S27: =S25*$D$27 -> 7244526.1 | ... AB27: =AB25*$D$27 -> 7188583.8
C28: Total User Base | L28: =L26+L27 -> 18226212 | M28: =M26+M27 -> 18239701 | N28: =N26+N27 -> 18253190 | O28: =O26+O27 -> 18266679 | P28: =P26+P27 -> 18303629 | Q28: =Q26+Q27 -> 18340578 | R28: =R26+R27 -> 18377527 | S28: =S26+S27 -> 18414476 | ... AB28: =AB26+AB27 -> 24698580
C29: Our reach | M29: =M12/4 -> 0.0005 | N29: =N30/N24 -> 0.00059524544 | O29: =O30/O24 -> 0.00093079741 | P29: =P30/P24 -> 0.0013580136 | Q29: =Q30/Q24 -> 0.0019761712 | R29: =R30/R24 -> 0.00291391 | S29: =S30/S24 -> 0.0043647821 | T29: =T30/T24 -> 0.0060670812 | U29: =U30/U24 -> 0.0092604635 | ... AB29: =AB30/AB24 -> 0.029091108
C30: Total number of Customers (Registered Users) | M30: =M28*M29 -> 9119.8506 | N30: =ROUNDUP(M30*(1+M31),0) -> 16582 | O30: =ROUNDUP(N30*(1+N31),0) -> 25961 | P30: =ROUNDUP(O30*(1+O31),0) -> 37888 | Q30: =ROUNDUP(P30*(1+P31),0) -> 55151 | R30: =ROUNDUP(Q30*(1+Q31),0) -> 81346 | S30: =ROUNDUP(R30*(1+R31),0) -> 121886 | T30: =ROUNDUP(S30*(1+S31),0) -> 169236 | U30: =ROUNDUP(T30*(1+T31),0) -> 258028 | ... AB30: =ROUNDUP(AA30*(1+AA31),0) -> 1273463
C31: Growth Rate (Customer Acquisition) | M31: =M14 -> 0.818125 | N31: =N14 -> 0.56560096 | O31: =O14 -> 0.45940318 | P31: =P14 -> 0.455625 | Q31: =Q14 -> 0.47496429 | R31: =R14 -> 0.49836111 | S31: =S14 -> 0.38847527 | T31: =T14 -> 0.5246586 | ... AB31: =AB14 -> 0
C32: Avg. shopping instances | D32: 2 | E32: per quarter per Man
C33: Avg. orders assisted by Woolly (in %) | M33: 0.1 | N33: 0.1 | O33: 0.1 | P33: 0.1 | Q33: 0.1 | R33: 0.1 | S33: 0.1 | T33: 0.1 | U33: 0.1 | V33: 0.1 | W33: 0.1 | X33: 0.1 | Y33: 0.1 | Z33: 0.1 | AA33: 0.1 | AB33: 0.1
C34: Total number of orders assisted | M34: =ROUNDUP(M30*($D$15*M33),0) -> 3648 | N34: =ROUNDUP(N30*($D$15*N33),0) -> 6633 | O34: =ROUNDUP(O30*($D$15*O33),0) -> 10385 | P34: =ROUNDUP(P30*($D$15*P33),0) -> 15156 | Q34: =ROUNDUP(Q30*($D$15*Q33),0) -> 22061 | R34: =ROUNDUP(R30*($D$15*R33),0) -> 32539 | S34: =ROUNDUP(S30*($D$15*S33),0) -> 48755 | T34: =ROUNDUP(T30*($D$15*T33),0) -> 67695 | ... AB34: =ROUNDUP(AB30*($D$15*AB33),0) -> 509386
C35: Average Order Value, AOV (in US$) | M35: 97 | N35: 97 | O35: 97 | P35: 97 | Q35: 97 | R35: 97 | S35: 97 | T35: 97 | U35: 97 | V35: 97 | W35: 97 | X35: 97 | Y35: 98 | Z35: 99 | AA35: 100 | AB35: 101
C36: Projected GMV generated (in US$) | M36: =M35*M34 -> 353856 | N36: =N35*N34 -> 643401 | O36: =O35*O34 -> 1007345 | P36: =P35*P34 -> 1470132 | Q36: =Q35*Q34 -> 2139917 | R36: =R35*R34 -> 3156283 | S36: =S35*S34 -> 4729235 | T36: =T35*T34 -> 6566415 | ... AB36: =AB35*AB34 -> 51447986
C37: Average Commission Rate (%) | M37: 0.05 | N37: 0.05 | O37: 0.05 | P37: 0.05 | Q37: 0.05 | R37: 0.05 | S37: 0.05 | T37: 0.05 | U37: 0.05 | V37: 0.05 | W37: 0.05 | X37: 0.05 | Y37: 0.05 | Z37: 0.05 | AA37: 0.05 | AB37: 0.05
C38: Revenue - Men | K38: =K37*K36 -> 0 | L38: =L37*L36 -> 0 | M38: =M37*M36 -> 17692.8 | N38: =N37*N36 -> 32170.05 | O38: =O37*O36 -> 50367.25 | P38: =P37*P36 -> 73506.6 | Q38: =Q37*Q36 -> 106995.85 | R38: =R37*R36 -> 157814.15 | ... AB38: =AB37*AB36 -> 2572399.3
C40: Total number of Registered Users | K40: =J30+K13 -> 0 | L40: =K30+L13 -> 0 | M40: =M30+M13 -> 56891.373 | N40: =N30+N13 -> 103437 | O40: =O30+O13 -> 161942 | P40: =P30+P13 -> 236340 | Q40: =Q30+Q13 -> 344023 | R40: =R30+R13 -> 507422 | S40: =S30+S13 -> 760302 | T40: =T30+T13 -> 1055661 | ... AB40: =AB30+AB13 -> 7943561
C41: Total Projected GMV (in US$) | K41: =J36+K19 -> 0 | L41: =K36+L19 -> 0 | M41: =M36+M19 -> 2207429 | N41: =N36+N19 -> 4013375 | O41: =O36+O19 -> 6283466 | P41: =P36+P19 -> 9170089 | Q41: =Q36+Q19 -> 13348170 | R41: =R36+R19 -> 19688090 | S41: =S36+S19 -> 29499834 | T41: =T36+T19 -> 40959705 | ... AB41: =AB36+AB19 -> 320920026
C42: Total Projected Revenues - Affiliate Marketing (in US$) | K42: =K21+J38 -> 0 | L42: =L21+K38 -> 0 | M42: =M21+M38 -> 128907.18 | N42: =N21+N38 -> 234368.49 | O42: =O21+O38 -> 366934.51 | P42: =P21+P38 -> 535504.02 | Q42: =Q21+Q38 -> 779491.03 | R42: =R21+R38 -> 1149722.6 | S42: =S21+S38 -> 1722697.7 | T42: =T21+T38 -> 2391918.1 | ... AB42: =AB21+AB38 -> 18740722
B44: Total Projected Revenues (in US$) | K44: =K42 -> 0 | L44: =L42 -> 0 | M44: =M42 -> 128907.18 | N44: =N42 -> 234368.49 | O44: =O42 -> 366934.51 | P44: =P42 -> 535504.02 | Q44: =Q42 -> 779491.03 | R44: =R42 -> 1149722.6 | ... AB44: =AB42 -> 18740722
B46: Expense Assumptions
B48: a. | C48: Compensation | E48: ='Hiring Plan'!D144 -> 0 | F48: ='Hiring Plan'!E144 -> 0 | G48: ='Hiring Plan'!F144 -> 9500 | H48: ='Hiring Plan'!G144 -> 28500 | I48: ='Hiring Plan'!H144 -> 28500 | J48: ='Hiring Plan'!I144 -> 28500 | K48: ='Hiring Plan'!J144 -> 190000 | L48: ='Hiring Plan'!K144 -> 190000 | ... AB48: ='Hiring Plan'!AA144 -> 787311.63
B49: b. | C49: Outsourcing - Contractors | E49: ='2017 IS'!P60 -> 605.27 | F49: ='2017 IS'!Q60 -> 10233.34 | G49: ='2017 IS'!R60 -> 9371.74 | H49: ='2017 IS'!S60 -> 12839.02 | I49: 15000 | J49: 15000 | K49: ='Hiring Plan'!J146 -> 32601.562 | L49: ='Hiring Plan'!K146 -> 32601.562 | M49: ='Hiring Plan'!L146 -> 13198.125 | N49: ='Hiring Plan'!M146 -> 13198.125 | O49: ='Hiring Plan'!N146 -> 13198.125 | P49: ='Hiring Plan'!O146 -> 13198.125 | Q49: ='Hiring Plan'!P146 -> 13361.138 | R49: ='Hiring Plan'!Q146 -> 13361.138 | ... AB49: ='Hiring Plan'!AA146 -> 8540.625
B50: c. | C50: Office Rent, Utilities & Maintenance | E50: ='2017 IS'!P61 -> 77.8 | F50: ='2017 IS'!Q61 -> 3619.52 | G50: ='2017 IS'!R61 -> -13.37 | H50: ='2017 IS'!S61 -> 0 | I50: ='Hiring Plan'!H146 -> 0 | J50: ='Hiring Plan'!I146 -> 0 | K50: =SUM(K54:K56) -> 28560 | L50: =SUM(L54:L56) -> 28560 | M50: =SUM(M54:M56) -> 28560 | N50: =SUM(N54:N56) -> 28560 | O50: =SUM(O54:O56) -> 29988 | P50: =SUM(P54:P56) -> 29988 | Q50: =SUM(Q54:Q56) -> 44982 | R50: =SUM(R54:R56) -> 44982 | ... AB50: =SUM(AB54:AB56) -> 49658.779
C51: Office Space Requirement (Sqft) | D51: 150 | E51: sqft per employee | G51: ='Hiring Plan'!F147 -> 0 | H51: ='Hiring Plan'!G147 -> 0 | I51: ='Hiring Plan'!H147 -> 0 | J51: ='Hiring Plan'!I147 -> 0 | K51: 2000 | L51: 2000 | M51: 2000 | N51: 2000 | O51: 2000 | P51: 2000 | Q51: 3000 | R51: 3000 | S51: 3000 | T51: 3000 | U51: 3000 | V51: 3000 | W51: 3000 | X51: 3000 | Y51: 3001 | Z51: 3002 | AA51: 3003 | AB51: 3004
C52: Rental (in US$) | D52: 4 | E52: Per Sqft per month | G52: ='Hiring Plan'!F148 -> 0 | H52: ='Hiring Plan'!G148 -> 0 | I52: ='Hiring Plan'!H148 -> 0 | J52: ='Hiring Plan'!I148 -> 0 | K52: =D52 -> 4 | L52: =D52 -> 4 | M52: =L52 -> 4 | N52: =M52 -> 4 | O52: =$N$52*(1+$D$53) -> 4.2 | P52: =$N$52*(1+$D$53) -> 4.2 | Q52: =$N$52*(1+$D$53) -> 4.2 | R52: =$N$52*(1+$D$53) -> 4.2 | S52: =$R$52*(1+$D$53) -> 4.41 | T52: =$R$52*(1+$D$53) -> 4.41 | U52: =$R$52*(1+$D$53) -> 4.41 | V52: =$R$52*(1+$D$53) -> 4.41 | W52: =$V$52*(1+$D$53) -> 4.6305 | X52: =$V$52*(1+$D$53) -> 4.6305 | Y52: =$V$52*(1+$D$53) -> 4.6305 | Z52: =$V$52*(1+$D$53) -> 4.6305 | AA52: =$V$52*(1+$D$53) -> 4.6305 | AB52: =$V$52*(1+$D$53) -> 4.6305
C53: Annual Escalation in Rent | D53: 0.05 | G53: ='Hiring Plan'!F149 -> 0 | H53: ='Hiring Plan'!G149 -> 0 | I53: ='Hiring Plan'!H149 -> 0 | J53: ='Hiring Plan'!I149 -> 0 | K53: ='Hiring Plan'!J149 -> 0 | L53: ='Hiring Plan'!K149 -> 0 | M53: ='Hiring Plan'!L149 -> 0 | N53: ='Hiring Plan'!M149 -> 0 | ... AB53: ='Hiring Plan'!AA149 -> 0
C54: Office Rent ($) | F54: - | G54: - | H54: - | I54: - | J54: - | K54: =K51*(K52*3) -> 24000 | L54: =L51*(L52*3) -> 24000 | M54: =M51*(M52*3) -> 24000 | N54: =N51*(N52*3) -> 24000 | O54: =O51*(O52*3) -> 25200 | P54: =P51*(P52*3) -> 25200 | Q54: =Q51*(Q52*3) -> 37800 | R54: =R51*(R52*3) -> 37800 | ... AB54: =AB51*(AB52*3) -> 41730.066
C55: Utilities ($) | D55: 0.05 | E55: of Rent | F55: - | G55: - | H55: - | I55: - | J55: - | K55: =K54*$D$55 -> 1200 | L55: =L54*$D$55 -> 1200 | M55: =M54*$D$55 -> 1200 | N55: =N54*$D$55 -> 1200 | O55: =O54*$D$55 -> 1260 | P55: =P54*$D$55 -> 1260 | Q55: =Q54*$D$55 -> 1890 | R55: =R54*$D$55 -> 1890 | ... AB55: =AB54*$D$55 -> 2086.5033
C56: Maintenance ($) | D56: 0.14 | E56: of Rent | F56: - | G56: - | H56: - | I56: - | J56: - | K56: =K54*$D$56 -> 3360 | L56: =L54*$D$56 -> 3360 | M56: =M54*$D$56 -> 3360 | N56: =N54*$D$56 -> 3360 | O56: =O54*$D$56 -> 3528 | P56: =P54*$D$56 -> 3528 | Q56: =Q54*$D$56 -> 5292 | R56: =R54*$D$56 -> 5292 | ... AB56: =AB54*$D$56 -> 5842.2092
B57: d. | C57: Tech Assets & Subscriptions | E57: ='2017 IS'!P62 -> 2589.7 | F57: ='2017 IS'!Q62 -> 3713.94 | G57: ='2017 IS'!R62 -> 3437.96 | H57: ='2017 IS'!S62 -> 3046.62 | I57: 5000 | J57: 5000 | K57: =SUM(K58:K66) -> 22330 | L57: =SUM(L58:L66) -> 26392.5 | M57: =SUM(M58:M66) -> 36358.922 | N57: =SUM(N58:N66) -> 48843.369 | O57: =SUM(O58:O66) -> 64606.28 | P57: =SUM(P58:P66) -> 85833.528 | Q57: =SUM(Q58:Q66) -> 115429.24 | R57: =SUM(R58:R66) -> 157484.31 | ... AB57: =SUM(AB58:AB66) -> 1556235.1
C58: AWS | E58: ='Hiring Plan'!D153 -> 0 | F58: ='Hiring Plan'!E153 -> 0 | G58: ='Hiring Plan'!F153 -> 0 | H58: 0 | I58: 0 | J58: 0 | K58: 1875 | L58: =K58*(1+L$14) -> 1875 | M58: =L58*(1+M$14) -> 3408.9844 | N58: =M58*(1+N$14) -> 5337.1092 | O58: =N58*(1+O$14) -> 7788.9942 | P58: =O58*(1+P$14) -> 11337.855 | Q58: =P58*(1+Q$14) -> 16722.931 | R58: =Q58*(1+R$14) -> 25056.989 | S58: =R58*(1+S$14) -> 34791.01 | ... AB58: =AA58*(1+AB$14) -> 261792.25
C59: MaxCDN | E59: =SUM('Assumptions & Sensitivity'!K67:P67) -> 539707 | F59: ='Hiring Plan'!E154 -> 0 | G59: ='Hiring Plan'!F154 -> 0 | H59: 0 | I59: 0 | J59: 0 | K59: 40 | L59: =K59*(1+L$14) -> 40 | M59: =L59*(1+M$14) -> 72.725 | N59: =M59*(1+N$14) -> 113.85833 | O59: =N59*(1+O$14) -> 166.16521 | P59: =O59*(1+P$14) -> 241.87423 | Q59: =P59*(1+Q$14) -> 356.75585 | R59: =Q59*(1+R$14) -> 534.5491 | S59: =R59*(1+S$14) -> 742.20821 | ... AB59: =AA59*(1+AB$14) -> 5584.9014
C60: Google Suite (Apps) | E60: ='Hiring Plan'!D152 -> 0 | F60: ='Hiring Plan'!E152 -> 0 | G60: ='Hiring Plan'!F152 -> 0 | H60: 0 | I60: 0 | J60: 0 | K60: ='Hiring Plan'!J98*15 -> 105 | L60: ='Hiring Plan'!K98*15 -> 105 | M60: ='Hiring Plan'!L98*15 -> 105 | N60: ='Hiring Plan'!M98*15 -> 97.5 | O60: ='Hiring Plan'!N98*15 -> 112.5 | P60: ='Hiring Plan'!O98*15 -> 112.5 | Q60: ='Hiring Plan'!P98*15 -> 150 | R60: ='Hiring Plan'!Q98*15 -> 150 | ... AB60: ='Hiring Plan'!AA98*15 -> 345.525
C61: Google Cloud/API | E61: ='Hiring Plan'!D156 -> 0 | F61: ='Hiring Plan'!E156 -> 0 | G61: ='Hiring Plan'!F156 -> 0 | H61: 0 | I61: 0 | J61: 0 | K61: 110 | L61: =K61*(1+L$14) -> 110 | M61: =L61*(1+M$14) -> 199.99375 | N61: =M61*(1+N$14) -> 313.11041 | O61: =N61*(1+O$14) -> 456.95433 | P61: =O61*(1+P$14) -> 665.15414 | Q61: =P61*(1+Q$14) -> 981.0786 | R61: =Q61*(1+R$14) -> 1470.01 | S61: =R61*(1+S$14) -> 2041.0726 | ... AB61: =AA61*(1+AB$14) -> 15358.479
C62: Bing Cloud/API (Azure) | E62: ='Hiring Plan'!D157 -> 0 | F62: ='Hiring Plan'!E157 -> 0 | G62: ='Hiring Plan'!F157 -> 0 | H62: 0 | I62: 0 | J62: 0 | K62: 225 | L62: =K62*(1+L$14) -> 225 | M62: =L62*(1+M$14) -> 409.07813 | N62: =M62*(1+N$14) -> 640.45311 | O62: =N62*(1+O$14) -> 934.6793 | P62: =O62*(1+P$14) -> 1360.5426 | Q62: =P62*(1+Q$14) -> 2006.7517 | R62: =Q62*(1+R$14) -> 3006.8387 | S62: =R62*(1+S$14) -> 4174.9212 | ... AB62: =AA62*(1+AB$14) -> 31415.07
C63: Data Hosting (ColoGuard) | E63: ='Hiring Plan'!D158 -> 0 | F63: ='Hiring Plan'!E158 -> 0 | G63: ='Hiring Plan'!F158 -> 0 | H63: 0 | I63: 0 | J63: 0 | K63: 2375 | L63: =K63*(1+L$14) -> 2375 | M63: =L63*(1+M$14) -> 4318.0469 | N63: =M63*(1+N$14) -> 6760.3383 | O63: =N63*(1+O$14) -> 9866.0593 | P63: =O63*(1+P$14) -> 14361.283 | Q63: =P63*(1+Q$14) -> 21182.379 | R63: =Q63*(1+R$14) -> 31738.853 | S63: =R63*(1+S$14) -> 44068.612 | ... AB63: =AA63*(1+AB$14) -> 331603.52
C64: MainGear | E64: ='Hiring Plan'!D159 -> 0 | F64: ='Hiring Plan'!E159 -> 0 | G64: ='Hiring Plan'!F159 -> 0 | H64: 0 | I64: 0 | J64: 0 | K64: 16250 | L64: =K64*(1+25%) -> 20312.5 | M64: =L64*(1+25%) -> 25390.625 | N64: =M64*(1+25%) -> 31738.281 | O64: =N64*(1+25%) -> 39672.852 | P64: =O64*(1+25%) -> 49591.064 | Q64: =P64*(1+25%) -> 61988.831 | R64: =Q64*(1+25%) -> 77486.038 | S64: =R64*(1+25%) -> 96857.548 | ... AB64: =AA64*(1+25%) -> 721644.97
C65: GitHub | E65: ='Hiring Plan'!D160 -> 0 | F65: ='Hiring Plan'!E160 -> 0 | G65: ='Hiring Plan'!F160 -> 0 | H65: 0 | I65: 0 | J65: 0 | K65: 100 | L65: =K65*(1+L$14) -> 100 | M65: =L65*(1+M$14) -> 181.8125 | N65: =M65*(1+N$14) -> 284.64582 | O65: =N65*(1+O$14) -> 415.41302 | P65: =O65*(1+P$14) -> 604.68558 | Q65: =P65*(1+Q$14) -> 891.88964 | R65: =Q65*(1+R$14) -> 1336.3727 | S65: =R65*(1+S$14) -> 1855.5205 | ... AB65: =AA65*(1+AB$14) -> 13962.253
C66: Indexing | E66: ='Hiring Plan'!D161 -> 0 | F66: ='Hiring Plan'!E161 -> 0 | G66: ='Hiring Plan'!F161 -> 0 | H66: 0 | I66: 0 | J66: 0 | K66: 1250 | L66: =K66*(1+L$14) -> 1250 | M66: =L66*(1+M$14) -> 2272.6563 | N66: =M66*(1+N$14) -> 3558.0728 | O66: =N66*(1+O$14) -> 5192.6628 | P66: =O66*(1+P$14) -> 7558.5698 | Q66: =P66*(1+Q$14) -> 11148.62 | R66: =Q66*(1+R$14) -> 16704.659 | S66: =R66*(1+S$14) -> 23194.006 | ... AB66: =AA66*(1+AB$14) -> 174528.17
B67: e. | C67: AI Development | E67: ='2017 IS'!P63 -> 0 | F67: =SUM(F68:F70) -> 0 | G67: =SUM(G68:G70) -> 0 | H67: =SUM(H68:H70) -> 0 | I67: =SUM(I68:I70) -> 0 | J67: =SUM(J68:J70) -> 0 | K67: =SUM(K68:K70) -> 152275 | L67: =SUM(L68:L70) -> 120712.5 | M67: =SUM(M68:M70) -> 66679.875 | ... AB67: =SUM(AB68:AB70) -> 38692.969
C68: Equipment Lease (computers, desks) | E68: ='Hiring Plan'!D163 -> 0 | F68: ='Hiring Plan'!E163 -> 0 | G68: ='Hiring Plan'!F163 -> 0 | H68: 0 | I68: 0 | J68: 0 | K68: 40000 | L68: 0 | M68: 0 | N68: 0 | O68: 0 | P68: 0 | Q68: 0 | R68: 100000 | S68: 0 | T68: 0 | U68: 0 | V68: 0 | W68: 0 | X68: 0 | Y68: 1 | Z68: 2 | AA68: 3 | AB68: 4
C69: AI Training | E69: ='AI Training Costs'!G100 -> 0 | F69: ='AI Training Costs'!H100 -> 0 | G69: ='AI Training Costs'!I100 -> 0 | H69: ='AI Training Costs'!J100 -> 0 | I69: ='AI Training Costs'!L100 -> 0 | J69: ='AI Training Costs'!M100 -> 0 | K69: ='AI Training Costs'!N100 -> 85500 | L69: ='AI Training Costs'!O100 -> 93937.5 | M69: ='AI Training Costs'!Q100 -> 38700 | N69: ='AI Training Costs'!R100 -> 38700 | O69: ='AI Training Costs'!S100 -> 38700 | P69: ='AI Training Costs'!T100 -> 38700 | Q69: ='AI Training Costs'!V100 -> 14750 | R69: ='AI Training Costs'!W100 -> 14750 | S69: ='AI Training Costs'!X100 -> 14750 | T69: ='AI Training Costs'!Y100 -> 14750 | U69: ='AI Training Costs'!AA100 -> 9450 | V69: ='AI Training Costs'!AB100 -> 9450 | W69: ='AI Training Costs'!AC100 -> 9450 | X69: ='AI Training Costs'!AD100 -> 9450 | Y69: ='AI Training Costs'!AE100 -> 37800 | Z69: ='AI Training Costs'!AG100 -> 9450 | AA69: ='AI Training Costs'!AH100 -> 9450 | AB69: ='AI Training Costs'!AI100 -> 9450
C70: AI Photo Lab | E70: ='AI Training Costs'!G102 -> 0 | F70: ='AI Training Costs'!H102 -> 0 | G70: ='AI Training Costs'!I102 -> 0 | H70: ='AI Training Costs'!J102 -> 0 | I70: ='AI Training Costs'!L102 -> 0 | J70: ='AI Training Costs'!M102 -> 0 | K70: ='AI Training Costs'!N102 -> 26775 | L70: ='AI Training Costs'!O102 -> 26775 | M70: ='AI Training Costs'!Q102 -> 27979.875 | N70: ='AI Training Costs'!R102 -> 27979.875 | O70: ='AI Training Costs'!S102 -> 27979.875 | P70: ='AI Training Costs'!T102 -> 27979.875 | Q70: ='AI Training Costs'!V102 -> 29238.969 | R70: ='AI Training Costs'!W102 -> 29238.969 | S70: ='AI Training Costs'!X102 -> 29238.969 | T70: ='AI Training Costs'!Y102 -> 29238.969 | U70: ='AI Training Costs'!AA102 -> 29238.969 | V70: ='AI Training Costs'!AB102 -> 29238.969 | W70: ='AI Training Costs'!AC102 -> 29238.969 | X70: ='AI Training Costs'!AD102 -> 29238.969 | Y70: ='AI Training Costs'!AE102 -> 116955.88 | Z70: ='AI Training Costs'!AG102 -> 29238.969 | AA70: ='AI Training Costs'!AH102 -> 29238.969 | AB70: ='AI Training Costs'!AI102 -> 29238.969
B71: f. | C71: Software Subscriptions | D71: 100 | E71: ='2017 IS'!P64 -> 639.62 | F71: ='2017 IS'!Q64 -> 322.96 | G71: ='2017 IS'!R64 -> 482.16 | H71: ='2017 IS'!S64 -> 457.8 | I71: 500 | J71: 500 | K71: =($D$71*3)*'Hiring Plan'!J98 -> 2100 | L71: =($D$71*3)*'Hiring Plan'!K98 -> 2100 | M71: =($D$71*3)*'Hiring Plan'!L98 -> 2100 | N71: =($D$71*3)*'Hiring Plan'!M98 -> 1950 | O71: =($D$71*3)*'Hiring Plan'!N98 -> 2250 | P71: =($D$71*3)*'Hiring Plan'!O98 -> 2250 | Q71: =($D$71*3)*'Hiring Plan'!P98 -> 3000 | R71: =($D$71*3)*'Hiring Plan'!Q98 -> 3000 | ... AB71: =($D$71*3)*'Hiring Plan'!AA98 -> 6910.5
B72: g. | C72: Equipment Lease (computers, desks) | D72: 200 | E72: ='2017 IS'!P65 -> 0 | F72: ='2017 IS'!Q65 -> 0 | G72: ='2017 IS'!R65 -> 0 | H72: ='2017 IS'!S65 -> 0 | I72: 0 | J72: ='Hiring Plan'!I165 -> 0 | K72: =($D$72)*'Hiring Plan'!I98 -> 400 | L72: =($D$72)*'Hiring Plan'!J98 -> 1400 | M72: =($D$72)*'Hiring Plan'!K98 -> 1400 | N72: =($D$72)*'Hiring Plan'!L98 -> 1400 | O72: =($D$72)*'Hiring Plan'!M98 -> 1300 | P72: =($D$72)*'Hiring Plan'!N98 -> 1500 | Q72: =($D$72)*'Hiring Plan'!O98 -> 1500 | R72: =($D$72)*'Hiring Plan'!P98 -> 2000 | ... AB72: =($D$72)*'Hiring Plan'!Z98 -> 4607
B73: h. | C73: Legal Fees | E73: ='2017 IS'!P66 -> 20276.39 | F73: ='2017 IS'!Q66 -> 26415.18 | G73: ='2017 IS'!R66 -> 10434.47 | H73: ='2017 IS'!S66 -> 7278 | I73: 10000 | J73: 10000 | K73: 15000 | L73: 15000 | M73: 15000 | N73: 15000 | O73: 15000 | P73: 15000 | Q73: 20000 | R73: 20000 | S73: 30000 | T73: 30000 | U73: 30000 | V73: 30000 | W73: 30000 | X73: 30000 | Y73: 30001 | Z73: 30002 | AA73: 30003 | AB73: 30004
B74: i. | C74: Direct Marketing Expenses | D74: 0.3 | E74: ='2017 IS'!P67 -> 0 | F74: ='2017 IS'!Q67 -> 0 | G74: ='2017 IS'!R67 -> 0 | H74: ='2017 IS'!S67 -> 129.99 | I74: 0 | J74: 0 | K74: 0 | L74: 75000 | M74: 100000 | N74: 100000 | O74: 100000 | P74: 100000 | Q74: =Q44*$D$74 -> 233847.31 | R74: =R44*$D$74 -> 344916.77 | S74: =S44*$D$74 -> 516809.31 | T74: =T44*$D$74 -> 717575.44 | U74: =U44*$D$74 -> 1094059.3 | V74: =V44*$D$74 -> 1422275 | W74: =W44*$D$74 -> 1848959.3 | X74: =X44*$D$74 -> 2403647.2 | ... AB74: =AB44*$D$74 -> 5622216.5
B75: j. | C75: Travel & Entertainment | E75: ='2017 IS'!P68 -> 3196.54 | F75: ='2017 IS'!Q68 -> 4670.05 | G75: ='2017 IS'!R68 -> 11004.31 | H75: ='2017 IS'!S68 -> 1732.84 | I75: 5000 | J75: 5000 | K75: 6000 | L75: =K75 -> 6000 | M75: 10000 | N75: =M75 -> 10000 | O75: =N75 -> 10000 | P75: =O75 -> 10000 | Q75: 15000 | R75: =Q75 -> 15000 | S75: 50000 | T75: 50000 | U75: 50000 | V75: 50000 | W75: 50000 | X75: 50000 | Y75: 50001 | Z75: 50002 | AA75: 50003 | AB75: 50004
B76: k. | C76: Misc. Expenses | D76: 0.01 | E76: ='2017 IS'!P69 -> 2784.24 | F76: ='2017 IS'!Q69 -> 5662.71 | G76: ='2017 IS'!R69 -> 4481.83 | H76: ='2017 IS'!S69 -> 6082.87 | I76: 5000 | J76: 5000 | K76: 5000 | L76: 5000 | M76: =M44*$D$76 -> 1289.0718 | N76: =N44*$D$76 -> 2343.6849 | O76: =O44*$D$76 -> 3669.3451 | P76: =P44*$D$76 -> 5355.0402 | Q76: =Q44*$D$76 -> 7794.9103 | R76: =R44*$D$76 -> 11497.226 | S76: =S44*$D$76 -> 17226.977 | T76: =T44*$D$76 -> 23919.181 | ... AB76: =AB44*$D$76 -> 187407.22
B77: Total Cumulative Expenses (in US$) | D77: 0 | E77: =E48+E49+E50+E57+E67+E71+E72+E73+E74+E75+E76 -> 30169.56 | F77: =F48+F49+F50+F57+F67+F71+F72+F73+F74+F75+F76 -> 54637.7 | G77: =G48+G49+G50+G57+G67+G71+G72+G73+G74+G75+G76 -> 48699.1 | H77: =H48+H49+H50+H57+H67+H71+H72+H73+H74+H75+H76 -> 60067.14 | I77: =I48+I49+I50+I57+I67+I71+I72+I73+I74+I75+I76 -> 69000 | J77: =J48+J49+J50+J57+J67+J71+J72+J73+J74+J75+J76 -> 69000 | K77: =K48+K49+K50+K57+K67+K71+K72+K73+K74+K75+K76 -> 454266.56 | L77: =L48+L49+L50+L57+L67+L71+L72+L73+L74+L75+L76 -> 502766.56 | ... AB77: =AB48+AB49+AB50+AB57+AB67+AB71+AB72+AB73+AB74+AB75+AB76 -> 8341588.4
C78: SG&A | G78: =G50+G73+G75+G76 -> 25907.24 | H78: =H50+H73+H75+H76 -> 15093.71 | I78: =I50+I73+I75+I76 -> 20000 | J78: =J50+J73+J75+J76 -> 20000 | K78: =K50+K73+K75+K76 -> 54560 | L78: =L50+L73+L75+L76 -> 54560 | M78: =M50+M73+M75+M76 -> 54849.072 | N78: =N50+N73+N75+N76 -> 55903.685 | ... AB78: =AB50+AB73+AB75+AB76 -> 317074
C79: Marketing Employee Compensation | E79: ='Hiring Plan'!D118 -> 0 | F79: ='Hiring Plan'!E118 -> 0 | G79: ='Hiring Plan'!F118 -> 0 | H79: ='Hiring Plan'!G118 -> 0 | I79: ='Hiring Plan'!H118 -> 0 | J79: ='Hiring Plan'!I118 -> 0 | K79: ='Hiring Plan'!J118 -> 25000 | L79: ='Hiring Plan'!K118 -> 25000 | ... AB79: ='Hiring Plan'!AA118 -> 163772.38
C80: CAC to date ( Calculated ) | M80: =(SUM($E$74:M74)+SUM($E$79:M79))/M40 -> 4.3966242 | N80: =(SUM($E$74:N74)+SUM($E$79:N79))/N40 -> 3.6266519 | O80: =(SUM($E$74:O74)+SUM($E$79:O79))/O40 -> 3.0883279 | P80: =(SUM($E$74:P74)+SUM($E$79:P79))/P40 -> 2.6450452 | Q80: =(SUM($E$74:Q74)+SUM($E$79:Q79))/Q40 -> 2.5953273 | R80: =(SUM($E$74:R74)+SUM($E$79:R79))/R40 -> 2.5060878 | S80: =(SUM($E$74:S74)+SUM($E$79:S79))/S40 -> 2.4363061 | T80: =(SUM($E$74:T74)+SUM($E$79:T79))/T40 -> 2.537537 | ... AB80: =(SUM($E$74:AB74)+SUM($E$79:AB79))/AB40 -> 3.512639
C81: CAC per period | L81: NA | M81: =(M74+M79)/(M40-L40) -> 2.1971697 | N81: =(N74+N79)/(N40-M40) -> 2.6855369 | O81: =(O74+O79)/(O40-N40) -> 2.1365695 | P81: =(P74+P79)/(P40-O40) -> 1.6801527 | Q81: =(Q74+Q79)/(Q40-P40) -> 2.4862077 | R81: =(R74+R79)/(R40-Q40) -> 2.3182013 | S81: =(S74+S79)/(S40-R40) -> 2.296284 | T81: =(T74+T79)/(T40-S40) -> 2.7981218 | ... AB81: =(AB74+AB79)/(AB40-AA40) -> 4.3703232
B82: Working Capital & Balance Sheet Drivers
B83: A/C Receivables (# days of Revenues) | D83: 30
B84: A/C Payables (# days of Operating Costs) | D84: 21
B86: Paid-up Capital | D86: 250000
B87: Shares Issued | D87: 1000000
B88: Share Price | D88: =D86/D87 -> 0.25
B89: Investment - Investor | D89: 1000000 | J89: 4000000
B90: Equity Offered | D90: 0.15 | J90: 0.2
B91: Shares Issued | D91: =(D87/(1-D90))-D87 -> 176470.59
B92: Share Price | D92: =D89/D91 -> 5.6666667
B94: Corporate Tax Rate | D94: 0.21
B95: Annual growth rate in Cashflows beyond year 4 | D95: 0.05
B96: Discount Rate | D96: 0.5
B98: Free Cashflow to Seed Investor | D98: 2017 | E98: 2018 | F98: 2019 | G98: 2020 | H98: 2021 | I98: 2022
B99: Investment made | D99: =-D89 -> -1000000 | F99: 0 | G99: 0 | H99: 0 | I99: 0
B100: Cashflow from Operations (attributed to investor) | D100: =CFS!$H$3*D90 -> -29036.025 | E100: =CFS!$M$3*D90 -> -146851.51 | F100: =CFS!$R$3*D90 -> -162444.95 | G100: =CFS!$W$3*$D$90 -> 100957.08 | H100: =CFS!$AB$3*$D$90 -> 993082.43 | I100: =CFS!$AG$3*$D$90 -> 3308520.3
B101: Terminal Value at the end of 4th year | I101: =I100*(1+$D$95)/($D$96-$D$95) -> 7719880.8
B102: Total Cash Flows | D102: =SUM(D99:D101) -> -1029036 | E102: =SUM(E99:E101) -> -146851.51 | F102: =SUM(F99:F101) -> -162444.95 | G102: =SUM(G99:G101) -> 100957.08 | H102: =SUM(H99:H101) -> 993082.43 | I102: =SUM(I99:I101) -> 11028401
B103: Net Present Value | D103: =D102+NPV(D96,E102:I102) -> 479242.58
B104: IRR | D104: =IRR(D102:I102) -> 0.61249915
B106: Free Cashflow to Series A Investor | D106: 2017 | E106: 2018 | F106: 2019 | G106: 2020 | H106: 2021 | I106: 2022
B107: Investment made | D107: 0 | E107: =-J89 -> -4000000 | F107: 0 | G107: 0 | H107: 0 | I107: 0
B108: Cashflow from Operations (attributed to investor) | D108: =CFS!$H$3*J90 -> -38714.7 | E108: =CFS!$M$3*J90 -> -195802.01 | F108: =CFS!$R$3*J90 -> -216593.27 | G108: =CFS!$W$3*J90 -> 134609.44 | H108: =CFS!$AB$3*J90 -> 1324109.9 | I108: =CFS!$AG$3*J90 -> 4411360.4
B109: Terminal Value at the end of 4th year | I109: =I108*(1+$D$95)/($D$96-$D$95) -> 10293174
B110: Total Cash Flows | D110: =SUM(D107:D109) -> -38714.7 | E110: =SUM(E107:E109) -> -4195802 | F110: =SUM(F107:F109) -> -216593.27 | G110: =SUM(G107:G109) -> 134609.44 | H110: =SUM(H107:H109) -> 1324109.9 | I110: =SUM(I107:I109) -> 14704535
B111: Net Present Value | D111: =SUM(D110:E110)+NPV(D96,F110:I110) -> -1022157.5
...

Sheet Hiring Plan
B2: Hiring Plan | D2: Q1-17 | E2: Q2-17 | F2: Q3-17 | G2: Q4-17 | H2: Q1-18 | I2: Q2-18 | J2: Q3-18 | K2: Q4-18 | L2: Q1-19 | M2: Q2-19 | N2: Q3-19 | O2: Q4-19 | P2: Q1-20 | Q2: Q2-20 | R2: Q3-20 | S2: Q4-20 | T2: Q1-21 | U2: Q2-21 | V2: Q3-21 | W2: Q4-21 | X2: Q4-22 | Y2: Q4-23 | Z2: Q4-24 | AA2: Q4-25
B4: Salary Inflation (annual) - 2018 onwards | D4: 0.035
B6: Quarterly Wages (in US$)
C7: Administration
C8: CEO | D8: 0 | E8: 0 | F8: 0 | G8: 0 | H8: 0 | I8: 0 | J8: 12500 | K8: =J8 -> 12500 | L8: 35000 | M8: =L8 -> 35000 | N8: =M8 -> 35000 | O8: =N8 -> 35000 | P8: =L8*(1+$D$4) -> 36225 | Q8: =$P$8 -> 36225 | R8: =$P$8 -> 36225 | S8: =$P$8 -> 36225 | T8: =P8*(1+$D$4) -> 37492.875 | U8: =$P$8 -> 36225 | V8: =$P$8 -> 36225 | W8: =$P$8 -> 36225 | X8: =$P$8 -> 36225 | Y8: =$P$8 -> 36225 | Z8: =$P$8 -> 36225 | AA8: =$P$8 -> 36225
C9: CPO | D9: 0 | E9: 0 | F9: 0 | G9: 0 | H9: 0 | I9: 0 | J9: 12500 | K9: =J9 -> 12500 | L9: 40000 | M9: =L9 -> 40000 | N9: =M9 -> 40000 | O9: =N9 -> 40000 | P9: =L9*(1+$D$4) -> 41400 | Q9: =P9 -> 41400 | R9: =Q9 -> 41400 | S9: =R9 -> 41400 | T9: =P9*(1+$D$4) -> 42849 | U9: =T9 -> 42849 | V9: =U9 -> 42849 | W9: =V9 -> 42849 | X9: =W9 -> 42849 | Y9: =X9 -> 42849 | Z9: =Y9 -> 42849 | AA9: =Z9 -> 42849
C10: EA | D10: 0 | E10: 0 | F10: 0 | G10: 0 | H10: 0 | I10: 0 | J10: 0 | K10: 0 | L10: 0 | M10: =L10 -> 0 | N10: =M10 -> 0 | O10: =N10 -> 0 | P10: =M10*(1+$D$4) -> 0 | Q10: =P10 -> 0 | R10: =Q10 -> 0 | S10: =R10 -> 0 | T10: =P10*(1+$D$4) -> 0 | U10: =T10 -> 0 | V10: =U10 -> 0 | W10: =V10 -> 0 | X10: =W10 -> 0 | Y10: =X10 -> 0 | Z10: =Y10 -> 0 | AA10: =Z10 -> 0
C11: Technology
C12: Director - Engineering | D12: 0 | E12: 0 | F12: 0 | G12: 0 | H12: =G12 -> 0 | I12: =H12 -> 0 | J12: =I12 -> 0 | K12: =J12 -> 0 | L12: =K12*(1+$D$4) -> 0 | M12: =L12 -> 0 | N12: =M12 -> 0 | O12: =N12 -> 0 | P12: 0 | Q12: =P12 -> 0 | R12: =Q12 -> 0 | S12: =R12 -> 0 | T12: 0 | U12: =T12 -> 0 | V12: =U12 -> 0 | W12: =V12 -> 0 | X12: =W12 -> 0 | Y12: =X12 -> 0 | Z12: =Y12 -> 0 | AA12: =Z12 -> 0
C13: AI Engineer(s) | D13: 0 | E13: 0 | F13: 0 | G13: 0 | H13: 0 | I13: 0 | J13: 40000 | K13: =J13 -> 40000 | L13: =K13*(D4+1) -> 41400 | M13: =L13 -> 41400 | N13: =M13 -> 41400 | O13: =N13 -> 41400 | P13: =O13*($D$4+1) -> 42849 | Q13: =P13 -> 42849 | R13: =Q13 -> 42849 | S13: =R13 -> 42849 | T13: =P13*(1+$D$4) -> 44348.715 | U13: =T13 -> 44348.715 | V13: =U13 -> 44348.715 | W13: =V13 -> 44348.715 | X13: =W13 -> 44348.715 | Y13: =X13 -> 44348.715 | Z13: =Y13 -> 44348.715 | AA13: =Z13 -> 44348.715
C14: AI Engineer Hires | D14: 0 | E14: 0 | F14: =E14 -> 0 | G14: =F14 -> 0 | H14: =G14 -> 0 | I14: =H14 -> 0 | J14: 2 | K14: 2 | L14: 2 | M14: 2 | N14: 2 | O14: =N14 -> 2 | P14: =O14 -> 2 | Q14: =P14 -> 2 | R14: 3 | S14: =R14 -> 3 | T14: 4 | U14: =T14 -> 4 | V14: =U14 -> 4 | W14: =V14 -> 4 | X14: =W14 -> 4 | Y14: =X14 -> 4 | Z14: =Y14 -> 4 | AA14: =Z14 -> 4
C15: Engineer(s) | D15: 0 | E15: 0 | F15: 0 | G15: 0 | H15: =G15 -> 0 | I15: =H15 -> 0 | J15: 30000 | K15: =J15 -> 30000 | L15: =K15*(1+$D$4) -> 31050 | M15: =L15 -> 31050 | N15: =M15 -> 31050 | O15: =N15 -> 31050 | P15: =O15*(1+$D$4) -> 32136.75 | Q15: =P15 -> 32136.75 | R15: =Q15 -> 32136.75 | S15: =R15 -> 32136.75 | T15: =P15*(1+$D$4) -> 33261.536 | U15: =T15 -> 33261.536 | V15: =U15 -> 33261.536 | W15: =V15 -> 33261.536 | X15: =W15 -> 33261.536 | Y15: =X15 -> 33261.536 | Z15: =Y15 -> 33261.536 | AA15: =Z15 -> 33261.536
C16: Engineers Hires | D16: 0 | E16: 0 | F16: 0 | G16: 0 | H16: 0 | I16: 0 | J16: 2 | K16: =J16 -> 2 | L16: =K16 -> 2 | M16: 1.5 | N16: =M16 -> 1.5 | O16: =N16 -> 1.5 | P16: 2 | Q16: =P16 -> 2 | R16: 3 | S16: =R16 -> 3 | T16: 4 | U16: =T16 -> 4 | V16: =U16 -> 4 | W16: =V16 -> 4 | X16: =W16 -> 4 | Y16: =X16 -> 4 | Z16: =Y16 -> 4 | AA16: =Z16 -> 4
C17: Dev Ops | D17: 0 | E17: =D17 -> 0 | F17: =E17 -> 0 | G17: =F17 -> 0 | H17: =G17 -> 0 | I17: =H17 -> 0 | J17: =I17 -> 0 | K17: =J17 -> 0 | L17: =K17 -> 0 | ... Q17: =P17 -> 0 | R17: 37500 | S17: =R17 -> 37500 | T17: =S17*(1+$D$4) -> 38812.5 | U17: =T17 -> 38812.5 | V17: =U17 -> 38812.5 | W17: =V17 -> 38812.5 | X17: =W17 -> 38812.5 | Y17: =X17 -> 38812.5 | Z17: =Y17 -> 38812.5 | AA17: =Z17 -> 38812.5
C18: Director - Product | D18: 0 | E18: =D18 -> 0 | F18: =E18 -> 0 | G18: =F18 -> 0 | H18: =G18 -> 0 | I18: =H18 -> 0 | J18: =I18 -> 0 | K18: =J18 -> 0 | L18: =K18 -> 0 | ... AA18: =Z18 -> 0
C19: Product Manager | D19: 0 | E19: =D19 -> 0 | F19: =E19 -> 0 | G19: =F19 -> 0 | H19: =G19 -> 0 | I19: =H19 -> 0 | J19: =I19 -> 0 | K19: =J19 -> 0 | L19: =K19 -> 0 | ... AA19: =Z19 -> 0
C20: Project Manager | D20: 0 | E20: =D20 -> 0 | F20: =E20 -> 0 | G20: =F20 -> 0 | H20: =G20 -> 0 | I20: =H20 -> 0 | J20: =I20 -> 0 | K20: =J20 -> 0 | L20: =K20 -> 0 | ... AA20: =Z20 -> 0
C21: IT Engineer | D21: 0 | E21: =D21 -> 0 | F21: =E21 -> 0 | G21: =F21 -> 0 | H21: =G21 -> 0 | I21: =H21 -> 0 | J21: =I21 -> 0 | K21: =J21 -> 0 | L21: =K21 -> 0 | ... AA21: =Z21 -> 0
C22: UI Designer | D22: 0 | E22: =D22 -> 0 | F22: =E22 -> 0 | G22: =F22 -> 0 | H22: =G22 -> 0 | I22: =H22 -> 0 | J22: =I22 -> 0 | K22: =J22 -> 0 | L22: =K22 -> 0 | ... AA22: =Z22 -> 0
C23: UX Designer | D23: 0 | E23: =D23 -> 0 | F23: =E23 -> 0 | G23: =F23 -> 0 | H23: =G23 -> 0 | I23: =H23 -> 0 | J23: =I23 -> 0 | K23: =J23 -> 0 | L23: =K23 -> 0 | ... Q23: =P23 -> 0 | R23: 33000 | S23: =R23 -> 33000 | T23: =R23*(1+$D$4) -> 34155 | U23: =T23 -> 34155 | V23: =U23 -> 34155 | W23: =V23 -> 34155 | X23: =W23 -> 34155 | Y23: =X23 -> 34155 | Z23: =Y23 -> 34155 | AA23: =Z23 -> 34155
C24: Data Analyst | D24: 0 | E24: =D24 -> 0 | F24: =E24 -> 0 | G24: =F24 -> 0 | H24: =G24 -> 0 | I24: =H24 -> 0 | J24: =I24 -> 0 | K24: =J24 -> 0 | L24: =K24 -> 0 | ... AA24: =Z24 -> 0
C25: Data Scientist | D25: 0 | E25: 0 | F25: 0 | G25: 0 | H25: 0 | I25: 0 | J25: 0 | K25: 0 | L25: 0 | M25: =L25 -> 0 | N25: 0 | O25: =N25 -> 0 | P25: =O25 -> 0 | Q25: =P25 -> 0 | R25: =Q25 -> 0 | S25: =R25 -> 0 | T25: =S25 -> 0 | U25: =T25 -> 0 | V25: =U25 -> 0 | ... AA25: =Z25 -> 0
C26: Marketing
C27: VP Marketing | D27: 0 | E27: 0 | F27: 0 | G27: 0 | H27: 0 | I27: 0 | J27: =I27 -> 0 | K27: =J27 -> 0 | L27: =K27*(1+$D$4) -> 0 | M27: 0 | N27: =M27 -> 0 | O27: =N27 -> 0 | P27: =O27 -> 0 | Q27: =P27 -> 0 | R27: =Q27 -> 0 | S27: 45000 | T27: =S27*(1+$D$4) -> 46575 | U27: =T27 -> 46575 | V27: =U27 -> 46575 | W27: =V27 -> 46575 | X27: =W27 -> 46575 | Y27: =X27 -> 46575 | Z27: =Y27 -> 46575 | AA27: =Z27 -> 46575
C28: Sr. Manager Marketing | D28: 0 | E28: 0 | F28: =E28 -> 0 | G28: =F28 -> 0 | H28: 0 | I28: 0 | J28: 25000 | K28: 25000 | L28: 25000 | M28: =L28 -> 25000 | N28: =M28 -> 25000 | O28: =N28 -> 25000 | P28: =O28*(1+$D$4) -> 25875 | Q28: =P28 -> 25875 | R28: =Q28 -> 25875 | S28: =R28 -> 25875 | T28: =P28*(1+$D$4) -> 26780.625 | U28: =T28 -> 26780.625 | V28: =U28 -> 26780.625 | W28: =V28 -> 26780.625 | X28: =W28 -> 26780.625 | Y28: =X28 -> 26780.625 | Z28: =Y28 -> 26780.625 | AA28: =Z28 -> 26780.625
C29: Copywriter | D29: 0 | E29: 0 | F29: 0 | G29: 0 | H29: 0 | I29: 0 | J29: =I29 -> 0 | K29: =J29 -> 0 | L29: =K29 -> 0 | M29: =L29 -> 0 | N29: =M29 -> 0 | O29: =N29 -> 0 | P29: =O29*(1+$D$4) -> 0 | Q29: =P29 -> 0 | R29: =Q29 -> 0 | S29: =R29 -> 0 | T29: =P29*(1+$D$4) -> 0 | U29: =T29 -> 0 | V29: =U29 -> 0 | W29: =V29 -> 0 | X29: =W29 -> 0 | Y29: =X29 -> 0 | Z29: =Y29 -> 0 | AA29: =Z29 -> 0
C30: Designer | D30: 0 | E30: 0 | F30: 0 | G30: 0 | H30: 0 | I30: 0 | J30: 0 | K30: 0 | L30: 0 | M30: =L30 -> 0 | N30: 0 | O30: =N30 -> 0 | P30: =O30*(1+$D$4) -> 0 | Q30: =P30 -> 0 | R30: 0 | S30: =R30 -> 0 | T30: =S30*(1+$D$4) -> 0 | U30: =T30 -> 0 | V30: 0 | W30: =V30 -> 0 | X30: =W30 -> 0 | Y30: =X30 -> 0 | Z30: =Y30 -> 0 | AA30: =Z30 -> 0
C31: Search | D31: 0 | E31: 0 | F31: =E31 -> 0 | G31: =F31 -> 0 | H31: 0 | I31: 0 | J31: =I31 -> 0 | K31: =J31 -> 0 | L31: 0 | M31: =L31 -> 0 | N31: =M31 -> 0 | O31: =N31 -> 0 | P31: =O31*(1+$D$4) -> 0 | Q31: =P31 -> 0 | R31: =Q31 -> 0 | S31: =R31 -> 0 | T31: =S31*(1+$D$4) -> 0 | U31: =T31 -> 0 | V31: =U31 -> 0 | W31: =V31 -> 0 | X31: =W31 -> 0 | Y31: =X31 -> 0 | Z31: =Y31 -> 0 | AA31: =Z31 -> 0
C32: Display/Partnerships | D32: 0 | E32: 0 | F32: 0 | G32: 0 | H32: 0 | I32: 0 | J32: 0 | K32: 0 | L32: 0 | M32: =L32 -> 0 | N32: =M32 -> 0 | O32: =N32 -> 0 | P32: =O32*(1+$D$4) -> 0 | Q32: =P32 -> 0 | R32: =Q32 -> 0 | S32: =R32 -> 0 | T32: =S32*(1+$D$4) -> 0 | U32: =T32 -> 0 | V32: =U32 -> 0 | W32: =V32 -> 0 | X32: =W32 -> 0 | Y32: =X32 -> 0 | Z32: =Y32 -> 0 | AA32: =Z32 -> 0
C33: Email/SMS | D33: 0 | E33: 0 | F33: 0 | G33: 0 | H33: 0 | I33: 0 | J33: 0 | K33: =J33 -> 0 | L33: =K33*(1+$D$4) -> 0 | M33: =L33 -> 0 | N33: =M33 -> 0 | O33: =N33 -> 0 | P33: =O33*(1+$D$4) -> 0 | Q33: =P33 -> 0 | R33: =Q33 -> 0 | S33: =R33 -> 0 | T33: =S33*(1+$D$4) -> 0 | U33: =T33 -> 0 | V33: =U33 -> 0 | W33: =V33 -> 0 | X33: =W33 -> 0 | Y33: =X33 -> 0 | Z33: =Y33 -> 0 | AA33: =Z33 -> 0
C34: Director - Business Development | D34: 0 | E34: 0 | F34: 0 | G34: 0 | H34: 0 | I34: 0 | J34: =I34 -> 0 | K34: =J34 -> 0 | L34: =K34*(1+$D$4) -> 0 | M34: =L34 -> 0 | N34: =M34 -> 0 | O34: 0 | P34: =O34*(1+$D$4) -> 0 | Q34: =P34 -> 0 | R34: =Q34 -> 0 | S34: =R34 -> 0 | T34: =S34 -> 0 | U34: =T34 -> 0 | V34: 50000 | W34: =V34 -> 50000 | X34: =W34 -> 50000 | Y34: =X34 -> 50000 | Z34: =Y34 -> 50000 | AA34: =Z34 -> 50000
C35: Business Development | D35: 0 | E35: 0 | F35: 0 | G35: 0 | H35: 0 | I35: 0 | J35: =I35 -> 0 | K35: =J35 -> 0 | L35: 0 | M35: =L35 -> 0 | N35: 0 | O35: 0 | P35: 0 | Q35: =P35 -> 0 | R35: 30000 | S35: =R35 -> 30000 | T35: =S35*(1+$D$4) -> 31050 | U35: =T35 -> 31050 | V35: =U35 -> 31050 | W35: =V35 -> 31050 | X35: =W35 -> 31050 | Y35: =X35 -> 31050 | Z35: =Y35 -> 31050 | AA35: =Z35 -> 31050
C36: Business Development Hires | D36: 0 | E36: =D36 -> 0 | F36: 0 | G36: 0 | H36: =G36 -> 0 | I36: =H36 -> 0 | J36: =I36 -> 0 | K36: =J36 -> 0 | L36: 0 | M36: 0 | N36: =M36 -> 0 | O36: =N36 -> 0 | P36: =O36 -> 0 | Q36: =P36 -> 0 | R36: 1 | S36: =R36 -> 1 | T36: =S36*(1+$D$4) -> 1.035 | U36: =T36 -> 1.035 | V36: =U36 -> 1.035 | W36: =V36 -> 1.035 | X36: =W36 -> 1.035 | Y36: =X36 -> 1.035 | Z36: =Y36 -> 1.035 | AA36: =Z36 -> 1.035
C37: Customer Service | D37: 0 | E37: 0 | F37: 0 | G37: 0 | H37: 0 | I37: 0 | J37: =I37 -> 0 | K37: =J37 -> 0 | L37: =K37*(1+$D$4) -> 0 | M37: =L37 -> 0 | N37: =M37 -> 0 | O37: =N37 -> 0 | P37: 8000 | Q37: =P37 -> 8000 | R37: =Q37 -> 8000 | S37: =R37 -> 8000 | T37: =P37*(1+$D$4) -> 8280 | U37: =T37 -> 8280 | V37: =U37 -> 8280 | W37: =V37 -> 8280 | X37: =W37 -> 8280 | Y37: =X37 -> 8280 | Z37: =Y37 -> 8280 | AA37: =Z37 -> 8280
C38: Editorial | H38: 0 | I38: 0 | J38: =I38 -> 0 | K38: =J38 -> 0 | L38: =K38*(1+$D$4) -> 0 | M38: =L38 -> 0 | N38: 0 | O38: =N38 -> 0 | P38: =O38*(1+$D$4) -> 0 | Q38: =P38 -> 0 | R38: =Q38 -> 0 | S38: =R38 -> 0 | T38: =S38*(1+$D$4) -> 0 | U38: =T38 -> 0 | V38: =U38 -> 0 | W38: =V38 -> 0 | X38: =W38 -> 0 | Y38: =X38 -> 0 | Z38: =Y38 -> 0 | AA38: =Z38 -> 0
C39: Fashion Editor | D39: 0 | E39: 0 | F39: 0 | G39: 0 | H39: 0 | I39: =H39 -> 0 | J39: 0 | K39: =J39 -> 0 | L39: =K39*(1+$D$4) -> 0 | M39: =L39 -> 0 | N39: =M39 -> 0 | O39: =N39 -> 0 | P39: =O39*(1+$D$4) -> 0 | Q39: =P39 -> 0 | R39: =Q39 -> 0 | S39: =R39 -> 0 | T39: =S39*(1+$D$4) -> 0 | U39: =T39 -> 0 | V39: 35000 | W39: =V39 -> 35000 | X39: =W39 -> 35000 | Y39: =X39 -> 35000 | Z39: =Y39 -> 35000 | AA39: =Z39 -> 35000
C40: Fashion Associate | D40: 0 | E40: 0 | F40: 0 | G40: 0 | H40: 0 | I40: =H40 -> 0 | J40: 0 | K40: =J40 -> 0 | L40: =K40*(1+$D$4) -> 0 | M40: =L40 -> 0 | N40: =M40 -> 0 | O40: =N40 -> 0 | P40: =O40 -> 0 | Q40: =P40 -> 0 | R40: =Q40 -> 0 | S40: =R40 -> 0 | T40: 11500 | U40: =T40 -> 11500 | V40: =U40 -> 11500 | W40: =V40 -> 11500 | X40: =W40 -> 11500 | Y40: =X40 -> 11500 | Z40: =Y40 -> 11500 | AA40: =Z40 -> 11500
C41: HR / Recruitment
C42: HR Manager | D42: 0 | E42: 0 | F42: 0 | G42: 0 | H42: 0 | I42: 0 | J42: =I42 -> 0 | K42: =J42 -> 0 | L42: 0 | M42: =L42 -> 0 | N42: =M42 -> 0 | O42: =N42 -> 0 | P42: =O42*(1+$D$4) -> 0 | Q42: =P42 -> 0 | R42: =Q42 -> 0 | S42: =R42 -> 0 | T42: =S42*(1+$D$4) -> 0 | U42: =T42 -> 0 | V42: 35000 | W42: =V42 -> 35000 | X42: =W42 -> 35000 | Y42: =X42 -> 35000 | Z42: =Y42 -> 35000 | AA42: =Z42 -> 35000
C43: Recruiter | D43: 0 | E43: 0 | F43: 0 | G43: 0 | H43: 0 | I43: =H43 -> 0 | J43: =I43 -> 0 | K43: =J43 -> 0 | L43: 0 | M43: =L43 -> 0 | N43: =M43 -> 0 | O43: =N43 -> 0 | P43: =O43 -> 0 | Q43: =P43 -> 0 | R43: =Q43 -> 0 | S43: =R43 -> 0 | T43: 35000 | U43: =T43 -> 35000 | V43: =U43 -> 35000 | W43: =V43 -> 35000 | X43: =W43 -> 35000 | Y43: =X43 -> 35000 | Z43: =Y43 -> 35000 | AA43: =Z43 -> 35000
C44: General Counsel | D44: 0 | E44: 0 | F44: 0 | G44: 0 | H44: 0 | I44: 0 | J44: 0 | K44: 0 | L44: 0 | M44: 0 | N44: 0 | O44: =N44 -> 0 | P44: =O44 -> 0 | Q44: =P44 -> 0 | R44: =Q44 -> 0 | S44: =R44 -> 0 | T44: =S44 -> 0 | U44: =T44 -> 0 | V44: =U44 -> 0 | ... AA44: =Z44 -> 0
C45: Finance & Accounting
C46: CFO | D46: 0 | E46: 0 | F46: 0 | G46: 0 | H46: 0 | I46: 0 | J46: 0 | K46: 0 | L46: 0 | M46: 0 | N46: 0 | O46: 0 | P46: 0 | Q46: 0 | R46: =Q46 -> 0 | S46: =R46 -> 0 | T46: =S46*(1+$D$4) -> 0 | U46: =T46 -> 0 | V46: =U46 -> 0 | W46: =V46 -> 0 | X46: =W46 -> 0 | Y46: =X46 -> 0 | Z46: =Y46 -> 0 | AA46: =Z46 -> 0
C47: Manager - Finance | D47: 0 | E47: 0 | F47: 0 | G47: 0 | H47: 0 | I47: 0 | J47: 0 | K47: 0 | L47: 0 | M47: =L47 -> 0 | N47: =M47 -> 0 | O47: =$L$47 -> 0 | P47: 0 | Q47: =P47 -> 0 | R47: =Q47 -> 0 | S47: =R47 -> 0 | T47: 0 | U47: =T47 -> 0 | V47: =U47 -> 0 | W47: =V47 -> 0 | X47: =W47 -> 0 | Y47: =X47 -> 0 | Z47: =Y47 -> 0 | AA47: =Z47 -> 0
C48: Accounting Manager | D48: 0 | E48: 0 | F48: 0 | G48: =F48 -> 0 | H48: 0 | I48: =H48 -> 0 | J48: =I48 -> 0 | K48: =J48 -> 0 | L48: =K48*(1+$D$4) -> 0 | M48: =L48 -> 0 | N48: 30000 | O48: =N48 -> 30000 | P48: =O48*(1+$D$4) -> 31050 | Q48: =P48 -> 31050 | R48: =Q48 -> 31050 | S48: =R48 -> 31050 | T48: =P48*(1+$D$4) -> 32136.75 | U48: =T48 -> 32136.75 | V48: =U48 -> 32136.75 | W48: =V48 -> 32136.75 | X48: =W48 -> 32136.75 | Y48: =X48 -> 32136.75 | Z48: =Y48 -> 32136.75 | AA48: =Z48 -> 32136.75
C49: Accounts Payable | D49: 0 | E49: 0 | F49: =E49 -> 0 | G49: =F49 -> 0 | H49: 0 | I49: =H49 -> 0 | J49: =I49 -> 0 | K49: =J49 -> 0 | L49: =K49*(1+$D$4) -> 0 | M49: =L49 -> 0 | N49: 0 | O49: =N49 -> 0 | P49: 12000 | Q49: =P49 -> 12000 | R49: =Q49 -> 12000 | S49: =R49 -> 12000 | T49: =P49*(1+$D$4) -> 12420 | U49: =T49 -> 12420 | V49: =U49 -> 12420 | W49: =V49 -> 12420 | X49: =W49 -> 12420 | Y49: =X49 -> 12420 | Z49: =Y49 -> 12420 | AA49: =Z49 -> 12420
C50: Photography Hourly Labor
C51: Photo Administrator | D51: 0 | E51: 0 | F51: 0 | G51: 0 | H51: 0 | I51: 0 | J51: 5040 | K51: =J51 -> 5040 | L51: =K51*(1+$D$4) -> 5216.4 | M51: =L51 -> 5216.4 | N51: =M51 -> 5216.4 | O51: =N51 -> 5216.4 | P51: =O51*(1+$D$4) -> 5398.974 | Q51: =P51 -> 5398.974 | R51: =Q51 -> 5398.974 | S51: =R51 -> 5398.974 | T51: =P51*(1+$D$4) -> 5587.9381 | U51: =T51 -> 5587.9381 | V51: =U51 -> 5587.9381 | W51: =V51 -> 5587.9381 | X51: =W51 -> 5587.9381 | Y51: =X51 -> 5587.9381 | Z51: =Y51 -> 5587.9381 | AA51: =Z51 -> 5587.9381
C52: Models (hourly/not professional) | D52: 0 | E52: 0 | F52: 0 | G52: 0 | H52: 0 | I52: 0 | J52: 5040 | K52: =J52 -> 5040 | L52: =K52*(1+$D$4) -> 5216.4 | M52: =L52 -> 5216.4 | N52: =M52 -> 5216.4 | O52: =N52 -> 5216.4 | P52: =O52*(1+$D$4) -> 5398.974 | Q52: =P52 -> 5398.974 | R52: =Q52 -> 5398.974 | S52: =R52 -> 5398.974 | T52: =P52*(1+$D$4) -> 5587.9381 | U52: =T52 -> 5587.9381 | V52: =U52 -> 5587.9381 | W52: =V52 -> 5587.9381 | X52: =W52 -> 5587.9381 | Y52: =X52 -> 5587.9381 | Z52: =Y52 -> 5587.9381 | AA52: =Z52 -> 5587.9381
B54: Hiring Plan
C55: Administration | D55: =SUM(D56:D58) -> 0 | E55: =SUM(E56:E58) -> 0 | F55: =SUM(F56:F58) -> 0 | G55: =SUM(G56:G58) -> 2 | H55: =SUM(H56:H58) -> 2 | I55: =SUM(I56:I58) -> 2 | J55: =SUM(J56:J58) -> 2 | K55: =SUM(K56:K58) -> 2 | ... AA55: =SUM(AA56:AA58) -> 2
C56: CEO | D56: 0 | E56: 0 | F56: 0 | G56: 1 | H56: =$G$56 -> 1 | I56: =$G$56 -> 1 | J56: =$G$56 -> 1 | K56: =$G$56 -> 1 | L56: =$G$56 -> 1 | M56: =$G$56 -> 1 | N56: =$G$56 -> 1 | O56: =$G$56 -> 1 | ... AA56: =$G$56 -> 1
C57: CPO | D57: 0 | E57: 0 | F57: 0 | G57: 1 | H57: =$G$57 -> 1 | I57: =$G$57 -> 1 | J57: =$G$57 -> 1 | K57: =$G$57 -> 1 | L57: =$G$57 -> 1 | M57: =$G$57 -> 1 | N57: =$G$57 -> 1 | O57: =$G$57 -> 1 | ... AA57: =$G$57 -> 1
C58: EA | D58: 0 | E58: 0 | F58: 0 | G58: 0 | H58: 0 | I58: 0 | J58: 0 | K58: =$J$58 -> 0 | L58: =$J$58 -> 0 | M58: =$J$58 -> 0 | N58: =$J$58 -> 0 | O58: =$J$58 -> 0 | P58: =O58 -> 0 | Q58: =P58 -> 0 | R58: =Q58 -> 0 | S58: =R58 -> 0 | T58: =S58 -> 0 | U58: =T58 -> 0 | V58: =U58 -> 0 | W58: =V58 -> 0 | ... AA58: =Z58 -> 0
C59: Technology | D59: =SUM(D60:D71) -> 0 | E59: =SUM(E60:E71) -> 0 | F59: =SUM(F60:F71) -> 0 | G59: =SUM(G60:G71) -> 0 | H59: =SUM(H60:H71) -> 0 | I59: =SUM(I60:I71) -> 0 | J59: =SUM(J60:J71) -> 4 | K59: =SUM(K60:K71) -> 4 | ... AA59: =SUM(AA60:AA71) -> 10
C60: Director - Engineering | D60: =IF(D12>0,1,0) -> 0 | E60: =IF(E12>0,1,0) -> 0 | F60: =IF(F12>0,1,0) -> 0 | G60: =IF(G12>0,1,0) -> 0 | H60: =IF(H12>0,1,0) -> 0 | I60: =IF(I12>0,1,0) -> 0 | J60: =IF(J12>0,1,0) -> 0 | K60: =IF(K12>0,1,0) -> 0 | ... AA60: =IF(AA12>0,1,0) -> 0
C61: AI Engineer | D61: =D14 -> 0 | E61: =E14 -> 0 | F61: =F14 -> 0 | G61: =G14 -> 0 | H61: =H14 -> 0 | I61: =I14 -> 0 | J61: =J14 -> 2 | K61: =K14 -> 2 | ... AA61: =AA14 -> 4
C62: Engineers | D62: =D16 -> 0 | E62: =E16 -> 0 | F62: =F16 -> 0 | G62: =G16 -> 0 | H62: =H16 -> 0 | I62: =I16 -> 0 | J62: =J16 -> 2 | K62: =K16 -> 2 | ... AA62: =AA16 -> 4
C63: Dev Ops | D63: =IF(D17>0,1,0) -> 0 | E63: =IF(E17>0,1,0) -> 0 | F63: =IF(F17>0,1,0) -> 0 | G63: =IF(G17>0,1,0) -> 0 | H63: =IF(H17>0,1,0) -> 0 | I63: =IF(I17>0,1,0) -> 0 | J63: =IF(J17>0,1,0) -> 0 | K63: =IF(K17>0,1,0) -> 0 | ... AA63: =IF(AA17>0,1,0) -> 1
C64: Director - Product | D64: =IF(D18>0,1,0) -> 0 | E64: =IF(E18>0,1,0) -> 0 | F64: =IF(F18>0,1,0) -> 0 | G64: =IF(G18>0,1,0) -> 0 | H64: =IF(H18>0,1,0) -> 0 | I64: =IF(I18>0,1,0) -> 0 | J64: =IF(J18>0,1,0) -> 0 | K64: =IF(K18>0,1,0) -> 0 | ... AA64: =IF(AA18>0,1,0) -> 0
C65: Product Manager | D65: =IF(D19>0,1,0) -> 0 | E65: =IF(E19>0,1,0) -> 0 | F65: =IF(F19>0,1,0) -> 0 | G65: =IF(G19>0,1,0) -> 0 | H65: =IF(H19>0,1,0) -> 0 | I65: =IF(I19>0,1,0) -> 0 | J65: =IF(J19>0,1,0) -> 0 | K65: =IF(K19>0,1,0) -> 0 | ... AA65: =IF(AA19>0,1,0) -> 0
C66: Project Manager | D66: =IF(D20>0,1,0) -> 0 | E66: =IF(E20>0,1,0) -> 0 | F66: =IF(F20>0,1,0) -> 0 | G66: =IF(G20>0,1,0) -> 0 | H66: =IF(H20>0,1,0) -> 0 | I66: =IF(I20>0,1,0) -> 0 | J66: =IF(J20>0,1,0) -> 0 | K66: =IF(K20>0,1,0) -> 0 | ... AA66: =IF(AA20>0,1,0) -> 0
C67: IT Engineer | D67: =IF(D21>0,1,0) -> 0 | E67: =IF(E21>0,1,0) -> 0 | F67: =IF(F21>0,1,0) -> 0 | G67: =IF(G21>0,1,0) -> 0 | H67: =IF(H21>0,1,0) -> 0 | I67: =IF(I21>0,1,0) -> 0 | J67: =IF(J21>0,1,0) -> 0 | K67: =IF(K21>0,1,0) -> 0 | ... AA67: =IF(AA21>0,1,0) -> 0
C68: UI Designer | D68: =IF(D22>0,1,0) -> 0 | E68: =IF(E22>0,1,0) -> 0 | F68: =IF(F22>0,1,0) -> 0 | G68: =IF(G22>0,1,0) -> 0 | H68: =IF(H22>0,1,0) -> 0 | I68: =IF(I22>0,1,0) -> 0 | J68: =IF(J22>0,1,0) -> 0 | K68: =IF(K22>0,1,0) -> 0 | ... AA68: =IF(AA22>0,1,0) -> 0
C69: UX Designer | D69: =IF(D23>0,1,0) -> 0 | E69: =IF(E23>0,1,0) -> 0 | F69: =IF(F23>0,1,0) -> 0 | G69: =IF(G23>0,1,0) -> 0 | H69: =IF(H23>0,1,0) -> 0 | I69: =IF(I23>0,1,0) -> 0 | J69: =IF(J23>0,1,0) -> 0 | K69: =IF(K23>0,1,0) -> 0 | ... AA69: =IF(AA23>0,1,0) -> 1
C70: Data Analyst | D70: =IF(D24>0,1,0) -> 0 | E70: =IF(E24>0,1,0) -> 0 | F70: =IF(F24>0,1,0) -> 0 | G70: =IF(G24>0,1,0) -> 0 | H70: =IF(H24>0,1,0) -> 0 | I70: =IF(I24>0,1,0) -> 0 | J70: =IF(J24>0,1,0) -> 0 | K70: =IF(K24>0,1,0) -> 0 | ... AA70: =IF(AA24>0,1,0) -> 0
C71: Data Scientist | D71: =IF(D25>0,1,0) -> 0 | E71: =IF(E25>0,1,0) -> 0 | F71: =IF(F25>0,1,0) -> 0 | G71: =IF(G25>0,1,0) -> 0 | H71: =IF(H25>0,1,0) -> 0 | I71: =IF(I25>0,1,0) -> 0 | J71: =IF(J25>0,1,0) -> 0 | K71: =IF(K25>0,1,0) -> 0 | ... AA71: =IF(AA25>0,1,0) -> 0
C72: Marketing | D72: =SUM(D73:D82) -> 0 | E72: =SUM(E73:E82) -> 0 | F72: =SUM(F73:F82) -> 0 | G72: =SUM(G73:G82) -> 0 | H72: =SUM(H73:H82) -> 0 | I72: =SUM(I73:I82) -> 0 | J72: =SUM(J73:J82) -> 1 | K72: =SUM(K73:K82) -> 1 | ... AA72: =SUM(AA73:AA82) -> 5.035
C73: VP Marketing | D73: =IF(D27>0,1,0) -> 0 | E73: =IF(E27>0,1,0) -> 0 | F73: =IF(F27>0,1,0) -> 0 | G73: =IF(G27>0,1,0) -> 0 | H73: =IF(H27>0,1,0) -> 0 | I73: =IF(I27>0,1,0) -> 0 | J73: =IF(J27>0,1,0) -> 0 | K73: =IF(K27>0,1,0) -> 0 | ... AA73: =IF(AA27>0,1,0) -> 1
C74: =C28 -> Sr. Manager Marketing | D74: =IF(D28>0,1,0) -> 0 | E74: =IF(E28>0,1,0) -> 0 | F74: =IF(F28>0,1,0) -> 0 | G74: =IF(G28>0,1,0) -> 0 | H74: =IF(H28>0,1,0) -> 0 | I74: =IF(I28>0,1,0) -> 0 | J74: =IF(J28>0,1,0) -> 1 | K74: =IF(K28>0,1,0) -> 1 | ... AA74: =IF(AA28>0,1,0) -> 1
C75: Copywriter | D75: =IF(D29>0,1,0) -> 0 | E75: =IF(E29>0,1,0) -> 0 | F75: =IF(F29>0,1,0) -> 0 | G75: =IF(G29>0,1,0) -> 0 | H75: =IF(H29>0,1,0) -> 0 | I75: =IF(I29>0,1,0) -> 0 | J75: =IF(J29>0,1,0) -> 0 | K75: =IF(K29>0,1,0) -> 0 | ... AA75: =IF(AA29>0,1,0) -> 0
C76: Designer | D76: =IF(D30>0,1,0) -> 0 | E76: =IF(E30>0,1,0) -> 0 | F76: =IF(F30>0,1,0) -> 0 | G76: =IF(G30>0,1,0) -> 0 | H76: =IF(H30>0,1,0) -> 0 | I76: =IF(I30>0,1,0) -> 0 | J76: =IF(J30>0,1,0) -> 0 | K76: =IF(K30>0,1,0) -> 0 | ... AA76: =IF(AA30>0,1,0) -> 0
C77: Search | D77: =IF(D31>0,1,0) -> 0 | E77: =IF(E31>0,1,0) -> 0 | F77: =IF(F31>0,1,0) -> 0 | G77: =IF(G31>0,1,0) -> 0 | H77: =IF(H31>0,1,0) -> 0 | I77: =IF(I31>0,1,0) -> 0 | J77: =IF(J31>0,1,0) -> 0 | K77: =IF(K31>0,1,0) -> 0 | ... AA77: =IF(AA31>0,1,0) -> 0
C78: Display/Partnerships | D78: =IF(D32>0,1,0) -> 0 | E78: =IF(E32>0,1,0) -> 0 | F78: =IF(F32>0,1,0) -> 0 | G78: =IF(G32>0,1,0) -> 0 | H78: =IF(H32>0,1,0) -> 0 | I78: =IF(I32>0,1,0) -> 0 | J78: =IF(J32>0,1,0) -> 0 | K78: =IF(K32>0,1,0) -> 0 | ... AA78: =IF(AA32>0,1,0) -> 0
C79: Email/SMS | D79: =IF(D33>0,1,0) -> 0 | E79: =IF(E33>0,1,0) -> 0 | F79: =IF(F33>0,1,0) -> 0 | G79: =IF(G33>0,1,0) -> 0 | H79: =IF(H33>0,1,0) -> 0 | I79: =IF(I33>0,1,0) -> 0 | J79: =IF(J33>0,1,0) -> 0 | K79: =IF(K33>0,1,0) -> 0 | ... AA79: =IF(AA33>0,1,0) -> 0
C80: Director - Business Development | D80: =IF(D34>0,1,0) -> 0 | E80: =IF(E34>0,1,0) -> 0 | F80: =IF(F34>0,1,0) -> 0 | G80: =IF(G34>0,1,0) -> 0 | H80: =IF(H34>0,1,0) -> 0 | I80: =IF(I34>0,1,0) -> 0 | J80: =IF(J34>0,1,0) -> 0 | K80: =IF(K34>0,1,0) -> 0 | ... AA80: =IF(AA34>0,1,0) -> 1
C81: Business Development | D81: =IF(D35>0,1,0) -> 0 | E81: =IF(E35>0,1,0) -> 0 | F81: =IF(F35>0,1,0) -> 0 | G81: =IF(G35>0,1,0) -> 0 | H81: =IF(H35>0,1,0) -> 0 | I81: =IF(I35>0,1,0) -> 0 | J81: =IF(J35>0,1,0) -> 0 | K81: =IF(K35>0,1,0) -> 0 | ... Q81: =IF(Q35>0,1,0) -> 0 | R81: =IF(R35>0,R36,0) -> 1 | S81: =IF(S35>0,S36,0) -> 1 | T81: =IF(T35>0,T36,0) -> 1.035 | U81: =IF(U35>0,U36,0) -> 1.035 | V81: =IF(V35>0,V36,0) -> 1.035 | W81: =IF(W35>0,W36,0) -> 1.035 | X81: =IF(X35>0,X36,0) -> 1.035 | Y81: =IF(Y35>0,Y36,0) -> 1.035 | ... AA81: =IF(AA35>0,AA36,0) -> 1.035
C82: Customer Service | D82: =IF(D37>0,1,0) -> 0 | E82: =IF(E37>0,1,0) -> 0 | F82: =IF(F37>0,1,0) -> 0 | G82: =IF(G37>0,1,0) -> 0 | H82: =IF(H37>0,1,0) -> 0 | I82: =IF(I37>0,1,0) -> 0 | J82: =IF(J37>0,1,0) -> 0 | K82: =IF(K37>0,1,0) -> 0 | ... AA82: =IF(AA37>0,1,0) -> 1
C83: Editorial | D83: =SUM(D84:D85) -> 0 | E83: =SUM(E84:E85) -> 0 | F83: =SUM(F84:F85) -> 0 | G83: =SUM(G84:G85) -> 0 | H83: =SUM(H84:H85) -> 0 | I83: =SUM(I84:I85) -> 0 | J83: =SUM(J84:J85) -> 0 | K83: =SUM(K84:K85) -> 0 | ... AA83: =SUM(AA84:AA85) -> 2
C84: Fashion Editor | D84: 0 | E84: 0 | F84: 0 | G84: 0 | H84: 0 | I84: 0 | J84: 0 | K84: 0 | L84: =K84 -> 0 | M84: 0 | N84: =M84 -> 0 | O84: =N84 -> 0 | P84: =O84 -> 0 | Q84: =P84 -> 0 | R84: =Q84 -> 0 | S84: =R84 -> 0 | T84: =S84 -> 0 | U84: =T84 -> 0 | V84: 1 | W84: =V84 -> 1 | X84: =W84 -> 1 | Y84: =X84 -> 1 | Z84: =Y84 -> 1 | AA84: =Z84 -> 1
C85: Fashion Associate | D85: 0 | E85: 0 | F85: 0 | G85: 0 | H85: 0 | I85: 0 | J85: 0 | K85: 0 | L85: =K85 -> 0 | M85: =L85 -> 0 | N85: =M85 -> 0 | O85: =N85 -> 0 | P85: =O85 -> 0 | Q85: =P85 -> 0 | R85: =Q85 -> 0 | S85: =R85 -> 0 | T85: 1 | U85: =T85 -> 1 | V85: =U85 -> 1 | W85: =V85 -> 1 | X85: =W85 -> 1 | Y85: =X85 -> 1 | Z85: =Y85 -> 1 | AA85: =Z85 -> 1
C86: HR / Recruitment | D86: =SUM(D87:D88) -> 0 | E86: =SUM(E87:E88) -> 0 | F86: =SUM(F87:F88) -> 0 | G86: =SUM(G87:G88) -> 0 | H86: =SUM(H87:H88) -> 0 | I86: =SUM(I87:I88) -> 0 | J86: =SUM(J87:J88) -> 0 | K86: =SUM(K87:K88) -> 0 | ... AA86: =SUM(AA87:AA88) -> 2
C87: HR Manager | D87: 0 | E87: 0 | F87: 0 | G87: 0 | H87: 0 | I87: 0 | J87: 0 | K87: 0 | L87: 0 | M87: 0 | N87: 0 | O87: 0 | P87: =O87 -> 0 | Q87: =P87 -> 0 | R87: =Q87 -> 0 | S87: =R87 -> 0 | T87: =S87 -> 0 | U87: =T87 -> 0 | V87: 1 | W87: =V87 -> 1 | X87: =W87 -> 1 | Y87: =X87 -> 1 | Z87: =Y87 -> 1 | AA87: =Z87 -> 1
C88: Recruiter | D88: 0 | E88: 0 | F88: 0 | G88: 0 | H88: 0 | I88: =H88 -> 0 | J88: =I88 -> 0 | K88: =J88 -> 0 | L88: 0 | M88: 0 | N88: =M88 -> 0 | O88: =N88 -> 0 | P88: =O88 -> 0 | Q88: =P88 -> 0 | R88: =Q88 -> 0 | S88: =R88 -> 0 | T88: 1 | U88: =T88 -> 1 | V88: =U88 -> 1 | W88: =V88 -> 1 | X88: =W88 -> 1 | Y88: =X88 -> 1 | Z88: =Y88 -> 1 | AA88: =Z88 -> 1
C89: General Counsel | D89: 0 | E89: 0 | F89: 0 | G89: 0 | H89: 0 | I89: 0 | J89: 0 | K89: 0 | L89: 0 | M89: =L89 -> 0 | N89: 0 | O89: =$N$89 -> 0 | P89: =O89 -> 0 | Q89: =P89 -> 0 | R89: =Q89 -> 0 | S89: =R89 -> 0 | T89: =S89 -> 0 | U89: =T89 -> 0 | V89: =U89 -> 0 | W89: =V89 -> 0 | ... AA89: =Z89 -> 0
C90: Finance & Accounts | D90: =SUM(D91:D94) -> 0 | E90: =SUM(E91:E94) -> 0 | F90: =SUM(F91:F94) -> 0 | G90: =SUM(G91:G94) -> 0 | H90: 0 | I90: 0 | J90: 0 | K90: 0 | L90: =SUM(L91:L94) -> 0 | M90: =SUM(M91:M94) -> 0 | N90: =SUM(N91:N94) -> 1 | O90: =SUM(O91:O94) -> 1 | P90: =SUM(P91:P94) -> 2 | Q90: =SUM(Q91:Q94) -> 2 | R90: =SUM(R91:R94) -> 2 | S90: =SUM(S91:S94) -> 2 | ... AA90: =SUM(AA91:AA94) -> 2
C91: CFO | D91: 0 | E91: 0 | F91: 0 | G91: 0 | H91: 0 | I91: 0 | J91: 0 | K91: 0 | L91: 0 | M91: 0 | N91: 0 | O91: 0 | P91: 0 | Q91: =P91 -> 0 | R91: =Q91 -> 0 | S91: =R91 -> 0 | T91: =S91 -> 0 | U91: =T91 -> 0 | V91: =U91 -> 0 | W91: =V91 -> 0 | X91: =W91 -> 0 | ... AA91: =Z91 -> 0
C92: Manager - Finance | D92: 0 | E92: 0 | F92: 0 | G92: 0 | H92: 0 | I92: 0 | J92: 0 | K92: 0 | L92: 0 | M92: =L92 -> 0 | N92: =M92 -> 0 | O92: 0 | P92: 0 | Q92: =P92 -> 0 | R92: =Q92 -> 0 | S92: =R92 -> 0 | T92: =S92 -> 0 | U92: =T92 -> 0 | V92: =U92 -> 0 | W92: =V92 -> 0 | X92: =W92 -> 0 | ... AA92: =Z92 -> 0
C93: Accounting Manager | D93: 0 | E93: 0 | F93: 0 | G93: =F93 -> 0 | H93: 0 | I93: =H93 -> 0 | J93: 0 | K93: =J93 -> 0 | L93: 0 | M93: 0 | N93: 1 | O93: =N93 -> 1 | P93: =O93 -> 1 | Q93: =P93 -> 1 | R93: =Q93 -> 1 | S93: =R93 -> 1 | T93: =S93 -> 1 | U93: =T93 -> 1 | V93: =U93 -> 1 | ... AA93: =Z93 -> 1
C94: Accounts Payable | D94: 0 | E94: 0 | F94: =E94 -> 0 | G94: =F94 -> 0 | H94: 0 | I94: 0 | J94: 0 | K94: 0 | L94: 0 | M94: =L94 -> 0 | N94: 0 | O94: 0 | P94: 1 | Q94: =P94 -> 1 | R94: =Q94 -> 1 | S94: =R94 -> 1 | T94: =S94 -> 1 | U94: =T94 -> 1 | V94: =U94 -> 1 | W94: =V94 -> 1 | X94: =W94 -> 1 | ... AA94: =Z94 -> 1
C95: Photography Hourly Labor | D95: =SUM(D96:D97) -> 0 | E95: =SUM(E96:E97) -> 0 | F95: =SUM(F96:F97) -> 0 | G95: =SUM(G96:G97) -> 0 | H95: =SUM(H96:H97) -> 0 | I95: =SUM(I96:I97) -> 0 | J95: =SUM(J96:J97) -> 0 | K95: =SUM(K96:K97) -> 0 | ... AA95: =SUM(AA96:AA97) -> 0
C96: Photo Administrator | D96: 0 | E96: 0 | F96: =E96 -> 0 | G96: =F96 -> 0 | H96: 0 | I96: 0 | J96: 0 | K96: =J96 -> 0 | L96: =K96 -> 0 | M96: =L96 -> 0 | N96: =M96 -> 0 | O96: =N96 -> 0 | P96: =O96 -> 0 | Q96: =P96 -> 0 | R96: =Q96 -> 0 | ... AA96: =Z96 -> 0
C97: Models (hourly/not professional) | D97: 0 | E97: 0 | F97: =E97 -> 0 | G97: =F97 -> 0 | H97: 0 | I97: 0 | J97: 0 | K97: =J97 -> 0 | L97: =K97 -> 0 | M97: =L97 -> 0 | N97: =M97 -> 0 | O97: =N97 -> 0 | P97: =O97 -> 0 | Q97: =P97 -> 0 | R97: =Q97 -> 0 | ... AA97: =Z97 -> 0
B98: Total FTE | D98: =D55+D59+D72+D90 -> 0 | E98: =E55+E59+E72+E90 -> 0 | F98: =F55+F59+F72+F90 -> 0 | G98: =SUM(G90,G89,G86,G83,G72,G59,G55) -> 2 | H98: =SUM(H95,H90,H89,H86,H83,H72,H59,H55) -> 2 | I98: =SUM(I95,I90,I89,I86,I83,I72,I59,I55) -> 2 | J98: =SUM(J95,J90,J89,J86,J83,J72,J59,J55) -> 7 | K98: =SUM(K95,K90,K89,K86,K83,K72,K59,K55) -> 7 | L98: =SUM(L95,L90,L89,L86,L83,L72,L59,L55) -> 7 | M98: =SUM(M95,M90,M89,M86,M83,M72,M59,M55) -> 6.5 | N98: =SUM(N95,N90,N89,N86,N83,N72,N59,N55) -> 7.5 | O98: =SUM(O95,O90,O89,O86,O83,O72,O59,O55) -> 7.5 | ... AA98: =SUM(AA95,AA90,AA89,AA86,AA83,AA72,AA59,AA55) -> 23.035
B100: Total Wages (in US$)
C101: Administration | D101: =SUM(D102:D104) -> 0 | E101: =SUM(E102:E104) -> 0 | F101: =SUM(F102:F104) -> 0 | G101: =SUM(G102:G104) -> 0 | H101: =SUM(H102:H104) -> 0 | I101: =SUM(I102:I104) -> 0 | J101: =SUM(J102:J104) -> 25000 | K101: =SUM(K102:K104) -> 25000 | ... AA101: =SUM(AA102:AA104) -> 79074
C102: CEO | D102: =D56*D8 -> 0 | E102: =E56*E8 -> 0 | F102: =F56*F8 -> 0 | G102: =G56*G8 -> 0 | H102: =H56*H8 -> 0 | I102: =I56*I8 -> 0 | J102: =J56*J8 -> 12500 | K102: =K56*K8 -> 12500 | ... AA102: =AA56*AA8 -> 36225
C103: CPO | D103: 0 | E103: 0 | F103: 0 | G103: =G57*G9 -> 0 | H103: =H57*H9 -> 0 | I103: =I57*I9 -> 0 | J103: =J57*J9 -> 12500 | K103: =K57*K9 -> 12500 | L103: =L57*L9 -> 40000 | M103: =M57*M9 -> 40000 | N103: =N57*N9 -> 40000 | ... AA103: =AA57*AA9 -> 42849
C104: EA | D104: =D58*D10 -> 0 | E104: =E58*E10 -> 0 | F104: =F58*F10 -> 0 | G104: =G58*G10 -> 0 | H104: =H58*H10 -> 0 | I104: =I58*I10 -> 0 | J104: =J58*J10 -> 0 | K104: =K58*K10 -> 0 | ... AA104: =AA58*AA10 -> 0
C105: Technology | D105: =SUM(D106:D117) -> 0 | E105: =SUM(E106:E117) -> 0 | F105: =SUM(F106:F117) -> 9500 | G105: =SUM(G106:G117) -> 28500 | H105: =SUM(H106:H117) -> 28500 | I105: =SUM(I106:I117) -> 28500 | J105: =SUM(J106:J117) -> 140000 | K105: =SUM(K106:K117) -> 140000 | ... AA105: =SUM(AA106:AA117) -> 383408.5
...

Sheet P&L
B2: Income Statement (in US$) | E2: Q1-17 | F2: Q2-17 | G2: Q3-17 | H2: Q4-17 | I2: 2017 | J2: Q1-18 | K2: Q2-18 | L2: Q3-18 | M2: Q4-18 | N2: 2018 | O2: Q1-19 | P2: Q2-19 | Q2: Q3-19 | R2: Q4-19 | S2: 2019 | T2: Q1-20 | U2: Q2-20 | V2: Q3-20 | W2: Q4-20 | X2: 2020 | Y2: Q1-21 | Z2: Q2-21 | AA2: Q3-21 | AB2: Q4-21 | AC2: 2021 | AD2: Q1-22 | AE2: Q2-22 | AF2: Q3-22 | AG2: Q4-22 | AH2: 2022
B3: Revenues | E3: =E4 -> 0 | F3: =F4 -> 0 | G3: =G4 -> 0 | H3: =H4 -> 0 | I3: =I4 -> 0 | J3: =J4 -> 0 | K3: =K4 -> 0 | L3: =L4 -> 0 | ... AH3: =AH4 -> 57483213
C4: Affiliate Marketing | E4: =SUM(E5:E6) -> 0 | F4: =SUM(F5:F6) -> 0 | G4: =SUM(G5:G6) -> 0 | H4: =SUM(H5:H6) -> 0 | I4: =SUM(E4:H4) -> 0 | J4: =SUM(J5:J6) -> 0 | K4: =SUM(K5:K6) -> 0 | L4: =SUM(L5:L6) -> 0 | M4: =SUM(M5:M6) -> 0 | N4: =SUM(J4:M4) -> 0 | O4: =SUM(O5:O6) -> 128907.18 | P4: =SUM(P5:P6) -> 234368.49 | Q4: =SUM(Q5:Q6) -> 366934.51 | R4: =SUM(R5:R6) -> 535504.02 | S4: =SUM(O4:R4) -> 1265714.2 | T4: =SUM(T5:T6) -> 779491.03 | U4: =SUM(U5:U6) -> 1149722.6 | V4: =SUM(V5:V6) -> 1722697.7 | W4: =SUM(W5:W6) -> 2391918.1 | X4: =SUM(T4:W4) -> 6043829.4 | Y4: =SUM(Y5:Y6) -> 3646864.4 | Z4: =SUM(Z5:Z6) -> 4740916.7 | AA4: =SUM(AA5:AA6) -> 6163197.6 | AB4: =SUM(AB5:AB6) -> 8012157.3 | AC4: =SUM(Y4:AB4) -> 22563136 | AD4: =SUM(AD5:AD6) -> 10523180 | AE4: =SUM(AE5:AE6) -> 12756675 | AF4: =SUM(AF5:AF6) -> 15462636 | AG4: =SUM(AG5:AG6) -> 18740722 | AH4: =SUM(AD4:AG4) -> 57483213
D5: Women | E5: ='Assumptions & Sensitivity'!E21 -> 0 | F5: ='Assumptions & Sensitivity'!F21 -> 0 | G5: ='Assumptions & Sensitivity'!G21 -> 0 | H5: ='Assumptions & Sensitivity'!H21 -> 0 | I5: =SUM(E5:H5) -> 0 | J5: ='Assumptions & Sensitivity'!I21 -> 0 | K5: ='Assumptions & Sensitivity'!J21 -> 0 | L5: ='Assumptions & Sensitivity'!K21 -> 0 | M5: ='Assumptions & Sensitivity'!L21 -> 0 | N5: =SUM(J5:M5) -> 0 | O5: ='Assumptions & Sensitivity'!M21 -> 111214.38 | P5: ='Assumptions & Sensitivity'!N21 -> 202198.44 | Q5: ='Assumptions & Sensitivity'!O21 -> 316567.26 | R5: ='Assumptions & Sensitivity'!P21 -> 461997.42 | S5: =SUM(O5:R5) -> 1091977.5 | T5: ='Assumptions & Sensitivity'!Q21 -> 672495.18 | U5: ='Assumptions & Sensitivity'!R21 -> 991908.42 | V5: ='Assumptions & Sensitivity'!S21 -> 1486235.9 | W5: ='Assumptions & Sensitivity'!T21 -> 2063597.4 | X5: =SUM(T5:W5) -> 5214236.9 | Y5: ='Assumptions & Sensitivity'!U21 -> 3146286.2 | Z5: ='Assumptions & Sensitivity'!V21 -> 4090168 | AA5: ='Assumptions & Sensitivity'!W21 -> 5317221.8 | AB5: ='Assumptions & Sensitivity'!X21 -> 6912390.7 | AC5: =SUM(Y5:AB5) -> 19466067 | AD5: ='Assumptions & Sensitivity'!Y21 -> 9078743.5 | AE5: ='Assumptions & Sensitivity'!Z21 -> 11005662 | AF5: ='Assumptions & Sensitivity'!AA21 -> 13340196 | AG5: ='Assumptions & Sensitivity'!AB21 -> 16168322 | AH5: =SUM(AD5:AG5) -> 49592924
D6: Men | E6: ='Assumptions & Sensitivity'!E38 -> 0 | F6: ='Assumptions & Sensitivity'!F38 -> 0 | G6: ='Assumptions & Sensitivity'!G38 -> 0 | H6: ='Assumptions & Sensitivity'!H38 -> 0 | I6: =SUM(E6:H6) -> 0 | J6: ='Assumptions & Sensitivity'!I38 -> 0 | K6: ='Assumptions & Sensitivity'!J38 -> 0 | L6: ='Assumptions & Sensitivity'!K38 -> 0 | M6: ='Assumptions & Sensitivity'!L38 -> 0 | N6: =SUM(J6:M6) -> 0 | O6: ='Assumptions & Sensitivity'!M38 -> 17692.8 | P6: ='Assumptions & Sensitivity'!N38 -> 32170.05 | Q6: ='Assumptions & Sensitivity'!O38 -> 50367.25 | R6: ='Assumptions & Sensitivity'!P38 -> 73506.6 | S6: =SUM(O6:R6) -> 173736.7 | T6: ='Assumptions & Sensitivity'!Q38 -> 106995.85 | U6: ='Assumptions & Sensitivity'!R38 -> 157814.15 | V6: ='Assumptions & Sensitivity'!S38 -> 236461.75 | W6: ='Assumptions & Sensitivity'!T38 -> 328320.75 | X6: =SUM(T6:W6) -> 829592.5 | Y6: ='Assumptions & Sensitivity'!U38 -> 500578.2 | Z6: ='Assumptions & Sensitivity'!V38 -> 650748.75 | AA6: ='Assumptions & Sensitivity'!W38 -> 845975.8 | AB6: ='Assumptions & Sensitivity'!X38 -> 1099766.6 | AC6: =SUM(Y6:AB6) -> 3097069.4 | AD6: ='Assumptions & Sensitivity'!Y38 -> 1444436.7 | AE6: ='Assumptions & Sensitivity'!Z38 -> 1751013 | AF6: ='Assumptions & Sensitivity'!AA38 -> 2122440 | AG6: ='Assumptions & Sensitivity'!AB38 -> 2572399.3 | AH6: =SUM(AD6:AG6) -> 7890289
B7: Gross Profits | E7: =E3 -> 0 | F7: =F3 -> 0 | G7: =G3 -> 0 | H7: =H3 -> 0 | I7: =SUM(E7:H7) -> 0 | J7: =J3 -> 0 | K7: =K3 -> 0 | L7: =L3 -> 0 | M7: =M3 -> 0 | N7: =SUM(J7:M7) -> 0 | O7: =O3 -> 128907.18 | P7: =P3 -> 234368.49 | Q7: =Q3 -> 366934.51 | R7: =R3 -> 535504.02 | S7: =SUM(O7:R7) -> 1265714.2 | T7: =T3 -> 779491.03 | U7: =U3 -> 1149722.6 | V7: =V3 -> 1722697.7 | W7: =W3 -> 2391918.1 | X7: =SUM(T7:W7) -> 6043829.4 | Y7: =Y3 -> 3646864.4 | Z7: =Z3 -> 4740916.7 | AA7: =AA3 -> 6163197.6 | AB7: =AB3 -> 8012157.3 | AC7: =SUM(Y7:AB7) -> 22563136 | AD7: =AD3 -> 10523180 | AE7: =AE3 -> 12756675 | AF7: =AF3 -> 15462636 | AG7: =AG3 -> 18740722 | AH7: =SUM(AD7:AG7) -> 57483213
C8: Less: Operating Costs | E8: ='Assumptions & Sensitivity'!E77 -> 30169.56 | F8: ='Assumptions & Sensitivity'!F77 -> 54637.7 | G8: ='Assumptions & Sensitivity'!G77 -> 48699.1 | H8: ='Assumptions & Sensitivity'!H77 -> 60067.14 | I8: =SUM(E8:H8) -> 193573.5 | J8: ='Assumptions & Sensitivity'!I77 -> 69000 | K8: ='Assumptions & Sensitivity'!J77 -> 69000 | L8: ='Assumptions & Sensitivity'!K77 -> 454266.56 | M8: ='Assumptions & Sensitivity'!L77 -> 502766.56 | N8: =SUM(J8:M8) -> 1095033.1 | O8: ='Assumptions & Sensitivity'!M77 -> 519485.99 | P8: ='Assumptions & Sensitivity'!N77 -> 517350.05 | Q8: ='Assumptions & Sensitivity'!O77 -> 566066.62 | R8: ='Assumptions & Sensitivity'!P77 -> 589179.57 | S8: =SUM(O8:R8) -> 2192082.2 | T8: ='Assumptions & Sensitivity'!Q77 -> 803425.06 | U8: ='Assumptions & Sensitivity'!R77 -> 1060751.9 | V8: ='Assumptions & Sensitivity'!S77 -> 1413074.6 | W8: ='Assumptions & Sensitivity'!T77 -> 1749229.9 | X8: =SUM(T8:W8) -> 5026481.5 | Y8: ='Assumptions & Sensitivity'!U77 -> 2354164.4 | Z8: ='Assumptions & Sensitivity'!V77 -> 2796618.3 | AA8: ='Assumptions & Sensitivity'!W77 -> 3493826.4 | AB8: ='Assumptions & Sensitivity'!X77 -> 4238131.9 | AC8: =SUM(Y8:AB8) -> 12882741 | AD8: ='Assumptions & Sensitivity'!Y77 -> 5303088 | AE8: ='Assumptions & Sensitivity'!Z77 -> 6087661.8 | AF8: ='Assumptions & Sensitivity'!AA77 -> 7181033.3 | AG8: ='Assumptions & Sensitivity'!AB77 -> 8341588.4 | AH8: =SUM(AD8:AG8) -> 26913371
B9: Profit (Losses) Before Taxes (PBT) | E9: =E7-E8 -> -30169.56 | F9: =F7-F8 -> -54637.7 | G9: =G7-G8 -> -48699.1 | H9: =H7-H8 -> -60067.14 | I9: =SUM(E9:H9) -> -193573.5 | J9: =J7-J8 -> -69000 | K9: =K7-K8 -> -69000 | L9: =L7-L8 -> -454266.56 | M9: =M7-M8 -> -502766.56 | N9: =SUM(J9:M9) -> -1095033.1 | O9: =O7-O8 -> -390578.81 | P9: =P7-P8 -> -282981.56 | Q9: =Q7-Q8 -> -199132.11 | R9: =R7-R8 -> -53675.548 | S9: =SUM(O9:R9) -> -926368.04 | T9: =T7-T8 -> -23934.033 | U9: =U7-U8 -> 88970.657 | V9: =V7-V8 -> 309623.05 | W9: =W7-W8 -> 642688.27 | X9: =SUM(T9:W9) -> 1017347.9 | Y9: =Y7-Y8 -> 1292700 | Z9: =Z7-Z8 -> 1944298.4 | AA9: =AA7-AA8 -> 2669371.3 | AB9: =AB7-AB8 -> 3774025.4 | AC9: =SUM(Y9:AB9) -> 9680395 | AD9: =AD7-AD8 -> 5220092.2 | AE9: =AE7-AE8 -> 6669012.9 | AF9: =AF7-AF8 -> 8281602.7 | AG9: =AG7-AG8 -> 10399133 | AH9: =SUM(AD9:AG9) -> 30569841
C10: Cumulative PBT | E10: =SUM($E$9:E9) -> -30169.56 | F10: =SUM($E$9:F9) -> -84807.26 | G10: =SUM($E$9:G9) -> -133506.36 | H10: =SUM($E$9:H9) -> -193573.5 | I10: =H10 -> -193573.5 | J10: =I10+J9 -> -262573.5 | K10: =J10+K9 -> -331573.5 | L10: =K10+L9 -> -785840.06 | M10: =L10+M9 -> -1288606.6 | N10: =M10 -> -1288606.6 | O10: =N10+O9 -> -1679185.4 | P10: =O10+P9 -> -1962167 | Q10: =P10+Q9 -> -2161299.1 | R10: =Q10+R9 -> -2214974.7 | S10: =R10 -> -2214974.7 | T10: =S10+T9 -> -2238908.7 | U10: =T10+U9 -> -2149938 | V10: =U10+V9 -> -1840315 | W10: =V10+W9 -> -1197626.7 | X10: =W10 -> -1197626.7 | Y10: =X10+Y9 -> 95073.242 | Z10: =Y10+Z9 -> 2039371.6 | AA10: =Z10+AA9 -> 4708742.9 | AB10: =AA10+AB9 -> 8482768.3 | AC10: =AB10 -> 8482768.3 | AD10: =AB10+AD9 -> 13702861 | AE10: =AD10+AE9 -> 20371873 | AF10: =AE10+AF9 -> 28653476 | AG10: =AF10+AG9 -> 39052609 | AH10: =AG10 -> 39052609
C11: Less: Taxes | E11: =IF(E9<=0,0,IF(E10<=0,0,(MIN(E9,E10)*'Assumptions & Sensitivity'!$D$94))) -> 0 | F11: =IF(F9<=0,0,IF(F10<=0,0,(MIN(F9,F10)*'Assumptions & Sensitivity'!$D$94))) -> 0 | G11: =IF(G9<=0,0,IF(G10<=0,0,(MIN(G9,G10)*'Assumptions & Sensitivity'!$D$94))) -> 0 | H11: =IF(H9<=0,0,IF(H10<=0,0,(MIN(H9,H10)*'Assumptions & Sensitivity'!$D$94))) -> 0 | I11: =SUM(E11:H11) -> 0 | J11: =IF(J9<=0,0,IF(J10<=0,0,(MIN(J9,J10)*'Assumptions & Sensitivity'!$D$94))) -> 0 | K11: =IF(K9<=0,0,IF(K10<=0,0,(MIN(K9,K10)*'Assumptions & Sensitivity'!$D$94))) -> 0 | L11: =IF(L9<=0,0,IF(L10<=0,0,(MIN(L9,L10)*'Assumptions & Sensitivity'!$D$94))) -> 0 | M11: =IF(M9<=0,0,IF(M10<=0,0,(MIN(M9,M10)*'Assumptions & Sensitivity'!$D$94))) -> 0 | N11: =SUM(J11:M11) -> 0 | O11: =IF(O9<=0,0,IF(O10<=0,0,(MIN(O9,O10)*'Assumptions & Sensitivity'!$D$94))) -> 0 | P11: =IF(P9<=0,0,IF(P10<=0,0,(MIN(P9,P10)*'Assumptions & Sensitivity'!$D$94))) -> 0 | Q11: =IF(Q9<=0,0,IF(Q10<=0,0,(MIN(Q9,Q10)*'Assumptions & Sensitivity'!$D$94))) -> 0 | R11: =IF(R9<=0,0,IF(R10<=0,0,(MIN(R9,R10)*'Assumptions & Sensitivity'!$D$94))) -> 0 | S11: =SUM(O11:R11) -> 0 | T11: =IF(T9<=0,0,IF(T10<=0,0,(MIN(T9,T10)*'Assumptions & Sensitivity'!$D$94))) -> 0 | U11: =IF(U9<=0,0,IF(U10<=0,0,(MIN(U9,U10)*'Assumptions & Sensitivity'!$D$94))) -> 0 | V11: =IF(V9<=0,0,IF(V10<=0,0,(MIN(V9,V10)*'Assumptions & Sensitivity'!$D$94))) -> 0 | W11: =IF(W9<=0,0,IF(W10<=0,0,(MIN(W9,W10)*'Assumptions & Sensitivity'!$D$94))) -> 0 | X11: =SUM(T11:W11) -> 0 | Y11: =IF(Y9<=0,0,IF(Y10<=0,0,(MIN(Y9,Y10)*'Assumptions & Sensitivity'!$D$94))) -> 19965.381 | Z11: =IF(Z9<=0,0,IF(Z10<=0,0,(MIN(Z9,Z10)*'Assumptions & Sensitivity'!$D$94))) -> 408302.66 | AA11: =IF(AA9<=0,0,IF(AA10<=0,0,(MIN(AA9,AA10)*'Assumptions & Sensitivity'!$D$94))) -> 560567.96 | AB11: =IF(AB9<=0,0,IF(AB10<=0,0,(MIN(AB9,AB10)*'Assumptions & Sensitivity'!$D$94))) -> 792545.33 | AC11: =SUM(Y11:AB11) -> 1781381.3 | AD11: =IF(AD9<=0,0,IF(AD10<=0,0,(MIN(AD9,AD10)*'Assumptions & Sensitivity'!$D$94))) -> 1096219.4 | AE11: =IF(AE9<=0,0,IF(AE10<=0,0,(MIN(AE9,AE10)*'Assumptions & Sensitivity'!$D$94))) -> 1400492.7 | AF11: =IF(AF9<=0,0,IF(AF10<=0,0,(MIN(AF9,AF10)*'Assumptions & Sensitivity'!$D$94))) -> 1739136.6 | AG11: =IF(AG9<=0,0,IF(AG10<=0,0,(MIN(AG9,AG10)*'Assumptions & Sensitivity'!$D$94))) -> 2183818 | AH11: =SUM(AD11:AG11) -> 6419666.7
B12: Net Profit | E12: =E9-E11 -> -30169.56 | F12: =F9-F11 -> -54637.7 | G12: =G9-G11 -> -48699.1 | H12: =H9-H11 -> -60067.14 | I12: =I9-I11 -> -193573.5 | J12: =J9-J11 -> -69000 | K12: =K9-K11 -> -69000 | L12: =L9-L11 -> -454266.56 | ... AH12: =AH9-AH11 -> 24150175

Sheet BS
B2: Balance Sheet | E2: 2016 | F2: Q1-17 | G2: Q2-17 | H2: Q3-17 | I2: Q4-17 | J2: 2017 | K2: Q1-18 | L2: Q2-18 | M2: Q3-18 | N2: Q4-18 | O2: 2018 | P2: Q1-19 | Q2: Q2-19 | R2: Q3-19 | S2: Q4-19 | T2: 2019 | U2: Q1-20 | V2: Q2-20 | W2: Q3-20 | X2: Q4-20 | Y2: 2020 | Z2: Q1-21 | AA2: Q2-21 | AB2: Q3-21 | AC2: Q4-21 | AD2: 2021 | AE2: Q1-22 | AF2: Q2-22 | AG2: Q3-22 | AH2: Q4-22 | AI2: 2022
B3: Current Liabilities & Provisions | E3: =SUM(E4:E4) -> 0 | F3: =SUM(F4:F4) -> 0 | G3: =SUM(G4:G4) -> 0 | H3: =SUM(H4:H4) -> 0 | I3: =SUM(I4:I4) -> 0 | J3: =I3 -> 0 | K3: =SUM(K4:K4) -> 15923.077 | L3: =SUM(L4:L4) -> 15923.077 | M3: =SUM(M4:M4) -> 104830.75 | N3: =SUM(N4:N4) -> 116023.05 | O3: =N3 -> 116023.05 | P3: =SUM(P4:P4) -> 119881.38 | Q3: =SUM(Q4:Q4) -> 119388.47 | R3: =SUM(R4:R4) -> 130630.76 | S3: =SUM(S4:S4) -> 135964.52 | T3: =S3 -> 135964.52 | U3: =SUM(U4:U4) -> 185405.78 | V3: =SUM(V4:V4) -> 244788.9 | W3: =SUM(W4:W4) -> 326094.15 | X3: =SUM(X4:X4) -> 403668.43 | Y3: =X3 -> 403668.43 | Z3: =SUM(Z4:Z4) -> 543268.71 | AA3: =SUM(AA4:AA4) -> 645373.46 | AB3: =SUM(AB4:AB4) -> 806267.63 | AC3: =SUM(AC4:AC4) -> 978030.44 | AD3: =AC3 -> 978030.44 | AE3: =SUM(AE4:AE4) -> 2972940.2 | AF3: =SUM(AF4:AF4) -> 1223789.5 | AG3: =SUM(AG4:AG4) -> 1404845 | AH3: =SUM(AH4:AH4) -> 1657161.5 | AI3: =AH3 -> 1657161.5
C4: [+] Accounts payable | F4: 0 | G4: 0 | H4: 0 | I4: 0 | J4: =I4 -> 0 | K4: =('Assumptions & Sensitivity'!$D$84/91)*'P&L'!J8 -> 15923.077 | L4: =('Assumptions & Sensitivity'!$D$84/91)*'P&L'!K8 -> 15923.077 | M4: =('Assumptions & Sensitivity'!$D$84/91)*'P&L'!L8 -> 104830.75 | N4: =('Assumptions & Sensitivity'!$D$84/91)*'P&L'!M8 -> 116023.05 | O4: =N4 -> 116023.05 | P4: =('Assumptions & Sensitivity'!$D$84/91)*'P&L'!O8 -> 119881.38 | Q4: =('Assumptions & Sensitivity'!$D$84/91)*'P&L'!P8 -> 119388.47 | R4: =('Assumptions & Sensitivity'!$D$84/91)*'P&L'!Q8 -> 130630.76 | S4: =('Assumptions & Sensitivity'!$D$84/91)*'P&L'!R8 -> 135964.52 | T4: =S4 -> 135964.52 | U4: =('Assumptions & Sensitivity'!$D$84/91)*'P&L'!T8 -> 185405.78 | V4: =('Assumptions & Sensitivity'!$D$84/91)*'P&L'!U8 -> 244788.9 | W4: =('Assumptions & Sensitivity'!$D$84/91)*'P&L'!V8 -> 326094.15 | X4: =('Assumptions & Sensitivity'!$D$84/91)*'P&L'!W8 -> 403668.43 | Y4: =X4 -> 403668.43 | Z4: =('Assumptions & Sensitivity'!$D$84/91)*'P&L'!Y8 -> 543268.71 | AA4: =('Assumptions & Sensitivity'!$D$84/91)*'P&L'!Z8 -> 645373.46 | AB4: =('Assumptions & Sensitivity'!$D$84/91)*'P&L'!AA8 -> 806267.63 | AC4: =('Assumptions & Sensitivity'!$D$84/91)*'P&L'!AB8 -> 978030.44 | AD4: =AC4 -> 978030.44 | AE4: =('Assumptions & Sensitivity'!$D$84/91)*'P&L'!AC8 -> 2972940.2 | AF4: =('Assumptions & Sensitivity'!$D$84/91)*'P&L'!AD8 -> 1223789.5 | AG4: =('Assumptions & Sensitivity'!$D$84/91)*'P&L'!AE8 -> 1404845 | AH4: =('Assumptions & Sensitivity'!$D$84/91)*'P&L'!AF8 -> 1657161.5 | AI4: =AH4 -> 1657161.5
B5: Shareholders Equity | E5: =SUM(E6:E7) -> 250000 | F5: =SUM(F6:F7) -> 219830.44 | G5: =SUM(G6:G7) -> 1165192.7 | H5: =SUM(H6:H7) -> 1116493.6 | I5: =SUM(I6:I7) -> 1056426.5 | J5: =I5 -> 1056426.5 | K5: =SUM(K6:K7) -> 987426.5 | L5: =SUM(L6:L7) -> 4918426.5 | M5: =SUM(M6:M7) -> 4464159.9 | N5: =SUM(N6:N7) -> 3961393.4 | O5: =N5 -> 3961393.4 | P5: =SUM(P6:P7) -> 3570814.6 | Q5: =SUM(Q6:Q7) -> 3287833 | R5: =SUM(R6:R7) -> 3088700.9 | S5: =SUM(S6:S7) -> 3035025.3 | T5: =S5 -> 3035025.3 | U5: =SUM(U6:U7) -> 3011091.3 | V5: =SUM(V6:V7) -> 3100062 | W5: =SUM(W6:W7) -> 3409685 | X5: =SUM(X6:X7) -> 4052373.3 | Y5: =X5 -> 4052373.3 | Z5: =SUM(Z6:Z7) -> 5325107.9 | AA5: =SUM(AA6:AA7) -> 6861103.6 | AB5: =SUM(AB6:AB7) -> 8969906.9 | AC5: =SUM(AC6:AC7) -> 11951387 | AD5: =AC5 -> 11951387 | AE5: =SUM(AE6:AE7) -> 11951387 | AF5: =SUM(AF6:AF7) -> 0 | AG5: =SUM(AG6:AG7) -> 0 | AH5: =SUM(AH6:AH7) -> 0 | AI5: =AH5 -> 0
C6: Paid-up Capital | E6: ='Assumptions & Sensitivity'!D86 -> 250000 | F6: ='Equity Schedule'!F12 -> 250000 | G6: ='Equity Schedule'!G12 -> 1250000 | H6: ='Equity Schedule'!H12 -> 1250000 | I6: ='Equity Schedule'!I12 -> 1250000 | J6: =I6 -> 1250000 | K6: ='Equity Schedule'!K12 -> 1250000 | L6: ='Equity Schedule'!L12 -> 5250000 | M6: ='Equity Schedule'!M12 -> 5250000 | N6: ='Equity Schedule'!N12 -> 5250000 | O6: =N6 -> 5250000 | P6: ='Equity Schedule'!P12 -> 5250000 | Q6: ='Equity Schedule'!Q12 -> 5250000 | R6: ='Equity Schedule'!R12 -> 5250000 | S6: ='Equity Schedule'!S12 -> 5250000 | T6: =S6 -> 5250000 | U6: ='Equity Schedule'!U12 -> 5250000 | V6: ='Equity Schedule'!V12 -> 5250000 | W6: ='Equity Schedule'!W12 -> 5250000 | X6: ='Equity Schedule'!X12 -> 5250000 | Y6: =X6 -> 5250000 | Z6: ='Equity Schedule'!Z12 -> 5250000 | AA6: ='Equity Schedule'!AA12 -> 5250000 | AB6: ='Equity Schedule'!AB12 -> 5250000 | AC6: ='Equity Schedule'!AC12 -> 5250000 | AD6: =AC6 -> 5250000 | AE6: ='Equity Schedule'!AD12 -> 5250000 | AF6: ='Equity Schedule'!AE12 -> 0 | AG6: ='Equity Schedule'!AF12 -> 0 | AH6: ='Equity Schedule'!AG12 -> 0 | AI6: =AH6 -> 0
C7: [+] Retained Earnings | E7: ='Equity Schedule'!E17 -> 0 | F7: ='Equity Schedule'!F17 -> -30169.56 | G7: ='Equity Schedule'!G17 -> -84807.26 | H7: ='Equity Schedule'!H17 -> -133506.36 | I7: ='Equity Schedule'!I17 -> -193573.5 | J7: =I7 -> -193573.5 | K7: ='Equity Schedule'!K17 -> -262573.5 | L7: ='Equity Schedule'!L17 -> -331573.5 | M7: ='Equity Schedule'!M17 -> -785840.06 | N7: ='Equity Schedule'!N17 -> -1288606.6 | O7: =N7 -> -1288606.6 | P7: ='Equity Schedule'!P17 -> -1679185.4 | Q7: ='Equity Schedule'!Q17 -> -1962167 | R7: ='Equity Schedule'!R17 -> -2161299.1 | S7: ='Equity Schedule'!S17 -> -2214974.7 | T7: =S7 -> -2214974.7 | U7: ='Equity Schedule'!U17 -> -2238908.7 | V7: ='Equity Schedule'!V17 -> -2149938 | W7: ='Equity Schedule'!W17 -> -1840315 | X7: ='Equity Schedule'!X17 -> -1197626.7 | Y7: =X7 -> -1197626.7 | Z7: ='Equity Schedule'!Z17 -> 75107.861 | AA7: ='Equity Schedule'!AA17 -> 1611103.6 | AB7: ='Equity Schedule'!AB17 -> 3719906.9 | AC7: ='Equity Schedule'!AC17 -> 6701386.9 | AD7: =AC7 -> 6701386.9 | AE7: ='Equity Schedule'!AD17 -> 6701386.9 | AF7: ='Equity Schedule'!AE17 -> 0 | AG7: ='Equity Schedule'!AF17 -> 0 | AH7: ='Equity Schedule'!AG17 -> 0 | AI7: =AH7 -> 0
B8: Total Liabilities & Shareholders' Equity | E8: =E3+E5 -> 250000 | F8: =F3+F5 -> 219830.44 | G8: =G3+G5 -> 1165192.7 | H8: =H3+H5 -> 1116493.6 | I8: =I3+I5 -> 1056426.5 | J8: =I8 -> 1056426.5 | K8: =K3+K5 -> 1003349.6 | L8: =L3+L5 -> 4934349.6 | M8: =M3+M5 -> 4568990.7 | N8: =N3+N5 -> 4077416.4 | O8: =N8 -> 4077416.4 | P8: =P3+P5 -> 3690695.9 | Q8: =Q3+Q5 -> 3407221.5 | R8: =R3+R5 -> 3219331.6 | S8: =S3+S5 -> 3170989.8 | T8: =S8 -> 3170989.8 | U8: =U3+U5 -> 3196497.1 | V8: =V3+V5 -> 3344850.9 | W8: =W3+W5 -> 3735779.2 | X8: =X3+X5 -> 4456041.7 | Y8: =X8 -> 4456041.7 | Z8: =Z3+Z5 -> 5868376.6 | AA8: =AA3+AA5 -> 7506477 | AB8: =AB3+AB5 -> 9776174.5 | AC8: =AC3+AC5 -> 12929417 | AD8: =AC8 -> 12929417 | AE8: =AE3+AE5 -> 14924327 | AF8: =AF3+AF5 -> 1223789.5 | AG8: =AG3+AG5 -> 1404845 | AH8: =AH3+AH5 -> 1657161.5 | AI8: =AH8 -> 1657161.5
B9: Current Assets | E9: =SUM(E10:E11) -> 250000 | F9: =SUM(F10:F11) -> 219830.44 | G9: =SUM(G10:G11) -> 1165192.7 | H9: =SUM(H10:H11) -> 1116493.6 | I9: =SUM(I10:I11) -> 1056426.5 | J9: =I9 -> 1056426.5 | K9: =SUM(K10:K11) -> 1003349.6 | L9: =SUM(L10:L11) -> 4934349.6 | M9: =SUM(M10:M11) -> 4568990.7 | N9: =SUM(N10:N11) -> 4077416.4 | O9: =N9 -> 4077416.4 | P9: =SUM(P10:P11) -> 3690695.9 | Q9: =SUM(Q10:Q11) -> 3407221.5 | R9: =SUM(R10:R11) -> 3219331.6 | S9: =SUM(S10:S11) -> 3170989.8 | T9: =S9 -> 3170989.8 | U9: =SUM(U10:U11) -> 3196497.1 | V9: =SUM(V10:V11) -> 3344850.9 | W9: =SUM(W10:W11) -> 3735779.2 | X9: =SUM(X10:X11) -> 4456041.7 | Y9: =X9 -> 4456041.7 | Z9: =SUM(Z10:Z11) -> 5868376.6 | AA9: =SUM(AA10:AA11) -> 7506477 | AB9: =SUM(AB10:AB11) -> 9776174.5 | AC9: =SUM(AC10:AC11) -> 12929417 | AD9: =AC9 -> 12929417 | AE9: =SUM(AE10:AE11) -> 17726443 | AF9: =SUM(AF10:AF11) -> 21656241 | AG9: =SUM(AG10:AG11) -> 25934380 | AH9: =SUM(AH10:AH11) -> 31539714 | AI9: =AH9 -> 31539714
B10: Cash & Cash Equivalent | E10: =E8 -> 250000 | F10: =CFS!D13 -> 219830.44 | G10: =CFS!E13 -> 1165192.7 | H10: =CFS!F13 -> 1116493.6 | I10: =CFS!G13 -> 1056426.5 | J10: =I10 -> 1056426.5 | K10: =CFS!I13 -> 1003349.6 | L10: =CFS!J13 -> 4934349.6 | M10: =CFS!K13 -> 4568990.7 | N10: =CFS!L13 -> 4077416.4 | O10: =N10 -> 4077416.4 | P10: =CFS!N13 -> 3648199.1 | Q10: =CFS!O13 -> 3329957.1 | R10: =CFS!P13 -> 3098364.2 | S10: =CFS!Q13 -> 2994450.1 | T10: =S10 -> 2994450.1 | U10: =CFS!S13 -> 2939522 | V10: =CFS!T13 -> 2965821.4 | W10: =CFS!U13 -> 3167856.8 | X10: =CFS!V13 -> 3667497.3 | Y10: =X10 -> 3667497.3 | Z10: =CFS!X13 -> 4666113.6 | AA10: =CFS!Y13 -> 5943537.5 | AB10: =CFS!Z13 -> 7744351.1 | AC10: =CFS!AA13 -> 10288047 | AD10: =AC10 -> 10288047 | AE10: =CFS!AB13 -> 10288047 | AF10: =CFS!AC13 -> 18187060 | AG10: =CFS!AD13 -> 21728883 | AH10: =CFS!AE13 -> 26442142 | AI10: =AH10 -> 26442142
B11: Accounts Receivables | E11: 0 | F11: =('Assumptions & Sensitivity'!$D$83/91)*'P&L'!E3 -> 0 | G11: =('Assumptions & Sensitivity'!$D$83/91)*'P&L'!F3 -> 0 | H11: =('Assumptions & Sensitivity'!$D$83/91)*'P&L'!G3 -> 0 | I11: =('Assumptions & Sensitivity'!$D$83/91)*'P&L'!H3 -> 0 | J11: =I11 -> 0 | K11: =('Assumptions & Sensitivity'!$D$83/91)*'P&L'!J3 -> 0 | L11: =('Assumptions & Sensitivity'!$D$83/91)*'P&L'!K3 -> 0 | M11: =('Assumptions & Sensitivity'!$D$83/91)*'P&L'!L3 -> 0 | N11: =('Assumptions & Sensitivity'!$D$83/91)*'P&L'!M3 -> 0 | O11: =N11 -> 0 | P11: =('Assumptions & Sensitivity'!$D$83/91)*'P&L'!O3 -> 42496.873 | Q11: =('Assumptions & Sensitivity'!$D$83/91)*'P&L'!P3 -> 77264.337 | R11: =('Assumptions & Sensitivity'!$D$83/91)*'P&L'!Q3 -> 120967.42 | S11: =('Assumptions & Sensitivity'!$D$83/91)*'P&L'!R3 -> 176539.79 | T11: =S11 -> 176539.79 | U11: =('Assumptions & Sensitivity'!$D$83/91)*'P&L'!T3 -> 256975.06 | V11: =('Assumptions & Sensitivity'!$D$83/91)*'P&L'!U3 -> 379029.42 | W11: =('Assumptions & Sensitivity'!$D$83/91)*'P&L'!V3 -> 567922.32 | X11: =('Assumptions & Sensitivity'!$D$83/91)*'P&L'!W3 -> 788544.45 | Y11: =X11 -> 788544.45 | Z11: =('Assumptions & Sensitivity'!$D$83/91)*'P&L'!Y3 -> 1202263 | AA11: =('Assumptions & Sensitivity'!$D$83/91)*'P&L'!Z3 -> 1562939.6 | AB11: =('Assumptions & Sensitivity'!$D$83/91)*'P&L'!AA3 -> 2031823.4 | AC11: =('Assumptions & Sensitivity'!$D$83/91)*'P&L'!AB3 -> 2641370.5 | AD11: =AC11 -> 2641370.5 | AE11: =('Assumptions & Sensitivity'!$D$83/91)*'P&L'!AC3 -> 7438396.5 | AF11: =('Assumptions & Sensitivity'!$D$83/91)*'P&L'!AD3 -> 3469180.3 | AG11: =('Assumptions & Sensitivity'!$D$83/91)*'P&L'!AE3 -> 4205497.2 | AH11: =('Assumptions & Sensitivity'!$D$83/91)*'P&L'!AF3 -> 5097572.3 | AI11: =AH11 -> 5097572.3
B12: Total Assets | E12: =E9 -> 250000 | F12: =F9 -> 219830.44 | G12: =G9 -> 1165192.7 | H12: =H9 -> 1116493.6 | I12: =I9 -> 1056426.5 | J12: =I12 -> 1056426.5 | K12: =K9 -> 1003349.6 | L12: =L9 -> 4934349.6 | M12: =M9 -> 4568990.7 | N12: =N9 -> 4077416.4 | O12: =N12 -> 4077416.4 | P12: =P9 -> 3690695.9 | Q12: =Q9 -> 3407221.5 | R12: =R9 -> 3219331.6 | S12: =S9 -> 3170989.8 | T12: =S12 -> 3170989.8 | U12: =U9 -> 3196497.1 | V12: =V9 -> 3344850.9 | W12: =W9 -> 3735779.2 | X12: =X9 -> 4456041.7 | Y12: =X12 -> 4456041.7 | Z12: =Z9 -> 5868376.6 | AA12: =AA9 -> 7506477 | AB12: =AB9 -> 9776174.5 | AC12: =AC9 -> 12929417 | AD12: =AC12 -> 12929417 | AE12: =AE9 -> 17726443 | AF12: =AF9 -> 21656241 | AG12: =AG9 -> 25934380 | AH12: =AH9 -> 31539714 | AI12: =AH12 -> 31539714
C14: Balance Check | E14: =ABS(E8-E12)<1 -> TRUE | F14: =ABS(F8-F12)<1 -> TRUE | G14: =ABS(G8-G12)<1 -> TRUE | H14: =ABS(H8-H12)<1 -> TRUE | I14: =ABS(I8-I12)<1 -> TRUE | J14: =ABS(J8-J12)<1 -> TRUE | K14: =ABS(K8-K12)<1 -> TRUE | L14: =ABS(L8-L12)<1 -> TRUE | ... AC14: =ABS(AC8-AC12)<1 -> TRUE | AD14: =ABS(AM8-AM12)<1 -> TRUE | AE14: =ABS(AD8-AD12)<1 -> TRUE | AF14: =ABS(AJ8-AJ12)<1 -> TRUE | AG14: =ABS(AK8-AK12)<1 -> TRUE | AH14: =ABS(AL8-AL12)<1 -> TRUE | AI14: =ABS(AR8-AR12)<1 -> TRUE
E15: =E12-E8 -> 0 | F15: =F12-F8 -> 0 | G15: =G12-G8 -> 0 | H15: =H12-H8 -> 0 | I15: =I12-I8 -> 0 | J15: =J12-J8 -> 0 | K15: =K12-K8 -> 0 | L15: =L12-L8 -> 0 | ... AC15: =AC12-AC8 -> 0 | AD15: =AM12-AM8 -> 0 | AE15: =AD12-AD8 -> 0 | AF15: =AJ12-AJ8 -> 0 | AG15: =AK12-AK8 -> 0 | AH15: =AL12-AL8 -> 0 | AI15: =AR12-AR8 -> 0

Sheet CFS
B2: Cashflow Statement (in US$) | D2: Q1-17 | E2: Q2-17 | F2: Q3-17 | G2: Q4-17 | H2: 2017 | I2: Q1-18 | J2: Q2-18 | K2: Q3-18 | L2: Q4-18 | M2: 2018 | N2: Q1-19 | O2: Q2-19 | P2: Q3-19 | Q2: Q4-19 | R2: 2019 | S2: Q1-20 | T2: Q2-20 | U2: Q3-20 | V2: Q4-20 | W2: 2020 | X2: Q1-21 | Y2: Q2-21 | Z2: Q3-21 | AA2: Q4-21 | AB2: 2021 | AC2: Q1-22 | AD2: Q2-22 | AE2: Q3-22 | AF2: Q4-22 | AG2: 2022
C3: Cashflow from Operating Activities | D3: =SUM(D4:D5) -> -30169.56 | E3: =SUM(E4:E5) -> -54637.7 | F3: =SUM(F4:F5) -> -48699.1 | G3: =SUM(G4:G5) -> -60067.14 | H3: =SUM(D3:G3) -> -193573.5 | I3: =SUM(I4:I5) -> -53076.923 | J3: =SUM(J4:J5) -> -69000 | K3: =SUM(K4:K5) -> -365358.89 | L3: =SUM(L4:L5) -> -491574.25 | M3: =SUM(I3:L3) -> -979010.07 | N3: =SUM(N4:N5) -> -429217.36 | O3: =SUM(O4:O5) -> -318241.94 | P3: =SUM(P4:P5) -> -231592.91 | Q3: =SUM(Q4:Q5) -> -103914.16 | R3: =SUM(N3:Q3) -> -1082966.4 | S3: =SUM(S4:S5) -> -54928.043 | T3: =SUM(T4:T5) -> 26299.422 | U3: =SUM(U4:U5) -> 202035.4 | V3: =SUM(V4:V5) -> 499640.43 | W3: =SUM(S3:V3) -> 673047.21 | X3: =SUM(X4:X5) -> 998616.32 | Y3: =SUM(Y4:Y5) -> 1277423.9 | Z3: =SUM(Z4:Z5) -> 1800813.6 | AA3: =SUM(AA4:AA5) -> 2543695.7 | AB3: =SUM(X3:AA3) -> 6620549.6 | AC3: =SUM(AC4:AC5) -> 7899013.7 | AD3: =SUM(AD4:AD5) -> 3541822.2 | AE3: =SUM(AE4:AE5) -> 4713258.8 | AF3: =SUM(AF4:AF5) -> 5902707.5 | AG3: =SUM(AC3:AF3) -> 22056802
C4: PAT | D4: ='P&L'!E12 -> -30169.56 | E4: ='P&L'!F12 -> -54637.7 | F4: ='P&L'!G12 -> -48699.1 | G4: ='P&L'!H12 -> -60067.14 | H4: =SUM(D4:G4) -> -193573.5 | I4: ='P&L'!J12 -> -69000 | J4: ='P&L'!K12 -> -69000 | K4: ='P&L'!L12 -> -454266.56 | L4: ='P&L'!M12 -> -502766.56 | M4: =SUM(I4:L4) -> -1095033.1 | N4: ='P&L'!O12 -> -390578.81 | O4: ='P&L'!P12 -> -282981.56 | P4: ='P&L'!Q12 -> -199132.11 | Q4: ='P&L'!R12 -> -53675.548 | R4: =SUM(N4:Q4) -> -926368.04 | S4: ='P&L'!T12 -> -23934.033 | T4: ='P&L'!U12 -> 88970.657 | U4: ='P&L'!V12 -> 309623.05 | V4: ='P&L'!W12 -> 642688.27 | W4: =SUM(S4:V4) -> 1017347.9 | X4: ='P&L'!Y12 -> 1272734.6 | Y4: ='P&L'!Z12 -> 1535995.7 | Z4: ='P&L'!AA12 -> 2108803.3 | AA4: ='P&L'!AB12 -> 2981480.1 | AB4: =SUM(X4:AA4) -> 7899013.7 | AC4: ='P&L'!AC12 -> 7899013.7 | AD4: ='P&L'!AD12 -> 4123872.9 | AE4: ='P&L'!AE12 -> 5268520.2 | AF4: ='P&L'!AF12 -> 6542466.2 | AG4: =SUM(AC4:AF4) -> 23833873
C5: [+] Net Change in Working Capital | D5: =WC!E7 -> 0 | E5: =(WC!F7-WC!E7)*-1 -> 0 | F5: =(WC!G7-WC!F7)*-1 -> 0 | G5: =(WC!H7-WC!G7)*-1 -> 0 | H5: =SUM(D5:G5) -> 0 | I5: =(WC!I7-WC!H7)*-1 -> 15923.077 | J5: =(WC!J7-WC!I7)*-1 -> 0 | K5: =(WC!K7-WC!J7)*-1 -> 88907.668 | L5: =(WC!L7-WC!K7)*-1 -> 11192.308 | M5: =SUM(I5:L5) -> 116023.05 | N5: =(WC!M7-WC!L7)*-1 -> -38638.542 | O5: =(WC!N7-WC!M7)*-1 -> -35260.374 | P5: =(WC!O7-WC!N7)*-1 -> -32460.798 | Q5: =(WC!P7-WC!O7)*-1 -> -50238.61 | R5: =SUM(N5:Q5) -> -156598.32 | S5: =(WC!Q7-WC!P7)*-1 -> -30994.01 | T5: =(WC!R7-WC!Q7)*-1 -> -62671.234 | U5: =(WC!S7-WC!R7)*-1 -> -107587.65 | V5: =(WC!T7-WC!S7)*-1 -> -143047.84 | W5: =SUM(S5:V5) -> -344300.74 | X5: =(WC!U7-WC!T7)*-1 -> -274118.26 | Y5: =(WC!V7-WC!U7)*-1 -> -258571.84 | Z5: =(WC!W7-WC!V7)*-1 -> -307989.66 | AA5: =(WC!X7-WC!W7)*-1 -> -437784.33 | AB5: =SUM(X5:AA5) -> -1278464.1 | AC5: =(WC!Y7-WC!X7)*-1 -> 0 | AD5: =(WC!Z7-WC!Y7)*-1 -> -582050.65 | AE5: =(WC!AA7-WC!Z7)*-1 -> -555261.37 | AF5: =(WC!AB7-WC!AA7)*-1 -> -639758.65 | AG5: =SUM(AC5:AF5) -> -1777070.7
C6: Cashflow from Investment Activities | D6: =SUM(D7:D7) -> 0 | E6: =SUM(E7:E7) -> 0 | F6: =SUM(F7:F7) -> 0 | G6: =SUM(G7:G7) -> 0 | H6: =SUM(D6:G6) -> 0 | I6: =SUM(I7:I7) -> 0 | J6: =SUM(J7:J7) -> 0 | K6: =SUM(K7:K7) -> 0 | L6: =SUM(L7:L7) -> 0 | M6: =SUM(I6:L6) -> 0 | N6: =SUM(N7:N7) -> 0 | O6: =SUM(O7:O7) -> 0 | P6: =SUM(P7:P7) -> 0 | Q6: =SUM(Q7:Q7) -> 0 | R6: =SUM(N6:Q6) -> 0 | S6: =SUM(S7:S7) -> 0 | T6: =SUM(T7:T7) -> 0 | U6: =SUM(U7:U7) -> 0 | V6: =SUM(V7:V7) -> 0 | W6: =SUM(S6:V6) -> 0 | X6: =SUM(X7:X7) -> 0 | Y6: =SUM(Y7:Y7) -> 0 | Z6: =SUM(Z7:Z7) -> 0 | AA6: =SUM(AA7:AA7) -> 0 | AB6: =SUM(X6:AA6) -> 0 | AC6: =SUM(AC7:AC7) -> 0 | AD6: =SUM(AD7:AD7) -> 0 | AE6: =SUM(AE7:AE7) -> 0 | AF6: =SUM(AF7:AF7) -> 0 | AG6: =SUM(AC6:AF6) -> 0
C8: Cashflow from Financing Activities | D8: =SUM(D9:D9) -> 0 | E8: =SUM(E9:E9) -> 1000000 | F8: =SUM(F9:F9) -> 0 | G8: =SUM(G9:G9) -> 0 | H8: =SUM(D8:G8) -> 1000000 | I8: =SUM(I9:I9) -> 0 | J8: =SUM(J9:J9) -> 4000000 | K8: =SUM(K9:K9) -> 0 | L8: =SUM(L9:L9) -> 0 | M8: =SUM(I8:L8) -> 4000000 | N8: =SUM(N9:N9) -> 0 | O8: =SUM(O9:O9) -> 0 | P8: =SUM(P9:P9) -> 0 | Q8: =SUM(Q9:Q9) -> 0 | R8: =SUM(N8:Q8) -> 0 | S8: =SUM(S9:S9) -> 0 | T8: =SUM(T9:T9) -> 0 | U8: =SUM(U9:U9) -> 0 | V8: =SUM(V9:V9) -> 0 | W8: =SUM(S8:V8) -> 0 | X8: =SUM(X9:X9) -> 0 | Y8: =SUM(Y9:Y9) -> 0 | Z8: =SUM(Z9:Z9) -> 0 | AA8: =SUM(AA9:AA9) -> 0 | AB8: =SUM(X8:AA8) -> 0 | AC8: =SUM(AC9:AC9) -> 0 | AD8: =SUM(AD9:AD9) -> 0 | AE8: =SUM(AE9:AE9) -> 0 | AF8: =SUM(AF9:AF9) -> 0 | AG8: =SUM(AC8:AF8) -> 0
C9: [+] New Equity Raised | D9: ='Equity Schedule'!F11 -> 0 | E9: ='Equity Schedule'!G11 -> 1000000 | F9: ='Equity Schedule'!H11 -> 0 | G9: ='Equity Schedule'!I11 -> 0 | H9: =SUM(D9:G9) -> 1000000 | I9: ='Equity Schedule'!K11 -> 0 | J9: ='Equity Schedule'!L11 -> 4000000 | K9: ='Equity Schedule'!M11 -> 0 | L9: ='Equity Schedule'!N11 -> 0 | M9: =SUM(I9:L9) -> 4000000 | N9: ='Equity Schedule'!P11 -> 0 | O9: ='Equity Schedule'!Q11 -> 0 | P9: ='Equity Schedule'!R11 -> 0 | Q9: ='Equity Schedule'!S11 -> 0 | R9: =SUM(N9:Q9) -> 0 | S9: ='Equity Schedule'!U11 -> 0 | T9: ='Equity Schedule'!V11 -> 0 | U9: ='Equity Schedule'!W11 -> 0 | V9: ='Equity Schedule'!X11 -> 0 | W9: =SUM(S9:V9) -> 0 | X9: ='Equity Schedule'!Z11 -> 0 | Y9: ='Equity Schedule'!AA11 -> 0 | Z9: ='Equity Schedule'!AB11 -> 0 | AA9: ='Equity Schedule'!AC11 -> 0 | AB9: =SUM(X9:AA9) -> 0 | AC9: ='Equity Schedule'!AD11 -> 0 | AD9: ='Equity Schedule'!AE11 -> 0 | AE9: ='Equity Schedule'!AF11 -> 0 | AF9: ='Equity Schedule'!AG11 -> 0 | AG9: =SUM(AC9:AF9) -> 0
C10: Net Cashflow | D10: =D8+D6+D3 -> -30169.56 | E10: =E8+E6+E3 -> 945362.3 | F10: =F8+F6+F3 -> -48699.1 | G10: =G8+G6+G3 -> -60067.14 | H10: =SUM(D10:G10) -> 806426.5 | I10: =I8+I6+I3 -> -53076.923 | J10: =J8+J6+J3 -> 3931000 | K10: =K8+K6+K3 -> -365358.89 | L10: =L8+L6+L3 -> -491574.25 | M10: =SUM(I10:L10) -> 3020989.9 | N10: =N8+N6+N3 -> -429217.36 | O10: =O8+O6+O3 -> -318241.94 | P10: =P8+P6+P3 -> -231592.91 | Q10: =Q8+Q6+Q3 -> -103914.16 | R10: =SUM(N10:Q10) -> -1082966.4 | S10: =S8+S6+S3 -> -54928.043 | T10: =T8+T6+T3 -> 26299.422 | U10: =U8+U6+U3 -> 202035.4 | V10: =V8+V6+V3 -> 499640.43 | W10: =SUM(S10:V10) -> 673047.21 | X10: =X8+X6+X3 -> 998616.32 | Y10: =Y8+Y6+Y3 -> 1277423.9 | Z10: =Z8+Z6+Z3 -> 1800813.6 | AA10: =AA8+AA6+AA3 -> 2543695.7 | AB10: =SUM(X10:AA10) -> 6620549.6 | AC10: =AC8+AC6+AC3 -> 7899013.7 | AD10: =AD8+AD6+AD3 -> 3541822.2 | AE10: =AE8+AE6+AE3 -> 4713258.8 | AF10: =AF8+AF6+AF3 -> 5902707.5 | AG10: =SUM(AC10:AF10) -> 22056802
C11: Opening Balance | D11: ='Equity Schedule'!E12 -> 250000 | E11: =D13 -> 219830.44 | F11: =E13 -> 1165192.7 | G11: =F13 -> 1116493.6 | H11: =D11 -> 250000 | I11: =G13 -> 1056426.5 | J11: =I13 -> 1003349.6 | K11: =J13 -> 4934349.6 | L11: =K13 -> 4568990.7 | M11: =I11 -> 1056426.5 | N11: =L13 -> 4077416.4 | O11: =N13 -> 3648199.1 | P11: =O13 -> 3329957.1 | Q11: =P13 -> 3098364.2 | R11: =N11 -> 4077416.4 | S11: =Q13 -> 2994450.1 | T11: =S13 -> 2939522 | U11: =T13 -> 2965821.4 | V11: =U13 -> 3167856.8 | W11: =S11 -> 2994450.1 | X11: =V13 -> 3667497.3 | Y11: =X13 -> 4666113.6 | Z11: =Y13 -> 5943537.5 | AA11: =Z13 -> 7744351.1 | AB11: =X11 -> 3667497.3 | AC11: =AA13 -> 10288047 | AD11: =AC13 -> 18187060 | AE11: =AD13 -> 21728883 | AF11: =AE13 -> 26442142 | AG11: =AC11 -> 10288047
C12: Net Cashflow | D12: =D10 -> -30169.56 | E12: =E10 -> 945362.3 | F12: =F10 -> -48699.1 | G12: =G10 -> -60067.14 | H12: =SUM(D12:G12) -> 806426.5 | I12: =I10 -> -53076.923 | J12: =J10 -> 3931000 | K12: =K10 -> -365358.89 | L12: =L10 -> -491574.25 | M12: =SUM(I12:L12) -> 3020989.9 | N12: =N10 -> -429217.36 | O12: =O10 -> -318241.94 | P12: =P10 -> -231592.91 | Q12: =Q10 -> -103914.16 | R12: =SUM(N12:Q12) -> -1082966.4 | S12: =S10 -> -54928.043 | T12: =T10 -> 26299.422 | U12: =U10 -> 202035.4 | V12: =V10 -> 499640.43 | W12: =SUM(S12:V12) -> 673047.21 | X12: =X10 -> 998616.32 | Y12: =Y10 -> 1277423.9 | Z12: =Z10 -> 1800813.6 | AA12: =AA10 -> 2543695.7 | AB12: =SUM(X12:AA12) -> 6620549.6 | AC12: =AC10 -> 7899013.7 | AD12: =AD10 -> 3541822.2 | AE12: =AE10 -> 4713258.8 | AF12: =AF10 -> 5902707.5 | AG12: =SUM(AC12:AF12) -> 22056802
C13: Closing Balance | D13: =D11+D12 -> 219830.44 | E13: =E11+E12 -> 1165192.7 | F13: =F11+F12 -> 1116493.6 | G13: =G11+G12 -> 1056426.5 | H13: =G13 -> 1056426.5 | I13: =I11+I12 -> 1003349.6 | J13: =J11+J12 -> 4934349.6 | K13: =K11+K12 -> 4568990.7 | L13: =L11+L12 -> 4077416.4 | M13: =L13 -> 4077416.4 | N13: =N11+N12 -> 3648199.1 | O13: =O11+O12 -> 3329957.1 | P13: =P11+P12 -> 3098364.2 | Q13: =Q11+Q12 -> 2994450.1 | R13: =Q13 -> 2994450.1 | S13: =S11+S12 -> 2939522 | T13: =T11+T12 -> 2965821.4 | U13: =U11+U12 -> 3167856.8 | V13: =V11+V12 -> 3667497.3 | W13: =V13 -> 3667497.3 | X13: =X11+X12 -> 4666113.6 | Y13: =Y11+Y12 -> 5943537.5 | Z13: =Z11+Z12 -> 7744351.1 | AA13: =AA11+AA12 -> 10288047 | AB13: =AA13 -> 10288047 | AC13: =AC11+AC12 -> 18187060 | AD13: =AD11+AD12 -> 21728883 | AE13: =AE11+AE12 -> 26442142 | AF13: =AF11+AF12 -> 32344849 | AG13: =AF13 -> 32344849

Sheet AOV
A1: AOV in 2014 | B1: 123.72
A2: Annual Growth in AOV | B2: ='Assumptions & Sensitivity'!#REF! -> #REF!
A3: 1 | B3: 2 | C3: 3 | D3: 4 | E3: 5
A4: 2015 | B4: 2016 | C4: 2017 | D4: 2018 | E4: 2019
A5: =$B1*((1+$B2)^A3) -> #REF! | B5: =$B1*((1+$B2)^B3) -> #REF! | C5: =$B1*((1+$B2)^C3) -> #REF! | D5: =$B1*((1+$B2)^D3) -> #REF! | E5: =$B1*((1+$B2)^E3) -> #REF!

Sheet Quarter Effect Worksheet
A1: Cumulative Quarterly Sales Breakdown Year 1
A2: Year End Sales | C2: ='Marketshare Assumptions'!B14 -> #REF!
A3: Est Q1 Sales | C3: =C2*0.1 -> #REF!
A6: Quarter | C6: 1 | D6: 2 | E6: 3 | F6: 4 | G6: Annual Total
A7: Cum Sales per Quarter | D7: =C3 -> #REF! | E7: =D7*(1+((($C2/$C3)^(1/2))-1)) -> #REF! | F7: =E7*(1+((($C2/$C3)^(1/2))-1)) -> #REF!
A8: Increase in Sales per Quarter | D8: =D7-C7 -> #REF! | E8: =E7-D7 -> #REF! | F8: =F7-E7 -> #REF! | G8: =SUM(C8:F8) -> #REF!
A9: Growth Factor | D9: 0 | E9: =((E8-D8)/D8)+1 -> #REF! | F9: =((F8-E8)/E8)+1 -> #REF!
A10: GeoMean Growth Rate | C10: =F3*(1+(C6*1.3)) -> 0
A12: Cumulative Quarterly Sales Breakdown Year 2
A13: Year End Sales | C13: ='Marketshare Assumptions'!C14 -> #REF!
A14: Est Q1 Sales | C14: =F7*(1+(C10*1.3)) -> #REF!
A17: Quarter | C17: 1 | D17: 2 | E17: 3 | F17: 4 | G17: Annual Total
A18: Cum Sales per Quarter | C18: =C14 -> #REF! | D18: =C18*(1+((($C13/$C14)^(1/3))-1)) -> #REF! | E18: =D18*(1+((($C13/$C14)^(1/3))-1)) -> #REF! | F18: =E18*(1+((($C13/$C14)^(1/3))-1)) -> #REF!
A19: Increase in Sales per Quarter | C19: =C18-B18 -> #REF! | D19: =D18-C18 -> #REF! | E19: =E18-D18 -> #REF! | F19: =F18-E18 -> #REF! | G19: =SUM(C19:F19) -> #REF!
A20: Growth Factor | D20: =((D19-C19)/C19)+1 -> #REF! | E20: =((E19-D19)/D19)+1 -> #REF! | F20: =((F19-E19)/E19)+1 -> #REF!
A21: GeoMean Growth Rate | C21: =(PRODUCT(D20:F20)^(1/3))-1 -> #REF!
A23: Cumulative Quarterly Sales Breakdown Year 3
A24: Year End Sales | C24: ='Marketshare Assumptions'!D14 -> #REF!
A25: Est Q1 Sales | C25: =F18*(1+(C21/1.5)) -> #REF!
A28: Quarter | C28: 1 | D28: 2 | E28: 3 | F28: 4 | G28: Annual Total
A29: Cum Sales per Quarter | C29: =C25 -> #REF! | D29: =C29*(1+((($C24/$C25)^(1/3))-1)) -> #REF! | E29: =D29*(1+((($C24/$C25)^(1/3))-1)) -> #REF! | F29: =E29*(1+((($C24/$C25)^(1/3))-1)) -> #REF!
A30: Increase in Sales per Quarter | C30: =C29-B29 -> #REF! | D30: =D29-C29 -> #REF! | E30: =E29-D29 -> #REF! | F30: =F29-E29 -> #REF! | G30: =SUM(C30:F30) -> #REF!
A31: Growth Factor | D31: =((D30-C30)/C30)+1 -> #REF! | E31: =((E30-D30)/D30)+1 -> #REF! | F31: =((F30-E30)/E30)+1 -> #REF!
A32: GeoMean Growth Rate | C32: =(PRODUCT(D31:F31)^(1/3))-1 -> #REF!
A36: 0.15
A37: 0.14
A38: 0.13
A39: 0.12
A40: 0.11
A41: 0.1

Sheet Marketshare Assumptions
A1: Growth Rate Given Expected Beginning and Year 3 Target (Average of Dowside, Base Case, and Upside)
A2: Max Marketshare | B2: 0.2
A3: Target Marketshare in Year 3 | B3: ='Assumptions & Sensitivity'!#REF! -> #REF!
A4: Launch Year Marketshare | B4: ='Assumptions & Sensitivity'!#REF! -> #REF!
A7: Cumulative Customer Adoption | B7: 1 | C7: 2 | D7: 3
B8: =B4 -> #REF! | C8: =IF(B8*(1+((($B3/$B4)^(1/2))-1))<$B2,B8*(1+((($B3/$B4)^(1/2))-1)),$B2) -> #REF! | D8: =IF(C8*(1+((($B3/$B4)^(1/2))-1))<$B2,C8*(1+((($B3/$B4)^(1/2))-1)),$B2) -> #REF!
B10: 2017 | C10: 2018 | D10: 2019
A11: Expected mComm Revenue Apparel transacted by females in agegroup | B11: 2.5270995e+09 | C11: 3.0579249e+09 | D11: 3.6776695e+09
A12: Expected Marketshare | B12: =B8*(3/4) -> #REF! | C12: =C8 -> #REF! | D12: =D8 -> #REF!
A13: Expected Sales Generated by App Z | B13: =B11*B12 -> #REF! | C13: =C11*C12 -> #REF! | D13: =D11*D12 -> #REF!
A14: Expected Revenue App z | B14: =B13*0.1 -> #REF! | C14: =C13*0.1 -> #REF! | D14: =D13*0.1 -> #REF!
A16: Qarterly Sales
A17: Q1 2017 | B17: Q2 2017 | C17: Q3 2017 | D17: Q4 2017 | E17: FY 2017 | F17: Q1 2018 | G17: Q2 2018 | H17: Q3 2018 | I17: Q4 2018 | J17: FY 2018 | K17: Q1 2019 | L17: Q2 2019 | M17: Q3 2019 | N17: Q4 2019 | O17: FY 2019
A18: ='Quarter Effect Worksheet'!C8/0.1 -> 0 | B18: ='Quarter Effect Worksheet'!D8/0.1 -> #REF! | C18: ='Quarter Effect Worksheet'!E8/0.1 -> #REF! | D18: ='Quarter Effect Worksheet'!F8/0.1 -> #REF! | E18: =SUM(A18:D18) -> #REF! | F18: ='Quarter Effect Worksheet'!C19/0.1 -> #REF! | G18: ='Quarter Effect Worksheet'!D19/0.1 -> #REF! | H18: ='Quarter Effect Worksheet'!E19/0.1 -> #REF! | I18: ='Quarter Effect Worksheet'!F19/0.1 -> #REF! | J18: =SUM(F18:I18) -> #REF! | K18: ='Quarter Effect Worksheet'!C30/0.1 -> #REF! | L18: ='Quarter Effect Worksheet'!D30/0.1 -> #REF! | M18: ='Quarter Effect Worksheet'!E30/0.1 -> #REF! | N18: ='Quarter Effect Worksheet'!F30/0.1 -> #REF! | O18: =SUM(K18:N18) -> #REF!

Sheet WC
B2: Working Capital Schedule (in US$) | E2: Q1-17 | F2: Q2-17 | G2: Q3-17 | H2: Q4-17 | I2: Q1-18 | J2: Q2-18 | K2: Q3-18 | L2: Q4-18 | M2: Q1-19 | N2: Q2-19 | O2: Q3-19 | P2: Q4-19 | Q2: Q1-20 | R2: Q2-20 | S2: Q3-20 | T2: Q4-20 | U2: Q1-21 | V2: Q2-21 | W2: Q3-21 | X2: Q4-21 | Y2: Q1-22 | Z2: Q2-22 | AA2: Q3-22 | AB2: Q4-22
C3: Current Assets excluding Cash | E3: =SUM(E4:E4) -> 0 | F3: =SUM(F4:F4) -> 0 | G3: =SUM(G4:G4) -> 0 | H3: =SUM(H4:H4) -> 0 | I3: =SUM(I4:I4) -> 0 | J3: =SUM(J4:J4) -> 0 | K3: =SUM(K4:K4) -> 0 | L3: =SUM(L4:L4) -> 0 | ... AB3: =SUM(AB4:AB4) -> 5097572.3
D4: [+] Account Receivables | E4: =BS!F11 -> 0 | F4: =BS!G11 -> 0 | G4: =BS!H11 -> 0 | H4: =BS!I11 -> 0 | I4: =BS!K11 -> 0 | J4: =BS!L11 -> 0 | K4: =BS!M11 -> 0 | L4: =BS!N11 -> 0 | M4: =BS!P11 -> 42496.873 | N4: =BS!Q11 -> 77264.337 | O4: =BS!R11 -> 120967.42 | P4: =BS!S11 -> 176539.79 | Q4: =BS!U11 -> 256975.06 | R4: =BS!V11 -> 379029.42 | S4: =BS!W11 -> 567922.32 | T4: =BS!X11 -> 788544.45 | U4: =BS!Z11 -> 1202263 | V4: =BS!AA11 -> 1562939.6 | W4: =BS!AB11 -> 2031823.4 | X4: =BS!AC11 -> 2641370.5 | Y4: =BS!AD11 -> 2641370.5 | Z4: =BS!AF11 -> 3469180.3 | AA4: =BS!AG11 -> 4205497.2 | AB4: =BS!AH11 -> 5097572.3
C5: Current Liabilities & Provisions | E5: =SUM(E6:E6) -> 0 | F5: =SUM(F6:F6) -> 0 | G5: =SUM(G6:G6) -> 0 | H5: =SUM(H6:H6) -> 0 | I5: =SUM(I6:I6) -> 15923.077 | J5: =SUM(J6:J6) -> 15923.077 | K5: =SUM(K6:K6) -> 104830.75 | L5: =SUM(L6:L6) -> 116023.05 | ... AB5: =SUM(AB6:AB6) -> 1657161.5
D6: [+] Accounts payable | E6: =BS!F4 -> 0 | F6: =BS!G4 -> 0 | G6: =BS!H4 -> 0 | H6: =BS!I4 -> 0 | I6: =BS!K4 -> 15923.077 | J6: =BS!L4 -> 15923.077 | K6: =BS!M4 -> 104830.75 | L6: =BS!N4 -> 116023.05 | M6: =BS!P4 -> 119881.38 | N6: =BS!Q4 -> 119388.47 | O6: =BS!R4 -> 130630.76 | P6: =BS!S4 -> 135964.52 | Q6: =BS!U4 -> 185405.78 | R6: =BS!V4 -> 244788.9 | S6: =BS!W4 -> 326094.15 | T6: =BS!X4 -> 403668.43 | U6: =BS!Z4 -> 543268.71 | V6: =BS!AA4 -> 645373.46 | W6: =BS!AB4 -> 806267.63 | X6: =BS!AC4 -> 978030.44 | Y6: =BS!AD4 -> 978030.44 | Z6: =BS!AF4 -> 1223789.5 | AA6: =BS!AG4 -> 1404845 | AB6: =BS!AH4 -> 1657161.5
C7: Working Capital | E7: =E3-E5 -> 0 | F7: =F3-F5 -> 0 | G7: =G3-G5 -> 0 | H7: =H3-H5 -> 0 | I7: =I3-I5 -> -15923.077 | J7: =J3-J5 -> -15923.077 | K7: =K3-K5 -> -104830.75 | L7: =L3-L5 -> -116023.05 | ... AB7: =AB3-AB5 -> 3440410.8

Sheet Equity Schedule
B2: Equity Schedule (in US$) | E2: 2016 | F2: Q1-17 | G2: Q2-17 | H2: Q3-17 | I2: Q4-17 | J2: 2017 | K2: Q1-18 | L2: Q2-18 | M2: Q3-18 | N2: Q4-18 | O2: 2018 | P2: Q1-19 | Q2: Q2-19 | R2: Q3-19 | S2: Q4-19 | T2: 2019 | U2: Q1-20 | V2: Q2-20 | W2: Q3-20 | X2: Q4-20 | Y2: 2020 | Z2: Q1-21 | AA2: Q2-21 | AB2: Q3-21 | AC2: Q4-21 | AD2: 2021
B3: Shares issued
C4: Opening | E4: 0 | F4: =E7 -> 1000000 | G4: =F7 -> 1000000 | H4: =G7 -> 1176470.6 | I4: =H7 -> 1176470.6 | J4: =F4 -> 1000000 | K4: =I7 -> 1176470.6 | L4: =K7 -> 1176470.6 | M4: =L7 -> 1176470.6 | N4: =M7 -> 1176470.6 | O4: =K4 -> 1176470.6 | P4: =N7 -> 1176470.6 | Q4: =P7 -> 1176470.6 | R4: =Q7 -> 1176470.6 | S4: =R7 -> 1176470.6 | T4: =P4 -> 1176470.6 | U4: =S7 -> 1176470.6 | V4: =U7 -> 1176470.6 | W4: =V7 -> 1176470.6 | X4: =W7 -> 1176470.6 | Y4: =U4 -> 1176470.6 | Z4: =X7 -> 1176470.6 | AA4: =Z7 -> 1176470.6 | AB4: =AA7 -> 1176470.6 | AC4: =AB7 -> 1176470.6 | AD4: =Z4 -> 1176470.6
C5: [+] Issued during the year | E5: ='Assumptions & Sensitivity'!D87 -> 1000000 | F5: 0 | G5: ='Assumptions & Sensitivity'!D91 -> 176470.59 | H5: 0 | I5: 0 | J5: =SUM(F5:I5) -> 176470.59 | K5: 0 | L5: 0 | M5: 0 | N5: 0 | O5: =SUM(K5:N5) -> 0 | P5: 0 | Q5: 0 | R5: 0 | S5: 0 | T5: =SUM(P5:S5) -> 0 | U5: 0 | V5: 0 | W5: 0 | X5: 0 | Y5: =SUM(U5:X5) -> 0 | Z5: 0 | AA5: 0 | AB5: 0 | AC5: 0 | AD5: =SUM(Z5:AC5) -> 0
D6: Share Issue Price (US$) | E6: ='Assumptions & Sensitivity'!D88 -> 0.25 | F6: =IF(F5=0,0,F11/F5) -> 0 | G6: =IF(G5=0,0,G11/G5) -> 5.6666667 | H6: =IF(H5=0,0,H11/H5) -> 0 | I6: =IF(I5=0,0,I11/I5) -> 0 | J6: 0 | K6: =IF(K5=0,0,K11/K5) -> 0 | L6: =IF(L5=0,0,L11/L5) -> 0 | M6: =IF(M5=0,0,M11/M5) -> 0 | N6: =IF(N5=0,0,N11/N5) -> 0 | O6: =L6 -> 0 | P6: =IF(P5=0,0,P11/P5) -> 0 | Q6: =IF(Q5=0,0,Q11/Q5) -> 0 | R6: =IF(R5=0,0,R11/R5) -> 0 | S6: =IF(S5=0,0,S11/S5) -> 0 | T6: 0 | U6: =IF(U5=0,0,U11/U5) -> 0 | V6: =IF(V5=0,0,V11/V5) -> 0 | W6: =IF(W5=0,0,W11/W5) -> 0 | X6: =IF(X5=0,0,X11/X5) -> 0 | Y6: 0 | Z6: =IF(Z5=0,0,Z11/Z5) -> 0 | AA6: =IF(AA5=0,0,AA11/AA5) -> 0 | AB6: =IF(AB5=0,0,AB11/AB5) -> 0 | AC6: =IF(AC5=0,0,AC11/AC5) -> 0 | AD6: 0
C7: Closing | E7: =E4+E5 -> 1000000 | F7: =F4+F5 -> 1000000 | G7: =G4+G5 -> 1176470.6 | H7: =H4+H5 -> 1176470.6 | I7: =I4+I5 -> 1176470.6 | J7: =I7 -> 1176470.6 | K7: =K4+K5 -> 1176470.6 | L7: =L4+L5 -> 1176470.6 | M7: =M4+M5 -> 1176470.6 | N7: =N4+N5 -> 1176470.6 | O7: =N7 -> 1176470.6 | P7: =P4+P5 -> 1176470.6 | Q7: =Q4+Q5 -> 1176470.6 | R7: =R4+R5 -> 1176470.6 | S7: =S4+S5 -> 1176470.6 | T7: =S7 -> 1176470.6 | U7: =U4+U5 -> 1176470.6 | V7: =V4+V5 -> 1176470.6 | W7: =W4+W5 -> 1176470.6 | X7: =X4+X5 -> 1176470.6 | Y7: =X7 -> 1176470.6 | Z7: =Z4+Z5 -> 1176470.6 | AA7: =AA4+AA5 -> 1176470.6 | AB7: =AB4+AB5 -> 1176470.6 | AC7: =AC4+AC5 -> 1176470.6 | AD7: =AC7 -> 1176470.6
B9: Paid Up Capital
C10: Opening | F10: =E12 -> 250000 | G10: =F12 -> 250000 | H10: =G12 -> 1250000 | I10: =H12 -> 1250000 | J10: =F10 -> 250000 | K10: =I12 -> 1250000 | L10: =K12 -> 1250000 | M10: =L12 -> 5250000 | N10: =M12 -> 5250000 | O10: =K10 -> 1250000 | P10: =N12 -> 5250000 | Q10: =P12 -> 5250000 | R10: =Q12 -> 5250000 | S10: =R12 -> 5250000 | T10: =P10 -> 5250000 | U10: =S12 -> 5250000 | V10: =U12 -> 5250000 | W10: =V12 -> 5250000 | X10: =W12 -> 5250000 | Y10: =U10 -> 5250000 | Z10: =X12 -> 5250000 | AA10: =Z12 -> 5250000 | AB10: =AA12 -> 5250000 | AC10: =AB12 -> 5250000 | AD10: =Z10 -> 5250000
C11: [+] Issued | E11: =E6*E5 -> 250000 | F11: 0 | G11: ='Assumptions & Sensitivity'!D89 -> 1000000 | H11: 0 | I11: 0 | J11: =SUM(F11:I11) -> 1000000 | K11: 0 | L11: ='Assumptions & Sensitivity'!J89 -> 4000000 | M11: 0 | N11: 0 | O11: =SUM(K11:N11) -> 4000000 | P11: 0 | Q11: 0 | R11: 0 | S11: 0 | T11: =SUM(P11:S11) -> 0 | U11: 0 | V11: 0 | W11: 0 | X11: 0 | Y11: =SUM(U11:X11) -> 0 | Z11: 0 | AA11: 0 | AB11: 0 | AC11: 0 | AD11: =SUM(Z11:AC11) -> 0
C12: Closing | E12: =E10+E11 -> 250000 | F12: =F10+F11 -> 250000 | G12: =G10+G11 -> 1250000 | H12: =H10+H11 -> 1250000 | I12: =I10+I11 -> 1250000 | J12: =I12 -> 1250000 | K12: =K10+K11 -> 1250000 | L12: =L10+L11 -> 5250000 | M12: =M10+M11 -> 5250000 | N12: =N10+N11 -> 5250000 | O12: =N12 -> 5250000 | P12: =P10+P11 -> 5250000 | Q12: =Q10+Q11 -> 5250000 | R12: =R10+R11 -> 5250000 | S12: =S10+S11 -> 5250000 | T12: =S12 -> 5250000 | U12: =U10+U11 -> 5250000 | V12: =V10+V11 -> 5250000 | W12: =W10+W11 -> 5250000 | X12: =X10+X11 -> 5250000 | Y12: =X12 -> 5250000 | Z12: =Z10+Z11 -> 5250000 | AA12: =AA10+AA11 -> 5250000 | AB12: =AB10+AB11 -> 5250000 | AC12: =AC10+AC11 -> 5250000 | AD12: =AC12 -> 5250000
B14: Retained Earnings Account
C15: Opening | E15: 0 | F15: =E17 -> 0 | G15: =F17 -> -30169.56 | H15: =G17 -> -84807.26 | I15: =H17 -> -133506.36 | J15: =F15 -> 0 | K15: =I17 -> -193573.5 | L15: =K17 -> -262573.5 | M15: =L17 -> -331573.5 | N15: =M17 -> -785840.06 | O15: =K15 -> -193573.5 | P15: =N17 -> -1288606.6 | Q15: =P17 -> -1679185.4 | R15: =Q17 -> -1962167 | S15: =R17 -> -2161299.1 | T15: =P15 -> -1288606.6 | U15: =S17 -> -2214974.7 | V15: =U17 -> -2238908.7 | W15: =V17 -> -2149938 | X15: =W17 -> -1840315 | Y15: =U15 -> -2214974.7 | Z15: =X17 -> -1197626.7 | AA15: =Z17 -> 75107.861 | AB15: =AA17 -> 1611103.6 | AC15: =AB17 -> 3719906.9 | AD15: =Z15 -> -1197626.7
C16: [+]Net Profit | E16: 0 | F16: ='P&L'!E12 -> -30169.56 | G16: ='P&L'!F12 -> -54637.7 | H16: ='P&L'!G12 -> -48699.1 | I16: ='P&L'!H12 -> -60067.14 | J16: =SUM(F16:I16) -> -193573.5 | K16: ='P&L'!J12 -> -69000 | L16: ='P&L'!K12 -> -69000 | M16: ='P&L'!L12 -> -454266.56 | N16: ='P&L'!M12 -> -502766.56 | O16: =SUM(K16:N16) -> -1095033.1 | P16: ='P&L'!O12 -> -390578.81 | Q16: ='P&L'!P12 -> -282981.56 | R16: ='P&L'!Q12 -> -199132.11 | S16: ='P&L'!R12 -> -53675.548 | T16: =SUM(P16:S16) -> -926368.04 | U16: ='P&L'!T12 -> -23934.033 | V16: ='P&L'!U12 -> 88970.657 | W16: ='P&L'!V12 -> 309623.05 | X16: ='P&L'!W12 -> 642688.27 | Y16: =SUM(U16:X16) -> 1017347.9 | Z16: ='P&L'!Y12 -> 1272734.6 | AA16: ='P&L'!Z12 -> 1535995.7 | AB16: ='P&L'!AA12 -> 2108803.3 | AC16: ='P&L'!AB12 -> 2981480.1 | AD16: =SUM(Z16:AC16) -> 7899013.7
C17: Closing | E17: =E15+E16 -> 0 | F17: =F15+F16 -> -30169.56 | G17: =G15+G16 -> -84807.26 | H17: =H15+H16 -> -133506.36 | I17: =I15+I16 -> -193573.5 | J17: =I17 -> -193573.5 | K17: =K15+K16 -> -262573.5 | L17: =L15+L16 -> -331573.5 | M17: =M15+M16 -> -785840.06 | N17: =N15+N16 -> -1288606.6 | O17: =N17 -> -1288606.6 | P17: =P15+P16 -> -1679185.4 | Q17: =Q15+Q16 -> -1962167 | R17: =R15+R16 -> -2161299.1 | S17: =S15+S16 -> -2214974.7 | T17: =S17 -> -2214974.7 | U17: =U15+U16 -> -2238908.7 | V17: =V15+V16 -> -2149938 | W17: =W15+W16 -> -1840315 | X17: =X15+X16 -> -1197626.7 | Y17: =X17 -> -1197626.7 | Z17: =Z15+Z16 -> 75107.861 | AA17: =AA15+AA16 -> 1611103.6 | AB17: =AB15+AB16 -> 3719906.9 | AC17: =AC15+AC16 -> 6701386.9 | AD17: =AC17 -> 6701386.9
B18: Total Reserves & Surplus | E18: =E12+E17 -> 250000 | F18: =F12+F17 -> 219830.44 | G18: =G12+G17 -> 1165192.7 | H18: =H12+H17 -> 1116493.6 | I18: =I12+I17 -> 1056426.5 | J18: =I18 -> 1056426.5 | K18: =K12+K17 -> 987426.5 | L18: =L12+L17 -> 4918426.5 | M18: =M12+M17 -> 4464159.9 | N18: =N12+N17 -> 3961393.4 | O18: =N18 -> 3961393.4 | P18: =P12+P17 -> 3570814.6 | Q18: =Q12+Q17 -> 3287833 | R18: =R12+R17 -> 3088700.9 | S18: =S12+S17 -> 3035025.3 | T18: =S18 -> 3035025.3 | U18: =U12+U17 -> 3011091.3 | V18: =V12+V17 -> 3100062 | W18: =W12+W17 -> 3409685 | X18: =X12+X17 -> 4052373.3 | Y18: =X18 -> 4052373.3 | Z18: =Z12+Z17 -> 5325107.9 | AA18: =AA12+AA17 -> 6861103.6 | AB18: =AB12+AB17 -> 8969906.9 | AC18: =AC12+AC17 -> 11951387 | AD18: =AC18 -> 11951387

Sheet Cap Table
B2: Cap Table | C2: Founders & ESOPs | F2: Investor
C3: Investment | D3: #Shares | E3: % holding | F3: Investment | G3: #Shares | H3: % holding
B4: Founders & ESOPs | C4: ='Assumptions & Sensitivity'!D86 -> 250000 | D4: ='Assumptions & Sensitivity'!D87 -> 1000000 | E4: =D4/D7 -> 1 | F4: 0 | G4: =D4 -> 1000000 | H4: =G4/G7 -> 0.85
B5: Seed Investor | C5: 0 | D5: 0 | E5: 0 | F5: ='Assumptions & Sensitivity'!D89 -> 1000000 | G5: ='Assumptions & Sensitivity'!D91 -> 176470.59 | H5: =G5/G7 -> 0.15
B6: Share Issue Price | C6: =C4/D4 -> 0.25 | F6: =F5/G5 -> 5.6666667
B7: Total Shares | D7: =SUM(D4:D5) -> 1000000 | E7: =SUM(E4:E5) -> 1 | G7: =SUM(G4:G5) -> 1176470.6 | H7: =SUM(H4:H5) -> 1
B8: Pre-money Valuation | D8: 0 | G8: =G9-F5 -> 5666666.7
B9: Post-money Valuation | D9: 0 | G9: =F5/H5 -> 6666666.7

Sheet Operational Costs
A2: Web scraping fee/site | B2: 50
A3: Liveshots Crowd/product captured | B3: 8
A4: Products cost | B4: 5
A5: Labeling | B5: 1
A6: Software subscriptions/employee/month | B6: 84
A7: Equipment Lease/employee/month | B7: 67
A8: Hourly employees $10/hour/month | B8: 1680

Sheet Revenue Assumptions
B1: 2017* | C1: 2018 | D1: 2019
A2: Expected mComm Revenue (eMarketer mComm revenue forecast, June 2016) | B2: 169100000000 | C2: 204620000000 | D2: 246090000000
A3: Expected Percent mComm Revenue Apparel (ecommerce growth mean, eMarketer June 2016, see:I35) | B3: =$I$35 -> 0.18486456 | C3: =$I$35 -> 0.18486456 | D3: =$I$35 -> 0.18486456
A4: Expected mComm Revenue Apparel | B4: =B2*B3 -> 3.1260596e+10 | C4: =C2*C3 -> 3.7826985e+10 | D4: =D2*D3 -> 4.5493319e+10
A5: Expected mComm Revenue Apparel by 18-34 YO Age Group (Experian mComm % by Age) | B5: 14567036338 | C5: 17626889270 | D5: 21199302026
A6: Expected mComm Revenue Apparel by 18-34 YO Age Group Females (U.S. Census Bureau) | B6: 7123280770 | C6: 8619548853 | D6: 10366458691
A7: Expected Marketshare (avg. marketshare growth of Facebook, Wanelo, and Instagram) | B7: 4.4e-05 | C7: 0.001264 | D7: 0.01817
A8: Expected GMV Generated by Woolly | B8: 313239 | C8: 10895800 | D8: 188345183
A9: Expected Revenue Generated by Woolly | B9: 15662 | C9: 544790 | D9: 9417259
A10: Expected GMV Generated by Woolly | B10: 313239 | C10: 10895800 | D10: 188345183
A11: Expected Revenue Generated by Woolly | B11: 15662 | C11: 544790 | D11: 9417259
A13: *Partial year
A16: U.S. Mobile Commerce Sales 2014-2020, eMarketer June 2016 (excludes travel and event tickets)
B17: 2014 | C17: 2015 | D17: 2016 | E17: 2017 | F17: 2018 | G17: 2019 | H17: 2020
A18: mComm Rev ($B) | B18: 56.67 | C18: 89.17 | D18: 130.92 | E18: 169.1 | F18: 204.62 | G18: 246.09 | H18: 294.22
A19: YOY Growth | B19: 0.359 | C19: 0.574 | D19: 0.468 | E19: 0.292 | F19: 0.21 | G19: 0.203 | H19: 0.196
A20: % of retail eComm | B20: 0.19 | C20: 0.26 | D20: 0.33 | E20: 0.37 | F20: 0.39 | G20: 0.41 | H20: 0.43
A21: % of total retail | B21: 0.012 | C21: 0.019 | D21: 0.027 | E21: 0.034 | F21: 0.04 | G21: 0.046 | H21: 0.054
A22: Smartphone Rev ($B) | B22: 20.12 | C22: 39.68 | D22: 69.12 | E22: 92.33 | F22: 113.85 | G22: 139.56 | H22: 169.92
A23: YOY Growth | B23: 0.378 | C23: 0.972 | D23: 0.742 | E23: 0.336 | F23: 0.233 | G23: 0.226 | H23: 0.218
A24: % of mComm | B24: 0.355 | C24: 0.445 | D24: 0.528 | E24: 0.546 | F24: 0.556 | G24: 0.567 | H24: 0.578
A26: US Smartphone Buyers and Penetration 2014-2020 (in millions), eMarketer Feb 2016
B27: 2014 | C27: 2015 | D27: 2016 | E27: 2017 | F27: 2018 | G27: 2019 | H27: 2020
A28: Smartphone Buyers | B28: 67.2 | C28: 78.3 | D28: 87.8 | E28: 95.1 | F28: 100.7 | G28: 105.6 | H28: 109.5
A29: % Digital Buyers | B29: 0.408 | C29: 0.456 | D29: 0.491 | E29: 0.512 | F29: 0.526 | G29: 0.541 | H29: 0.55
A31: U.S. apparel and accessories ecommerce revenue 2013-2019, eMarketer June 2015 and Feb 2016 update
B32: 2013 | C32: 2014 | D32: 2015 | E32: 2016 | F32: 2017 | G32: 2018 | H32: 2019
A33: eComm Apparel Rev | B33: 45.5 | C33: 55.5 | D33: 63.5 | E33: 71.8 | F33: 80.7 | G33: 90.1 | H33: 100
A34: eComm Rev | B34: 260.67 | C34: 298.26 | D34: 340.61 | E34: 384.89 | F34: 431.84 | G34: 481.94 | H34: 534.95
A35: apparel % of eComm | B35: 0.1746 | C35: 0.1861 | D35: 0.1864 | E35: 0.1865 | F35: 0.1869 | G35: 0.187 | H35: 0.1869 | I35: =GEOMEAN(B35:H35) -> 0.18486456
A37: eMarketer, June 2016: % US Smartphone User Penetration by Age
B38: 2014 | C38: 2015 | D38: 2016 | E38: 2017 | F38: 2018 | G38: 2019 | H38: 2020
A39: 0-11 | B39: 28.7 | C39: 35.3 | D39: 41 | E39: 45 | F39: 47.1 | G39: 48.9 | H39: 49.7
A40: 43086 | B40: 71 | C40: 78.5 | D40: 84 | E40: 89 | F40: 91 | G40: 92 | H40: 92.9
A41: 18-24 | B41: 85.2 | C41: 90.1 | D41: 94.9 | E41: 98 | F41: 98.4 | G41: 99 | H41: 99.4
A42: 25-34 | B42: 84 | C42: 90.2 | D42: 95.2 | E42: 97 | F42: 97.1 | G42: 97.2 | H42: 97.3
A43: 35-44 | B43: 81.6 | C43: 87.7 | D43: 92 | E43: 94 | F43: 94.8 | G43: 96.1 | H43: 97
A44: 45-54 | B44: 66.9 | C44: 75.8 | D44: 82.8 | E44: 88.3 | F44: 92.8 | G44: 95.9 | H44: 97.9
A45: 55-64 | B45: 59.1 | C45: 67.6 | D45: 75.7 | E45: 80.9 | F45: 85.5 | G45: 89.5 | H45: 93
A46: 65+ | B46: 36.6 | C46: 40.7 | D46: 44.4 | E46: 49.6 | F46: 52.8 | G46: 55.7 | H46: 55.4
A47: Total: | B47: 67.6 | C47: 73.8 | D47: 79 | E47: 82.7 | F47: 84.8 | G47: 86.5 | H47: 87.3
A49: Share of Mobile Commerce by Age, Experian (2H 2014-1H 2015) U.S.
A50: Age | B50: 18-24 | C50: 25-34 | D50: 35-44 | E50: 45-54 | F50: 55-64 | G50: 65+
A51: Mobile Purchase % | B51: 0.166 | C51: 0.3 | D51: 0.274 | E51: 0.156 | F51: 0.078 | G51: 0.026
D52: 0.1096

Sheet AI Training Costs
A1: Assumptions
A2: Description | B2: Unit
A3: # of Shoes | B3: 1500 | F3: Total | N3: =$B$3/2 -> 750 | O3: =$B$3/2 -> 750 | P3: =SUM(L3:O3) -> 1500 | Q3: =$B$18 -> 400 | R3: =$B$18 -> 400 | S3: =$B$18 -> 400 | T3: =$B$18 -> 400 | U3: =SUM(Q3:T3) -> 1600 | V3: =$B$18 -> 400 | W3: =$B$18 -> 400 | X3: =$B$18 -> 400 | Y3: =$B$18 -> 400 | Z3: =SUM(V3:Y3) -> 1600 | AA3: =$B$18 -> 400 | AB3: =$B$18 -> 400 | AC3: =$B$18 -> 400 | AD3: =$B$18 -> 400 | AE3: =SUM(AA3:AD3) -> 1600 | AF3: =$B$18 -> 400 | AG3: =$B$18 -> 400 | AH3: =$B$18 -> 400 | AI3: =$B$18 -> 400 | AJ3: =SUM(AF3:AI3) -> 1600
A4: # of Apparel Items | B4: 3000 | F4: Total | N4: =$B$4/2 -> 1500 | O4: =$B$4/2 -> 1500 | P4: =SUM(L4:O4) -> 3000 | Q4: =$B$18 -> 400 | R4: =$B$18 -> 400 | S4: =$B$18 -> 400 | T4: =$B$18 -> 400 | U4: =SUM(Q4:T4) -> 1600 | V4: =$B$18 -> 400 | W4: =$B$18 -> 400 | X4: =$B$18 -> 400 | Y4: =$B$18 -> 400 | Z4: =SUM(V4:Y4) -> 1600 | AA4: =$B$18 -> 400 | AB4: =$B$18 -> 400 | AC4: =$B$18 -> 400 | AD4: =$B$18 -> 400 | AE4: =SUM(AA4:AD4) -> 1600 | AF4: =$B$18 -> 400 | AG4: =$B$18 -> 400 | AH4: =$B$18 -> 400 | AI4: =$B$18 -> 400 | AJ4: =SUM(AF4:AI4) -> 1600
A5: # of Accessories | B5: 1500 | F5: Total | N5: =$B$5/2 -> 750 | O5: =$B$5/2 -> 750 | P5: =SUM(L5:O5) -> 1500 | Q5: =$B$18 -> 400 | R5: =$B$18 -> 400 | S5: =$B$18 -> 400 | T5: =$B$18 -> 400 | U5: =SUM(Q5:T5) -> 1600 | V5: =$B$18 -> 400 | W5: =$B$18 -> 400 | X5: =$B$18 -> 400 | Y5: =$B$18 -> 400 | Z5: =SUM(V5:Y5) -> 1600 | AA5: =$B$18 -> 400 | AB5: =$B$18 -> 400 | AC5: =$B$18 -> 400 | AD5: =$B$18 -> 400 | AE5: =SUM(AA5:AD5) -> 1600 | AF5: =$B$18 -> 400 | AG5: =$B$18 -> 400 | AH5: =$B$18 -> 400 | AI5: =$B$18 -> 400 | AJ5: =SUM(AF5:AI5) -> 1600
A6: Bought/Resold | B6: 0.3 | N6: =B6 -> 0.3 | O6: =N6 -> 0.3 | P6: =AVERAGE(L6:O6) -> 0.3 | Q6: =P6 -> 0.3 | R6: =Q6 -> 0.3 | S6: =R6 -> 0.3 | T6: =S6 -> 0.3 | U6: =AVERAGE(Q6:T6) -> 0.3 | V6: 0.15 | W6: =V6 -> 0.15 | X6: =W6 -> 0.15 | Y6: =X6 -> 0.15 | Z6: =AVERAGE(V6:Y6) -> 0.15 | AA6: 0.05 | AB6: 0.05 | AC6: =AB6 -> 0.05 | AD6: =AC6 -> 0.05 | AE6: =AVERAGE(AA6:AD6) -> 0.05 | AF6: =AD6 -> 0.05 | AG6: =AF6 -> 0.05 | AH6: =AG6 -> 0.05 | AI6: =AH6 -> 0.05 | AJ6: =AVERAGE(AF6:AI6) -> 0.05
A7: Charity Items | B7: 0.4 | N7: =B7 -> 0.4 | O7: =N7 -> 0.4 | P7: =AVERAGE(L7:O7) -> 0.4 | Q7: =P7 -> 0.4 | R7: =Q7 -> 0.4 | S7: =R7 -> 0.4 | T7: =S7 -> 0.4 | U7: =AVERAGE(Q7:T7) -> 0.4 | V7: 0.3 | W7: =V7 -> 0.3 | X7: =W7 -> 0.3 | Y7: =X7 -> 0.3 | Z7: =AVERAGE(V7:Y7) -> 0.3 | AA7: 0.15 | AB7: =AA7 -> 0.15 | AC7: =AB7 -> 0.15 | AD7: =AC7 -> 0.15 | AE7: =AVERAGE(AA7:AD7) -> 0.15 | AF7: =AD7 -> 0.15 | AG7: =AF7 -> 0.15 | AH7: =AG7 -> 0.15 | AI7: =AH7 -> 0.15 | AJ7: =AVERAGE(AF7:AI7) -> 0.15
A8: Bought | B8: 0.3 | N8: =B8 -> 0.3 | O8: =N8 -> 0.3 | P8: =AVERAGE(L8:O8) -> 0.3 | Q8: =P8 -> 0.3 | R8: =Q8 -> 0.3 | S8: =R8 -> 0.3 | T8: =S8 -> 0.3 | U8: =AVERAGE(Q8:T8) -> 0.3 | V8: 0.05 | W8: =V8 -> 0.05 | X8: =W8 -> 0.05 | Y8: =X8 -> 0.05 | Z8: =AVERAGE(V8:Y8) -> 0.05 | AA8: =Z8 -> 0.05 | AB8: =AA8 -> 0.05 | AC8: =AB8 -> 0.05 | AD8: =AC8 -> 0.05 | AE8: =AVERAGE(AA8:AD8) -> 0.05 | AF8: =AD8 -> 0.05 | AG8: =AF8 -> 0.05 | AH8: =AG8 -> 0.05 | AI8: =AH8 -> 0.05 | AJ8: =AVERAGE(AF8:AI8) -> 0.05
A9: Free | B9: 0 | N9: =B9 -> 0 | O9: =N9 -> 0 | P9: =AVERAGE(L9:O9) -> 0 | Q9: =P9 -> 0 | R9: =Q9 -> 0 | S9: =R9 -> 0 | T9: =S9 -> 0 | U9: =AVERAGE(Q9:T9) -> 0 | V9: 0.5 | W9: =V9 -> 0.5 | X9: =W9 -> 0.5 | Y9: =X9 -> 0.5 | Z9: =AVERAGE(V9:Y9) -> 0.5 | AA9: 0.75 | AB9: =AA9 -> 0.75 | AC9: =AB9 -> 0.75 | AD9: =AC9 -> 0.75 | AE9: =AVERAGE(AA9:AD9) -> 0.75 | AF9: =AD9 -> 0.75 | AG9: =AF9 -> 0.75 | AH9: =AG9 -> 0.75 | AI9: =AH9 -> 0.75 | AJ9: =AVERAGE(AF9:AI9) -> 0.75
A10: Wholesale cost/shoe | B10: 100 | F10: Avg. | N10: =B10 -> 100 | O10: 100 | P10: =AVERAGE(L10:O10) -> 100 | Q10: =$B10 -> 100 | R10: =$B10 -> 100 | S10: =$B10 -> 100 | T10: =$B10 -> 100 | U10: =$B10 -> 100 | V10: =$B10 -> 100 | W10: =$B10 -> 100 | X10: =$B10 -> 100 | ... AJ10: =$B10 -> 100
A11: Wholesale cost/apparel | B11: 25 | F11: Avg. | N11: =B11 -> 25 | O11: 25 | P11: =AVERAGE(L11:O11) -> 25 | Q11: =$B11 -> 25 | R11: =$B11 -> 25 | S11: =$B11 -> 25 | T11: =$B11 -> 25 | U11: =$B11 -> 25 | V11: =$B11 -> 25 | W11: =$B11 -> 25 | X11: =$B11 -> 25 | ... AJ11: =$B11 -> 25
A12: Wholesale Cost/accessories | B12: 50 | F12: Avg. | N12: =B12 -> 50 | O12: 75 | P12: =AVERAGE(L12:O12) -> 62.5 | Q12: =$B12 -> 50 | R12: =$B12 -> 50 | S12: =$B12 -> 50 | T12: =$B12 -> 50 | U12: =$B12 -> 50 | V12: =$B12 -> 50 | W12: =$B12 -> 50 | X12: =$B12 -> 50 | ... AJ12: =$B12 -> 50
A13: Cost/Charity item | B13: 10 | N13: =B13 -> 10 | O13: =N13 -> 10 | P13: =O13 -> 10 | Q13: =P13 -> 10 | R13: =Q13 -> 10 | S13: =R13 -> 10 | T13: =S13 -> 10 | U13: =T13 -> 10 | V13: =U13 -> 10 | ... AE13: =AD13 -> 10 | AF13: =AD13 -> 10 | AG13: =AF13 -> 10 | AH13: =AG13 -> 10 | AI13: =AH13 -> 10 | AJ13: =AI13 -> 10
A14: Resell value % | B14: 0.5 | N14: =B14 -> 0.5 | O14: =N14 -> 0.5 | P14: =O14 -> 0.5 | Q14: =P14 -> 0.5 | R14: =Q14 -> 0.5 | S14: =R14 -> 0.5 | T14: =S14 -> 0.5 | U14: =T14 -> 0.5 | V14: =U14 -> 0.5 | ... AE14: =AD14 -> 0.5 | AF14: =AD14 -> 0.5 | AG14: =AF14 -> 0.5 | AH14: =AG14 -> 0.5 | AI14: =AH14 -> 0.5 | AJ14: =AI14 -> 0.5
A15: Shipping | B15: 2 | F15: Avg. | N15: =B15 -> 2 | O15: =$B$15 -> 2 | P15: =AVERAGE(L15:O15) -> 2 | Q15: =$B$15 -> 2 | R15: =$B$15 -> 2 | S15: =$B$15 -> 2 | T15: =$B$15 -> 2 | U15: =AVERAGE(Q15:T15) -> 2 | V15: =$B$15 -> 2 | W15: =$B$15 -> 2 | X15: =$B$15 -> 2 | Y15: =$B$15 -> 2 | Z15: =AVERAGE(V15:Y15) -> 2 | AA15: =$B$15 -> 2 | AB15: =$B$15 -> 2 | AC15: =$B$15 -> 2 | AD15: =$B$15 -> 2 | AE15: =AVERAGE(AA15:AD15) -> 2 | AF15: =$B$15 -> 2 | AG15: =$B$15 -> 2 | AH15: =$B$15 -> 2 | AI15: =$B$15 -> 2 | AJ15: =AVERAGE(AF15:AI15) -> 2
A16: Labor (hrs/item) | B16: 0.25 | F16: Avg. | N16: =B16 -> 0.25 | O16: =$B$16 -> 0.25 | P16: =AVERAGE(L16:O16) -> 0.25 | Q16: =$B$16 -> 0.25 | R16: =$B$16 -> 0.25 | S16: =$B$16 -> 0.25 | T16: =$B$16 -> 0.25 | U16: =AVERAGE(Q16:T16) -> 0.25 | V16: =$B$16 -> 0.25 | W16: =$B$16 -> 0.25 | X16: =$B$16 -> 0.25 | Y16: =$B$16 -> 0.25 | Z16: =AVERAGE(V16:Y16) -> 0.25 | AA16: =$B$16 -> 0.25 | AB16: =$B$16 -> 0.25 | AC16: =$B$16 -> 0.25 | AD16: =$B$16 -> 0.25 | AE16: =AVERAGE(AA16:AD16) -> 0.25 | AF16: =$B$16 -> 0.25 | AG16: =$B$16 -> 0.25 | AH16: =$B$16 -> 0.25 | AI16: =$B$16 -> 0.25 | AJ16: =AVERAGE(AF16:AI16) -> 0.25
A17: Photo Labor expense/hr | B17: 15 | F17: Avg. | N17: =B17 -> 15 | O17: =$B$17 -> 15 | P17: =AVERAGE(L17:O17) -> 15 | Q17: =$B$17*(1+$B$47) -> 15.525 | R17: =$B$17*(1+$B$47) -> 15.525 | S17: =$B$17*(1+$B$47) -> 15.525 | T17: =$B$17*(1+$B$47) -> 15.525 | U17: =AVERAGE(Q17:T17) -> 15.525 | V17: =$B$17*(1+$B$47)^2 -> 16.068375 | W17: =$B$17*(1+$B$47)^2 -> 16.068375 | X17: =$B$17*(1+$B$47)^2 -> 16.068375 | Y17: =$B$17*(1+$B$47)^2 -> 16.068375 | Z17: =AVERAGE(V17:Y17) -> 16.068375 | AA17: 0 | AB17: 0 | AC17: 0 | AD17: 0 | AE17: =AVERAGE(AA17:AD17) -> 0 | AF17: 0 | AG17: 0 | AH17: 0 | AI17: 0 | AJ17: =AVERAGE(AF17:AI17) -> 0
A18: # of Ongoing items / Quarter | B18: 400
A19: # photos/item | B19: 60 | N19: =B19 -> 60 | O19: =N19 -> 60 | P19: =O19 -> 60 | Q19: =P19 -> 60 | R19: =Q19 -> 60 | S19: =R19 -> 60 | T19: =S19 -> 60 | U19: =T19 -> 60 | V19: =U19 -> 60 | ... AE19: =AD19 -> 60 | AF19: =AD19 -> 60 | AG19: =AF19 -> 60 | AH19: =AG19 -> 60 | AI19: =AH19 -> 60 | AJ19: =AI19 -> 60
A20: Photo Tagging Labor (items/hr) | B20: 90 | N20: =B20 -> 90 | O20: =N20 -> 90 | P20: =O20 -> 90 | Q20: =P20 -> 90 | R20: =Q20 -> 90 | S20: =R20 -> 90 | T20: =S20 -> 90 | U20: =T20 -> 90 | V20: =U20 -> 90 | ... AE20: =AD20 -> 90 | AF20: =AD20 -> 90 | AG20: =AF20 -> 90 | AH20: =AG20 -> 90 | AI20: =AH20 -> 90 | AJ20: =AI20 -> 90
A21: Photo tagging Labor expense/hr | B21: 3.75 | N21: =B21 -> 3.75 | O21: =N21 -> 3.75 | P21: =O21 -> 3.75 | Q21: =P21 -> 3.75 | R21: =Q21 -> 3.75 | S21: =R21 -> 3.75 | T21: =S21 -> 3.75 | U21: =T21 -> 3.75 | V21: =U21 -> 3.75 | ... AE21: =AD21 -> 3.75 | AF21: =AD21 -> 3.75 | AG21: =AF21 -> 3.75 | AH21: =AG21 -> 3.75 | AI21: =AH21 -> 3.75 | AJ21: =AI21 -> 3.75
A22: Syn. Tagging Labor (items/hr) | B22: 120 | N22: =B22 -> 120 | O22: =N22 -> 120 | P22: =O22 -> 120 | Q22: =P22 -> 120 | R22: =Q22 -> 120 | S22: =R22 -> 120 | T22: =S22 -> 120 | U22: =T22 -> 120 | V22: =U22 -> 120 | ... AE22: =AD22 -> 120 | AF22: =AD22 -> 120 | AG22: =AF22 -> 120 | AH22: =AG22 -> 120 | AI22: =AH22 -> 120 | AJ22: =AI22 -> 120
A23: Syn. Tagging Labor exp. (items/hr) | B23: 3.75 | N23: =B23 -> 3.75 | O23: =N23 -> 3.75 | P23: =O23 -> 3.75 | Q23: =P23 -> 3.75 | R23: =Q23 -> 3.75 | S23: =R23 -> 3.75 | T23: =S23 -> 3.75 | U23: =T23 -> 3.75 | V23: =U23 -> 3.75 | ... AE23: =AD23 -> 3.75 | AF23: =AD23 -> 3.75 | AG23: =AF23 -> 3.75 | AH23: =AG23 -> 3.75 | AI23: =AH23 -> 3.75 | AJ23: =AI23 -> 3.75
A24: Syn. Tags per item | B24: 3.75 | N24: =B24 -> 3.75 | O24: =N24 -> 3.75 | P24: =O24 -> 3.75 | Q24: =P24 -> 3.75 | R24: =Q24 -> 3.75 | S24: =R24 -> 3.75 | T24: =S24 -> 3.75 | U24: =T24 -> 3.75 | V24: =U24 -> 3.75 | ... AE24: =AD24 -> 3.75 | AF24: =AD24 -> 3.75 | AG24: =AF24 -> 3.75 | AH24: =AG24 -> 3.75 | AI24: =AH24 -> 3.75 | AJ24: =AI24 -> 3.75
A25: S & H (Items/hr) | B25: 20 | N25: =B25 -> 20 | O25: =N25 -> 20 | P25: =O25 -> 20 | Q25: =P25 -> 20 | R25: =Q25 -> 20 | S25: =R25 -> 20 | T25: =S25 -> 20 | U25: =T25 -> 20 | V25: =U25 -> 20 | ... AE25: =AD25 -> 20 | AF25: =AD25 -> 20 | AG25: =AF25 -> 20 | AH25: =AG25 -> 20 | AI25: =AH25 -> 20 | AJ25: =AI25 -> 20
A26: S & H Labor (expense/hr) | B26: 15 | N26: =B26 -> 15 | O26: =N26 -> 15 | P26: =O26 -> 15 | Q26: =P26 -> 15 | R26: =Q26 -> 15 | S26: =R26 -> 15 | T26: =S26 -> 15 | U26: =T26 -> 15 | V26: =U26 -> 15 | ... AE26: =AD26 -> 15 | AF26: =AD26 -> 15 | AG26: =AF26 -> 15 | AH26: =AG26 -> 15 | AI26: =AH26 -> 15 | AJ26: =AI26 -> 15
A27: Modeling Labor expense | B27: 15 | N27: =B27 -> 15 | O27: =N27 -> 15 | P27: =O27 -> 15 | Q27: =P27 -> 15 | R27: =Q27 -> 15 | S27: =R27 -> 15 | T27: =S27 -> 15 | U27: =T27 -> 15 | V27: =U27 -> 15 | ... AE27: =AD27 -> 15 | AF27: =AD27 -> 15 | AG27: =AF27 -> 15 | AH27: =AG27 -> 15 | AI27: =AH27 -> 15 | AJ27: =AI27 -> 15
G28: Q1-17 | H28: Q2-17 | I28: Q3-17 | J28: Q4-17 | K28: 2017 | L28: Q1-18 | M28: Q2-18 | N28: Q3-18 | O28: Q4-18 | P28: 2018 | Q28: Q1-19 | R28: Q2-19 | S28: Q3-19 | T28: Q4-19 | U28: 2019 | V28: Q1-20 | W28: Q2-20 | X28: Q3-20 | Y28: Q4-20 | Z28: 2020 | AA28: Q1-21 | AB28: Q2-21 | AC28: Q3-21 | AD28: Q4-21 | AE28: 2021 | AF28: Q1-22 | AG28: Q2-22 | AH28: Q3-22 | AI28: Q4-22 | AJ28: 2021
C30: Shoes
F31: Bought/Resold | G31: =G6*G$3 -> 0 | H31: =H6*H$3 -> 0 | I31: =I6*I$3 -> 0 | J31: =J6*J$3 -> 0 | K31: =SUM(G31:J31) -> 0 | L31: =L6*L$3 -> 0 | M31: =M6*M$3 -> 0 | N31: =N6*N$3 -> 225 | O31: =O6*O$3 -> 225 | P31: =SUM(L31:O31) -> 450 | Q31: =Q6*Q$3 -> 120 | R31: =R6*R$3 -> 120 | S31: =S6*S$3 -> 120 | T31: =T6*T$3 -> 120 | U31: =SUM(Q31:T31) -> 480 | V31: =V6*V$3 -> 60 | W31: =W6*W$3 -> 60 | X31: =X6*X$3 -> 60 | Y31: =Y6*Y$3 -> 60 | Z31: =SUM(V31:Y31) -> 240 | AA31: =AA6*AA$3 -> 20 | AB31: =AB6*AB$3 -> 20 | AC31: =AC6*AC$3 -> 20 | AD31: =AD6*AD$3 -> 20 | AE31: =SUM(AA31:AD31) -> 80 | AF31: =AF6*AF$3 -> 20 | AG31: =AG6*AG$3 -> 20 | AH31: =AH6*AH$3 -> 20 | AI31: =AI6*AI$3 -> 20 | AJ31: =SUM(AF31:AI31) -> 80
F32: Charity Items | G32: =G7*G$3 -> 0 | H32: =H7*H$3 -> 0 | I32: =I7*I$3 -> 0 | J32: =J7*J$3 -> 0 | K32: =SUM(G32:J32) -> 0 | L32: =L7*L$3 -> 0 | M32: =M7*M$3 -> 0 | N32: =N7*N$3 -> 300 | O32: =O7*O$3 -> 300 | P32: =SUM(L32:O32) -> 600 | Q32: =Q7*Q$3 -> 160 | R32: =R7*R$3 -> 160 | S32: =S7*S$3 -> 160 | T32: =T7*T$3 -> 160 | U32: =SUM(Q32:T32) -> 640 | V32: =V7*V$3 -> 120 | W32: =W7*W$3 -> 120 | X32: =X7*X$3 -> 120 | Y32: =Y7*Y$3 -> 120 | Z32: =SUM(V32:Y32) -> 480 | AA32: =AA7*AA$3 -> 60 | AB32: =AB7*AB$3 -> 60 | AC32: =AC7*AC$3 -> 60 | AD32: =AD7*AD$3 -> 60 | AE32: =SUM(AA32:AD32) -> 240 | AF32: =AF7*AF$3 -> 60 | AG32: =AG7*AG$3 -> 60 | AH32: =AH7*AH$3 -> 60 | AI32: =AI7*AI$3 -> 60 | AJ32: =SUM(AF32:AI32) -> 240
F33: Bought Outright | G33: =G8*G$3 -> 0 | H33: =H8*H$3 -> 0 | I33: =I8*I$3 -> 0 | J33: =J8*J$3 -> 0 | K33: =SUM(G33:J33) -> 0 | L33: =L8*L$3 -> 0 | M33: =M8*M$3 -> 0 | N33: =N8*N$3 -> 225 | O33: =O8*O$3 -> 225 | P33: =SUM(L33:O33) -> 450 | Q33: =Q8*Q$3 -> 120 | R33: =R8*R$3 -> 120 | S33: =S8*S$3 -> 120 | T33: =T8*T$3 -> 120 | U33: =SUM(Q33:T33) -> 480 | V33: =V8*V$3 -> 20 | W33: =W8*W$3 -> 20 | X33: =X8*X$3 -> 20 | Y33: =Y8*Y$3 -> 20 | Z33: =SUM(V33:Y33) -> 80 | AA33: =AA8*AA$3 -> 20 | AB33: =AB8*AB$3 -> 20 | AC33: =AC8*AC$3 -> 20 | AD33: =AD8*AD$3 -> 20 | AE33: =SUM(AA33:AD33) -> 80 | AF33: =AF8*AF$3 -> 20 | AG33: =AG8*AG$3 -> 20 | AH33: =AH8*AH$3 -> 20 | AI33: =AI8*AI$3 -> 20 | AJ33: =SUM(AF33:AI33) -> 80
F34: Free | G34: =G9*G$3 -> 0 | H34: =H9*H$3 -> 0 | I34: =I9*I$3 -> 0 | J34: =J9*J$3 -> 0 | K34: =SUM(G34:J34) -> 0 | L34: =L9*L$3 -> 0 | M34: =M9*M$3 -> 0 | N34: =N9*N$3 -> 0 | O34: =O9*O$3 -> 0 | P34: =SUM(L34:O34) -> 0 | Q34: =Q9*Q$3 -> 0 | R34: =R9*R$3 -> 0 | S34: =S9*S$3 -> 0 | T34: =T9*T$3 -> 0 | U34: =SUM(Q34:T34) -> 0 | V34: =V9*V$3 -> 200 | W34: =W9*W$3 -> 200 | X34: =X9*X$3 -> 200 | Y34: =Y9*Y$3 -> 200 | Z34: =SUM(V34:Y34) -> 800 | AA34: =AA9*AA$3 -> 300 | AB34: =AB9*AB$3 -> 300 | AC34: =AC9*AC$3 -> 300 | AD34: =AD9*AD$3 -> 300 | AE34: =SUM(AA34:AD34) -> 1200 | AF34: =AF9*AF$3 -> 300 | AG34: =AG9*AG$3 -> 300 | AH34: =AH9*AH$3 -> 300 | AI34: =AI9*AI$3 -> 300 | AJ34: =SUM(AF34:AI34) -> 1200
D35: Total Items | G35: =SUM(G31:G34) -> 0 | H35: =SUM(H31:H34) -> 0 | I35: =SUM(I31:I34) -> 0 | J35: =SUM(J31:J34) -> 0 | K35: =SUM(G35:J35) -> 0 | L35: =SUM(L31:L34) -> 0 | M35: =SUM(M31:M34) -> 0 | N35: =SUM(N31:N34) -> 750 | O35: =SUM(O31:O34) -> 750 | P35: =SUM(L35:O35) -> 1500 | Q35: =SUM(Q31:Q34) -> 400 | R35: =SUM(R31:R34) -> 400 | S35: =SUM(S31:S34) -> 400 | T35: =SUM(T31:T34) -> 400 | U35: =SUM(Q35:T35) -> 1600 | V35: =SUM(V31:V34) -> 400 | W35: =SUM(W31:W34) -> 400 | X35: =SUM(X31:X34) -> 400 | Y35: =SUM(Y31:Y34) -> 400 | Z35: =SUM(V35:Y35) -> 1600 | AA35: =SUM(AA31:AA34) -> 400 | AB35: =SUM(AB31:AB34) -> 400 | AC35: =SUM(AC31:AC34) -> 400 | AD35: =SUM(AD31:AD34) -> 400 | AE35: =SUM(AA35:AD35) -> 1600 | AF35: =SUM(AF31:AF34) -> 400 | AG35: =SUM(AG31:AG34) -> 400 | AH35: =SUM(AH31:AH34) -> 400 | AI35: =SUM(AI31:AI34) -> 400 | AJ35: =SUM(AF35:AI35) -> 1600
F36: Bought/Resold | G36: =(G31*G10*(1-G14)) -> 0 | H36: =(H31*H10*(1-H14)) -> 0 | I36: =(I31*I10*(1-I14)) -> 0 | J36: =(J31*J10*(1-J14)) -> 0 | K36: =SUM(G36:J36) -> 0 | L36: =(L31*L10*(1-L14)) -> 0 | M36: =(M31*M10*(1-M14)) -> 0 | N36: =(N31*N10*(1-N14)) -> 11250 | O36: =(O31*O10*(1-O14)) -> 11250 | P36: =SUM(L36:O36) -> 22500 | Q36: =(Q31*Q10*(1-Q14)) -> 6000 | R36: =(R31*R10*(1-R14)) -> 6000 | S36: =(S31*S10*(1-S14)) -> 6000 | T36: =(T31*T10*(1-T14)) -> 6000 | U36: =SUM(Q36:T36) -> 24000 | V36: =(V31*V10*(1-V14)) -> 3000 | W36: =(W31*W10*(1-W14)) -> 3000 | X36: =(X31*X10*(1-X14)) -> 3000 | Y36: =(Y31*Y10*(1-Y14)) -> 3000 | Z36: =SUM(V36:Y36) -> 12000 | AA36: =(AA31*AA10*(1-AA14)) -> 1000 | AB36: =(AB31*AB10*(1-AB14)) -> 1000 | AC36: =(AC31*AC10*(1-AC14)) -> 1000 | AD36: =(AD31*AD10*(1-AD14)) -> 1000 | AE36: =SUM(AA36:AD36) -> 4000 | AF36: =(AF31*AF10*(1-AF14)) -> 1000 | AG36: =(AG31*AG10*(1-AG14)) -> 1000 | AH36: =(AH31*AH10*(1-AH14)) -> 1000 | AI36: =(AI31*AI10*(1-AI14)) -> 1000 | AJ36: =SUM(AF36:AI36) -> 4000
F37: Charity Items | G37: =G32*G13 -> 0 | H37: =H32*H13 -> 0 | I37: =I32*I13 -> 0 | J37: =J32*J13 -> 0 | K37: =SUM(G37:J37) -> 0 | L37: =L32*L13 -> 0 | M37: =M32*M13 -> 0 | N37: =N32*N13 -> 3000 | O37: =O32*O13 -> 3000 | P37: =SUM(L37:O37) -> 6000 | Q37: =Q32*Q13 -> 1600 | R37: =R32*R13 -> 1600 | S37: =S32*S13 -> 1600 | T37: =T32*T13 -> 1600 | U37: =SUM(Q37:T37) -> 6400 | V37: =V32*V13 -> 1200 | W37: =W32*W13 -> 1200 | X37: =X32*X13 -> 1200 | Y37: =Y32*Y13 -> 1200 | Z37: =SUM(V37:Y37) -> 4800 | AA37: =AA32*AA13 -> 600 | AB37: =AB32*AB13 -> 600 | AC37: =AC32*AC13 -> 600 | AD37: =AD32*AD13 -> 600 | AE37: =SUM(AA37:AD37) -> 2400 | AF37: =AF32*AF13 -> 600 | AG37: =AG32*AG13 -> 600 | AH37: =AH32*AH13 -> 600 | AI37: =AI32*AI13 -> 600 | AJ37: =SUM(AF37:AI37) -> 2400
F38: Bought Outright | G38: =G33*G10 -> 0 | H38: =H33*H10 -> 0 | I38: =I33*I10 -> 0 | J38: =J33*J10 -> 0 | K38: =SUM(G38:J38) -> 0 | L38: =L33*L10 -> 0 | M38: =M33*M10 -> 0 | N38: =N33*N10 -> 22500 | O38: =O33*O10 -> 22500 | P38: =SUM(L38:O38) -> 45000 | Q38: =Q33*Q10 -> 12000 | R38: =R33*R10 -> 12000 | S38: =S33*S10 -> 12000 | T38: =T33*T10 -> 12000 | U38: =SUM(Q38:T38) -> 48000 | V38: =V33*V10 -> 2000 | W38: =W33*W10 -> 2000 | X38: =X33*X10 -> 2000 | Y38: =Y33*Y10 -> 2000 | Z38: =SUM(V38:Y38) -> 8000 | AA38: =AA33*AA10 -> 2000 | AB38: =AB33*AB10 -> 2000 | AC38: =AC33*AC10 -> 2000 | AD38: =AD33*AD10 -> 2000 | AE38: =SUM(AA38:AD38) -> 8000 | AF38: =AF33*AF10 -> 2000 | AG38: =AG33*AG10 -> 2000 | AH38: =AH33*AH10 -> 2000 | AI38: =AI33*AI10 -> 2000 | AJ38: =SUM(AF38:AI38) -> 8000
F39: Free | G39: =G34*0 -> 0 | H39: =H34*0 -> 0 | I39: =I34*0 -> 0 | J39: =J34*0 -> 0 | K39: =SUM(G39:J39) -> 0 | L39: =L34*0 -> 0 | M39: =M34*0 -> 0 | N39: =N34*0 -> 0 | O39: =O34*0 -> 0 | P39: =SUM(L39:O39) -> 0 | Q39: =Q34*0 -> 0 | R39: =R34*0 -> 0 | S39: =S34*0 -> 0 | T39: =T34*0 -> 0 | U39: =SUM(Q39:T39) -> 0 | V39: =V34*0 -> 0 | W39: =W34*0 -> 0 | X39: =X34*0 -> 0 | Y39: =Y34*0 -> 0 | Z39: =SUM(V39:Y39) -> 0 | AA39: =AA34*0 -> 0 | AB39: =AB34*0 -> 0 | AC39: =AC34*0 -> 0 | AD39: =AD34*0 -> 0 | AE39: =SUM(AA39:AD39) -> 0 | AF39: =AF34*0 -> 0 | AG39: =AG34*0 -> 0 | AH39: =AH34*0 -> 0 | AI39: =AI34*0 -> 0 | AJ39: =SUM(AF39:AI39) -> 0
E40: Product Costs | G40: =SUM(G36:G39) -> 0 | H40: =SUM(H36:H39) -> 0 | I40: =SUM(I36:I39) -> 0 | J40: =SUM(J36:J39) -> 0 | K40: =SUM(G40:J40) -> 0 | L40: =SUM(L36:L39) -> 0 | M40: =SUM(M36:M39) -> 0 | N40: =SUM(N36:N39) -> 36750 | O40: =SUM(O36:O39) -> 36750 | P40: =SUM(L40:O40) -> 73500 | Q40: =SUM(Q36:Q39) -> 19600 | R40: =SUM(R36:R39) -> 19600 | S40: =SUM(S36:S39) -> 19600 | T40: =SUM(T36:T39) -> 19600 | U40: =SUM(Q40:T40) -> 78400 | V40: =SUM(V36:V39) -> 6200 | W40: =SUM(W36:W39) -> 6200 | X40: =SUM(X36:X39) -> 6200 | Y40: =SUM(Y36:Y39) -> 6200 | Z40: =SUM(V40:Y40) -> 24800 | AA40: =SUM(AA36:AA39) -> 3600 | AB40: =SUM(AB36:AB39) -> 3600 | AC40: =SUM(AC36:AC39) -> 3600 | AD40: =SUM(AD36:AD39) -> 3600 | AE40: =SUM(AA40:AD40) -> 14400 | AF40: =SUM(AF36:AF39) -> 3600 | AG40: =SUM(AG36:AG39) -> 3600 | AH40: =SUM(AH36:AH39) -> 3600 | AI40: =SUM(AI36:AI39) -> 3600 | AJ40: =SUM(AF40:AI40) -> 14400
E41: Shipping | G41: =G3*G15 -> 0 | H41: =H3*H15 -> 0 | I41: =I3*I15 -> 0 | J41: =J3*J15 -> 0 | K41: =SUM(G41:J41) -> 0 | L41: =L3*L15 -> 0 | M41: =M3*M15 -> 0 | N41: =N3*N15 -> 1500 | O41: =O3*O15 -> 1500 | P41: =SUM(L41:O41) -> 3000 | Q41: =Q3*Q15 -> 800 | R41: =R3*R15 -> 800 | S41: =S3*S15 -> 800 | T41: =T3*T15 -> 800 | U41: =SUM(Q41:T41) -> 3200 | V41: =V3*V15 -> 800 | W41: =W3*W15 -> 800 | X41: =X3*X15 -> 800 | Y41: =Y3*Y15 -> 800 | Z41: =SUM(V41:Y41) -> 3200 | AA41: =AA3*AA15 -> 800 | AB41: =AB3*AB15 -> 800 | AC41: =AC3*AC15 -> 800 | AD41: =AD3*AD15 -> 800 | AE41: =SUM(AA41:AD41) -> 3200 | AF41: =AF3*AF15 -> 800 | AG41: =AG3*AG15 -> 800 | AH41: =AH3*AH15 -> 800 | AI41: =AI3*AI15 -> 800 | AJ41: =SUM(AF41:AI41) -> 3200
F42: Photography Labor | G42: =G3*G$16*G$17 -> 0 | H42: =H3*H$16*H$17 -> 0 | I42: =I3*I$16*I$17 -> 0 | J42: =J3*J$16*J$17 -> 0 | K42: =SUM(G42:J42) -> 0 | L42: =L3*L$16*L$17 -> 0 | M42: =M3*M$16*M$17 -> 0 | N42: =N3*N$16*N$17 -> 2812.5 | O42: =O3*O$16*O$17 -> 2812.5 | P42: =SUM(L42:O42) -> 5625 | Q42: =Q3*Q$16*Q$17 -> 1552.5 | R42: =R3*R$16*R$17 -> 1552.5 | S42: =S3*S$16*S$17 -> 1552.5 | T42: =T3*T$16*T$17 -> 1552.5 | U42: =SUM(Q42:T42) -> 6210 | V42: =V3*V$16*V$17 -> 1606.8375 | W42: =W3*W$16*W$17 -> 1606.8375 | X42: =X3*X$16*X$17 -> 1606.8375 | Y42: =Y3*Y$16*Y$17 -> 1606.8375 | Z42: =SUM(V42:Y42) -> 6427.35 | AA42: =AA3*AA$16*AA$17 -> 0 | AB42: =AB3*AB$16*AB$17 -> 0 | AC42: =AC3*AC$16*AC$17 -> 0 | AD42: =AD3*AD$16*AD$17 -> 0 | AE42: =SUM(AA42:AD42) -> 0 | AF42: =AF3*AF$16*AF$17 -> 0 | AG42: =AG3*AG$16*AG$17 -> 0 | AH42: =AH3*AH$16*AH$17 -> 0 | AI42: =AI3*AI$16*AI$17 -> 0 | AJ42: =SUM(AF42:AI42) -> 0
F43: S & H Labor | G43: =IFERROR(G3/G$25*G$26, 0) -> 0 | H43: =IFERROR(H3/H$25*H$26, 0) -> 0 | I43: =IFERROR(I3/I$25*I$26, 0) -> 0 | J43: =IFERROR(J3/J$25*J$26, 0) -> 0 | K43: =SUM(G43:J43) -> 0 | L43: =IFERROR(L3/L$25*L$26, 0) -> 0 | M43: =IFERROR(M3/M$25*M$26, 0) -> 0 | N43: =IFERROR(N3/N$25*N$26, 0) -> 562.5 | O43: =IFERROR(O3/O$25*O$26, 0) -> 562.5 | P43: =SUM(L43:O43) -> 1125 | Q43: =IFERROR(Q3/Q$25*Q$26, 0) -> 300 | R43: =IFERROR(R3/R$25*R$26, 0) -> 300 | S43: =IFERROR(S3/S$25*S$26, 0) -> 300 | T43: =IFERROR(T3/T$25*T$26, 0) -> 300 | U43: =SUM(Q43:T43) -> 1200 | V43: =IFERROR(V3/V$25*V$26, 0) -> 300 | W43: =IFERROR(W3/W$25*W$26, 0) -> 300 | X43: =IFERROR(X3/X$25*X$26, 0) -> 300 | Y43: =IFERROR(Y3/Y$25*Y$26, 0) -> 300 | Z43: =SUM(V43:Y43) -> 1200 | AA43: =IFERROR(AA3/AA$25*AA$26, 0) -> 300 | AB43: =IFERROR(AB3/AB$25*AB$26, 0) -> 300 | AC43: =IFERROR(AC3/AC$25*AC$26, 0) -> 300 | AD43: =IFERROR(AD3/AD$25*AD$26, 0) -> 300 | AE43: =SUM(AA43:AD43) -> 1200 | AF43: =IFERROR(AF3/AF$25*AF$26, 0) -> 300 | AG43: =IFERROR(AG3/AG$25*AG$26, 0) -> 300 | AH43: =IFERROR(AH3/AH$25*AH$26, 0) -> 300 | AI43: =IFERROR(AI3/AI$25*AI$26, 0) -> 300 | AJ43: =SUM(AF43:AI43) -> 1200
F44: Tagging Labor | G44: =IFERROR(G3*G$19/G$20*G$21,0) -> 0 | H44: =IFERROR(H3*H$19/H$20*H$21,0) -> 0 | I44: =IFERROR(I3*I$19/I$20*I$21,0) -> 0 | J44: =IFERROR(J3*J$19/J$20*J$21,0) -> 0 | K44: =SUM(G44:J44) -> 0 | L44: =IFERROR(L3*L$19/L$20*L$21,0) -> 0 | M44: =IFERROR(M3*M$19/M$20*M$21,0) -> 0 | N44: =IFERROR(N3*N$19/N$20*N$21,0) -> 1875 | O44: =IFERROR(O3*O$19/O$20*O$21,0) -> 1875 | P44: =SUM(L44:O44) -> 3750 | Q44: =IFERROR(Q3*Q$19/Q$20*Q$21,0) -> 1000 | R44: =IFERROR(R3*R$19/R$20*R$21,0) -> 1000 | S44: =IFERROR(S3*S$19/S$20*S$21,0) -> 1000 | T44: =IFERROR(T3*T$19/T$20*T$21,0) -> 1000 | U44: =SUM(Q44:T44) -> 4000 | V44: =IFERROR(V3*V$19/V$20*V$21,0) -> 1000 | W44: =IFERROR(W3*W$19/W$20*W$21,0) -> 1000 | X44: =IFERROR(X3*X$19/X$20*X$21,0) -> 1000 | Y44: =IFERROR(Y3*Y$19/Y$20*Y$21,0) -> 1000 | Z44: =SUM(V44:Y44) -> 4000 | AA44: =IFERROR(AA3*AA$19/AA$20*AA$21,0) -> 1000 | AB44: =IFERROR(AB3*AB$19/AB$20*AB$21,0) -> 1000 | AC44: =IFERROR(AC3*AC$19/AC$20*AC$21,0) -> 1000 | AD44: =IFERROR(AD3*AD$19/AD$20*AD$21,0) -> 1000 | AE44: =SUM(AA44:AD44) -> 4000 | AF44: =IFERROR(AF3*AF$19/AF$20*AF$21,0) -> 1000 | AG44: =IFERROR(AG3*AG$19/AG$20*AG$21,0) -> 1000 | AH44: =IFERROR(AH3*AH$19/AH$20*AH$21,0) -> 1000 | AI44: =IFERROR(AI3*AI$19/AI$20*AI$21,0) -> 1000 | AJ44: =SUM(AF44:AI44) -> 4000
F45: Synthetic Tagging Labor | G45: =IFERROR(G3*G$24/G$22*G$23,0) -> 0 | H45: =IFERROR(H3*H$24/H$22*H$23,0) -> 0 | I45: =IFERROR(I3*I$24/I$22*I$23,0) -> 0 | J45: =IFERROR(J3*J$24/J$22*J$23,0) -> 0 | K45: =SUM(G45:J45) -> 0 | L45: =IFERROR(L3*L$24/L$22*L$23,0) -> 0 | M45: =IFERROR(M3*M$24/M$22*M$23,0) -> 0 | N45: =IFERROR(N3*N$24/N$22*N$23,0) -> 87.890625 | O45: =IFERROR(O3*O$24/O$22*O$23,0) -> 87.890625 | P45: =SUM(L45:O45) -> 175.78125 | Q45: =IFERROR(Q3*Q$24/Q$22*Q$23,0) -> 46.875 | R45: =IFERROR(R3*R$24/R$22*R$23,0) -> 46.875 | S45: =IFERROR(S3*S$24/S$22*S$23,0) -> 46.875 | T45: =IFERROR(T3*T$24/T$22*T$23,0) -> 46.875 | U45: =SUM(Q45:T45) -> 187.5 | V45: =IFERROR(V3*V$24/V$22*V$23,0) -> 46.875 | W45: =IFERROR(W3*W$24/W$22*W$23,0) -> 46.875 | X45: =IFERROR(X3*X$24/X$22*X$23,0) -> 46.875 | Y45: =IFERROR(Y3*Y$24/Y$22*Y$23,0) -> 46.875 | Z45: =SUM(V45:Y45) -> 187.5 | AA45: =IFERROR(AA3*AA$24/AA$22*AA$23,0) -> 46.875 | AB45: =IFERROR(AB3*AB$24/AB$22*AB$23,0) -> 46.875 | AC45: =IFERROR(AC3*AC$24/AC$22*AC$23,0) -> 46.875 | AD45: =IFERROR(AD3*AD$24/AD$22*AD$23,0) -> 46.875 | AE45: =SUM(AA45:AD45) -> 187.5 | AF45: =IFERROR(AF3*AF$24/AF$22*AF$23,0) -> 46.875 | AG45: =IFERROR(AG3*AG$24/AG$22*AG$23,0) -> 46.875 | AH45: =IFERROR(AH3*AH$24/AH$22*AH$23,0) -> 46.875 | AI45: =IFERROR(AI3*AI$24/AI$22*AI$23,0) -> 46.875 | AJ45: =SUM(AF45:AI45) -> 187.5
F46: Modeling Labor | G46: =G3*G$16*G$27 -> 0 | H46: =H3*H$16*H$27 -> 0 | I46: =I3*I$16*I$27 -> 0 | J46: =J3*J$16*J$27 -> 0 | K46: =SUM(G46:J46) -> 0 | L46: =L3*L$16*L$27 -> 0 | M46: =M3*M$16*M$27 -> 0 | N46: =N3*N$16*N$27 -> 2812.5 | O46: =O3*O$16*O$27 -> 2812.5 | P46: =SUM(L46:O46) -> 5625 | Q46: =Q3*Q$16*Q$27 -> 1500 | R46: =R3*R$16*R$27 -> 1500 | S46: =S3*S$16*S$27 -> 1500 | T46: =T3*T$16*T$27 -> 1500 | U46: =SUM(Q46:T46) -> 6000 | V46: =V3*V$16*V$27 -> 1500 | W46: =W3*W$16*W$27 -> 1500 | X46: =X3*X$16*X$27 -> 1500 | Y46: =Y3*Y$16*Y$27 -> 1500 | Z46: =SUM(V46:Y46) -> 6000 | AA46: =AA3*AA$16*AA$27 -> 1500 | AB46: =AB3*AB$16*AB$27 -> 1500 | AC46: =AC3*AC$16*AC$27 -> 1500 | AD46: =AD3*AD$16*AD$27 -> 1500 | AE46: =SUM(AA46:AD46) -> 6000 | AF46: =AF3*AF$16*AF$27 -> 1500 | AG46: =AG3*AG$16*AG$27 -> 1500 | AH46: =AH3*AH$16*AH$27 -> 1500 | AI46: =AI3*AI$16*AI$27 -> 1500 | AJ46: =SUM(AF46:AI46) -> 6000
A47: Wage Inflation | B47: ='Hiring Plan'!D4 -> 0.035 | E47: Labor | G47: =SUM(G42:G46) -> 0 | H47: =SUM(H42:H46) -> 0 | I47: =SUM(I42:I46) -> 0 | J47: =SUM(J42:J46) -> 0 | K47: =SUM(G47:J47) -> 0 | L47: =SUM(L42:L46) -> 0 | M47: =SUM(M42:M46) -> 0 | N47: =SUM(N42:N46) -> 8150.3906 | O47: =SUM(O42:O46) -> 8150.3906 | P47: =SUM(L47:O47) -> 16300.781 | Q47: =SUM(Q42:Q46) -> 4399.375 | R47: =SUM(R42:R46) -> 4399.375 | S47: =SUM(S42:S46) -> 4399.375 | T47: =SUM(T42:T46) -> 4399.375 | U47: =SUM(Q47:T47) -> 17597.5 | V47: =SUM(V42:V46) -> 4453.7125 | W47: =SUM(W42:W46) -> 4453.7125 | X47: =SUM(X42:X46) -> 4453.7125 | Y47: =SUM(Y42:Y46) -> 4453.7125 | Z47: =SUM(V47:Y47) -> 17814.85 | AA47: =SUM(AA42:AA46) -> 2846.875 | AB47: =SUM(AB42:AB46) -> 2846.875 | AC47: =SUM(AC42:AC46) -> 2846.875 | AD47: =SUM(AD42:AD46) -> 2846.875 | AE47: =SUM(AA47:AD47) -> 11387.5 | AF47: =SUM(AF42:AF46) -> 2846.875 | AG47: =SUM(AG42:AG46) -> 2846.875 | AH47: =SUM(AH42:AH46) -> 2846.875 | AI47: =SUM(AI42:AI46) -> 2846.875 | AJ47: =SUM(AF47:AI47) -> 11387.5
D48: Shoe Costs | G48: =G40+G41+G47 -> 0 | H48: =H40+H41+H47 -> 0 | I48: =I40+I41+I47 -> 0 | J48: =J40+J41+J47 -> 0 | K48: =K40+K41+K47 -> 0 | L48: =L40+L41+L47 -> 0 | M48: =M40+M41+M47 -> 0 | N48: =N40+N41+N47 -> 46400.391 | ... AJ48: =AJ40+AJ41+AJ47 -> 28987.5
C50: Apparel
F51: Bought/Resold | G51: =G$4*G6 -> 0 | H51: =H$4*H6 -> 0 | I51: =I$4*I6 -> 0 | J51: =J$4*J6 -> 0 | K51: =SUM(G51:J51) -> 0 | L51: =L$4*L6 -> 0 | M51: =M$4*M6 -> 0 | N51: =N$4*N6 -> 450 | O51: =O$4*O6 -> 450 | P51: =SUM(L51:O51) -> 900 | Q51: =Q$4*Q6 -> 120 | R51: =R$4*R6 -> 120 | S51: =S$4*S6 -> 120 | T51: =T$4*T6 -> 120 | U51: =SUM(Q51:T51) -> 480 | V51: =V$4*V6 -> 60 | W51: =W$4*W6 -> 60 | X51: =X$4*X6 -> 60 | Y51: =Y$4*Y6 -> 60 | Z51: =SUM(V51:Y51) -> 240 | AA51: =AA$4*AA6 -> 20 | AB51: =AB$4*AB6 -> 20 | AC51: =AC$4*AC6 -> 20 | AD51: =AD$4*AD6 -> 20 | AE51: =SUM(AA51:AD51) -> 80 | AF51: =AF$4*AF6 -> 20 | AG51: =AG$4*AG6 -> 20 | AH51: =AH$4*AH6 -> 20 | AI51: =AI$4*AI6 -> 20 | AJ51: =SUM(AF51:AI51) -> 80
F52: Charity Items | G52: =G$4*G7 -> 0 | H52: =H$4*H7 -> 0 | I52: =I$4*I7 -> 0 | J52: =J$4*J7 -> 0 | K52: =SUM(G52:J52) -> 0 | L52: =L$4*L7 -> 0 | M52: =M$4*M7 -> 0 | N52: =N$4*N7 -> 600 | O52: =O$4*O7 -> 600 | P52: =SUM(L52:O52) -> 1200 | Q52: =Q$4*Q7 -> 160 | R52: =R$4*R7 -> 160 | S52: =S$4*S7 -> 160 | T52: =T$4*T7 -> 160 | U52: =SUM(Q52:T52) -> 640 | V52: =V$4*V7 -> 120 | W52: =W$4*W7 -> 120 | X52: =X$4*X7 -> 120 | Y52: =Y$4*Y7 -> 120 | Z52: =SUM(V52:Y52) -> 480 | AA52: =AA$4*AA7 -> 60 | AB52: =AB$4*AB7 -> 60 | AC52: =AC$4*AC7 -> 60 | AD52: =AD$4*AD7 -> 60 | AE52: =SUM(AA52:AD52) -> 240 | AF52: =AF$4*AF7 -> 60 | AG52: =AG$4*AG7 -> 60 | AH52: =AH$4*AH7 -> 60 | AI52: =AI$4*AI7 -> 60 | AJ52: =SUM(AF52:AI52) -> 240
F53: Bought Outright | G53: =G$4*G8 -> 0 | H53: =H$4*H8 -> 0 | I53: =I$4*I8 -> 0 | J53: =J$4*J8 -> 0 | K53: =SUM(G53:J53) -> 0 | L53: =L$4*L8 -> 0 | M53: =M$4*M8 -> 0 | N53: =N$4*N8 -> 450 | O53: =O$4*O8 -> 450 | P53: =SUM(L53:O53) -> 900 | Q53: =Q$4*Q8 -> 120 | R53: =R$4*R8 -> 120 | S53: =S$4*S8 -> 120 | T53: =T$4*T8 -> 120 | U53: =SUM(Q53:T53) -> 480 | V53: =V$4*V8 -> 20 | W53: =W$4*W8 -> 20 | X53: =X$4*X8 -> 20 | Y53: =Y$4*Y8 -> 20 | Z53: =SUM(V53:Y53) -> 80 | AA53: =AA$4*AA8 -> 20 | AB53: =AB$4*AB8 -> 20 | AC53: =AC$4*AC8 -> 20 | AD53: =AD$4*AD8 -> 20 | AE53: =SUM(AA53:AD53) -> 80 | AF53: =AF$4*AF8 -> 20 | AG53: =AG$4*AG8 -> 20 | AH53: =AH$4*AH8 -> 20 | AI53: =AI$4*AI8 -> 20 | AJ53: =SUM(AF53:AI53) -> 80
F54: Free | G54: =G$4*G9 -> 0 | H54: =H$4*H9 -> 0 | I54: =I$4*I9 -> 0 | J54: =J$4*J9 -> 0 | K54: =SUM(G54:J54) -> 0 | L54: =L$4*L9 -> 0 | M54: =M$4*M9 -> 0 | N54: =N$4*N9 -> 0 | O54: =O$4*O9 -> 0 | P54: =SUM(L54:O54) -> 0 | Q54: =Q$4*Q9 -> 0 | R54: =R$4*R9 -> 0 | S54: =S$4*S9 -> 0 | T54: =T$4*T9 -> 0 | U54: =SUM(Q54:T54) -> 0 | V54: =V$4*V9 -> 200 | W54: =W$4*W9 -> 200 | X54: =X$4*X9 -> 200 | Y54: =Y$4*Y9 -> 200 | Z54: =SUM(V54:Y54) -> 800 | AA54: =AA$4*AA9 -> 300 | AB54: =AB$4*AB9 -> 300 | AC54: =AC$4*AC9 -> 300 | AD54: =AD$4*AD9 -> 300 | AE54: =SUM(AA54:AD54) -> 1200 | AF54: =AF$4*AF9 -> 300 | AG54: =AG$4*AG9 -> 300 | AH54: =AH$4*AH9 -> 300 | AI54: =AI$4*AI9 -> 300 | AJ54: =SUM(AF54:AI54) -> 1200
D55: Total Items | G55: =SUM(G51:G54) -> 0 | H55: =SUM(H51:H54) -> 0 | I55: =SUM(I51:I54) -> 0 | J55: =SUM(J51:J54) -> 0 | K55: =SUM(G55:J55) -> 0 | L55: =SUM(L51:L54) -> 0 | M55: =SUM(M51:M54) -> 0 | N55: =SUM(N51:N54) -> 1500 | O55: =SUM(O51:O54) -> 1500 | P55: =SUM(L55:O55) -> 3000 | Q55: =SUM(Q51:Q54) -> 400 | R55: =SUM(R51:R54) -> 400 | S55: =SUM(S51:S54) -> 400 | T55: =SUM(T51:T54) -> 400 | U55: =SUM(Q55:T55) -> 1600 | V55: =SUM(V51:V54) -> 400 | W55: =SUM(W51:W54) -> 400 | X55: =SUM(X51:X54) -> 400 | Y55: =SUM(Y51:Y54) -> 400 | Z55: =SUM(V55:Y55) -> 1600 | AA55: =SUM(AA51:AA54) -> 400 | AB55: =SUM(AB51:AB54) -> 400 | AC55: =SUM(AC51:AC54) -> 400 | AD55: =SUM(AD51:AD54) -> 400 | AE55: =SUM(AA55:AD55) -> 1600 | AF55: =SUM(AF51:AF54) -> 400 | AG55: =SUM(AG51:AG54) -> 400 | AH55: =SUM(AH51:AH54) -> 400 | AI55: =SUM(AI51:AI54) -> 400 | AJ55: =SUM(AF55:AI55) -> 1600
F56: Bought/Resold | G56: =G51*G$11*(1-G14) -> 0 | H56: =H51*H$11*(1-H14) -> 0 | I56: =I51*I$11*(1-I14) -> 0 | J56: =J51*J$11*(1-J14) -> 0 | K56: =SUM(G56:J56) -> 0 | L56: =L51*L$11*(1-L14) -> 0 | M56: =M51*M$11*(1-M14) -> 0 | N56: =N51*N$11*(1-N14) -> 5625 | O56: =O51*O$11*(1-O14) -> 5625 | P56: =SUM(L56:O56) -> 11250 | Q56: =Q51*Q$11*(1-Q14) -> 1500 | R56: =R51*R$11*(1-R14) -> 1500 | S56: =S51*S$11*(1-S14) -> 1500 | T56: =T51*T$11*(1-T14) -> 1500 | U56: =SUM(Q56:T56) -> 6000 | V56: =V51*V$11*(1-V14) -> 750 | W56: =W51*W$11*(1-W14) -> 750 | X56: =X51*X$11*(1-X14) -> 750 | Y56: =Y51*Y$11*(1-Y14) -> 750 | Z56: =SUM(V56:Y56) -> 3000 | AA56: =AA51*AA$11*(1-AA14) -> 250 | AB56: =AB51*AB$11*(1-AB14) -> 250 | AC56: =AC51*AC$11*(1-AC14) -> 250 | AD56: =AD51*AD$11*(1-AD14) -> 250 | AE56: =SUM(AA56:AD56) -> 1000 | AF56: =AF51*AF$11*(1-AF14) -> 250 | AG56: =AG51*AG$11*(1-AG14) -> 250 | AH56: =AH51*AH$11*(1-AH14) -> 250 | AI56: =AI51*AI$11*(1-AI14) -> 250 | AJ56: =SUM(AF56:AI56) -> 1000
F57: Charity Items | G57: =G52*G$13 -> 0 | H57: =H52*H$13 -> 0 | I57: =I52*I$13 -> 0 | J57: =J52*J$13 -> 0 | K57: =SUM(G57:J57) -> 0 | L57: =L52*L$13 -> 0 | M57: =M52*M$13 -> 0 | N57: =N52*N$13 -> 6000 | O57: =O52*O$13 -> 6000 | P57: =SUM(L57:O57) -> 12000 | Q57: =Q52*Q$13 -> 1600 | R57: =R52*R$13 -> 1600 | S57: =S52*S$13 -> 1600 | T57: =T52*T$13 -> 1600 | U57: =SUM(Q57:T57) -> 6400 | V57: =V52*V$13 -> 1200 | W57: =W52*W$13 -> 1200 | X57: =X52*X$13 -> 1200 | Y57: =Y52*Y$13 -> 1200 | Z57: =SUM(V57:Y57) -> 4800 | AA57: =AA52*AA$13 -> 600 | AB57: =AB52*AB$13 -> 600 | AC57: =AC52*AC$13 -> 600 | AD57: =AD52*AD$13 -> 600 | AE57: =SUM(AA57:AD57) -> 2400 | AF57: =AF52*AF$13 -> 600 | AG57: =AG52*AG$13 -> 600 | AH57: =AH52*AH$13 -> 600 | AI57: =AI52*AI$13 -> 600 | AJ57: =SUM(AF57:AI57) -> 2400
F58: Bought Outright | G58: =G53*G$11 -> 0 | H58: =H53*H$11 -> 0 | I58: =I53*I$11 -> 0 | J58: =J53*J$11 -> 0 | K58: =SUM(G58:J58) -> 0 | L58: =L53*L$11 -> 0 | M58: =M53*M$11 -> 0 | N58: =N53*N$11 -> 11250 | O58: =O53*O$11 -> 11250 | P58: =SUM(L58:O58) -> 22500 | Q58: =Q53*Q$11 -> 3000 | R58: =R53*R$11 -> 3000 | S58: =S53*S$11 -> 3000 | T58: =T53*T$11 -> 3000 | U58: =SUM(Q58:T58) -> 12000 | V58: =V53*V$11 -> 500 | W58: =W53*W$11 -> 500 | X58: =X53*X$11 -> 500 | Y58: =Y53*Y$11 -> 500 | Z58: =SUM(V58:Y58) -> 2000 | AA58: =AA53*AA$11 -> 500 | AB58: =AB53*AB$11 -> 500 | AC58: =AC53*AC$11 -> 500 | AD58: =AD53*AD$11 -> 500 | AE58: =SUM(AA58:AD58) -> 2000 | AF58: =AF53*AF$11 -> 500 | AG58: =AG53*AG$11 -> 500 | AH58: =AH53*AH$11 -> 500 | AI58: =AI53*AI$11 -> 500 | AJ58: =SUM(AF58:AI58) -> 2000
F59: Free | G59: =G54*0 -> 0 | H59: =H54*0 -> 0 | I59: =I54*0 -> 0 | J59: =J54*0 -> 0 | K59: =SUM(G59:J59) -> 0 | L59: =L54*0 -> 0 | M59: =M54*0 -> 0 | N59: =N54*0 -> 0 | O59: =O54*0 -> 0 | P59: =SUM(L59:O59) -> 0 | Q59: =Q54*0 -> 0 | R59: =R54*0 -> 0 | S59: =S54*0 -> 0 | T59: =T54*0 -> 0 | U59: =SUM(Q59:T59) -> 0 | V59: =V54*0 -> 0 | W59: =W54*0 -> 0 | X59: =X54*0 -> 0 | Y59: =Y54*0 -> 0 | Z59: =SUM(V59:Y59) -> 0 | AA59: =AA54*0 -> 0 | AB59: =AB54*0 -> 0 | AC59: =AC54*0 -> 0 | AD59: =AD54*0 -> 0 | AE59: =SUM(AA59:AD59) -> 0 | AF59: =AF54*0 -> 0 | AG59: =AG54*0 -> 0 | AH59: =AH54*0 -> 0 | AI59: =AI54*0 -> 0 | AJ59: =SUM(AF59:AI59) -> 0
E60: Product Costs | G60: =SUM(G56:G59) -> 0 | H60: =SUM(H56:H59) -> 0 | I60: =SUM(I56:I59) -> 0 | J60: =SUM(J56:J59) -> 0 | K60: =SUM(G60:J60) -> 0 | L60: =SUM(L56:L59) -> 0 | M60: =SUM(M56:M59) -> 0 | N60: =SUM(N56:N59) -> 22875 | O60: =SUM(O56:O59) -> 22875 | P60: =SUM(L60:O60) -> 45750 | Q60: =SUM(Q56:Q59) -> 6100 | R60: =SUM(R56:R59) -> 6100 | S60: =SUM(S56:S59) -> 6100 | T60: =SUM(T56:T59) -> 6100 | U60: =SUM(Q60:T60) -> 24400 | V60: =SUM(V56:V59) -> 2450 | W60: =SUM(W56:W59) -> 2450 | X60: =SUM(X56:X59) -> 2450 | Y60: =SUM(Y56:Y59) -> 2450 | Z60: =SUM(V60:Y60) -> 9800 | AA60: =SUM(AA56:AA59) -> 1350 | AB60: =SUM(AB56:AB59) -> 1350 | AC60: =SUM(AC56:AC59) -> 1350 | AD60: =SUM(AD56:AD59) -> 1350 | AE60: =SUM(AA60:AD60) -> 5400 | AF60: =SUM(AF56:AF59) -> 1350 | AG60: =SUM(AG56:AG59) -> 1350 | AH60: =SUM(AH56:AH59) -> 1350 | AI60: =SUM(AI56:AI59) -> 1350 | AJ60: =SUM(AF60:AI60) -> 5400
E61: Shipping | G61: =G4*G15 -> 0 | H61: =H4*H15 -> 0 | I61: =I4*I15 -> 0 | J61: =J4*J15 -> 0 | K61: =SUM(G61:J61) -> 0 | L61: =L4*L15 -> 0 | M61: =M4*M15 -> 0 | N61: =N4*N15 -> 3000 | O61: =O4*O15 -> 3000 | P61: =SUM(L61:O61) -> 6000 | Q61: =Q4*Q15 -> 800 | R61: =R4*R15 -> 800 | S61: =S4*S15 -> 800 | T61: =T4*T15 -> 800 | U61: =SUM(Q61:T61) -> 3200 | V61: =V4*V15 -> 800 | W61: =W4*W15 -> 800 | X61: =X4*X15 -> 800 | Y61: =Y4*Y15 -> 800 | Z61: =SUM(V61:Y61) -> 3200 | AA61: =AA4*AA15 -> 800 | AB61: =AB4*AB15 -> 800 | AC61: =AC4*AC15 -> 800 | AD61: =AD4*AD15 -> 800 | AE61: =SUM(AA61:AD61) -> 3200 | AF61: =AF4*AF15 -> 800 | AG61: =AG4*AG15 -> 800 | AH61: =AH4*AH15 -> 800 | AI61: =AI4*AI15 -> 800 | AJ61: =SUM(AF61:AI61) -> 3200
D62: Photo Labor | G62: =G4*G$16*G$17 -> 0 | H62: =H4*H$16*H$17 -> 0 | I62: =I4*I$16*I$17 -> 0 | J62: =J4*J$16*J$17 -> 0 | K62: =SUM(G62:J62) -> 0 | L62: =L4*L$16*L$17 -> 0 | M62: =M4*M$16*M$17 -> 0 | N62: =N4*N$16*N$17 -> 5625 | O62: =O4*O$16*O$17 -> 5625 | P62: =SUM(L62:O62) -> 11250 | Q62: =Q4*Q$16*Q$17 -> 1552.5 | R62: =R4*R$16*R$17 -> 1552.5 | S62: =S4*S$16*S$17 -> 1552.5 | T62: =T4*T$16*T$17 -> 1552.5 | U62: =SUM(Q62:T62) -> 6210 | V62: =V4*V$16*V$17 -> 1606.8375 | W62: =W4*W$16*W$17 -> 1606.8375 | X62: =X4*X$16*X$17 -> 1606.8375 | Y62: =Y4*Y$16*Y$17 -> 1606.8375 | Z62: =SUM(V62:Y62) -> 6427.35 | AA62: =AA4*AA$16*AA$17 -> 0 | AB62: =AB4*AB$16*AB$17 -> 0 | AC62: =AC4*AC$16*AC$17 -> 0 | AD62: =AD4*AD$16*AD$17 -> 0 | AE62: =SUM(AA62:AD62) -> 0 | AF62: =AF4*AF$16*AF$17 -> 0 | AG62: =AG4*AG$16*AG$17 -> 0 | AH62: =AH4*AH$16*AH$17 -> 0 | AI62: =AI4*AI$16*AI$17 -> 0 | AJ62: =SUM(AF62:AI62) -> 0
D63: S & H Labor | G63: =IFERROR(G4/G$25*G$26, 0) -> 0 | H63: =IFERROR(H4/H$25*H$26, 0) -> 0 | I63: =IFERROR(I4/I$25*I$26, 0) -> 0 | J63: =IFERROR(J4/J$25*J$26, 0) -> 0 | K63: =SUM(G63:J63) -> 0 | L63: =IFERROR(L4/L$25*L$26, 0) -> 0 | M63: =IFERROR(M4/M$25*M$26, 0) -> 0 | N63: =IFERROR(N4/N$25*N$26, 0) -> 1125 | O63: =IFERROR(O4/O$25*O$26, 0) -> 1125 | P63: =SUM(L63:O63) -> 2250 | Q63: =IFERROR(Q4/Q$25*Q$26, 0) -> 300 | R63: =IFERROR(R4/R$25*R$26, 0) -> 300 | S63: =IFERROR(S4/S$25*S$26, 0) -> 300 | T63: =IFERROR(T4/T$25*T$26, 0) -> 300 | U63: =SUM(Q63:T63) -> 1200 | V63: =IFERROR(V4/V$25*V$26, 0) -> 300 | W63: =IFERROR(W4/W$25*W$26, 0) -> 300 | X63: =IFERROR(X4/X$25*X$26, 0) -> 300 | Y63: =IFERROR(Y4/Y$25*Y$26, 0) -> 300 | Z63: =SUM(V63:Y63) -> 1200 | AA63: =IFERROR(AA4/AA$25*AA$26, 0) -> 300 | AB63: =IFERROR(AB4/AB$25*AB$26, 0) -> 300 | AC63: =IFERROR(AC4/AC$25*AC$26, 0) -> 300 | AD63: =IFERROR(AD4/AD$25*AD$26, 0) -> 300 | AE63: =SUM(AA63:AD63) -> 1200 | AF63: =IFERROR(AF4/AF$25*AF$26, 0) -> 300 | AG63: =IFERROR(AG4/AG$25*AG$26, 0) -> 300 | AH63: =IFERROR(AH4/AH$25*AH$26, 0) -> 300 | AI63: =IFERROR(AI4/AI$25*AI$26, 0) -> 300 | AJ63: =SUM(AF63:AI63) -> 1200
D64: Tagging Labor | G64: =IFERROR(G4*G$19/G$20*G$21,0) -> 0 | H64: =IFERROR(H4*H$19/H$20*H$21,0) -> 0 | I64: =IFERROR(I4*I$19/I$20*I$21,0) -> 0 | J64: =IFERROR(J4*J$19/J$20*J$21,0) -> 0 | K64: =SUM(G64:J64) -> 0 | L64: =IFERROR(L4*L$19/L$20*L$21,0) -> 0 | M64: =IFERROR(M4*M$19/M$20*M$21,0) -> 0 | N64: =IFERROR(N4*N$19/N$20*N$21,0) -> 3750 | O64: =IFERROR(O4*O$19/O$20*O$21,0) -> 3750 | P64: =SUM(L64:O64) -> 7500 | Q64: =IFERROR(Q4*Q$19/Q$20*Q$21,0) -> 1000 | R64: =IFERROR(R4*R$19/R$20*R$21,0) -> 1000 | S64: =IFERROR(S4*S$19/S$20*S$21,0) -> 1000 | T64: =IFERROR(T4*T$19/T$20*T$21,0) -> 1000 | U64: =SUM(Q64:T64) -> 4000 | V64: =IFERROR(V4*V$19/V$20*V$21,0) -> 1000 | W64: =IFERROR(W4*W$19/W$20*W$21,0) -> 1000 | X64: =IFERROR(X4*X$19/X$20*X$21,0) -> 1000 | Y64: =IFERROR(Y4*Y$19/Y$20*Y$21,0) -> 1000 | Z64: =SUM(V64:Y64) -> 4000 | AA64: =IFERROR(AA4*AA$19/AA$20*AA$21,0) -> 1000 | AB64: =IFERROR(AB4*AB$19/AB$20*AB$21,0) -> 1000 | AC64: =IFERROR(AC4*AC$19/AC$20*AC$21,0) -> 1000 | AD64: =IFERROR(AD4*AD$19/AD$20*AD$21,0) -> 1000 | AE64: =SUM(AA64:AD64) -> 4000 | AF64: =IFERROR(AF4*AF$19/AF$20*AF$21,0) -> 1000 | AG64: =IFERROR(AG4*AG$19/AG$20*AG$21,0) -> 1000 | AH64: =IFERROR(AH4*AH$19/AH$20*AH$21,0) -> 1000 | AI64: =IFERROR(AI4*AI$19/AI$20*AI$21,0) -> 1000 | AJ64: =SUM(AF64:AI64) -> 4000
D65: Synthetic Tagging Labor | G65: =IFERROR(G4*G$24/G$22*G$23,0) -> 0 | H65: =IFERROR(H4*H$24/H$22*H$23,0) -> 0 | I65: =IFERROR(I4*I$24/I$22*I$23,0) -> 0 | J65: =IFERROR(J4*J$24/J$22*J$23,0) -> 0 | K65: =SUM(G65:J65) -> 0 | L65: =IFERROR(L4*L$24/L$22*L$23,0) -> 0 | M65: =IFERROR(M4*M$24/M$22*M$23,0) -> 0 | N65: =IFERROR(N4*N$24/N$22*N$23,0) -> 175.78125 | O65: =IFERROR(O4*O$24/O$22*O$23,0) -> 175.78125 | P65: =SUM(L65:O65) -> 351.5625 | Q65: =IFERROR(Q4*Q$24/Q$22*Q$23,0) -> 46.875 | R65: =IFERROR(R4*R$24/R$22*R$23,0) -> 46.875 | S65: =IFERROR(S4*S$24/S$22*S$23,0) -> 46.875 | T65: =IFERROR(T4*T$24/T$22*T$23,0) -> 46.875 | U65: =SUM(Q65:T65) -> 187.5 | V65: =IFERROR(V4*V$24/V$22*V$23,0) -> 46.875 | W65: =IFERROR(W4*W$24/W$22*W$23,0) -> 46.875 | X65: =IFERROR(X4*X$24/X$22*X$23,0) -> 46.875 | Y65: =IFERROR(Y4*Y$24/Y$22*Y$23,0) -> 46.875 | Z65: =SUM(V65:Y65) -> 187.5 | AA65: =IFERROR(AA4*AA$24/AA$22*AA$23,0) -> 46.875 | AB65: =IFERROR(AB4*AB$24/AB$22*AB$23,0) -> 46.875 | AC65: =IFERROR(AC4*AC$24/AC$22*AC$23,0) -> 46.875 | AD65: =IFERROR(AD4*AD$24/AD$22*AD$23,0) -> 46.875 | AE65: =SUM(AA65:AD65) -> 187.5 | AF65: =IFERROR(AF4*AF$24/AF$22*AF$23,0) -> 46.875 | AG65: =IFERROR(AG4*AG$24/AG$22*AG$23,0) -> 46.875 | AH65: =IFERROR(AH4*AH$24/AH$22*AH$23,0) -> 46.875 | AI65: =IFERROR(AI4*AI$24/AI$22*AI$23,0) -> 46.875 | AJ65: =SUM(AF65:AI65) -> 187.5
D66: Modeling Labor | G66: =G4*G$16*G$27 -> 0 | H66: =H4*H$16*H$27 -> 0 | I66: =I4*I$16*I$27 -> 0 | J66: =J4*J$16*J$27 -> 0 | K66: =SUM(G66:J66) -> 0 | L66: =L4*L$16*L$27 -> 0 | M66: =M4*M$16*M$27 -> 0 | N66: =N4*N$16*N$27 -> 5625 | O66: =O4*O$16*O$27 -> 5625 | P66: =SUM(L66:O66) -> 11250 | Q66: =Q4*Q$16*Q$27 -> 1500 | R66: =R4*R$16*R$27 -> 1500 | S66: =S4*S$16*S$27 -> 1500 | T66: =T4*T$16*T$27 -> 1500 | U66: =SUM(Q66:T66) -> 6000 | V66: =V4*V$16*V$27 -> 1500 | W66: =W4*W$16*W$27 -> 1500 | X66: =X4*X$16*X$27 -> 1500 | Y66: =Y4*Y$16*Y$27 -> 1500 | Z66: =SUM(V66:Y66) -> 6000 | AA66: =AA4*AA$16*AA$27 -> 1500 | AB66: =AB4*AB$16*AB$27 -> 1500 | AC66: =AC4*AC$16*AC$27 -> 1500 | AD66: =AD4*AD$16*AD$27 -> 1500 | AE66: =SUM(AA66:AD66) -> 6000 | AF66: =AF4*AF$16*AF$27 -> 1500 | AG66: =AG4*AG$16*AG$27 -> 1500 | AH66: =AH4*AH$16*AH$27 -> 1500 | AI66: =AI4*AI$16*AI$27 -> 1500 | AJ66: =SUM(AF66:AI66) -> 6000
E67: Labor | G67: =SUM(G62:G66) -> 0 | H67: =SUM(H62:H66) -> 0 | I67: =SUM(I62:I66) -> 0 | J67: =SUM(J62:J66) -> 0 | K67: =SUM(G67:J67) -> 0 | L67: =SUM(L62:L66) -> 0 | M67: =SUM(M62:M66) -> 0 | N67: =SUM(N62:N66) -> 16300.781 | O67: =SUM(O62:O66) -> 16300.781 | P67: =SUM(L67:O67) -> 32601.562 | Q67: =SUM(Q62:Q66) -> 4399.375 | R67: =SUM(R62:R66) -> 4399.375 | S67: =SUM(S62:S66) -> 4399.375 | T67: =SUM(T62:T66) -> 4399.375 | U67: =SUM(Q67:T67) -> 17597.5 | V67: =SUM(V62:V66) -> 4453.7125 | W67: =SUM(W62:W66) -> 4453.7125 | X67: =SUM(X62:X66) -> 4453.7125 | Y67: =SUM(Y62:Y66) -> 4453.7125 | Z67: =SUM(V67:Y67) -> 17814.85 | AA67: =SUM(AA62:AA66) -> 2846.875 | AB67: =SUM(AB62:AB66) -> 2846.875 | AC67: =SUM(AC62:AC66) -> 2846.875 | AD67: =SUM(AD62:AD66) -> 2846.875 | AE67: =SUM(AA67:AD67) -> 11387.5 | AF67: =SUM(AF62:AF66) -> 2846.875 | AG67: =SUM(AG62:AG66) -> 2846.875 | AH67: =SUM(AH62:AH66) -> 2846.875 | AI67: =SUM(AI62:AI66) -> 2846.875 | AJ67: =SUM(AF67:AI67) -> 11387.5
D68: Apparel Costs | G68: =G60+G61+G67 -> 0 | H68: =H60+H61+H67 -> 0 | I68: =I60+I61+I67 -> 0 | J68: =J60+J61+J67 -> 0 | K68: =K60+K61+K67 -> 0 | L68: =L60+L61+L67 -> 0 | M68: =M60+M61+M67 -> 0 | N68: =N60+N61+N67 -> 42175.781 | ... AJ68: =AJ60+AJ61+AJ67 -> 19987.5
C70: Accessories
F71: Bought/Resold | G71: =G$5*G6 -> 0 | H71: =H$5*H6 -> 0 | I71: =I$5*I6 -> 0 | J71: =J$5*J6 -> 0 | K71: =SUM(G71:J71) -> 0 | L71: =L$5*L6 -> 0 | M71: =M$5*M6 -> 0 | N71: =N$5*N6 -> 225 | O71: =O$5*O6 -> 225 | P71: =SUM(L71:O71) -> 450 | Q71: =Q$5*Q6 -> 120 | R71: =R$5*R6 -> 120 | S71: =S$5*S6 -> 120 | T71: =T$5*T6 -> 120 | U71: =SUM(Q71:T71) -> 480 | V71: =V$5*V6 -> 60 | W71: =W$5*W6 -> 60 | X71: =X$5*X6 -> 60 | Y71: =Y$5*Y6 -> 60 | Z71: =SUM(V71:Y71) -> 240 | AA71: =AA$5*AA6 -> 20 | AB71: =AB$5*AB6 -> 20 | AC71: =AC$5*AC6 -> 20 | AD71: =AD$5*AD6 -> 20 | AE71: =SUM(AA71:AD71) -> 80 | AF71: =AF$5*AF6 -> 20 | AG71: =AG$5*AG6 -> 20 | AH71: =AH$5*AH6 -> 20 | AI71: =AI$5*AI6 -> 20 | AJ71: =SUM(AF71:AI71) -> 80
F72: Charity Items | G72: =G$5*G7 -> 0 | H72: =H$5*H7 -> 0 | I72: =I$5*I7 -> 0 | J72: =J$5*J7 -> 0 | K72: =SUM(G72:J72) -> 0 | L72: =L$5*L7 -> 0 | M72: =M$5*M7 -> 0 | N72: =N$5*N7 -> 300 | O72: =O$5*O7 -> 300 | P72: =SUM(L72:O72) -> 600 | Q72: =Q$5*Q7 -> 160 | R72: =R$5*R7 -> 160 | S72: =S$5*S7 -> 160 | T72: =T$5*T7 -> 160 | U72: =SUM(Q72:T72) -> 640 | V72: =V$5*V7 -> 120 | W72: =W$5*W7 -> 120 | X72: =X$5*X7 -> 120 | Y72: =Y$5*Y7 -> 120 | Z72: =SUM(V72:Y72) -> 480 | AA72: =AA$5*AA7 -> 60 | AB72: =AB$5*AB7 -> 60 | AC72: =AC$5*AC7 -> 60 | AD72: =AD$5*AD7 -> 60 | AE72: =SUM(AA72:AD72) -> 240 | AF72: =AF$5*AF7 -> 60 | AG72: =AG$5*AG7 -> 60 | AH72: =AH$5*AH7 -> 60 | AI72: =AI$5*AI7 -> 60 | AJ72: =SUM(AF72:AI72) -> 240
F73: Bought Outright | G73: =G$5*G8 -> 0 | H73: =H$5*H8 -> 0 | I73: =I$5*I8 -> 0 | J73: =J$5*J8 -> 0 | K73: =SUM(G73:J73) -> 0 | L73: =L$5*L8 -> 0 | M73: =M$5*M8 -> 0 | N73: =N$5*N8 -> 225 | O73: =O$5*O8 -> 225 | P73: =SUM(L73:O73) -> 450 | Q73: =Q$5*Q8 -> 120 | R73: =R$5*R8 -> 120 | S73: =S$5*S8 -> 120 | T73: =T$5*T8 -> 120 | U73: =SUM(Q73:T73) -> 480 | V73: =V$5*V8 -> 20 | W73: =W$5*W8 -> 20 | X73: =X$5*X8 -> 20 | Y73: =Y$5*Y8 -> 20 | Z73: =SUM(V73:Y73) -> 80 | AA73: =AA$5*AA8 -> 20 | AB73: =AB$5*AB8 -> 20 | AC73: =AC$5*AC8 -> 20 | AD73: =AD$5*AD8 -> 20 | AE73: =SUM(AA73:AD73) -> 80 | AF73: =AF$5*AF8 -> 20 | AG73: =AG$5*AG8 -> 20 | AH73: =AH$5*AH8 -> 20 | AI73: =AI$5*AI8 -> 20 | AJ73: =SUM(AF73:AI73) -> 80
F74: Free | G74: =G$5*G9 -> 0 | H74: =H$5*H9 -> 0 | I74: =I$5*I9 -> 0 | J74: =J$5*J9 -> 0 | K74: =SUM(G74:J74) -> 0 | L74: =L$5*L9 -> 0 | M74: =M$5*M9 -> 0 | N74: =N$5*N9 -> 0 | O74: =O$5*O9 -> 0 | P74: =SUM(L74:O74) -> 0 | Q74: =Q$5*Q9 -> 0 | R74: =R$5*R9 -> 0 | S74: =S$5*S9 -> 0 | T74: =T$5*T9 -> 0 | U74: =SUM(Q74:T74) -> 0 | V74: =V$5*V9 -> 200 | W74: =W$5*W9 -> 200 | X74: =X$5*X9 -> 200 | Y74: =Y$5*Y9 -> 200 | Z74: =SUM(V74:Y74) -> 800 | AA74: =AA$5*AA9 -> 300 | AB74: =AB$5*AB9 -> 300 | AC74: =AC$5*AC9 -> 300 | AD74: =AD$5*AD9 -> 300 | AE74: =SUM(AA74:AD74) -> 1200 | AF74: =AF$5*AF9 -> 300 | AG74: =AG$5*AG9 -> 300 | AH74: =AH$5*AH9 -> 300 | AI74: =AI$5*AI9 -> 300 | AJ74: =SUM(AF74:AI74) -> 1200
D75: Total Items | G75: =SUM(G71:G74) -> 0 | H75: =SUM(H71:H74) -> 0 | I75: =SUM(I71:I74) -> 0 | J75: =SUM(J71:J74) -> 0 | K75: =SUM(G75:J75) -> 0 | L75: =SUM(L71:L74) -> 0 | M75: =SUM(M71:M74) -> 0 | N75: =SUM(N71:N74) -> 750 | O75: =SUM(O71:O74) -> 750 | P75: =SUM(L75:O75) -> 1500 | Q75: =SUM(Q71:Q74) -> 400 | R75: =SUM(R71:R74) -> 400 | S75: =SUM(S71:S74) -> 400 | T75: =SUM(T71:T74) -> 400 | U75: =SUM(Q75:T75) -> 1600 | V75: =SUM(V71:V74) -> 400 | W75: =SUM(W71:W74) -> 400 | X75: =SUM(X71:X74) -> 400 | Y75: =SUM(Y71:Y74) -> 400 | Z75: =SUM(V75:Y75) -> 1600 | AA75: =SUM(AA71:AA74) -> 400 | AB75: =SUM(AB71:AB74) -> 400 | AC75: =SUM(AC71:AC74) -> 400 | AD75: =SUM(AD71:AD74) -> 400 | AE75: =SUM(AA75:AD75) -> 1600 | AF75: =SUM(AF71:AF74) -> 400 | AG75: =SUM(AG71:AG74) -> 400 | AH75: =SUM(AH71:AH74) -> 400 | AI75: =SUM(AI71:AI74) -> 400 | AJ75: =SUM(AF75:AI75) -> 1600
F76: Bought/Resold | G76: =G71*G12*(1-G14) -> 0 | H76: =H71*H12*(1-H14) -> 0 | I76: =I71*I12*(1-I14) -> 0 | J76: =J71*J12*(1-J14) -> 0 | K76: =SUM(G76:J76) -> 0 | L76: =L71*L12*(1-L14) -> 0 | M76: =M71*M12*(1-M14) -> 0 | N76: =N71*N12*(1-N14) -> 5625 | O76: =O71*O12*(1-O14) -> 8437.5 | P76: =SUM(L76:O76) -> 14062.5 | Q76: =Q71*Q12*(1-Q14) -> 3000 | R76: =R71*R12*(1-R14) -> 3000 | S76: =S71*S12*(1-S14) -> 3000 | T76: =T71*T12*(1-T14) -> 3000 | U76: =SUM(Q76:T76) -> 12000 | V76: =V71*V12*(1-V14) -> 1500 | W76: =W71*W12*(1-W14) -> 1500 | X76: =X71*X12*(1-X14) -> 1500 | Y76: =Y71*Y12*(1-Y14) -> 1500 | Z76: =SUM(V76:Y76) -> 6000 | AA76: =AA71*AA12*(1-AA14) -> 500 | AB76: =AB71*AB12*(1-AB14) -> 500 | AC76: =AC71*AC12*(1-AC14) -> 500 | AD76: =AD71*AD12*(1-AD14) -> 500 | AE76: =SUM(AA76:AD76) -> 2000 | AF76: =AF71*AF12*(1-AF14) -> 500 | AG76: =AG71*AG12*(1-AG14) -> 500 | AH76: =AH71*AH12*(1-AH14) -> 500 | AI76: =AI71*AI12*(1-AI14) -> 500 | AJ76: =SUM(AF76:AI76) -> 2000
F77: Charity Items | G77: =G72*G13 -> 0 | H77: =H72*H13 -> 0 | I77: =I72*I13 -> 0 | J77: =J72*J13 -> 0 | K77: =SUM(G77:J77) -> 0 | L77: =L72*L13 -> 0 | M77: =M72*M13 -> 0 | N77: =N72*N13 -> 3000 | O77: =O72*O13 -> 3000 | P77: =SUM(L77:O77) -> 6000 | Q77: =Q72*Q13 -> 1600 | R77: =R72*R13 -> 1600 | S77: =S72*S13 -> 1600 | T77: =T72*T13 -> 1600 | U77: =SUM(Q77:T77) -> 6400 | V77: =V72*V13 -> 1200 | W77: =W72*W13 -> 1200 | X77: =X72*X13 -> 1200 | Y77: =Y72*Y13 -> 1200 | Z77: =SUM(V77:Y77) -> 4800 | AA77: =AA72*AA13 -> 600 | AB77: =AB72*AB13 -> 600 | AC77: =AC72*AC13 -> 600 | AD77: =AD72*AD13 -> 600 | AE77: =SUM(AA77:AD77) -> 2400 | AF77: =AF72*AF13 -> 600 | AG77: =AG72*AG13 -> 600 | AH77: =AH72*AH13 -> 600 | AI77: =AI72*AI13 -> 600 | AJ77: =SUM(AF77:AI77) -> 2400
F78: Bought Outright | G78: =G73*G12 -> 0 | H78: =H73*H12 -> 0 | I78: =I73*I12 -> 0 | J78: =J73*J12 -> 0 | K78: =SUM(G78:J78) -> 0 | L78: =L73*L12 -> 0 | M78: =M73*M12 -> 0 | N78: =N73*N12 -> 11250 | O78: =O73*O12 -> 16875 | P78: =SUM(L78:O78) -> 28125 | Q78: =Q73*Q12 -> 6000 | R78: =R73*R12 -> 6000 | S78: =S73*S12 -> 6000 | T78: =T73*T12 -> 6000 | U78: =SUM(Q78:T78) -> 24000 | V78: =V73*V12 -> 1000 | W78: =W73*W12 -> 1000 | X78: =X73*X12 -> 1000 | Y78: =Y73*Y12 -> 1000 | Z78: =SUM(V78:Y78) -> 4000 | AA78: =AA73*AA12 -> 1000 | AB78: =AB73*AB12 -> 1000 | AC78: =AC73*AC12 -> 1000 | AD78: =AD73*AD12 -> 1000 | AE78: =SUM(AA78:AD78) -> 4000 | AF78: =AF73*AF12 -> 1000 | AG78: =AG73*AG12 -> 1000 | AH78: =AH73*AH12 -> 1000 | AI78: =AI73*AI12 -> 1000 | AJ78: =SUM(AF78:AI78) -> 4000
F79: Free | G79: =G74*0 -> 0 | H79: =H74*0 -> 0 | I79: =I74*0 -> 0 | J79: =J74*0 -> 0 | K79: =SUM(G79:J79) -> 0 | L79: =L74*0 -> 0 | M79: =M74*0 -> 0 | N79: =N74*0 -> 0 | O79: =O74*0 -> 0 | P79: =SUM(L79:O79) -> 0 | Q79: =Q74*0 -> 0 | R79: =R74*0 -> 0 | S79: =S74*0 -> 0 | T79: =T74*0 -> 0 | U79: =SUM(Q79:T79) -> 0 | V79: =V74*0 -> 0 | W79: =W74*0 -> 0 | X79: =X74*0 -> 0 | Y79: =Y74*0 -> 0 | Z79: =SUM(V79:Y79) -> 0 | AA79: =AA74*0 -> 0 | AB79: =AB74*0 -> 0 | AC79: =AC74*0 -> 0 | AD79: =AD74*0 -> 0 | AE79: =SUM(AA79:AD79) -> 0 | AF79: =AF74*0 -> 0 | AG79: =AG74*0 -> 0 | AH79: =AH74*0 -> 0 | AI79: =AI74*0 -> 0 | AJ79: =SUM(AF79:AI79) -> 0
E80: Product Costs | G80: =SUM(G76:G79) -> 0 | H80: =SUM(H76:H79) -> 0 | I80: =SUM(I76:I79) -> 0 | J80: =SUM(J76:J79) -> 0 | K80: =SUM(G80:J80) -> 0 | L80: =SUM(L76:L79) -> 0 | M80: =SUM(M76:M79) -> 0 | N80: =SUM(N76:N79) -> 19875 | O80: =SUM(O76:O79) -> 28312.5 | P80: =SUM(L80:O80) -> 48187.5 | Q80: =SUM(Q76:Q79) -> 10600 | R80: =SUM(R76:R79) -> 10600 | S80: =SUM(S76:S79) -> 10600 | T80: =SUM(T76:T79) -> 10600 | U80: =SUM(Q80:T80) -> 42400 | V80: =SUM(V76:V79) -> 3700 | W80: =SUM(W76:W79) -> 3700 | X80: =SUM(X76:X79) -> 3700 | Y80: =SUM(Y76:Y79) -> 3700 | Z80: =SUM(V80:Y80) -> 14800 | AA80: =SUM(AA76:AA79) -> 2100 | AB80: =SUM(AB76:AB79) -> 2100 | AC80: =SUM(AC76:AC79) -> 2100 | AD80: =SUM(AD76:AD79) -> 2100 | AE80: =SUM(AA80:AD80) -> 8400 | AF80: =SUM(AF76:AF79) -> 2100 | AG80: =SUM(AG76:AG79) -> 2100 | AH80: =SUM(AH76:AH79) -> 2100 | AI80: =SUM(AI76:AI79) -> 2100 | AJ80: =SUM(AF80:AI80) -> 8400
E81: Shipping | G81: =G5*G15 -> 0 | H81: =H5*H15 -> 0 | I81: =I5*I15 -> 0 | J81: =J5*J15 -> 0 | K81: =SUM(G81:J81) -> 0 | L81: =L5*L15 -> 0 | M81: =M5*M15 -> 0 | N81: =N5*N15 -> 1500 | O81: =O5*O15 -> 1500 | P81: =SUM(L81:O81) -> 3000 | Q81: =Q5*Q15 -> 800 | R81: =R5*R15 -> 800 | S81: =S5*S15 -> 800 | T81: =T5*T15 -> 800 | U81: =SUM(Q81:T81) -> 3200 | V81: =V5*V15 -> 800 | W81: =W5*W15 -> 800 | X81: =X5*X15 -> 800 | Y81: =Y5*Y15 -> 800 | Z81: =SUM(V81:Y81) -> 3200 | AA81: =AA5*AA15 -> 800 | AB81: =AB5*AB15 -> 800 | AC81: =AC5*AC15 -> 800 | AD81: =AD5*AD15 -> 800 | AE81: =SUM(AA81:AD81) -> 3200 | AF81: =AF5*AF15 -> 800 | AG81: =AG5*AG15 -> 800 | AH81: =AH5*AH15 -> 800 | AI81: =AI5*AI15 -> 800 | AJ81: =SUM(AF81:AI81) -> 3200
D82: Photo Labor | G82: =G5*G$16*G$17 -> 0 | H82: =H5*H$16*H$17 -> 0 | I82: =I5*I$16*I$17 -> 0 | J82: =J5*J$16*J$17 -> 0 | K82: =SUM(G82:J82) -> 0 | L82: =L5*L$16*L$17 -> 0 | M82: =M5*M$16*M$17 -> 0 | N82: =N5*N$16*N$17 -> 2812.5 | O82: =O5*O$16*O$17 -> 2812.5 | P82: =SUM(L82:O82) -> 5625 | Q82: =Q5*Q$16*Q$17 -> 1552.5 | R82: =R5*R$16*R$17 -> 1552.5 | S82: =S5*S$16*S$17 -> 1552.5 | T82: =T5*T$16*T$17 -> 1552.5 | U82: =SUM(Q82:T82) -> 6210 | V82: =V5*V$16*V$17 -> 1606.8375 | W82: =W5*W$16*W$17 -> 1606.8375 | X82: =X5*X$16*X$17 -> 1606.8375 | Y82: =Y5*Y$16*Y$17 -> 1606.8375 | Z82: =SUM(V82:Y82) -> 6427.35 | AA82: =AA5*AA$16*AA$17 -> 0 | AB82: =AB5*AB$16*AB$17 -> 0 | AC82: =AC5*AC$16*AC$17 -> 0 | AD82: =AD5*AD$16*AD$17 -> 0 | AE82: =SUM(AA82:AD82) -> 0 | AF82: =AF5*AF$16*AF$17 -> 0 | AG82: =AG5*AG$16*AG$17 -> 0 | AH82: =AH5*AH$16*AH$17 -> 0 | AI82: =AI5*AI$16*AI$17 -> 0 | AJ82: =SUM(AF82:AI82) -> 0
D83: S & H Labor | G83: =IFERROR(G5/G$25*G$26, 0) -> 0 | H83: =IFERROR(H5/H$25*H$26, 0) -> 0 | I83: =IFERROR(I5/I$25*I$26, 0) -> 0 | J83: =IFERROR(J5/J$25*J$26, 0) -> 0 | K83: =SUM(G83:J83) -> 0 | L83: =IFERROR(L5/L$25*L$26, 0) -> 0 | M83: =IFERROR(M5/M$25*M$26, 0) -> 0 | N83: =IFERROR(N5/N$25*N$26, 0) -> 562.5 | O83: =IFERROR(O5/O$25*O$26, 0) -> 562.5 | P83: =SUM(L83:O83) -> 1125 | Q83: =IFERROR(Q5/Q$25*Q$26, 0) -> 300 | R83: =IFERROR(R5/R$25*R$26, 0) -> 300 | S83: =IFERROR(S5/S$25*S$26, 0) -> 300 | T83: =IFERROR(T5/T$25*T$26, 0) -> 300 | U83: =SUM(Q83:T83) -> 1200 | V83: =IFERROR(V5/V$25*V$26, 0) -> 300 | W83: =IFERROR(W5/W$25*W$26, 0) -> 300 | X83: =IFERROR(X5/X$25*X$26, 0) -> 300 | Y83: =IFERROR(Y5/Y$25*Y$26, 0) -> 300 | Z83: =SUM(V83:Y83) -> 1200 | AA83: =IFERROR(AA5/AA$25*AA$26, 0) -> 300 | AB83: =IFERROR(AB5/AB$25*AB$26, 0) -> 300 | AC83: =IFERROR(AC5/AC$25*AC$26, 0) -> 300 | AD83: =IFERROR(AD5/AD$25*AD$26, 0) -> 300 | AE83: =SUM(AA83:AD83) -> 1200 | AF83: =IFERROR(AF5/AF$25*AF$26, 0) -> 300 | AG83: =IFERROR(AG5/AG$25*AG$26, 0) -> 300 | AH83: =IFERROR(AH5/AH$25*AH$26, 0) -> 300 | AI83: =IFERROR(AI5/AI$25*AI$26, 0) -> 300 | AJ83: =SUM(AF83:AI83) -> 1200
D84: Tagging Labor | G84: =IFERROR(G5*G$19/G$20*G$21,0) -> 0 | H84: =IFERROR(H5*H$19/H$20*H$21,0) -> 0 | I84: =IFERROR(I5*I$19/I$20*I$21,0) -> 0 | J84: =IFERROR(J5*J$19/J$20*J$21,0) -> 0 | K84: =SUM(G84:J84) -> 0 | L84: =IFERROR(L5*L$19/L$20*L$21,0) -> 0 | M84: =IFERROR(M5*M$19/M$20*M$21,0) -> 0 | N84: =IFERROR(N5*N$19/N$20*N$21,0) -> 1875 | O84: =IFERROR(O5*O$19/O$20*O$21,0) -> 1875 | P84: =SUM(L84:O84) -> 3750 | Q84: =IFERROR(Q5*Q$19/Q$20*Q$21,0) -> 1000 | R84: =IFERROR(R5*R$19/R$20*R$21,0) -> 1000 | S84: =IFERROR(S5*S$19/S$20*S$21,0) -> 1000 | T84: =IFERROR(T5*T$19/T$20*T$21,0) -> 1000 | U84: =SUM(Q84:T84) -> 4000 | V84: =IFERROR(V5*V$19/V$20*V$21,0) -> 1000 | W84: =IFERROR(W5*W$19/W$20*W$21,0) -> 1000 | X84: =IFERROR(X5*X$19/X$20*X$21,0) -> 1000 | Y84: =IFERROR(Y5*Y$19/Y$20*Y$21,0) -> 1000 | Z84: =SUM(V84:Y84) -> 4000 | AA84: =IFERROR(AA5*AA$19/AA$20*AA$21,0) -> 1000 | AB84: =IFERROR(AB5*AB$19/AB$20*AB$21,0) -> 1000 | AC84: =IFERROR(AC5*AC$19/AC$20*AC$21,0) -> 1000 | AD84: =IFERROR(AD5*AD$19/AD$20*AD$21,0) -> 1000 | AE84: =SUM(AA84:AD84) -> 4000 | AF84: =IFERROR(AF5*AF$19/AF$20*AF$21,0) -> 1000 | AG84: =IFERROR(AG5*AG$19/AG$20*AG$21,0) -> 1000 | AH84: =IFERROR(AH5*AH$19/AH$20*AH$21,0) -> 1000 | AI84: =IFERROR(AI5*AI$19/AI$20*AI$21,0) -> 1000 | AJ84: =SUM(AF84:AI84) -> 4000
D85: Synthetic Tagging Labor | G85: =IFERROR(G5*G$24/G$22*G$23,0) -> 0 | H85: =IFERROR(H5*H$24/H$22*H$23,0) -> 0 | I85: =IFERROR(I5*I$24/I$22*I$23,0) -> 0 | J85: =IFERROR(J5*J$24/J$22*J$23,0) -> 0 | K85: =SUM(G85:J85) -> 0 | L85: =IFERROR(L5*L$24/L$22*L$23,0) -> 0 | M85: =IFERROR(M5*M$24/M$22*M$23,0) -> 0 | N85: =IFERROR(N5*N$24/N$22*N$23,0) -> 87.890625 | O85: =IFERROR(O5*O$24/O$22*O$23,0) -> 87.890625 | P85: =SUM(L85:O85) -> 175.78125 | Q85: =IFERROR(Q5*Q$24/Q$22*Q$23,0) -> 46.875 | R85: =IFERROR(R5*R$24/R$22*R$23,0) -> 46.875 | S85: =IFERROR(S5*S$24/S$22*S$23,0) -> 46.875 | T85: =IFERROR(T5*T$24/T$22*T$23,0) -> 46.875 | U85: =SUM(Q85:T85) -> 187.5 | V85: =IFERROR(V5*V$24/V$22*V$23,0) -> 46.875 | W85: =IFERROR(W5*W$24/W$22*W$23,0) -> 46.875 | X85: =IFERROR(X5*X$24/X$22*X$23,0) -> 46.875 | Y85: =IFERROR(Y5*Y$24/Y$22*Y$23,0) -> 46.875 | Z85: =SUM(V85:Y85) -> 187.5 | AA85: =IFERROR(AA5*AA$24/AA$22*AA$23,0) -> 46.875 | AB85: =IFERROR(AB5*AB$24/AB$22*AB$23,0) -> 46.875 | AC85: =IFERROR(AC5*AC$24/AC$22*AC$23,0) -> 46.875 | AD85: =IFERROR(AD5*AD$24/AD$22*AD$23,0) -> 46.875 | AE85: =SUM(AA85:AD85) -> 187.5 | AF85: =IFERROR(AF5*AF$24/AF$22*AF$23,0) -> 46.875 | AG85: =IFERROR(AG5*AG$24/AG$22*AG$23,0) -> 46.875 | AH85: =IFERROR(AH5*AH$24/AH$22*AH$23,0) -> 46.875 | AI85: =IFERROR(AI5*AI$24/AI$22*AI$23,0) -> 46.875 | AJ85: =SUM(AF85:AI85) -> 187.5
D86: Modeling Labor | G86: =G5*G$16*G$27 -> 0 | H86: =H5*H$16*H$27 -> 0 | I86: =I5*I$16*I$27 -> 0 | J86: =J5*J$16*J$27 -> 0 | K86: =SUM(G86:J86) -> 0 | L86: =L5*L$16*L$27 -> 0 | M86: =M5*M$16*M$27 -> 0 | N86: =N5*N$16*N$27 -> 2812.5 | O86: =O5*O$16*O$27 -> 2812.5 | P86: =SUM(L86:O86) -> 5625 | Q86: =Q5*Q$16*Q$27 -> 1500 | R86: =R5*R$16*R$27 -> 1500 | S86: =S5*S$16*S$27 -> 1500 | T86: =T5*T$16*T$27 -> 1500 | U86: =SUM(Q86:T86) -> 6000 | V86: =V5*V$16*V$27 -> 1500 | W86: =W5*W$16*W$27 -> 1500 | X86: =X5*X$16*X$27 -> 1500 | Y86: =Y5*Y$16*Y$27 -> 1500 | Z86: =SUM(V86:Y86) -> 6000 | AA86: =AA5*AA$16*AA$27 -> 1500 | AB86: =AB5*AB$16*AB$27 -> 1500 | AC86: =AC5*AC$16*AC$27 -> 1500 | AD86: =AD5*AD$16*AD$27 -> 1500 | AE86: =SUM(AA86:AD86) -> 6000 | AF86: =AF5*AF$16*AF$27 -> 1500 | AG86: =AG5*AG$16*AG$27 -> 1500 | AH86: =AH5*AH$16*AH$27 -> 1500 | AI86: =AI5*AI$16*AI$27 -> 1500 | AJ86: =SUM(AF86:AI86) -> 6000
E87: Labor | G87: =SUM(G82:G86) -> 0 | H87: =SUM(H82:H86) -> 0 | I87: =SUM(I82:I86) -> 0 | J87: =SUM(J82:J86) -> 0 | K87: =SUM(G87:J87) -> 0 | L87: =SUM(L82:L86) -> 0 | M87: =SUM(M82:M86) -> 0 | N87: =SUM(N82:N86) -> 8150.3906 | O87: =SUM(O82:O86) -> 8150.3906 | P87: =SUM(L87:O87) -> 16300.781 | Q87: =SUM(Q82:Q86) -> 4399.375 | R87: =SUM(R82:R86) -> 4399.375 | S87: =SUM(S82:S86) -> 4399.375 | T87: =SUM(T82:T86) -> 4399.375 | U87: =SUM(Q87:T87) -> 17597.5 | V87: =SUM(V82:V86) -> 4453.7125 | W87: =SUM(W82:W86) -> 4453.7125 | X87: =SUM(X82:X86) -> 4453.7125 | Y87: =SUM(Y82:Y86) -> 4453.7125 | Z87: =SUM(V87:Y87) -> 17814.85 | AA87: =SUM(AA82:AA86) -> 2846.875 | AB87: =SUM(AB82:AB86) -> 2846.875 | AC87: =SUM(AC82:AC86) -> 2846.875 | AD87: =SUM(AD82:AD86) -> 2846.875 | AE87: =SUM(AA87:AD87) -> 11387.5 | AF87: =SUM(AF82:AF86) -> 2846.875 | AG87: =SUM(AG82:AG86) -> 2846.875 | AH87: =SUM(AH82:AH86) -> 2846.875 | AI87: =SUM(AI82:AI86) -> 2846.875 | AJ87: =SUM(AF87:AI87) -> 11387.5
D88: Accessories Costs | G88: =G80+G81+G87 -> 0 | H88: =H80+H81+H87 -> 0 | I88: =I80+I81+I87 -> 0 | J88: =J80+J81+J87 -> 0 | K88: =K80+K81+K87 -> 0 | L88: =L80+L81+L87 -> 0 | M88: =M80+M81+M87 -> 0 | N88: =N80+N81+N87 -> 29525.391 | ... AJ88: =AJ80+AJ81+AJ87 -> 22987.5
D90: Total Library Costs | G90: =G48+G68+G88 -> 0 | H90: =H48+H68+H88 -> 0 | I90: =I48+I68+I88 -> 0 | J90: =J48+J68+J88 -> 0 | K90: =K48+K68+K88 -> 0 | L90: =L48+L68+L88 -> 0 | M90: =M48+M68+M88 -> 0 | N90: =N48+N68+N88 -> 118101.56 | ... AJ90: =AJ48+AJ68+AJ88 -> 71962.5
A91: Rent Inflation | B91: 0.045
A92: Rental Space (Sq. Ft) | B92: 5000 | C92: Rent
A93: Rent Sq. ft. /month | B93: 1.5 | E93: Rent | G93: 0 | H93: 0 | I93: 0 | J93: 0 | K93: =SUM(G93:J93) -> 0 | L93: 0 | M93: 0 | N93: =($B$92*$B$93)*3 -> 22500 | O93: =($B$92*$B$93)*3 -> 22500 | P93: =SUM(L93:O93) -> 45000 | Q93: =($B$92*$B$93*(1+$B$91))*3 -> 23512.5 | R93: =($B$92*$B$93*(1+$B$91))*3 -> 23512.5 | S93: =($B$92*$B$93*(1+$B$91))*3 -> 23512.5 | T93: =($B$92*$B$93*(1+$B$91))*3 -> 23512.5 | U93: =SUM(Q93:T93) -> 94050 | V93: =($B$92*$B$93*(1+$B$91)^2)*3 -> 24570.562 | W93: =($B$92*$B$93*(1+$B$91)^2)*3 -> 24570.562 | X93: =($B$92*$B$93*(1+$B$91)^2)*3 -> 24570.562 | Y93: =($B$92*$B$93*(1+$B$91)^2)*3 -> 24570.562 | Z93: =SUM(V93:Y93) -> 98282.25 | AA93: =($B$92*$B$93*(1+$B$91)^2)*3 -> 24570.562 | AB93: =($B$92*$B$93*(1+$B$91)^2)*3 -> 24570.562 | AC93: =($B$92*$B$93*(1+$B$91)^2)*3 -> 24570.562 | AD93: =($B$92*$B$93*(1+$B$91)^2)*3 -> 24570.562 | AE93: =SUM(AA93:AD93) -> 98282.25 | AF93: =($B$92*$B$93*(1+$B$91)^2)*3 -> 24570.562 | AG93: =($B$92*$B$93*(1+$B$91)^2)*3 -> 24570.562 | AH93: =($B$92*$B$93*(1+$B$91)^2)*3 -> 24570.562 | AI93: =($B$92*$B$93*(1+$B$91)^2)*3 -> 24570.562 | AJ93: =SUM(AF93:AI93) -> 98282.25
A94: Maintenance ($) | B94: 0.12 | E94: Maintenance | G94: 0 | H94: 0 | I94: 0 | J94: 0 | K94: =SUM(G94:J94) -> 0 | L94: 0 | M94: =M93*$B$94 -> 0 | N94: =N93*$B$94 -> 2700 | O94: =O93*$B$94 -> 2700 | P94: =SUM(L94:O94) -> 5400 | Q94: =Q93*$B$94 -> 2821.5 | R94: =R93*$B$94 -> 2821.5 | S94: =S93*$B$94 -> 2821.5 | T94: =T93*$B$94 -> 2821.5 | U94: =SUM(Q94:T94) -> 11286 | V94: =V93*$B$94 -> 2948.4675 | W94: =W93*$B$94 -> 2948.4675 | X94: =X93*$B$94 -> 2948.4675 | Y94: =Y93*$B$94 -> 2948.4675 | Z94: =SUM(V94:Y94) -> 11793.87 | AA94: =AA93*$B$94 -> 2948.4675 | AB94: =AB93*$B$94 -> 2948.4675 | AC94: =AC93*$B$94 -> 2948.4675 | AD94: =AD93*$B$94 -> 2948.4675 | AE94: =SUM(AA94:AD94) -> 11793.87 | AF94: =AF93*$B$94 -> 2948.4675 | AG94: =AG93*$B$94 -> 2948.4675 | AH94: =AH93*$B$94 -> 2948.4675 | AI94: =AI93*$B$94 -> 2948.4675 | AJ94: =SUM(AF94:AI94) -> 11793.87
A95: Utilities ($) | B95: 0.07 | E95: Utilities | G95: 0 | H95: 0 | I95: 0 | J95: 0 | K95: =SUM(G95:J95) -> 0 | L95: 0 | M95: =M93*$B$95 -> 0 | N95: =N93*$B$95 -> 1575 | O95: =O93*$B$95 -> 1575 | P95: =SUM(L95:O95) -> 3150 | Q95: =Q93*$B$95 -> 1645.875 | R95: =R93*$B$95 -> 1645.875 | S95: =S93*$B$95 -> 1645.875 | T95: =T93*$B$95 -> 1645.875 | U95: =SUM(Q95:T95) -> 6583.5 | V95: =V93*$B$95 -> 1719.9394 | W95: =W93*$B$95 -> 1719.9394 | X95: =X93*$B$95 -> 1719.9394 | Y95: =Y93*$B$95 -> 1719.9394 | Z95: =SUM(V95:Y95) -> 6879.7575 | AA95: =AA93*$B$95 -> 1719.9394 | AB95: =AB93*$B$95 -> 1719.9394 | AC95: =AC93*$B$95 -> 1719.9394 | AD95: =AD93*$B$95 -> 1719.9394 | AE95: =SUM(AA95:AD95) -> 6879.7575 | AF95: =AF93*$B$95 -> 1719.9394 | AG95: =AG93*$B$95 -> 1719.9394 | AH95: =AH93*$B$95 -> 1719.9394 | AI95: =AI93*$B$95 -> 1719.9394 | AJ95: =SUM(AF95:AI95) -> 6879.7575
D96: Facilities Costs | G96: =SUM(G93:G95) -> 0 | H96: =SUM(H93:H95) -> 0 | I96: =SUM(I93:I95) -> 0 | J96: =SUM(J93:J95) -> 0 | K96: =SUM(G96:J96) -> 0 | L96: =SUM(H96:K96) -> 0 | M96: =SUM(M93:M95) -> 0 | N96: =SUM(N93:N95) -> 26775 | O96: =SUM(O93:O95) -> 26775 | P96: =SUM(L96:O96) -> 53550 | Q96: =SUM(Q93:Q95) -> 27979.875 | R96: =SUM(R93:R95) -> 27979.875 | S96: =SUM(S93:S95) -> 27979.875 | T96: =SUM(T93:T95) -> 27979.875 | U96: =SUM(Q96:T96) -> 111919.5 | V96: =SUM(V93:V95) -> 29238.969 | W96: =SUM(W93:W95) -> 29238.969 | X96: =SUM(X93:X95) -> 29238.969 | Y96: =SUM(Y93:Y95) -> 29238.969 | Z96: =SUM(V96:Y96) -> 116955.88 | AA96: =SUM(AA93:AA95) -> 29238.969 | AB96: =SUM(AB93:AB95) -> 29238.969 | AC96: =SUM(AC93:AC95) -> 29238.969 | AD96: =SUM(AD93:AD95) -> 29238.969 | AE96: =SUM(AA96:AD96) -> 116955.88 | AF96: =SUM(AF93:AF95) -> 29238.969 | AG96: =SUM(AG93:AG95) -> 29238.969 | AH96: =SUM(AH93:AH95) -> 29238.969 | AI96: =SUM(AI93:AI95) -> 29238.969 | AJ96: =SUM(AF96:AI96) -> 116955.88
D98: Total Photography Costs | G98: =G90+G96 -> 0 | H98: =H90+H96 -> 0 | I98: =I90+I96 -> 0 | J98: =J90+J96 -> 0 | K98: =K90+K96 -> 0 | L98: =L90+L96 -> 0 | M98: =M90+M96 -> 0 | N98: =N90+N96 -> 144876.56 | ... AJ98: =AJ90+AJ96 -> 188918.38
E100: Product & Shipping | G100: =G40+G41+G60+G61+G80+G81 -> 0 | H100: =H40+H41+H60+H61+H80+H81 -> 0 | I100: =I40+I41+I60+I61+I80+I81 -> 0 | J100: =J40+J41+J60+J61+J80+J81 -> 0 | K100: =K40+K41+K60+K61+K80+K81 -> 0 | L100: =L40+L41+L60+L61+L80+L81 -> 0 | M100: =M40+M41+M60+M61+M80+M81 -> 0 | N100: =N40+N41+N60+N61+N80+N81 -> 85500 | ... AJ100: =AJ40+AJ41+AJ60+AJ61+AJ80+AJ81 -> 37800
E101: Labor | G101: =G47+G67+G87 -> 0 | H101: =H47+H67+H87 -> 0 | I101: =I47+I67+I87 -> 0 | J101: =J47+J67+J87 -> 0 | K101: =K47+K67+K87 -> 0 | L101: =L47+L67+L87 -> 0 | M101: =M47+M67+M87 -> 0 | N101: =N47+N67+N87 -> 32601.562 | ... AJ101: =AJ47+AJ67+AJ87 -> 34162.5
E102: Rent | G102: =G96 -> 0 | H102: =H96 -> 0 | I102: =I96 -> 0 | J102: =J96 -> 0 | K102: =K96 -> 0 | L102: =L96 -> 0 | M102: =M96 -> 0 | N102: =N96 -> 26775 | ... AJ102: =AJ96 -> 116955.88
E104: Photo Labor | G104: =G42+G62+G82 -> 0 | H104: =H42+H62+H82 -> 0 | I104: =I42+I62+I82 -> 0 | J104: =J42+J62+J82 -> 0 | K104: =K42+K62+K82 -> 0 | L104: =L42+L62+L82 -> 0 | M104: =M42+M62+M82 -> 0 | N104: =N42+N62+N82 -> 11250 | ... AJ104: =AJ42+AJ62+AJ82 -> 0
E105: S & H Labor | G105: =G43+G63+G83 -> 0 | H105: =H43+H63+H83 -> 0 | I105: =I43+I63+I83 -> 0 | J105: =J43+J63+J83 -> 0 | K105: =K43+K63+K83 -> 0 | L105: =L43+L63+L83 -> 0 | M105: =M43+M63+M83 -> 0 | N105: =N43+N63+N83 -> 2250 | ... AJ105: =AJ43+AJ63+AJ83 -> 3600
E106: Tagging Labor | G106: =G44+G64+G84 -> 0 | H106: =H44+H64+H84 -> 0 | I106: =I44+I64+I84 -> 0 | J106: =J44+J64+J84 -> 0 | K106: =K44+K64+K84 -> 0 | L106: =L44+L64+L84 -> 0 | M106: =M44+M64+M84 -> 0 | N106: =N44+N64+N84 -> 7500 | ... AJ106: =AJ44+AJ64+AJ84 -> 12000
E107: Synthetic Tagging Labor | G107: =G45+G65+G85 -> 0 | H107: =H45+H65+H85 -> 0 | I107: =I45+I65+I85 -> 0 | J107: =J45+J65+J85 -> 0 | K107: =K45+K65+K85 -> 0 | L107: =L45+L65+L85 -> 0 | M107: =M45+M65+M85 -> 0 | N107: =N45+N65+N85 -> 351.5625 | ... AJ107: =AJ45+AJ65+AJ85 -> 562.5
...

Sheet Reference
A1: Growth Rates
A5: Facebook | B5: Y1 | C5: Y2 | D5: Y3 | E5: Y4 | F5: Y5 | G5: Q1-Y6 | H5: Q2-Y6 | I5: Q3-Y6 | J5: Q4-Y6 | K5: Q1-Y7 | L5: Q2-Y7 | M5: Q3-Y7 | N5: Q4-Y7 | O5: Q1-Y8 | P5: Q2-Y8 | Q5: Q3-Y8 | R5: Q4-Y8 | S5: Q1-Y9 | T5: Q2-Y9 | U5: Q3-Y9 | V5: Q4-Y9 | W5: Q1-Y10 | X5: Q2-Y10 | Y5: Q3-Y10 | Z5: Q4-Y10 | AA5: Q1-Y11 | AB5: Q2-Y11 | AC5: Q3-Y11 | AD5: Q4-Y11 | AE5: Q1-Y12 | AF5: Q2-Y12 | AG5: Q3-Y12 | AH5: Q4-Y12 | AI5: Q1-Y13 | AJ5: Q2-Y13
A6: Users | B6: 1 | C6: 6 | D6: 12 | E6: 58 | F6: 145 | G6: 197 | H6: 242 | I6: 305 | J6: 360 | K6: 431 | L6: 482 | M6: 550 | N6: 608 | O6: 680 | P6: 739 | Q6: 800 | R6: 845 | S6: 901 | T6: 955 | U6: 1007 | V6: 1056 | W6: 1110 | X6: 1155 | Y6: 1189 | Z6: 1228 | AA6: 1276 | AB6: 1317 | AC6: 1350 | AD6: 1393 | AE6: 1441 | AF6: 1490 | AG6: 1545 | AH6: 1591 | AI6: 1654 | AJ6: 1712
A7: Growth | C7: =C6/B6-1 -> 5 | D7: =D6/C6-1 -> 1 | E7: =E6/D6-1 -> 3.8333333 | F7: =F6/E6-1 -> 1.5 | G7: =G6/F6-1 -> 0.35862069 | H7: =H6/G6-1 -> 0.2284264 | I7: =I6/H6-1 -> 0.26033058 | J7: =J6/I6-1 -> 0.18032787 | ... AJ7: =AJ6/AI6-1 -> 0.035066505
C8: =(C6/B6)^0.25-1 -> 0.56508458 | D8: =(D6/C6)^0.25-1 -> 0.18920712 | E8: =(E6/D6)^0.25-1 -> 0.48272868 | F8: =(F6/E6)^0.25-1 -> 0.25743343
C9: QoQ | D9: QoQ | E9: QoQ | F9: QoQ
D11: 40 | E11: 30 | F11: 20
A15: Instagram | B15: 40532 | C15: 40689 | D15: 40707 | E15: 40787 | F15: 40878 | G15: 41000
B16: 1 | C16: 4.25 | D16: 5 | E16: 10 | F16: 15 | G16: 30 | N16: https://www.macstories.net/news/a-look-back-at-instagrams-growth-as-it-hits-100-million-monthly-active-users/
A18: Optimistic
A19: Snapchat | B19: 46 | C19: 57 | D19: 62 | E19: 71 | F19: 80 | G19: 86 | H19: 94 | I19: 107 | J19: 122 | K19: 143 | L19: 153 | M19: 158
C20: =C19/B19-1 -> 0.23913043 | D20: =D19/C19-1 -> 0.087719298 | E20: =E19/D19-1 -> 0.14516129 | F20: =F19/E19-1 -> 0.12676056 | G20: =G19/F19-1 -> 0.075 | H20: =H19/G19-1 -> 0.093023256 | I20: =I19/H19-1 -> 0.13829787 | J20: =J19/I19-1 -> 0.14018692 | ... M20: =M19/L19-1 -> 0.032679739
B26: 7 | C26: 30 | D26: 90 | F26: 7 | G26: 30 | H26: 90
A27: 45 | B27: 0.6 | C27: 0.17 | D27: 0.09 | F27: 0.36 | G27: 0.31 | H27: 0.16
B29: =B27*B26+C27*C26+D26*D27 -> 17.4 | F29: =F27*F26+G27*G26+H26*H27 -> 26.22
C30: =90/B29 -> 5.1724138 | G30: =90/F29 -> 3.4324943
B38: http://www.emeraldinsight.com/doi/abs/10.1108/JRF-08-2013-0055
B39: https://www.equidam.com/the-discount-rate-in-the-valuation-of-a-startup/

Sheet 2017 IS
B2: Profit and Loss
B3: January - December 2017
C5: Jan 2017 | D5: Feb 2017 | E5: Mar 2017 | F5: Apr 2017 | G5: May 2017 | H5: Jun 2017 | I5: Jul 2017 | J5: Aug 2017 | K5: Sep 2017 | L5: Oct 2017 | M5: Nov 2017 | N5: Dec 2017 | O5: Total
B6: Income
B7: Total Income | O7: =(((((((((((C7)+(D7))+(E7))+(F7))+(G7))+(H7))+(I7))+(J7))+(K7))+(L7))+(M7))+(N7) -> 0
B8: Cost of Goods Sold
A9: Misc. Expenses | B9: Cost of labor - COS | C9: =0 -> 0 | D9: =0 -> 0 | E9: =0 -> 0 | F9: =0 -> 0 | G9: =0 -> 0 | H9: =0 -> 0 | I9: =0 -> 0 | J9: =0 -> 0 | ... L9: =0 -> 0 | M9: =2845 -> 2845 | N9: =0 -> 0 | O9: =(((((((((((C9)+(D9))+(E9))+(F9))+(G9))+(H9))+(I9))+(J9))+(K9))+(L9))+(M9))+(N9) -> 2845
B10: Total Cost of Goods Sold | C10: =C9 -> 0 | D10: =D9 -> 0 | E10: =E9 -> 0 | F10: =F9 -> 0 | G10: =G9 -> 0 | H10: =H9 -> 0 | I10: =I9 -> 0 | J10: =J9 -> 0 | ... N10: =N9 -> 0 | O10: =(((((((((((C10)+(D10))+(E10))+(F10))+(G10))+(H10))+(I10))+(J10))+(K10))+(L10))+(M10))+(N10) -> 2845
B11: Gross Profit | C11: =(C7)-(C10) -> 0 | D11: =(D7)-(D10) -> 0 | E11: =(E7)-(E10) -> 0 | F11: =(F7)-(F10) -> 0 | G11: =(G7)-(G10) -> 0 | H11: =(H7)-(H10) -> 0 | I11: =(I7)-(I10) -> 0 | J11: =(J7)-(J10) -> 0 | ... N11: =(N7)-(N10) -> 0 | O11: =(((((((((((C11)+(D11))+(E11))+(F11))+(G11))+(H11))+(I11))+(J11))+(K11))+(L11))+(M11))+(N11) -> -2845
B12: Expenses
A13: Marketing Expenses | B13: Advertising | C13: =0 -> 0 | D13: =0 -> 0 | E13: =0 -> 0 | F13: =0 -> 0 | G13: =0 -> 0 | H13: =0 -> 0 | I13: =0 -> 0 | J13: =0 -> 0 | ... L13: =0 -> 0 | M13: =129.99 -> 129.99 | N13: =0 -> 0 | O13: =(((((((((((C13)+(D13))+(E13))+(F13))+(G13))+(H13))+(I13))+(J13))+(K13))+(L13))+(M13))+(N13) -> 129.99
A14: Misc. Expenses | B14: Automobile Expense | C14: =0 -> 0 | D14: =0 -> 0 | E14: =0 -> 0 | F14: =0 -> 0 | G14: =0 -> 0 | H14: =0 -> 0 | I14: =0 -> 0 | J14: =0 -> 0 | ... N14: =0 -> 0 | O14: =(((((((((((C14)+(D14))+(E14))+(F14))+(G14))+(H14))+(I14))+(J14))+(K14))+(L14))+(M14))+(N14) -> 0
A15: Misc. Expenses | B15: Fuel | C15: =0 -> 0 | D15: =0 -> 0 | E15: =0 -> 0 | F15: =0 -> 0 | G15: =4.16 -> 4.16 | H15: =0 -> 0 | I15: =0 -> 0 | J15: =0 -> 0 | K15: =0 -> 0 | L15: =0 -> 0 | M15: =0 -> 0 | N15: =0 -> 0 | O15: =(((((((((((C15)+(D15))+(E15))+(F15))+(G15))+(H15))+(I15))+(J15))+(K15))+(L15))+(M15))+(N15) -> 4.16
A16: Misc. Expenses | B16: Gas | C16: =0 -> 0 | D16: =0 -> 0 | E16: =0 -> 0 | F16: =0 -> 0 | G16: =0 -> 0 | H16: =0 -> 0 | I16: =0 -> 0 | J16: =0 -> 0 | K16: =20.5 -> 20.5 | L16: =0 -> 0 | M16: =81.67 -> 81.67 | N16: =16.63 -> 16.63 | O16: =(((((((((((C16)+(D16))+(E16))+(F16))+(G16))+(H16))+(I16))+(J16))+(K16))+(L16))+(M16))+(N16) -> 118.8
A17: Misc. Expenses | B17: Parking | C17: =0 -> 0 | D17: =0 -> 0 | E17: =0 -> 0 | F17: =0 -> 0 | G17: =0 -> 0 | H17: =0 -> 0 | I17: =0 -> 0 | J17: =0 -> 0 | K17: =24 -> 24 | L17: =0 -> 0 | M17: =0 -> 0 | N17: =0 -> 0 | O17: =(((((((((((C17)+(D17))+(E17))+(F17))+(G17))+(H17))+(I17))+(J17))+(K17))+(L17))+(M17))+(N17) -> 24
B18: Total Automobile Expense | C18: =(((C14)+(C15))+(C16))+(C17) -> 0 | D18: =(((D14)+(D15))+(D16))+(D17) -> 0 | E18: =(((E14)+(E15))+(E16))+(E17) -> 0 | F18: =(((F14)+(F15))+(F16))+(F17) -> 0 | G18: =(((G14)+(G15))+(G16))+(G17) -> 4.16 | H18: =(((H14)+(H15))+(H16))+(H17) -> 0 | I18: =(((I14)+(I15))+(I16))+(I17) -> 0 | J18: =(((J14)+(J15))+(J16))+(J17) -> 0 | ... N18: =(((N14)+(N15))+(N16))+(N17) -> 16.63 | O18: =(((((((((((C18)+(D18))+(E18))+(F18))+(G18))+(H18))+(I18))+(J18))+(K18))+(L18))+(M18))+(N18) -> 146.96
A19: Misc. Expenses | B19: Bank Charges | C19: =105 -> 105 | D19: =0 -> 0 | E19: =15 -> 15 | F19: =0 -> 0 | G19: =96.53 -> 96.53 | H19: =37.03 -> 37.03 | I19: =118.53 -> 118.53 | J19: =129.18 -> 129.18 | K19: =129.68 -> 129.68 | L19: =129.38 -> 129.38 | M19: =79.44 -> 79.44 | N19: =129.63 -> 129.63 | O19: =(((((((((((C19)+(D19))+(E19))+(F19))+(G19))+(H19))+(I19))+(J19))+(K19))+(L19))+(M19))+(N19) -> 969.4
A20: Outsourcing - Contractors | B20: Bookkeeping and Accounting | C20: =0 -> 0 | D20: =0 -> 0 | E20: =0 -> 0 | F20: =0 -> 0 | G20: =0 -> 0 | H20: =0 -> 0 | I20: =0 -> 0 | J20: =0 -> 0 | K20: =142.5 -> 142.5 | L20: =90.25 -> 90.25 | M20: =313.5 -> 313.5 | N20: =665 -> 665 | O20: =(((((((((((C20)+(D20))+(E20))+(F20))+(G20))+(H20))+(I20))+(J20))+(K20))+(L20))+(M20))+(N20) -> 1211.25
A21: Misc. Expenses | B21: Books and Periodical | C21: =0 -> 0 | D21: =0 -> 0 | E21: =0 -> 0 | F21: =20 -> 20 | G21: =20 -> 20 | H21: =20 -> 20 | I21: =20 -> 20 | J21: =30.68 -> 30.68 | K21: =30.68 -> 30.68 | L21: =30.68 -> 30.68 | M21: =30.68 -> 30.68 | N21: =30.68 -> 30.68 | O21: =(((((((((((C21)+(D21))+(E21))+(F21))+(G21))+(H21))+(I21))+(J21))+(K21))+(L21))+(M21))+(N21) -> 233.4
A22: Misc. Expenses | B22: Dues & Subscriptions | C22: =18.49 -> 18.49 | D22: =117.49 -> 117.49 | E22: =7.81 -> 7.81 | F22: =24.47 -> 24.47 | G22: =67.49 -> 67.49 | H22: =117.48 -> 117.48 | I22: =68.48 -> 68.48 | J22: =96.46 -> 96.46 | K22: =54.99 -> 54.99 | L22: =45.99 -> 45.99 | M22: =59.48 -> 59.48 | N22: =59.48 -> 59.48 | O22: =(((((((((((C22)+(D22))+(E22))+(F22))+(G22))+(H22))+(I22))+(J22))+(K22))+(L22))+(M22))+(N22) -> 738.11
A23: Misc. Expenses | B23: Graphic Design | C23: =400 -> 400 | D23: =0 -> 0 | E23: =0 -> 0 | F23: =0 -> 0 | G23: =3500 -> 3500 | H23: =0 -> 0 | I23: =0 -> 0 | J23: =0 -> 0 | K23: =0 -> 0 | L23: =0 -> 0 | M23: =0 -> 0 | N23: =0 -> 0 | O23: =(((((((((((C23)+(D23))+(E23))+(F23))+(G23))+(H23))+(I23))+(J23))+(K23))+(L23))+(M23))+(N23) -> 3900
A24: Misc. Expenses | B24: Insurance | C24: =0 -> 0 | D24: =0 -> 0 | E24: =0 -> 0 | F24: =0 -> 0 | G24: =0 -> 0 | H24: =18 -> 18 | I24: =27 -> 27 | J24: =117 -> 117 | K24: =0 -> 0 | L24: =0 -> 0 | M24: =0 -> 0 | N24: =0 -> 0 | O24: =(((((((((((C24)+(D24))+(E24))+(F24))+(G24))+(H24))+(I24))+(J24))+(K24))+(L24))+(M24))+(N24) -> 162
A25: Legal Fees | B25: Legal & Professional Fees | C25: =1018.91 -> 1018.91 | D25: =7973.24 -> 7973.24 | E25: =11284.24 -> 11284.24 | F25: =8691.66 -> 8691.66 | G25: =2071.37 -> 2071.37 | H25: =15652.15 -> 15652.15 | I25: =242.97 -> 242.97 | J25: =9895.5 -> 9895.5 | K25: =296 -> 296 | L25: =2136 -> 2136 | M25: =5141 -> 5141 | N25: =1 -> 1 | O25: =(((((((((((C25)+(D25))+(E25))+(F25))+(G25))+(H25))+(I25))+(J25))+(K25))+(L25))+(M25))+(N25) -> 64404.04
B26: Incorporation Expenses | C26: =0 -> 0 | D26: =0 -> 0 | E26: =0 -> 0 | F26: =0 -> 0 | G26: =4085.5 -> 4085.5 | H26: =0 -> 0 | I26: =0 -> 0 | J26: =0 -> 0 | K26: =0 -> 0 | L26: =0 -> 0 | M26: =0 -> 0 | N26: =0 -> 0 | O26: =(((((((((((C26)+(D26))+(E26))+(F26))+(G26))+(H26))+(I26))+(J26))+(K26))+(L26))+(M26))+(N26) -> 4085.5
B27: Total Legal & Professional Fees | C27: =(C25)+(C26) -> 1018.91 | D27: =(D25)+(D26) -> 7973.24 | E27: =(E25)+(E26) -> 11284.24 | F27: =(F25)+(F26) -> 8691.66 | G27: =(G25)+(G26) -> 6156.87 | H27: =(H25)+(H26) -> 15652.15 | I27: =(I25)+(I26) -> 242.97 | J27: =(J25)+(J26) -> 9895.5 | ... N27: =(N25)+(N26) -> 1 | O27: =(((((((((((C27)+(D27))+(E27))+(F27))+(G27))+(H27))+(I27))+(J27))+(K27))+(L27))+(M27))+(N27) -> 68489.54
A28: Misc. Expenses | B28: Meals and Entertainment | C28: =116.82 -> 116.82 | D28: =412.12 -> 412.12 | E28: =209.87 -> 209.87 | F28: =449.6 -> 449.6 | G28: =409.36 -> 409.36 | H28: =465.31 -> 465.31 | I28: =1216.71 -> 1216.71 | J28: =525.74 -> 525.74 | K28: =792.29 -> 792.29 | L28: =7.3 -> 7.3 | M28: =36.66 -> 36.66 | N28: =133.59 -> 133.59 | O28: =(((((((((((C28)+(D28))+(E28))+(F28))+(G28))+(H28))+(I28))+(J28))+(K28))+(L28))+(M28))+(N28) -> 4775.37
A29: Misc. Expenses | B29: Office Expenses | C29: =0 -> 0 | D29: =0 -> 0 | E29: =600 -> 600 | F29: =0 -> 0 | G29: =0 -> 0 | H29: =0 -> 0 | I29: =0 -> 0 | J29: =0 -> 0 | K29: =0 -> 0 | L29: =0 -> 0 | M29: =0 -> 0 | N29: =0 -> 0 | O29: =(((((((((((C29)+(D29))+(E29))+(F29))+(G29))+(H29))+(I29))+(J29))+(K29))+(L29))+(M29))+(N29) -> 600
A30: Misc. Expenses | B30: Other General and Admin Expenses | C30: =0 -> 0 | D30: =0 -> 0 | E30: =163.3 -> 163.3 | F30: =0 -> 0 | G30: =0 -> 0 | H30: =0 -> 0 | I30: =0 -> 0 | J30: =0 -> 0 | K30: =0 -> 0 | L30: =0 -> 0 | M30: =0 -> 0 | N30: =0 -> 0 | O30: =(((((((((((C30)+(D30))+(E30))+(F30))+(G30))+(H30))+(I30))+(J30))+(K30))+(L30))+(M30))+(N30) -> 163.3
A31: Tech Assets & Subscriptions | B31: Rent - Server Cost | C31: =549.99 -> 549.99 | D31: =549.99 -> 549.99 | E31: =549.99 -> 549.99 | F31: =1049.99 -> 1049.99 | G31: =549.99 -> 549.99 | H31: =549.99 -> 549.99 | I31: =549.99 -> 549.99 | J31: =549.99 -> 549.99 | K31: =549.99 -> 549.99 | L31: =549.99 -> 549.99 | M31: =1524.99 -> 1524.99 | N31: =549.99 -> 549.99 | O31: =(((((((((((C31)+(D31))+(E31))+(F31))+(G31))+(H31))+(I31))+(J31))+(K31))+(L31))+(M31))+(N31) -> 8074.88
