Workbook

Sheet Inputs
A1: Legend
A3: Input
A4: Reference to Other Sheet
A5: Output/Calculation
A7: Assumptions
A8: Cutomer Baseline | B8: Input | C8: Calculation | D8: Notes
A9: New | B9: 62 | C9: =AVERAGE(Model!D4:I4) -> 62.166667 | D9: 6 - month average. Growth based on user input. Assumed new customers relatively constant based on trends.
A10: Legacy to New Team | B10: 3 | C10: =AVERAGE(Model!D5:I5) -> 2.6666667 | D10: 6 - month average. Historical figures relatively flat.
A11: Expansion | B11: 69 | C11: =Growth_Analysis!$J$15 -> 69 | D11: Modeled growth based on linear equation. More expansion opportunities as the base grows. Refer to Growth Analysis for expanded projection.
A12: Contraction | B12: 40 | C12: =Growth_Analysis!$J$16 -> 40 | D12: Modeled growth based on linear equation. More companies will contract the larger the customer base. Refer to Growth Analysis for expanded projection.
A13: Old Team to New Team | B13: 1 | C13: =AVERAGE(Model!F9:I9) -> 1 | D13: 6 - month average. Historical figures relatively flat.
A14: % Churn-Failed Reactivation | B14: 0.75 | C14: =AVERAGE(Model!F22:I22) -> 0.22222222 | D14: 2018 average (YTD). Opportunity to improve. Churn related to failed credit card payment needs to be addressed appropriately
A15: Churn % (Monthly) | B15: =C15 -> 0.0048816491 | C15: =AVERAGE(Model!F43:I43) -> 0.0048816491 | D15: 2018 average (YTD). Maintain low Churn percentage. Churn % remains relatively flat, but will grow overall as more customers are onboarded.
A16: Churn-Failed % (Monthly) | B16: 0.005 | C16: =AVERAGE(Model!F44:I44) -> 0.015580078 | D16: 2018 average (YTD). Opportunity to improve payments
A18: Growth (MoM) | B18: Input
A19: New | B19: 0.03
A20: Legacy to New Team | B20: 0
A21: Old Team to New Team | B21: 0
A23: Pricing | B23: Input | C23: Calculation
A24: ARR of New Customer | B24: 2451.3962 | C24: =AVERAGE(Summary!F83:I83) -> 2451.3962
A25: ARR of Legacy to New Team | B25: 2476 | C25: =AVERAGE(Summary!F84:I84) -> 2476
A26: ARR No Change | B26: 0 | C26: =AVERAGE(Summary!F85:I85) -> 0
A27: Increase in ARR of Expansion | B27: 2207.1889 | C27: =AVERAGE(Summary!F86:I86) -> 2207.1889
A28: Decrease in ARR of Contraction | B28: -2800.3313 | C28: =AVERAGE(Summary!F87:I87) -> -2800.3313
A29: Increase in ARR Old Team to New Team | B29: 1360 | C29: =AVERAGE(Summary!F88:I88) -> 1360
A30: Increase in ARR Churn - Failed Reactivation | B30: 2088 | C30: =AVERAGE(Summary!F89:I89) -> 2088
A31: Churn Decrease in ARR | B31: -5536 | C31: =AVERAGE(Summary!F90:I90) -> -5536
A32: Churn - Failed Decrease in ARR | B32: -3229.75 | C32: =AVERAGE(Summary!F91:I91) -> -3229.75
A34: Methodology
A35: 1) Categorized Customers by change_type and by month
A36: 2.) Plotted YTD figures to determine trends and performed a simple linear regression analysis for customer type
A37: 3.) Determined Starting ARR, Change in ARR, and Ending ARR by Customer
A38: 4.) Removed Outlier Data to normalize YTD figures. Removed client ID# 39NTHthWY3. Fell outside the normal range of all other figures. Assumption that was an error or a one-time charge.
A39: 5.) Calculated pricing based on YTD averages and by change_type

Sheet Summary
B33: =Model!B2 -> Adjusted Actuals * | C33: =Model!C2 -> 0 | D33: =Model!D2 -> 0 | E33: =Model!E2 -> 0 | F33: =Model!F2 -> 0 | G33: =Model!G2 -> 0 | H33: =Model!H2 -> 0 | I33: =Model!I2 -> 0 | J33: =Model!J2 -> Projected | S33: =Model!S2 -> Apr 18' - Dec 18' CMGR | T33: =Model!T2 -> 2H' CMGR
A34: =Model!A3 -> Customer Type | B34: =Model!B3 -> 42979 | C34: =Model!C3 -> 43009 | D34: =Model!D3 -> 43040 | E34: =Model!E3 -> 43070 | F34: =Model!F3 -> 43101 | G34: =Model!G3 -> 43132 | H34: =Model!H3 -> 43160 | ... Q34: =Model!Q3 -> 43435 | S34: =Model!S3 -> 0 | T34: =Model!T3 -> 0
A35: =Model!A4 -> New | B35: =Model!B4 -> 2 | C35: =Model!C4 -> 26 | D35: =Model!D4 -> 62 | E35: =Model!E4 -> 85 | F35: =Model!F4 -> 51 | G35: =Model!G4 -> 50 | H35: =Model!H4 -> 61 | ... Q35: =Model!Q4 -> 76 | S35: =Model!S4 -> 0.021713666 | T35: =Model!T4 -> 0.029055827
A36: =Model!A5 -> Legacy to New Team | B36: =Model!B5 -> 0 | C36: =Model!C5 -> 1 | D36: =Model!D5 -> 4 | E36: =Model!E5 -> 4 | F36: =Model!F5 -> 5 | G36: =Model!G5 -> 2 | H36: =Model!H5 -> 1 | ... Q36: =Model!Q5 -> 3 | S36: =Model!S5 -> N/A | T36: =Model!T5 -> 8.3526939e-15
A37: =Model!A6 -> No Change | B37: =Model!B6 -> 0 | C37: =Model!C6 -> 1 | D37: =Model!D6 -> 22 | E37: =Model!E6 -> 67 | F37: =Model!F6 -> 131 | G37: =Model!G6 -> 169 | H37: =Model!H6 -> 190 | ... Q37: =Model!Q6 -> 599 | S37: =Model!S6 -> 0.13146271 | T37: =Model!T6 -> 0.1190629
A38: =Model!A7 -> Expansion | B38: =Model!B7 -> 0 | C38: =Model!C7 -> 0 | D38: =Model!D7 -> 5 | E38: =Model!E7 -> 14 | F38: =Model!F7 -> 24 | G38: =Model!G7 -> 44 | H38: =Model!H7 -> 41 | ... Q38: =Model!Q7 -> 145 | S38: =Model!S7 -> 0.11661149 | T38: =Model!T7 -> 0.10419642
A39: =Model!A8 -> Contraction | B39: =Model!B8 -> 0 | C39: =Model!C8 -> 0 | D39: =Model!D8 -> 2 | E39: =Model!E8 -> 14 | F39: =Model!F8 -> 26 | G39: =Model!G8 -> 14 | H39: =Model!H8 -> 34 | ... Q39: =Model!Q8 -> 79 | S39: =Model!S8 -> 0.12404365 | T39: =Model!T8 -> 0.094321361
A40: =Model!A9 -> Old Team to New Team | B40: =Model!B9 -> 0 | C40: =Model!C9 -> 0 | D40: =Model!D9 -> 0 | E40: =Model!E9 -> 1 | F40: =Model!F9 -> 0 | G40: =Model!G9 -> 3 | H40: =Model!H9 -> 0 | ... Q40: =Model!Q9 -> 1 | S40: =Model!S9 -> 3.1899074e-12 | T40: =Model!T9 -> 8.2329818e-15
A41: =Model!A10 -> Churn-Failed Reactivation | B41: =Model!B10 -> 0 | C41: =Model!C10 -> 0 | D41: =Model!D10 -> 0 | E41: =Model!E10 -> 0 | F41: =Model!F10 -> 0 | G41: =Model!G10 -> 1 | H41: =Model!H10 -> 1 | ... Q41: =Model!Q10 -> 3 | S41: =Model!S10 -> N/A | T41: =Model!T10 -> 0.069913194
A42: =Model!A11 -> Total Customers | B42: =Model!B11 -> 2 | C42: =Model!C11 -> 28 | D42: =Model!D11 -> 95 | E42: =Model!E11 -> 185 | F42: =Model!F11 -> 237 | G42: =Model!G11 -> 283 | H42: =Model!H11 -> 328 | ... Q42: =Model!Q11 -> 906 | S42: =Model!S11 -> 0.11509309 | T42: =Model!T11 -> 0.10377803
A43: =Model!A12 -> Churn | B43: =Model!B12 -> 0 | C43: =Model!C12 -> 1 | D43: =Model!D12 -> 1 | E43: =Model!E12 -> 3 | F43: =Model!F12 -> 0 | G43: =Model!G12 -> 3 | H43: =Model!H12 -> 1 | ... Q43: =Model!Q12 -> 4 | S43: =Model!S12 -> 0.18920712 | T43: =Model!T12 -> 0.12246205
A44: =Model!A13 -> Churn-Failed | B44: =Model!B13 -> 0 | C44: =Model!C13 -> 0 | D44: =Model!D13 -> 1 | E44: =Model!E13 -> 0 | F44: =Model!F13 -> 3 | G44: =Model!G13 -> 3 | H44: =Model!H13 -> 4 | ... Q44: =Model!Q13 -> 4 | S44: =Model!S13 -> -0.049420175 | T44: =Model!T13 -> 0.12246205
A45: =Model!A14 -> Total Churn | B45: =Model!B14 -> 0 | C45: =Model!C14 -> 1 | D45: =Model!D14 -> 2 | E45: =Model!E14 -> 3 | F45: =Model!F14 -> 3 | G45: =Model!G14 -> 6 | H45: =Model!H14 -> 5 | ... Q45: =Model!Q14 -> 8 | S45: =Model!S14 -> 0.016831504 | T45: =Model!T14 -> 0.12246205
A46: =Model!A15 -> Total Customers | B46: =Model!B15 -> 2 | C46: =Model!C15 -> 27 | D46: =Model!D15 -> 93 | E46: =Model!E15 -> 182 | F46: =Model!F15 -> 234 | G46: =Model!G15 -> 277 | H46: =Model!H15 -> 323 | ... Q46: =Model!Q15 -> 898 | S46: =Model!S15 -> 0.11645616 | T46: =Model!T15 -> 0.10362109
A48: =Model!A53 -> Revenue - Starting ARR
A49: =Model!A54 -> New | B49: =Model!B54 -> 0 | C49: =Model!C54 -> 0 | D49: =Model!D54 -> 0 | E49: =Model!E54 -> 0 | F49: =Model!F54 -> 0 | G49: =Model!G54 -> 0 | H49: =Model!H54 -> 0 | ... Q49: =Model!Q54 -> 0 | S49: =Model!S54 -> N/A | T49: =Model!T54 -> N/A
A50: =Model!A55 -> Legacy to New Team | B50: =Model!B55 -> 0 | C50: =Model!C55 -> 0 | D50: =Model!D55 -> 0 | E50: =Model!E55 -> 0 | F50: =Model!F55 -> 0 | G50: =Model!G55 -> 0 | H50: =Model!H55 -> 0 | ... Q50: =Model!Q55 -> 0 | S50: =Model!S55 -> N/A | T50: =Model!T55 -> N/A
A51: =Model!A56 -> No Change | B51: =Model!B56 -> 0 | C51: =Model!C56 -> 1200 | D51: =Model!D56 -> 29520 | E51: =Model!E56 -> 94128 | F51: =Model!F56 -> 187908 | G51: =Model!G56 -> 241536 | H51: =Model!H56 -> 277992 | ... Q51: =Model!Q56 -> 880647.32 | S51: =Model!S56 -> 0.12954211 | T51: =Model!T56 -> 0.10802422
A52: =Model!A57 -> Expansion | B52: =Model!B57 -> 0 | C52: =Model!C57 -> 0 | D52: =Model!D57 -> 25668 | E52: =Model!E57 -> 86640 | F52: =Model!F57 -> 151416 | G52: =Model!G57 -> 224292 | H52: =Model!H57 -> 184872 | ... Q52: =Model!Q57 -> 799527.82 | S52: =Model!S57 -> 0.12954211 | T52: =Model!T57 -> 0.10802422
A53: =Model!A58 -> Contraction | B53: =Model!B58 -> 0 | C53: =Model!C58 -> 0 | D53: =Model!D58 -> 31236 | E53: =Model!E58 -> 245712 | F53: =Model!F58 -> 227472 | G53: =Model!G58 -> 119220 | H53: =Model!H58 -> 223116 | ... Q53: =Model!Q58 -> 444727.69 | S53: =Model!S58 -> 0.12954211 | T53: =Model!T58 -> 0.10802422
A54: =Model!A59 -> Old Team to New Team | B54: =Model!B59 -> 0 | C54: =Model!C59 -> 0 | D54: =Model!D59 -> 0 | E54: =Model!E59 -> 0 | F54: =Model!F59 -> 0 | G54: =Model!G59 -> 0 | H54: =Model!H59 -> 0 | ... Q54: =Model!Q59 -> 0 | S54: =Model!S59 -> N/A | T54: =Model!T59 -> N/A
A55: =Model!A60 -> Churn-Failed Reactivation | B55: =Model!B60 -> 0 | C55: =Model!C60 -> 0 | D55: =Model!D60 -> 0 | E55: =Model!E60 -> 0 | F55: =Model!F60 -> 0 | G55: =Model!G60 -> 0 | H55: =Model!H60 -> 0 | ... Q55: =Model!Q60 -> 0 | S55: =Model!S60 -> N/A | T55: =Model!T60 -> N/A
A56: =Model!A61 -> Churn | B56: =Model!B61 -> 0 | C56: =Model!C61 -> 9804 | D56: =Model!D61 -> 1728 | E56: =Model!E61 -> 14712 | F56: =Model!F61 -> 0 | G56: =Model!G61 -> 4752 | H56: =Model!H61 -> 1440 | ... Q56: =Model!Q61 -> 22144 | S56: =Model!S61 -> 0.062988461 | T56: =Model!T61 -> 0.12246205
A57: =Model!A62 -> Churn-Failed | B57: =Model!B62 -> 0 | C57: =Model!C62 -> 0 | D57: =Model!D62 -> 1440 | E57: =Model!E62 -> 0 | F57: =Model!F62 -> 7380 | G57: =Model!G62 -> 4320 | H57: =Model!H62 -> 17412 | ... Q57: =Model!Q62 -> 12919 | S57: =Model!S62 -> -0.09214474 | T57: =Model!T62 -> 0.12246205
A58: =Model!A63 -> Total Starting ARR | B58: =Model!B63 -> 0 | C58: =Model!C63 -> 11004 | D58: =Model!D63 -> 89592 | E58: =Model!E63 -> 441192 | F58: =Model!F63 -> 574176 | G58: =Model!G63 -> 594120 | H58: =Model!H63 -> 704832 | ... Q58: =Model!Q63 -> 2159965.8 | S58: =Model!S63 -> 0.12472559 | T58: =Model!T63 -> 0.10824842
A59: =Model!A65 -> Revenue - Change in ARR | S59: =Model!S65 -> 0 | T59: =Model!T65 -> 0
A60: =Model!A66 -> New | B60: =Model!B66 -> 11004 | C60: =Model!C66 -> 81816 | D60: =Model!D66 -> 320772 | E60: =Model!E66 -> 195756 | F60: =Model!F66 -> 80688 | G60: =Model!G66 -> 130092 | H60: =Model!H66 -> 173507 | ... Q60: =Model!Q66 -> 186306.11 | S60: =Model!S66 -> 0.0058981707 | T60: =Model!T66 -> 0.029055827
A61: =Model!A67 -> Legacy to New Team | B61: =Model!B67 -> 0 | C61: =Model!C67 -> 3456 | D61: =Model!D67 -> 38232 | E61: =Model!E67 -> 18960 | F61: =Model!F67 -> 20220 | G61: =Model!G67 -> 3888 | H61: =Model!H67 -> 1440 | ... Q61: =Model!Q67 -> 7428 | S61: =Model!S67 -> N/A | T61: =Model!T67 -> 8.3301817e-15
A62: =Model!A68 -> No Change | B62: =Model!B68 -> 0 | C62: =Model!C68 -> 0 | D62: =Model!D68 -> 0 | E62: =Model!E68 -> 0 | F62: =Model!F68 -> 0 | G62: =Model!G68 -> 0 | H62: =Model!H68 -> 0 | ... Q62: =Model!Q68 -> 0 | S62: =Model!S68 -> N/A | T62: =Model!T68 -> N/A
A63: =Model!A69 -> Expansion | B63: =Model!B69 -> 0 | C63: =Model!C69 -> 0 | D63: =Model!D69 -> 16200 | E63: =Model!E69 -> 82008 | F63: =Model!F69 -> 73272 | G63: =Model!G69 -> 98016 | H63: =Model!H69 -> 68712 | ... Q63: =Model!Q69 -> 320042.39 | S63: =Model!S69 -> 0.13982327 | T63: =Model!T69 -> 0.10419642
A64: =Model!A70 -> Contraction | B64: =Model!B70 -> 0 | C64: =Model!C70 -> 0 | D64: =Model!D70 -> -8976 | E64: =Model!E70 -> -143112 | F64: =Model!F70 -> -118032 | G64: =Model!G70 -> -54744 | H64: =Model!H70 -> -43704 | ... Q64: =Model!Q70 -> -221226.17 | S64: =Model!S70 -> 0.21876506 | T64: =Model!T70 -> 0.094321361
A65: =Model!A71 -> Old Team to New Team | B65: =Model!B71 -> 0 | C65: =Model!C71 -> 0 | D65: =Model!D71 -> 0 | E65: =Model!E71 -> 1200 | F65: =Model!F71 -> 0 | G65: =Model!G71 -> 3840 | H65: =Model!H71 -> 0 | ... Q65: =Model!Q71 -> 1360 | S65: =Model!S71 -> -0.0071193383 | T65: =Model!T71 -> 8.3593552e-15
A66: =Model!A72 -> Churn-Failed Reactivation | B66: =Model!B72 -> 0 | C66: =Model!C72 -> 0 | D66: =Model!D72 -> 0 | E66: =Model!E72 -> 0 | F66: =Model!F72 -> 0 | G66: =Model!G72 -> 1440 | H66: =Model!H72 -> 2736 | ... Q66: =Model!Q72 -> 6264 | S66: =Model!S72 -> N/A | T66: =Model!T72 -> 0.069913194
A67: =Model!A73 -> Churn | B67: =Model!B73 -> 0 | C67: =Model!C73 -> -9804 | D67: =Model!D73 -> -1728 | E67: =Model!E73 -> -14712 | F67: =Model!F73 -> 0 | G67: =Model!G73 -> -4752 | H67: =Model!H73 -> -1440 | ... Q67: =Model!Q73 -> -22144 | S67: =Model!S73 -> 0.062988461 | T67: =Model!T73 -> 0.12246205
A68: =Model!A74 -> Churn-Failed | B68: =Model!B74 -> 0 | C68: =Model!C74 -> 0 | D68: =Model!D74 -> -1440 | E68: =Model!E74 -> 0 | F68: =Model!F74 -> -7380 | G68: =Model!G74 -> -4320 | H68: =Model!H74 -> -17412 | ... Q68: =Model!Q74 -> -12919 | S68: =Model!S74 -> -0.09214474 | T68: =Model!T74 -> 0.12246205
A69: =Model!A75 -> Total Change in ARR | B69: =Model!B75 -> 11004 | C69: =Model!C75 -> 75468 | D69: =Model!D75 -> 363060 | E69: =Model!E75 -> 140100 | F69: =Model!F75 -> 48768 | G69: =Model!G75 -> 173460 | H69: =Model!H75 -> 183839 | ... Q69: =Model!Q75 -> 265111.32 | S69: =Model!S75 -> 0.032984318 | T69: =Model!T75 -> 0.048021379
A70: =Model!A77 -> Revenue - Ending ARR
A71: =Model!A78 -> New | B71: =Model!B78 -> 11004 | C71: =Model!C78 -> 81816 | D71: =Model!D78 -> 320772 | E71: =Model!E78 -> 195756 | F71: =Model!F78 -> 80688 | G71: =Model!G78 -> 130092 | H71: =Model!H78 -> 173507 | ... Q71: =Model!Q78 -> 186306.11 | S71: =Model!S78 -> 0.0058981707 | T71: =Model!T78 -> 0.029055827
A72: =Model!A79 -> Legacy to New Team | B72: =Model!B79 -> 0 | C72: =Model!C79 -> 3456 | D72: =Model!D79 -> 38232 | E72: =Model!E79 -> 18960 | F72: =Model!F79 -> 20220 | G72: =Model!G79 -> 3888 | H72: =Model!H79 -> 1440 | ... Q72: =Model!Q79 -> 7428 | S72: =Model!S79 -> N/A | T72: =Model!T79 -> 8.3301817e-15
A73: =Model!A80 -> No Change | B73: =Model!B80 -> 0 | C73: =Model!C80 -> 1200 | D73: =Model!D80 -> 29520 | E73: =Model!E80 -> 94128 | F73: =Model!F80 -> 187908 | G73: =Model!G80 -> 241536 | H73: =Model!H80 -> 277992 | ... Q73: =Model!Q80 -> 880647.32 | S73: =Model!S80 -> 0.12954211 | T73: =Model!T80 -> 0.10802422
A74: =Model!A81 -> Expansion | B74: =Model!B81 -> 0 | C74: =Model!C81 -> 0 | D74: =Model!D81 -> 41868 | E74: =Model!E81 -> 168648 | F74: =Model!F81 -> 224688 | G74: =Model!G81 -> 322308 | H74: =Model!H81 -> 253584 | ... Q74: =Model!Q81 -> 1119570.2 | S74: =Model!S81 -> 0.13239647 | T74: =Model!T81 -> 0.10692051
A75: =Model!A82 -> Contraction | B75: =Model!B82 -> 0 | C75: =Model!C82 -> 0 | D75: =Model!D82 -> 22260 | E75: =Model!E82 -> 102600 | F75: =Model!F82 -> 109440 | G75: =Model!G82 -> 64476 | H75: =Model!H82 -> 179412 | ... Q75: =Model!Q82 -> 223501.52 | S75: =Model!S82 -> 0.078183559 | T75: =Model!T82 -> 0.12286629
A76: =Model!A83 -> Old Team to New Team | B76: =Model!B83 -> 0 | C76: =Model!C83 -> 0 | D76: =Model!D83 -> 0 | E76: =Model!E83 -> 1200 | F76: =Model!F83 -> 0 | G76: =Model!G83 -> 3840 | H76: =Model!H83 -> 0 | ... Q76: =Model!Q83 -> 1360 | S76: =Model!S83 -> -0.0071193383 | T76: =Model!T83 -> 8.3593552e-15
A77: =Model!A84 -> Churn-Failed Reactivation | B77: =Model!B84 -> 0 | C77: =Model!C84 -> 0 | D77: =Model!D84 -> 0 | E77: =Model!E84 -> 0 | F77: =Model!F84 -> 0 | G77: =Model!G84 -> 1440 | H77: =Model!H84 -> 2736 | ... Q77: =Model!Q84 -> 6264 | S77: =Model!S84 -> N/A | T77: =Model!T84 -> 0.069913194
A78: =Model!A85 -> Churn | B78: =Model!B85 -> 0 | C78: =Model!C85 -> 0 | D78: =Model!D85 -> 0 | E78: =Model!E85 -> 0 | F78: =Model!F85 -> 0 | G78: =Model!G85 -> 0 | H78: =Model!H85 -> 0 | ... Q78: =Model!Q85 -> 0 | S78: =Model!S85 -> N/A | T78: =Model!T85 -> N/A
A79: =Model!A86 -> Churn-Failed | B79: =Model!B86 -> 0 | C79: =Model!C86 -> 0 | D79: =Model!D86 -> 0 | E79: =Model!E86 -> 0 | F79: =Model!F86 -> 0 | G79: =Model!G86 -> 0 | H79: =Model!H86 -> 0 | ... Q79: =Model!Q86 -> 0 | S79: =Model!S86 -> N/A | T79: =Model!T86 -> N/A
A80: =Model!A87 -> Total Ending ARR | B80: =Model!B87 -> 11004 | C80: =Model!C87 -> 86472 | D80: =Model!D87 -> 452652 | E80: =Model!E87 -> 581292 | F80: =Model!F87 -> 622944 | G80: =Model!G87 -> 767580 | H80: =Model!H87 -> 888671 | ... Q80: =Model!Q87 -> 2425077.1 | S80: =Model!S87 -> 0.11057268 | T80: =Model!T87 -> 0.10040376
A82: =Model!A122 -> Pricing
A83: =Model!A123 -> ARR of New Customer | B83: =Model!B123 -> 5502 | C83: =Model!C123 -> 3146.7692 | D83: =Model!D123 -> 5173.7419 | E83: =Model!E123 -> 2303.0118 | F83: =Model!F123 -> 1582.1176 | G83: =Model!G123 -> 2601.84 | H83: =Model!H123 -> 2844.377 | ... Q83: =Model!Q123 -> 2451.3962 | S83: =Model!S123 -> -0.015479381 | T83: =Model!T123 -> 8.4363113e-15
A84: =Model!A124 -> ARR of Legacy to New Team | B84: =Model!B124 -> N/A | C84: =Model!C124 -> 3456 | D84: =Model!D124 -> 9558 | E84: =Model!E124 -> 4740 | F84: =Model!F124 -> 4044 | G84: =Model!G124 -> 1944 | H84: =Model!H124 -> 1440 | ... Q84: =Model!Q124 -> 2476 | S84: =Model!S124 -> N/A | T84: =Model!T124 -> 8.2550107e-15
A85: =Model!A125 -> ARR No Change | B85: =Model!B125 -> N/A | C85: =Model!C125 -> 0 | D85: =Model!D125 -> 0 | E85: =Model!E125 -> 0 | F85: =Model!F125 -> 0 | G85: =Model!G125 -> 0 | H85: =Model!H125 -> 0 | ... Q85: =Model!Q125 -> 0 | S85: =Model!S125 -> N/A | T85: =Model!T125 -> N/A
A86: =Model!A126 -> Increase in ARR of Expansion | B86: =Model!B126 -> N/A | C86: =Model!C126 -> N/A | D86: =Model!D126 -> 3240 | E86: =Model!E126 -> 5857.7143 | F86: =Model!F126 -> 3053 | G86: =Model!G126 -> 2227.6364 | H86: =Model!H126 -> 1675.9024 | ... Q86: =Model!Q126 -> 2207.1889 | S86: =Model!S126 -> 0.020787689 | T86: =Model!T126 -> 8.3407736e-15
A87: =Model!A127 -> Decrease in ARR of Contraction | B87: =Model!B127 -> N/A | C87: =Model!C127 -> N/A | D87: =Model!D127 -> -4488 | E87: =Model!E127 -> -10222.286 | F87: =Model!F127 -> -4539.6923 | G87: =Model!G127 -> -3910.2857 | H87: =Model!H127 -> -1285.4118 | ... Q87: =Model!Q127 -> -2800.3313 | S87: =Model!S127 -> 0.084268448 | T87: =Model!T127 -> 6.6320872e-15
A88: =Model!A128 -> Increase in ARR Old Team to New Team | B88: =Model!B128 -> N/A | C88: =Model!C128 -> N/A | D88: =Model!D128 -> N/A | E88: =Model!E128 -> 1200 | F88: =Model!F128 -> N/A | G88: =Model!G128 -> 1280 | H88: =Model!H128 -> N/A | ... Q88: =Model!Q128 -> 1360 | S88: =Model!S128 -> -0.0071193383 | T88: =Model!T128 -> 8.3593552e-15
A89: =Model!A129 -> Increase in ARR Churn - Failed Reactivation | B89: =Model!B129 -> N/A | C89: =Model!C129 -> N/A | D89: =Model!D129 -> N/A | E89: =Model!E129 -> N/A | F89: =Model!F129 -> N/A | G89: =Model!G129 -> 1440 | H89: =Model!H129 -> 2736 | ... Q89: =Model!Q129 -> 2088 | S89: =Model!S129 -> N/A | T89: =Model!T129 -> 8.3767914e-15
A90: =Model!A130 -> Churn Decrease in ARR | B90: =Model!B130 -> N/A | C90: =Model!C130 -> -9804 | D90: =Model!D130 -> -1728 | E90: =Model!E130 -> -4904 | F90: =Model!F130 -> N/A | G90: =Model!G130 -> -1584 | H90: =Model!H130 -> -1440 | ... Q90: =Model!Q130 -> -5536 | S90: =Model!S130 -> -0.10613681 | T90: =Model!T130 -> 6.5709602e-15
A91: =Model!A131 -> Churn - Failed Decrease in ARR | B91: =Model!B131 -> N/A | C91: =Model!C131 -> N/A | D91: =Model!D131 -> -1440 | E91: =Model!E131 -> N/A | F91: =Model!F131 -> -2460 | G91: =Model!G131 -> -1440 | H91: =Model!H131 -> -4353 | ... Q91: =Model!Q131 -> -3229.75 | S91: =Model!S131 -> -0.044945794 | T91: =Model!T131 -> 6.6076774e-15
A93: * Removed Outlier Data
A94: Select Metrics
S95: YTD Average | T95: Projected Average | U95: H2 2018 Average
A96: =Model!A11 -> Total Customers | B96: =Model!B15 -> 2 | C96: =Model!C15 -> 27 | D96: =Model!D15 -> 93 | E96: =Model!E15 -> 182 | F96: =Model!F15 -> 234 | G96: =Model!G15 -> 277 | H96: =Model!H15 -> 323 | I96: =Model!I15 -> 372 | ... Q96: =Model!Q15 -> 898 | S96: =AVERAGE(F96:I96) -> 301.5 | T96: =AVERAGE(J96:Q96) -> 661.625 | U96: =AVERAGE(L96:Q96) -> 726.83333
A97: =Model!A4 -> New | B97: =Model!B4 -> 2 | C97: =Model!C4 -> 26 | D97: =Model!D4 -> 62 | E97: =Model!E4 -> 85 | F97: =Model!F4 -> 51 | G97: =Model!G4 -> 50 | H97: =Model!H4 -> 61 | ... Q97: =Model!Q4 -> 76 | S97: =AVERAGE(F97:I97) -> 56.5 | T97: =AVERAGE(J97:Q97) -> 69 | U97: =AVERAGE(L97:Q97) -> 71
A98: =Model!A35 -> Cumulative Customer Churn (2018) | B98: =Model!B35 -> 0 | C98: =Model!C35 -> 0 | D98: =Model!D35 -> 0 | E98: =Model!E35 -> 0 | F98: =Model!F35 -> 0 | G98: =Model!G35 -> 3 | H98: =Model!H35 -> 4 | ... Q98: =Model!Q35 -> 28
A99: =Model!A43 -> % Churn | B99: =Model!B43 -> 0 | C99: =Model!C43 -> 0.5 | D99: =Model!D43 -> 0.037037037 | E99: =Model!E43 -> 0.032258065 | F99: =Model!F43 -> 0 | G99: =Model!G43 -> 0.012820513 | H99: =Model!H43 -> 0.0036101083 | ... Q99: =Model!Q43 -> 0.0048367594 | S99: =AVERAGE(F99:I99) -> 0.0048816491 | T99: =AVERAGE(J99:Q99) -> 0.0048242712 | U99: =AVERAGE(L99:Q99) -> 0.0047700207
A100: =Model!A39 -> % Customers that Expand | B100: =Model!B39 -> 0 | C100: =Model!C39 -> 0 | D100: =Model!D39 -> 0.18518519 | E100: =Model!E39 -> 0.15053763 | F100: =Model!F39 -> 0.13186813 | G100: =Model!G39 -> 0.18803419 | H100: =Model!H39 -> 0.14801444 | ... Q100: =Model!Q39 -> 0.17533253 | S100: =AVERAGE(F100:I100) -> 0.16341882 | T100: =AVERAGE(J100:Q100) -> 0.18042403 | U100: =AVERAGE(L100:Q100) -> 0.17900005
A101: =Model!A40 -> % Customers that Contracted | B101: =Model!B40 -> 0 | C101: =Model!C40 -> 0 | D101: =Model!D40 -> 0.074074074 | E101: =Model!E40 -> 0.15053763 | F101: =Model!F40 -> 0.14285714 | G101: =Model!G40 -> 0.05982906 | H101: =Model!H40 -> 0.12274368 | ... Q101: =Model!Q40 -> 0.095525998 | S101: =AVERAGE(F101:I101) -> 0.10535128 | T101: =AVERAGE(J101:Q101) -> 0.1010156 | U101: =AVERAGE(L101:Q101) -> 0.099141797
A102: =Model!A46 -> Net Expansion | B102: =Model!B46 -> 0 | C102: =Model!C46 -> 0 | D102: =Model!D46 -> 3 | E102: =Model!E46 -> 0 | F102: =Model!F46 -> -2 | G102: =Model!G46 -> 30 | H102: =Model!H46 -> 7 | ... Q102: =Model!Q46 -> 66 | S102: =AVERAGE(F102:I102) -> 16 | T102: =AVERAGE(J102:Q102) -> 47.375 | U102: =AVERAGE(L102:Q102) -> 52.666667
A103: =Model!A47 -> Net Expansion % of Customer Base | B103: =Model!B47 -> 0 | C103: =Model!C47 -> 0 | D103: =Model!D47 -> 0.11111111 | E103: =Model!E47 -> 0 | F103: =Model!F47 -> -0.010989011 | G103: =Model!G47 -> 0.12820513 | H103: =Model!H47 -> 0.025270758 | ... Q103: =Model!Q47 -> 0.07980653 | S103: =AVERAGE(F103:I103) -> 0.058067539 | T103: =AVERAGE(J103:Q103) -> 0.079408427 | U103: =AVERAGE(L103:Q103) -> 0.079858251
A104: =Model!A48 -> Net Expansion Growth (MoM) | B104: =Model!B48 -> 0 | C104: =Model!C48 -> N/A | D104: =Model!D48 -> N/A | E104: =Model!E48 -> -1 | F104: =Model!F48 -> N/A | G104: =Model!G48 -> 16 | H104: =Model!H48 -> -0.76666667 | ... Q104: =Model!Q48 -> 0.1 | S104: =AVERAGE(F104:I104) -> 6.1253968 | T104: =AVERAGE(J104:Q104) -> 0.10948807 | U104: =AVERAGE(L104:Q104) -> 0.11724847
A105: =Model!A50 -> Expanded/Contracted Ratio | B105: =Model!B50 -> N/A | C105: =Model!C50 -> N/A | D105: =Model!D50 -> 2.5 | E105: =Model!E50 -> 1 | F105: =Model!F50 -> 0.92307692 | G105: =Model!G50 -> 3.1428571 | H105: =Model!H50 -> 1.2058824 | ... Q105: =Model!Q50 -> 1.835443 | S105: =AVERAGE(F105:I105) -> 1.8018251 | T105: =AVERAGE(J105:Q105) -> 1.7874309 | U105: =AVERAGE(L105:Q105) -> 1.8058861
A106: =Model!A24 -> Churn-Failed | B106: =Model!B24 -> 0 | C106: =Model!C24 -> 0 | D106: =Model!D24 -> 0.037037037 | E106: =Model!E24 -> 0 | F106: =Model!F24 -> 0.016483516 | G106: =Model!G24 -> 0.012820513 | H106: =Model!H24 -> 0.014440433 | ... Q106: =Model!Q24 -> 0.005 | S106: =AVERAGE(F106:I106) -> 0.015580078 | T106: =AVERAGE(J106:Q106) -> 0.005 | U106: =AVERAGE(L106:Q106) -> 0.005
A107: =Model!A22 -> Churn - Failed Reactiviation % of Churn Failed | B107: =Model!B22 -> 0 | C107: =Model!C22 -> N/A | D107: =Model!D22 -> N/A | E107: =Model!E22 -> 0 | F107: =Model!F22 -> N/A | G107: =Model!G22 -> 0.33333333 | H107: =Model!H22 -> 0.33333333 | ... Q107: =Model!Q22 -> 0.75 | S107: =AVERAGE(F107:I107) -> 0.22222222 | T107: =AVERAGE(J107:Q107) -> 0.75 | U107: =AVERAGE(L107:Q107) -> 0.75
A108: =Model!A126 -> Increase in ARR of Expansion | B108: =Model!B126 -> N/A | C108: =Model!C126 -> N/A | D108: =Model!D126 -> 3240 | E108: =Model!E126 -> 5857.7143 | F108: =Model!F126 -> 3053 | G108: =Model!G126 -> 2227.6364 | H108: =Model!H126 -> 1675.9024 | ... Q108: =Model!Q126 -> 2207.1889 | S108: =AVERAGE(F108:I108) -> 2207.1889 | T108: =AVERAGE(J108:Q108) -> 2207.1889 | U108: =AVERAGE(L108:Q108) -> 2207.1889
A109: =Model!A127 -> Decrease in ARR of Contraction | B109: =Model!B127 -> N/A | C109: =Model!C127 -> N/A | D109: =Model!D127 -> -4488 | E109: =Model!E127 -> -10222.286 | F109: =Model!F127 -> -4539.6923 | G109: =Model!G127 -> -3910.2857 | H109: =Model!H127 -> -1285.4118 | ... Q109: =Model!Q127 -> -2800.3313 | S109: =AVERAGE(F109:I109) -> -2800.3313 | T109: =AVERAGE(J109:Q109) -> -2800.3313 | U109: =AVERAGE(L109:Q109) -> -2800.3313
A111: OKRs
A113: Objective: Grow
A114: Win 69 new customers a month
A115: 898 Total Customers by year end
A117: Objective: Protect
A118: Reduce Churn to < 0.5%/month, (< 6% annual churn)
A119: Maintain Contraction < 10%
A120: Keep Average contraction/customer < $2,800
A121: Keep % Churn - Failed < 0.5 %/month
A122: Reactivate Churn - Failed > 75%
A124: Objective: Expand our services
A125: Increase expansion to > 18.5% of our customer base
... A135: 6. Evaluate sales quota & compensation and incentivize hitting year-end targets.

Sheet Model
B2: Adjusted Actuals * | J2: Projected | S2: Apr 18' - Dec 18' CMGR | T2: 2H' CMGR
A3: Customer Type | B3: 42979 | C3: 43009 | D3: 43040 | E3: 43070 | F3: 43101 | G3: 43132 | H3: 43160 | I3: 43191 | J3: 43221 | K3: 43252 | L3: 43282 | M3: 43313 | N3: 43344 | O3: 43374 | P3: 43405 | Q3: 43435
A4: New | B4: =COUNTIFS('data set'!$E:$E,Model!$A4,'data set'!$B:$B,Model!B$3) -> 2 | C4: =COUNTIFS('data set'!$E:$E,Model!$A4,'data set'!$B:$B,Model!C$3) -> 26 | D4: =COUNTIFS('data set'!$E:$E,Model!$A4,'data set'!$B:$B,Model!D$3) -> 62 | E4: =COUNTIFS('data set'!$E:$E,Model!$A4,'data set'!$B:$B,Model!E$3) -> 85 | F4: =COUNTIFS('data set'!$E:$E,Model!$A4,'data set'!$B:$B,Model!F$3) -> 51 | G4: =COUNTIFS('data set'!$E:$E,Model!$A4,'data set'!$B:$B,Model!G$3) -> 50 | H4: =COUNTIFS('data set'!$E:$E,Model!$A4,'data set'!$B:$B,Model!H$3) -> 61 | I4: =COUNTIFS('data set'!$E:$E,Model!$A4,'data set'!$B:$B,Model!I$3) -> 64 | J4: =Inputs!B9 -> 62 | K4: =ROUND(J4*(1+K27),0) -> 64 | L4: =ROUND(K4*(1+L27),0) -> 66 | M4: =ROUND(L4*(1+M27),0) -> 68 | N4: =ROUND(M4*(1+N27),0) -> 70 | O4: =ROUND(N4*(1+O27),0) -> 72 | P4: =ROUND(O4*(1+P27),0) -> 74 | Q4: =ROUND(P4*(1+Q27),0) -> 76 | S4: =IFERROR(RATE(MONTH($Q$3)-MONTH($I$3),0,-I4,Q4),"N/A") -> 0.021713666 | T4: =IFERROR(RATE(MONTH($Q$3)-MONTH($K$3),0,-K4,Q4),"N/A") -> 0.029055827
A5: Legacy to New Team | B5: =COUNTIFS('data set'!$E:$E,Model!$A5,'data set'!$B:$B,Model!B$3) -> 0 | C5: =COUNTIFS('data set'!$E:$E,Model!$A5,'data set'!$B:$B,Model!C$3) -> 1 | D5: =COUNTIFS('data set'!$E:$E,Model!$A5,'data set'!$B:$B,Model!D$3) -> 4 | E5: =COUNTIFS('data set'!$E:$E,Model!$A5,'data set'!$B:$B,Model!E$3) -> 4 | F5: =COUNTIFS('data set'!$E:$E,Model!$A5,'data set'!$B:$B,Model!F$3) -> 5 | G5: =COUNTIFS('data set'!$E:$E,Model!$A5,'data set'!$B:$B,Model!G$3) -> 2 | H5: =COUNTIFS('data set'!$E:$E,Model!$A5,'data set'!$B:$B,Model!H$3) -> 1 | I5: =COUNTIFS('data set'!$E:$E,Model!$A5,'data set'!$B:$B,Model!I$3) -> 0 | J5: =Inputs!B10 -> 3 | K5: =ROUND(J5*(1+K28),0) -> 3 | L5: =ROUND(K5*(1+L28),0) -> 3 | M5: =ROUND(L5*(1+M28),0) -> 3 | N5: =ROUND(M5*(1+N28),0) -> 3 | O5: =ROUND(N5*(1+O28),0) -> 3 | P5: =ROUND(O5*(1+P28),0) -> 3 | Q5: =ROUND(P5*(1+Q28),0) -> 3 | S5: =IFERROR(RATE(MONTH($Q$3)-MONTH($I$3),0,-I5,Q5),"N/A") -> N/A | T5: =IFERROR(RATE(MONTH($Q$3)-MONTH($K$3),0,-K5,Q5),"N/A") -> 8.3526939e-15
A6: No Change | B6: =COUNTIFS('data set'!$E:$E,Model!$A6,'data set'!$B:$B,Model!B$3) -> 0 | C6: =COUNTIFS('data set'!$E:$E,Model!$A6,'data set'!$B:$B,Model!C$3) -> 1 | D6: =COUNTIFS('data set'!$E:$E,Model!$A6,'data set'!$B:$B,Model!D$3) -> 22 | E6: =COUNTIFS('data set'!$E:$E,Model!$A6,'data set'!$B:$B,Model!E$3) -> 67 | F6: =COUNTIFS('data set'!$E:$E,Model!$A6,'data set'!$B:$B,Model!F$3) -> 131 | G6: =COUNTIFS('data set'!$E:$E,Model!$A6,'data set'!$B:$B,Model!G$3) -> 169 | H6: =COUNTIFS('data set'!$E:$E,Model!$A6,'data set'!$B:$B,Model!H$3) -> 190 | I6: =COUNTIFS('data set'!$E:$E,Model!$A6,'data set'!$B:$B,Model!I$3) -> 223 | J6: =I15-J7-J8-J5-J9 -> 259 | K6: =J15-K7-K8-K5-K9 -> 305 | L6: =K15-L7-L8-L5-L9 -> 351 | M6: =L15-M7-M8-M5-M9 -> 398 | N6: =M15-N7-N8-N5-N9 -> 447 | O6: =N15-O7-O8-O5-O9 -> 496 | P6: =O15-P7-P8-P5-P9 -> 547 | Q6: =P15-Q7-Q8-Q5-Q9 -> 599 | S6: =IFERROR(RATE(MONTH($Q$3)-MONTH($I$3),0,-I6,Q6),"N/A") -> 0.13146271 | T6: =IFERROR(RATE(MONTH($Q$3)-MONTH($K$3),0,-K6,Q6),"N/A") -> 0.1190629
A7: Expansion | B7: =COUNTIFS('data set'!$E:$E,Model!$A7,'data set'!$B:$B,Model!B$3) -> 0 | C7: =COUNTIFS('data set'!$E:$E,Model!$A7,'data set'!$B:$B,Model!C$3) -> 0 | D7: =COUNTIFS('data set'!$E:$E,Model!$A7,'data set'!$B:$B,Model!D$3) -> 5 | E7: =COUNTIFS('data set'!$E:$E,Model!$A7,'data set'!$B:$B,Model!E$3) -> 14 | F7: =COUNTIFS('data set'!$E:$E,Model!$A7,'data set'!$B:$B,Model!F$3) -> 24 | G7: =COUNTIFS('data set'!$E:$E,Model!$A7,'data set'!$B:$B,Model!G$3) -> 44 | H7: =COUNTIFS('data set'!$E:$E,Model!$A7,'data set'!$B:$B,Model!H$3) -> 41 | I7: =COUNTIFS('data set'!$E:$E,Model!$A7,'data set'!$B:$B,Model!I$3) -> 60 | J7: =Growth_Analysis!J15 -> 69 | K7: =Growth_Analysis!K15 -> 80 | L7: =Growth_Analysis!L15 -> 91 | M7: =Growth_Analysis!M15 -> 102 | N7: =Growth_Analysis!N15 -> 112 | O7: =Growth_Analysis!O15 -> 123 | P7: =Growth_Analysis!P15 -> 134 | Q7: =Growth_Analysis!Q15 -> 145 | S7: =IFERROR(RATE(MONTH($Q$3)-MONTH($I$3),0,-I7,Q7),"N/A") -> 0.11661149 | T7: =IFERROR(RATE(MONTH($Q$3)-MONTH($K$3),0,-K7,Q7),"N/A") -> 0.10419642
A8: Contraction | B8: =COUNTIFS('data set'!$E:$E,Model!$A8,'data set'!$B:$B,Model!B$3) -> 0 | C8: =COUNTIFS('data set'!$E:$E,Model!$A8,'data set'!$B:$B,Model!C$3) -> 0 | D8: =COUNTIFS('data set'!$E:$E,Model!$A8,'data set'!$B:$B,Model!D$3) -> 2 | E8: =COUNTIFS('data set'!$E:$E,Model!$A8,'data set'!$B:$B,Model!E$3) -> 14 | F8: =COUNTIFS('data set'!$E:$E,Model!$A8,'data set'!$B:$B,Model!F$3) -> 26 | G8: =COUNTIFS('data set'!$E:$E,Model!$A8,'data set'!$B:$B,Model!G$3) -> 14 | H8: =COUNTIFS('data set'!$E:$E,Model!$A8,'data set'!$B:$B,Model!H$3) -> 34 | I8: =COUNTIFS('data set'!$E:$E,Model!$A8,'data set'!$B:$B,Model!I$3) -> 31 | J8: =Growth_Analysis!J16 -> 40 | K8: =Growth_Analysis!K16 -> 46 | L8: =Growth_Analysis!L16 -> 51 | M8: =Growth_Analysis!M16 -> 57 | N8: =Growth_Analysis!N16 -> 62 | O8: =Growth_Analysis!O16 -> 68 | P8: =Growth_Analysis!P16 -> 74 | Q8: =Growth_Analysis!Q16 -> 79 | S8: =IFERROR(RATE(MONTH($Q$3)-MONTH($I$3),0,-I8,Q8),"N/A") -> 0.12404365 | T8: =IFERROR(RATE(MONTH($Q$3)-MONTH($K$3),0,-K8,Q8),"N/A") -> 0.094321361
A9: Old Team to New Team | B9: =COUNTIFS('data set'!$E:$E,Model!$A9,'data set'!$B:$B,Model!B$3) -> 0 | C9: =COUNTIFS('data set'!$E:$E,Model!$A9,'data set'!$B:$B,Model!C$3) -> 0 | D9: =COUNTIFS('data set'!$E:$E,Model!$A9,'data set'!$B:$B,Model!D$3) -> 0 | E9: =COUNTIFS('data set'!$E:$E,Model!$A9,'data set'!$B:$B,Model!E$3) -> 1 | F9: =COUNTIFS('data set'!$E:$E,Model!$A9,'data set'!$B:$B,Model!F$3) -> 0 | G9: =COUNTIFS('data set'!$E:$E,Model!$A9,'data set'!$B:$B,Model!G$3) -> 3 | H9: =COUNTIFS('data set'!$E:$E,Model!$A9,'data set'!$B:$B,Model!H$3) -> 0 | I9: =COUNTIFS('data set'!$E:$E,Model!$A9,'data set'!$B:$B,Model!I$3) -> 1 | J9: =Inputs!B13 -> 1 | K9: =ROUND(J9*(1+K29),0) -> 1 | L9: =ROUND(K9*(1+L29),0) -> 1 | M9: =ROUND(L9*(1+M29),0) -> 1 | N9: =ROUND(M9*(1+N29),0) -> 1 | O9: =ROUND(N9*(1+O29),0) -> 1 | P9: =ROUND(O9*(1+P29),0) -> 1 | Q9: =ROUND(P9*(1+Q29),0) -> 1 | S9: =IFERROR(RATE(MONTH($Q$3)-MONTH($I$3),0,-I9,Q9),"N/A") -> 3.1899074e-12 | T9: =IFERROR(RATE(MONTH($Q$3)-MONTH($K$3),0,-K9,Q9),"N/A") -> 8.2329818e-15
A10: Churn-Failed Reactivation | B10: =COUNTIFS('data set'!$E:$E,Model!$A10,'data set'!$B:$B,Model!B$3) -> 0 | C10: =COUNTIFS('data set'!$E:$E,Model!$A10,'data set'!$B:$B,Model!C$3) -> 0 | D10: =COUNTIFS('data set'!$E:$E,Model!$A10,'data set'!$B:$B,Model!D$3) -> 0 | E10: =COUNTIFS('data set'!$E:$E,Model!$A10,'data set'!$B:$B,Model!E$3) -> 0 | F10: =COUNTIFS('data set'!$E:$E,Model!$A10,'data set'!$B:$B,Model!F$3) -> 0 | G10: =COUNTIFS('data set'!$E:$E,Model!$A10,'data set'!$B:$B,Model!G$3) -> 1 | H10: =COUNTIFS('data set'!$E:$E,Model!$A10,'data set'!$B:$B,Model!H$3) -> 1 | I10: =COUNTIFS('data set'!$E:$E,Model!$A10,'data set'!$B:$B,Model!I$3) -> 0 | J10: =ROUND(I13*J22,0) -> 5 | K10: =ROUND(J13*K22,0) -> 2 | L10: =ROUND(K13*L22,0) -> 2 | M10: =ROUND(L13*M22,0) -> 2 | N10: =ROUND(M13*N22,0) -> 2 | O10: =ROUND(N13*O22,0) -> 2 | P10: =ROUND(O13*P22,0) -> 2 | Q10: =ROUND(P13*Q22,0) -> 3 | S10: =IFERROR(RATE(MONTH($Q$3)-MONTH($I$3),0,-I10,Q10),"N/A") -> N/A | T10: =IFERROR(RATE(MONTH($Q$3)-MONTH($K$3),0,-K10,Q10),"N/A") -> 0.069913194
A11: Total Customers | B11: =SUM(B4:B10) -> 2 | C11: =SUM(C4:C10) -> 28 | D11: =SUM(D4:D10) -> 95 | E11: =SUM(E4:E10) -> 185 | F11: =SUM(F4:F10) -> 237 | G11: =SUM(G4:G10) -> 283 | H11: =SUM(H4:H10) -> 328 | I11: =SUM(I4:I10) -> 379 | ... Q11: =SUM(Q4:Q10) -> 906 | S11: =IFERROR(RATE(MONTH($Q$3)-MONTH($I$3),0,-I11,Q11),"N/A") -> 0.11509309 | T11: =IFERROR(RATE(MONTH($Q$3)-MONTH($K$3),0,-K11,Q11),"N/A") -> 0.10377803
A12: Churn | B12: =COUNTIFS('data set'!$E:$E,Model!$A12,'data set'!$B:$B,Model!B$3) -> 0 | C12: =COUNTIFS('data set'!$E:$E,Model!$A12,'data set'!$B:$B,Model!C$3) -> 1 | D12: =COUNTIFS('data set'!$E:$E,Model!$A12,'data set'!$B:$B,Model!D$3) -> 1 | E12: =COUNTIFS('data set'!$E:$E,Model!$A12,'data set'!$B:$B,Model!E$3) -> 3 | F12: =COUNTIFS('data set'!$E:$E,Model!$A12,'data set'!$B:$B,Model!F$3) -> 0 | G12: =COUNTIFS('data set'!$E:$E,Model!$A12,'data set'!$B:$B,Model!G$3) -> 3 | H12: =COUNTIFS('data set'!$E:$E,Model!$A12,'data set'!$B:$B,Model!H$3) -> 1 | I12: =COUNTIFS('data set'!$E:$E,Model!$A12,'data set'!$B:$B,Model!I$3) -> 1 | J12: =ROUND(I$15*J23,0) -> 2 | K12: =ROUND(J$15*K23,0) -> 2 | L12: =ROUND(K$15*L23,0) -> 2 | M12: =ROUND(L$15*M23,0) -> 3 | N12: =ROUND(M$15*N23,0) -> 3 | O12: =ROUND(N$15*O23,0) -> 3 | P12: =ROUND(O$15*P23,0) -> 4 | Q12: =ROUND(P$15*Q23,0) -> 4 | S12: =IFERROR(RATE(MONTH($Q$3)-MONTH($I$3),0,-I12,Q12),"N/A") -> 0.18920712 | T12: =IFERROR(RATE(MONTH($Q$3)-MONTH($K$3),0,-K12,Q12),"N/A") -> 0.12246205
A13: Churn-Failed | B13: =COUNTIFS('data set'!$E:$E,Model!$A13,'data set'!$B:$B,Model!B$3) -> 0 | C13: =COUNTIFS('data set'!$E:$E,Model!$A13,'data set'!$B:$B,Model!C$3) -> 0 | D13: =COUNTIFS('data set'!$E:$E,Model!$A13,'data set'!$B:$B,Model!D$3) -> 1 | E13: =COUNTIFS('data set'!$E:$E,Model!$A13,'data set'!$B:$B,Model!E$3) -> 0 | F13: =COUNTIFS('data set'!$E:$E,Model!$A13,'data set'!$B:$B,Model!F$3) -> 3 | G13: =COUNTIFS('data set'!$E:$E,Model!$A13,'data set'!$B:$B,Model!G$3) -> 3 | H13: =COUNTIFS('data set'!$E:$E,Model!$A13,'data set'!$B:$B,Model!H$3) -> 4 | I13: =COUNTIFS('data set'!$E:$E,Model!$A13,'data set'!$B:$B,Model!I$3) -> 6 | J13: =ROUND(I$15*J24,0) -> 2 | K13: =ROUND(J$15*K24,0) -> 2 | L13: =ROUND(K$15*L24,0) -> 2 | M13: =ROUND(L$15*M24,0) -> 3 | N13: =ROUND(M$15*N24,0) -> 3 | O13: =ROUND(N$15*O24,0) -> 3 | P13: =ROUND(O$15*P24,0) -> 4 | Q13: =ROUND(P$15*Q24,0) -> 4 | S13: =IFERROR(RATE(MONTH($Q$3)-MONTH($I$3),0,-I13,Q13),"N/A") -> -0.049420175 | T13: =IFERROR(RATE(MONTH($Q$3)-MONTH($K$3),0,-K13,Q13),"N/A") -> 0.12246205
A14: Total Churn | B14: =SUM(B12:B13) -> 0 | C14: =SUM(C12:C13) -> 1 | D14: =SUM(D12:D13) -> 2 | E14: =SUM(E12:E13) -> 3 | F14: =SUM(F12:F13) -> 3 | G14: =SUM(G12:G13) -> 6 | H14: =SUM(H12:H13) -> 5 | I14: =SUM(I12:I13) -> 7 | ... Q14: =SUM(Q12:Q13) -> 8 | S14: =IFERROR(RATE(MONTH($Q$3)-MONTH($I$3),0,-I14,Q14),"N/A") -> 0.016831504 | T14: =IFERROR(RATE(MONTH($Q$3)-MONTH($K$3),0,-K14,Q14),"N/A") -> 0.12246205
A15: Total Customers | B15: =B11-B14 -> 2 | C15: =C11-C14 -> 27 | D15: =D11-D14 -> 93 | E15: =E11-E14 -> 182 | F15: =F11-F14 -> 234 | G15: =G11-G14 -> 277 | H15: =H11-H14 -> 323 | I15: =I11-I14 -> 372 | ... Q15: =Q11-Q14 -> 898 | S15: =IFERROR(RATE(MONTH($Q$3)-MONTH($I$3),0,-I15,Q15),"N/A") -> 0.11645616 | T15: =IFERROR(RATE(MONTH($Q$3)-MONTH($K$3),0,-K15,Q15),"N/A") -> 0.10362109
A17: Inputs/Assumptions
A18: New | B18: =B4 -> 2 | C18: =C4 -> 26 | D18: =D4 -> 62 | E18: =E4 -> 85 | F18: =F4 -> 51 | G18: =G4 -> 50 | H18: =H4 -> 61 | I18: =I4 -> 64 | J18: =Inputs!B9 -> 62 | K18: =ROUND(J18*(1+K27),0) -> 64 | L18: =ROUND(K18*(1+L27),0) -> 66 | M18: =ROUND(L18*(1+M27),0) -> 68 | N18: =ROUND(M18*(1+N27),0) -> 70 | O18: =ROUND(N18*(1+O27),0) -> 72 | P18: =ROUND(O18*(1+P27),0) -> 74 | Q18: =ROUND(P18*(1+Q27),0) -> 76 | S18: =IFERROR(RATE(MONTH($Q$3)-MONTH($I$3),0,-I18,Q18),"N/A") -> 0.021713666 | T18: =IFERROR(RATE(MONTH($Q$3)-MONTH($K$3),0,-K18,Q18),"N/A") -> 0.029055827
A19: Legacy to New Team | B19: =B5 -> 0 | C19: =C5 -> 1 | D19: =D5 -> 4 | E19: =E5 -> 4 | F19: =F5 -> 5 | G19: =G5 -> 2 | H19: =H5 -> 1 | I19: =I5 -> 0 | J19: =Inputs!B10 -> 3 | K19: =ROUND(J19*(1+K28),0) -> 3 | L19: =ROUND(K19*(1+L28),0) -> 3 | M19: =ROUND(L19*(1+M28),0) -> 3 | N19: =ROUND(M19*(1+N28),0) -> 3 | O19: =ROUND(N19*(1+O28),0) -> 3 | P19: =ROUND(O19*(1+P28),0) -> 3 | Q19: =ROUND(P19*(1+Q28),0) -> 3 | S19: =IFERROR(RATE(MONTH($Q$3)-MONTH($I$3),0,-I19,Q19),"N/A") -> N/A | T19: =IFERROR(RATE(MONTH($Q$3)-MONTH($K$3),0,-K19,Q19),"N/A") -> 8.3526939e-15
A20: Old Team to New Team | B20: =B9 -> 0 | C20: =C9 -> 0 | D20: =D9 -> 0 | E20: =E9 -> 1 | F20: =F9 -> 0 | G20: =G9 -> 3 | H20: =H9 -> 0 | I20: =I9 -> 1 | J20: =Inputs!B13 -> 1 | K20: =ROUND(J20*(1+K29),0) -> 1 | L20: =ROUND(K20*(1+L29),0) -> 1 | M20: =ROUND(L20*(1+M29),0) -> 1 | N20: =ROUND(M20*(1+N29),0) -> 1 | O20: =ROUND(N20*(1+O29),0) -> 1 | P20: =ROUND(O20*(1+P29),0) -> 1 | Q20: =ROUND(P20*(1+Q29),0) -> 1 | S20: =IFERROR(RATE(MONTH($Q$3)-MONTH($I$3),0,-I20,Q20),"N/A") -> 3.1899074e-12 | T20: =IFERROR(RATE(MONTH($Q$3)-MONTH($K$3),0,-K20,Q20),"N/A") -> 8.2329818e-15
A21: Churn % Assumptions
A22: Churn - Failed Reactiviation % of Churn Failed | C22: =IFERROR(C10/B13,"N/A") -> N/A | D22: =IFERROR(D10/C13,"N/A") -> N/A | E22: =IFERROR(E10/D13,"N/A") -> 0 | F22: =IFERROR(F10/E13,"N/A") -> N/A | G22: =IFERROR(G10/F13,"N/A") -> 0.33333333 | H22: =IFERROR(H10/G13,"N/A") -> 0.33333333 | I22: =IFERROR(I10/H13,"N/A") -> 0 | J22: =Inputs!B14 -> 0.75 | K22: =J22 -> 0.75 | L22: =K22 -> 0.75 | M22: =L22 -> 0.75 | N22: =M22 -> 0.75 | O22: =N22 -> 0.75 | P22: =O22 -> 0.75 | Q22: =P22 -> 0.75 | S22: =IFERROR(RATE(MONTH($Q$3)-MONTH($I$3),0,-I22,Q22),"N/A") -> N/A | T22: =IFERROR(RATE(MONTH($Q$3)-MONTH($K$3),0,-K22,Q22),"N/A") -> 8.3526939e-15
A23: Churn | C23: =C12/B15 -> 0.5 | D23: =D12/C15 -> 0.037037037 | E23: =E12/D15 -> 0.032258065 | F23: =F12/E15 -> 0 | G23: =G12/F15 -> 0.012820513 | H23: =H12/G15 -> 0.0036101083 | I23: =I12/H15 -> 0.0030959752 | J23: =Inputs!B15 -> 0.0048816491 | K23: =J23 -> 0.0048816491 | L23: =K23 -> 0.0048816491 | M23: =L23 -> 0.0048816491 | N23: =M23 -> 0.0048816491 | O23: =N23 -> 0.0048816491 | P23: =O23 -> 0.0048816491 | Q23: =P23 -> 0.0048816491 | S23: =IFERROR(RATE(MONTH($Q$3)-MONTH($I$3),0,-I23,Q23),"N/A") -> 0.058573786 | T23: =IFERROR(RATE(MONTH($Q$3)-MONTH($K$3),0,-K23,Q23),"N/A") -> 8.2611401e-15
A24: Churn-Failed | C24: =C13/B15 -> 0 | D24: =D13/C15 -> 0.037037037 | E24: =E13/D15 -> 0 | F24: =F13/E15 -> 0.016483516 | G24: =G13/F15 -> 0.012820513 | H24: =H13/G15 -> 0.014440433 | I24: =I13/H15 -> 0.018575851 | J24: =Inputs!B16 -> 0.005 | K24: =J24 -> 0.005 | L24: =K24 -> 0.005 | M24: =L24 -> 0.005 | N24: =M24 -> 0.005 | O24: =N24 -> 0.005 | P24: =O24 -> 0.005 | Q24: =P24 -> 0.005 | S24: =IFERROR(RATE(MONTH($Q$3)-MONTH($I$3),0,-I24,Q24),"N/A") -> -0.15130301 | T24: =IFERROR(RATE(MONTH($Q$3)-MONTH($K$3),0,-K24,Q24),"N/A") -> 8.323296e-15
S25: =IFERROR(RATE(MONTH($Q$3)-MONTH($I$3),0,-I25,Q25),"N/A") -> N/A | T25: =IFERROR(RATE(MONTH($Q$3)-MONTH($K$3),0,-K25,Q25),"N/A") -> N/A
A26: Growth % by Customer base | S26: =IFERROR(RATE(MONTH($Q$3)-MONTH($I$3),0,-I26,Q26),"N/A") -> N/A | T26: =IFERROR(RATE(MONTH($Q$3)-MONTH($K$3),0,-K26,Q26),"N/A") -> N/A
A27: New | C27: =IFERROR((C4-B4)/B4,"N/A") -> 12 | D27: =IFERROR((D4-C4)/C4,"N/A") -> 1.3846154 | E27: =IFERROR((E4-D4)/D4,"N/A") -> 0.37096774 | F27: =IFERROR((F4-E4)/E4,"N/A") -> -0.4 | G27: =IFERROR((G4-F4)/F4,"N/A") -> -0.019607843 | H27: =IFERROR((H4-G4)/G4,"N/A") -> 0.22 | I27: =IFERROR((I4-H4)/H4,"N/A") -> 0.049180328 | J27: =Inputs!B19 -> 0.03 | K27: =J27 -> 0.03 | L27: =K27 -> 0.03 | M27: =L27 -> 0.03 | N27: =M27 -> 0.03 | O27: =N27 -> 0.03 | P27: =O27 -> 0.03 | Q27: =P27 -> 0.03 | S27: =IFERROR(RATE(MONTH($Q$3)-MONTH($I$3),0,-I27,Q27),"N/A") -> -0.059916935 | T27: =IFERROR(RATE(MONTH($Q$3)-MONTH($K$3),0,-K27,Q27),"N/A") -> 8.2402099e-15
A28: Legacy to New Team | C28: =IFERROR((C5-B5)/B5,"N/A") -> N/A | D28: =IFERROR((D5-C5)/C5,"N/A") -> 3 | E28: =IFERROR((E5-D5)/D5,"N/A") -> 0 | F28: =IFERROR((F5-E5)/E5,"N/A") -> 0.25 | G28: =IFERROR((G5-F5)/F5,"N/A") -> -0.6 | H28: =IFERROR((H5-G5)/G5,"N/A") -> -0.5 | I28: =IFERROR((I5-H5)/H5,"N/A") -> -1 | J28: =Inputs!B20 -> 0 | K28: =J28 -> 0 | L28: =K28 -> 0 | M28: =L28 -> 0 | N28: =M28 -> 0 | O28: =N28 -> 0 | P28: =O28 -> 0 | Q28: =P28 -> 0 | S28: =IFERROR(RATE(MONTH($Q$3)-MONTH($I$3),0,-I28,Q28),"N/A") -> -0.999999 | T28: =IFERROR(RATE(MONTH($Q$3)-MONTH($K$3),0,-K28,Q28),"N/A") -> N/A
A29: Old Team to New Team | C29: =IFERROR((C9-B9)/B9,"N/A") -> N/A | D29: =IFERROR((D9-C9)/C9,"N/A") -> N/A | E29: =IFERROR((E9-D9)/D9,"N/A") -> N/A | F29: =IFERROR((F9-E9)/E9,"N/A") -> -1 | G29: =IFERROR((G9-F9)/F9,"N/A") -> N/A | H29: =IFERROR((H9-G9)/G9,"N/A") -> -1 | I29: =IFERROR((I9-H9)/H9,"N/A") -> N/A | J29: =Inputs!B21 -> 0 | K29: =J29 -> 0 | L29: =K29 -> 0 | M29: =L29 -> 0 | N29: =M29 -> 0 | O29: =N29 -> 0 | P29: =O29 -> 0 | Q29: =P29 -> 0 | S29: =IFERROR(RATE(MONTH($Q$3)-MONTH($I$3),0,-I29,Q29),"N/A") -> N/A | T29: =IFERROR(RATE(MONTH($Q$3)-MONTH($K$3),0,-K29,Q29),"N/A") -> N/A
A32: Metrics vs. Prior Period unless stated otherwise
A33: Overall Customer growth | C33: =(C15-B15)/B15 -> 12.5 | D33: =(D15-C15)/C15 -> 2.4444444 | E33: =(E15-D15)/D15 -> 0.95698925 | F33: =(F15-E15)/E15 -> 0.28571429 | G33: =(G15-F15)/F15 -> 0.18376068 | H33: =(H15-G15)/G15 -> 0.16606498 | I33: =(I15-H15)/H15 -> 0.15170279 | J33: =(J15-I15)/I15 -> 0.16935484 | ... Q33: =(Q15-P15)/P15 -> 0.085852479 | S33: =IFERROR(RATE(MONTH($Q$3)-MONTH($I$3),0,-I33,Q33),"N/A") -> -0.068688619 | T33: =IFERROR(RATE(MONTH($Q$3)-MONTH($K$3),0,-K33,Q33),"N/A") -> -0.081015046
A34: New Customer growth | C34: =(C4-B4)/B4 -> 12 | D34: =(D4-C4)/C4 -> 1.3846154 | E34: =(E4-D4)/D4 -> 0.37096774 | F34: =(F4-E4)/E4 -> -0.4 | G34: =(G4-F4)/F4 -> -0.019607843 | H34: =(H4-G4)/G4 -> 0.22 | I34: =(I4-H4)/H4 -> 0.049180328 | J34: =(J4-I4)/I4 -> -0.03125 | ... Q34: =(Q4-P4)/P4 -> 0.027027027 | S34: =IFERROR(RATE(MONTH($Q$3)-MONTH($I$3),0,-I34,Q34),"N/A") -> -0.072100679 | T34: =IFERROR(RATE(MONTH($Q$3)-MONTH($K$3),0,-K34,Q34),"N/A") -> -0.029057909
A35: Cumulative Customer Churn (2018) | F35: =F12 -> 0 | G35: =F35+G12 -> 3 | H35: =G35+H12 -> 4 | I35: =H35+I12 -> 5 | J35: =I35+J12 -> 7 | K35: =J35+K12 -> 9 | L35: =K35+L12 -> 11 | M35: =L35+M12 -> 14 | N35: =M35+N12 -> 17 | ... Q35: =P35+Q12 -> 28
A36: % New (# of New Customers/ Total # of Customers) | B36: =B4/B$15 -> 1 | C36: =C4/C$15 -> 0.96296296 | D36: =D4/D$15 -> 0.66666667 | E36: =E4/E$15 -> 0.46703297 | F36: =F4/F$15 -> 0.21794872 | G36: =G4/G$15 -> 0.18050542 | H36: =H4/H$15 -> 0.18885449 | I36: =I4/I$15 -> 0.17204301 | ... Q36: =Q4/Q$15 -> 0.084632517 | S36: =IFERROR(RATE(MONTH($Q$3)-MONTH($I$3),0,-I36,Q36),"N/A") -> -0.084860023 | T36: =IFERROR(RATE(MONTH($Q$3)-MONTH($K$3),0,-K36,Q36),"N/A") -> -0.067564188
A37: % Legacy to New Team | C37: =C5/B$15 -> 0.5 | D37: =D5/C$15 -> 0.14814815 | E37: =E5/D$15 -> 0.043010753 | F37: =F5/E$15 -> 0.027472527 | G37: =G5/F$15 -> 0.0085470085 | H37: =H5/G$15 -> 0.0036101083 | I37: =I5/H$15 -> 0 | J37: =J5/I$15 -> 0.0080645161 | ... Q37: =Q5/P$15 -> 0.0036275695 | S37: =IFERROR(RATE(MONTH($Q$3)-MONTH($I$3),0,-I37,Q37),"N/A") -> N/A | T37: =IFERROR(RATE(MONTH($Q$3)-MONTH($K$3),0,-K37,Q37),"N/A") -> -0.10154301
A38: % Customers that remained same | C38: =C6/B$15 -> 0.5 | D38: =D6/C$15 -> 0.81481481 | E38: =E6/D$15 -> 0.72043011 | F38: =F6/E$15 -> 0.71978022 | G38: =G6/F$15 -> 0.72222222 | H38: =H6/G$15 -> 0.68592058 | I38: =I6/H$15 -> 0.69040248 | J38: =J6/I$15 -> 0.69623656 | ... Q38: =Q6/P$15 -> 0.72430472 | S38: =IFERROR(RATE(MONTH($Q$3)-MONTH($I$3),0,-I38,Q38),"N/A") -> 0.0060101709 | T38: =IFERROR(RATE(MONTH($Q$3)-MONTH($K$3),0,-K38,Q38),"N/A") -> 0.0054298816
A39: % Customers that Expand | C39: =C7/B$15 -> 0 | D39: =D7/C$15 -> 0.18518519 | E39: =E7/D$15 -> 0.15053763 | F39: =F7/E$15 -> 0.13186813 | G39: =G7/F$15 -> 0.18803419 | H39: =H7/G$15 -> 0.14801444 | I39: =I7/H$15 -> 0.18575851 | J39: =J7/I$15 -> 0.18548387 | ... Q39: =Q7/P$15 -> 0.17533253 | S39: =IFERROR(RATE(MONTH($Q$3)-MONTH($I$3),0,-I39,Q39),"N/A") -> -0.0071943945 | T39: =IFERROR(RATE(MONTH($Q$3)-MONTH($K$3),0,-K39,Q39),"N/A") -> -0.0079270069
A40: % Customers that Contracted | C40: =C8/B$15 -> 0 | D40: =D8/C$15 -> 0.074074074 | E40: =E8/D$15 -> 0.15053763 | F40: =F8/E$15 -> 0.14285714 | G40: =G8/F$15 -> 0.05982906 | H40: =H8/G$15 -> 0.12274368 | I40: =I8/H$15 -> 0.095975232 | J40: =J8/I$15 -> 0.10752688 | ... Q40: =Q8/P$15 -> 0.095525998 | S40: =IFERROR(RATE(MONTH($Q$3)-MONTH($I$3),0,-I40,Q40),"N/A") -> -0.00058629354 | T40: =IFERROR(RATE(MONTH($Q$3)-MONTH($K$3),0,-K40,Q40),"N/A") -> -0.016799325
A41: % Old Team to New Team | C41: =C9/B$15 -> 0 | D41: =D9/C$15 -> 0 | E41: =E9/D$15 -> 0.010752688 | F41: =F9/E$15 -> 0 | G41: =G9/F$15 -> 0.012820513 | H41: =H9/G$15 -> 0 | I41: =I9/H$15 -> 0.0030959752 | J41: =J9/I$15 -> 0.002688172 | ... Q41: =Q9/P$15 -> 0.0012091898 | S41: =IFERROR(RATE(MONTH($Q$3)-MONTH($I$3),0,-I41,Q41),"N/A") -> -0.11087642 | T41: =IFERROR(RATE(MONTH($Q$3)-MONTH($K$3),0,-K41,Q41),"N/A") -> -0.10154301
A42: % Failed Churn - Reactivition | C42: =C10/B$15 -> 0 | D42: =D10/C$15 -> 0 | E42: =E10/D$15 -> 0 | F42: =F10/E$15 -> 0 | G42: =G10/F$15 -> 0.0042735043 | H42: =H10/G$15 -> 0.0036101083 | I42: =I10/H$15 -> 0 | J42: =J10/I$15 -> 0.01344086 | ... Q42: =Q10/P$15 -> 0.0036275695 | S42: =IFERROR(RATE(MONTH($Q$3)-MONTH($I$3),0,-I42,Q42),"N/A") -> N/A | T42: =IFERROR(RATE(MONTH($Q$3)-MONTH($K$3),0,-K42,Q42),"N/A") -> -0.038729014
A43: % Churn | C43: =C12/B$15 -> 0.5 | D43: =D12/C$15 -> 0.037037037 | E43: =E12/D$15 -> 0.032258065 | F43: =F12/E$15 -> 0 | G43: =G12/F$15 -> 0.012820513 | H43: =H12/G$15 -> 0.0036101083 | I43: =I12/H$15 -> 0.0030959752 | J43: =J12/I$15 -> 0.0053763441 | ... Q43: =Q12/P$15 -> 0.0048367594 | S43: =IFERROR(RATE(MONTH($Q$3)-MONTH($I$3),0,-I43,Q43),"N/A") -> 0.057352084 | T43: =IFERROR(RATE(MONTH($Q$3)-MONTH($K$3),0,-K43,Q43),"N/A") -> 0.0084838719
A44: % Churn -Failed | C44: =C13/B$15 -> 0 | D44: =D13/C$15 -> 0.037037037 | E44: =E13/D$15 -> 0 | F44: =F13/E$15 -> 0.016483516 | G44: =G13/F$15 -> 0.012820513 | H44: =H13/G$15 -> 0.014440433 | I44: =I13/H$15 -> 0.018575851 | J44: =J13/I$15 -> 0.0053763441 | ... Q44: =Q13/P$15 -> 0.0048367594 | S44: =IFERROR(RATE(MONTH($Q$3)-MONTH($I$3),0,-I44,Q44),"N/A") -> -0.15481707 | T44: =IFERROR(RATE(MONTH($Q$3)-MONTH($K$3),0,-K44,Q44),"N/A") -> 0.0084838719
A45: % Total Churn | C45: =C14/B$15 -> 0.5 | D45: =D14/C$15 -> 0.074074074 | E45: =E14/D$15 -> 0.032258065 | F45: =F14/E$15 -> 0.016483516 | G45: =G14/F$15 -> 0.025641026 | H45: =H14/G$15 -> 0.018050542 | I45: =I14/H$15 -> 0.021671827 | J45: =J14/I$15 -> 0.010752688 | ... Q45: =Q14/P$15 -> 0.0096735187 | S45: =IFERROR(RATE(MONTH($Q$3)-MONTH($I$3),0,-I45,Q45),"N/A") -> -0.095911136 | T45: =IFERROR(RATE(MONTH($Q$3)-MONTH($K$3),0,-K45,Q45),"N/A") -> 0.0084838719
A46: Net Expansion | C46: =C7-C8 -> 0 | D46: =D7-D8 -> 3 | E46: =E7-E8 -> 0 | F46: =F7-F8 -> -2 | G46: =G7-G8 -> 30 | H46: =H7-H8 -> 7 | I46: =I7-I8 -> 29 | J46: =J7-J8 -> 29 | ... Q46: =Q7-Q8 -> 66 | S46: =IFERROR(RATE(MONTH($Q$3)-MONTH($I$3),0,-I46,Q46),"N/A") -> 0.10826404 | T46: =IFERROR(RATE(MONTH($Q$3)-MONTH($K$3),0,-K46,Q46),"N/A") -> 0.11689112
A47: Net Expansion % of Customer Base | C47: =C46/B15 -> 0 | D47: =D46/C15 -> 0.11111111 | E47: =E46/D15 -> 0 | F47: =F46/E15 -> -0.010989011 | G47: =G46/F15 -> 0.12820513 | H47: =H46/G15 -> 0.025270758 | I47: =I46/H15 -> 0.089783282 | J47: =J46/I15 -> 0.077956989 | ... Q47: =Q46/P15 -> 0.07980653 | S47: =IFERROR(RATE(MONTH($Q$3)-MONTH($I$3),0,-I47,Q47),"N/A") -> -0.014616312 | T47: =IFERROR(RATE(MONTH($Q$3)-MONTH($K$3),0,-K47,Q47),"N/A") -> 0.0034786287
A48: Net Expansion Growth (MoM) | C48: =IFERROR((C46-B46)/ABS(B46),"N/A") -> N/A | D48: =IFERROR((D46-C46)/ABS(C46),"N/A") -> N/A | E48: =IFERROR((E46-D46)/ABS(D46),"N/A") -> -1 | F48: =IFERROR((F46-E46)/ABS(E46),"N/A") -> N/A | G48: =IFERROR((G46-F46)/ABS(F46),"N/A") -> 16 | H48: =IFERROR((H46-G46)/ABS(G46),"N/A") -> -0.76666667 | I48: =IFERROR((I46-H46)/ABS(H46),"N/A") -> 3.1428571 | J48: =IFERROR((J46-I46)/ABS(I46),"N/A") -> 0 | ... Q48: =IFERROR((Q46-P46)/ABS(P46),"N/A") -> 0.1 | S48: =IFERROR(RATE(MONTH($Q$3)-MONTH($I$3),0,-I48,Q48),"N/A") -> -0.35011813 | T48: =IFERROR(RATE(MONTH($Q$3)-MONTH($K$3),0,-K48,Q48),"N/A") -> -0.086788583
A49: % of Churn - Failed that are reactivated | C49: =IFERROR(C10/B13,"N/A") -> N/A | D49: =IFERROR(D10/C13,"N/A") -> N/A | E49: =IFERROR(E10/D13,"N/A") -> 0 | F49: =IFERROR(F10/E13,"N/A") -> N/A | G49: =IFERROR(G10/F13,"N/A") -> 0.33333333 | H49: =IFERROR(H10/G13,"N/A") -> 0.33333333 | I49: =IFERROR(I10/H13,"N/A") -> 0 | J49: =IFERROR(J10/I13,"N/A") -> 0.83333333 | ... Q49: =IFERROR(Q10/P13,"N/A") -> 0.75 | S49: =IFERROR(RATE(MONTH($Q$3)-MONTH($I$3),0,-I49,Q49),"N/A") -> N/A | T49: =IFERROR(RATE(MONTH($Q$3)-MONTH($K$3),0,-K49,Q49),"N/A") -> -0.046815707
A50: Expanded/Contracted Ratio | B50: =IFERROR(B7/B8, "N/A") -> N/A | C50: =IFERROR(C7/C8, "N/A") -> N/A | D50: =IFERROR(D7/D8, "N/A") -> 2.5 | E50: =IFERROR(E7/E8, "N/A") -> 1 | F50: =IFERROR(F7/F8, "N/A") -> 0.92307692 | G50: =IFERROR(G7/G8, "N/A") -> 3.1428571 | H50: =IFERROR(H7/H8, "N/A") -> 1.2058824 | I50: =IFERROR(I7/I8, "N/A") -> 1.9354839 | ... Q50: =IFERROR(Q7/Q8, "N/A") -> 1.835443 | S50: =IFERROR(RATE(MONTH($Q$3)-MONTH($I$3),0,-I50,Q50),"N/A") -> -0.0066119775 | T50: =IFERROR(RATE(MONTH($Q$3)-MONTH($K$3),0,-K50,Q50),"N/A") -> 0.0090239142
A53: Revenue - Starting ARR
A54: New | B54: =SUMIFS('data set'!$C:$C,'data set'!$E:$E,Model!$A54,'data set'!$B:$B,Model!B$3) -> 0 | C54: =SUMIFS('data set'!$C:$C,'data set'!$E:$E,Model!$A54,'data set'!$B:$B,Model!C$3) -> 0 | D54: =SUMIFS('data set'!$C:$C,'data set'!$E:$E,Model!$A54,'data set'!$B:$B,Model!D$3) -> 0 | E54: =SUMIFS('data set'!$C:$C,'data set'!$E:$E,Model!$A54,'data set'!$B:$B,Model!E$3) -> 0 | F54: =SUMIFS('data set'!$C:$C,'data set'!$E:$E,Model!$A54,'data set'!$B:$B,Model!F$3) -> 0 | G54: =SUMIFS('data set'!$C:$C,'data set'!$E:$E,Model!$A54,'data set'!$B:$B,Model!G$3) -> 0 | H54: =SUMIFS('data set'!$C:$C,'data set'!$E:$E,Model!$A54,'data set'!$B:$B,Model!H$3) -> 0 | I54: =SUMIFS('data set'!$C:$C,'data set'!$E:$E,Model!$A54,'data set'!$B:$B,Model!I$3) -> 0 | J54: =J90*I$87 -> 0 | K54: =K90*J$87 -> 0 | L54: =L90*K$87 -> 0 | M54: =M90*L$87 -> 0 | N54: =N90*M$87 -> 0 | O54: =O90*N$87 -> 0 | P54: =P90*O$87 -> 0 | Q54: =Q90*P$87 -> 0 | S54: =IFERROR(RATE(MONTH($Q$3)-MONTH($I$3),0,-I54,Q54),"N/A") -> N/A | T54: =IFERROR(RATE(MONTH($Q$3)-MONTH($K$3),0,-K54,Q54),"N/A") -> N/A
A55: Legacy to New Team | B55: =SUMIFS('data set'!$C:$C,'data set'!$E:$E,Model!$A55,'data set'!$B:$B,Model!B$3) -> 0 | C55: =SUMIFS('data set'!$C:$C,'data set'!$E:$E,Model!$A55,'data set'!$B:$B,Model!C$3) -> 0 | D55: =SUMIFS('data set'!$C:$C,'data set'!$E:$E,Model!$A55,'data set'!$B:$B,Model!D$3) -> 0 | E55: =SUMIFS('data set'!$C:$C,'data set'!$E:$E,Model!$A55,'data set'!$B:$B,Model!E$3) -> 0 | F55: =SUMIFS('data set'!$C:$C,'data set'!$E:$E,Model!$A55,'data set'!$B:$B,Model!F$3) -> 0 | G55: =SUMIFS('data set'!$C:$C,'data set'!$E:$E,Model!$A55,'data set'!$B:$B,Model!G$3) -> 0 | H55: =SUMIFS('data set'!$C:$C,'data set'!$E:$E,Model!$A55,'data set'!$B:$B,Model!H$3) -> 0 | I55: =SUMIFS('data set'!$C:$C,'data set'!$E:$E,Model!$A55,'data set'!$B:$B,Model!I$3) -> 0 | J55: =J91*I$87 -> 0 | K55: =K91*J$87 -> 0 | L55: =L91*K$87 -> 0 | M55: =M91*L$87 -> 0 | N55: =N91*M$87 -> 0 | O55: =O91*N$87 -> 0 | P55: =P91*O$87 -> 0 | Q55: =Q91*P$87 -> 0 | S55: =IFERROR(RATE(MONTH($Q$3)-MONTH($I$3),0,-I55,Q55),"N/A") -> N/A | T55: =IFERROR(RATE(MONTH($Q$3)-MONTH($K$3),0,-K55,Q55),"N/A") -> N/A
A56: No Change | B56: =SUMIFS('data set'!$C:$C,'data set'!$E:$E,Model!$A56,'data set'!$B:$B,Model!B$3) -> 0 | C56: =SUMIFS('data set'!$C:$C,'data set'!$E:$E,Model!$A56,'data set'!$B:$B,Model!C$3) -> 1200 | D56: =SUMIFS('data set'!$C:$C,'data set'!$E:$E,Model!$A56,'data set'!$B:$B,Model!D$3) -> 29520 | E56: =SUMIFS('data set'!$C:$C,'data set'!$E:$E,Model!$A56,'data set'!$B:$B,Model!E$3) -> 94128 | F56: =SUMIFS('data set'!$C:$C,'data set'!$E:$E,Model!$A56,'data set'!$B:$B,Model!F$3) -> 187908 | G56: =SUMIFS('data set'!$C:$C,'data set'!$E:$E,Model!$A56,'data set'!$B:$B,Model!G$3) -> 241536 | H56: =SUMIFS('data set'!$C:$C,'data set'!$E:$E,Model!$A56,'data set'!$B:$B,Model!H$3) -> 277992 | I56: =SUMIFS('data set'!$C:$C,'data set'!$E:$E,Model!$A56,'data set'!$B:$B,Model!I$3) -> 332340 | J56: =J92*I$87 -> 412912.49 | K56: =K92*J$87 -> 475889.9 | L56: =L92*K$87 -> 538172.52 | M56: =M92*L$87 -> 603366.03 | N56: =N92*M$87 -> 670223.58 | O56: =O92*N$87 -> 738896.85 | P56: =P92*O$87 -> 809062.62 | Q56: =Q92*P$87 -> 880647.32 | S56: =IFERROR(RATE(MONTH($Q$3)-MONTH($I$3),0,-I56,Q56),"N/A") -> 0.12954211 | T56: =IFERROR(RATE(MONTH($Q$3)-MONTH($K$3),0,-K56,Q56),"N/A") -> 0.10802422
A57: Expansion | B57: =SUMIFS('data set'!$C:$C,'data set'!$E:$E,Model!$A57,'data set'!$B:$B,Model!B$3) -> 0 | C57: =SUMIFS('data set'!$C:$C,'data set'!$E:$E,Model!$A57,'data set'!$B:$B,Model!C$3) -> 0 | D57: =SUMIFS('data set'!$C:$C,'data set'!$E:$E,Model!$A57,'data set'!$B:$B,Model!D$3) -> 25668 | E57: =SUMIFS('data set'!$C:$C,'data set'!$E:$E,Model!$A57,'data set'!$B:$B,Model!E$3) -> 86640 | F57: =SUMIFS('data set'!$C:$C,'data set'!$E:$E,Model!$A57,'data set'!$B:$B,Model!F$3) -> 151416 | G57: =SUMIFS('data set'!$C:$C,'data set'!$E:$E,Model!$A57,'data set'!$B:$B,Model!G$3) -> 224292 | H57: =SUMIFS('data set'!$C:$C,'data set'!$E:$E,Model!$A57,'data set'!$B:$B,Model!H$3) -> 184872 | I57: =SUMIFS('data set'!$C:$C,'data set'!$E:$E,Model!$A57,'data set'!$B:$B,Model!I$3) -> 301727 | J57: =J93*I$87 -> 374877.68 | K57: =K93*J$87 -> 432054.02 | L57: =L93*K$87 -> 488599.56 | M57: =M93*L$87 -> 547787.87 | N57: =N93*M$87 -> 608486.94 | O57: =O93*N$87 -> 670834.47 | P57: =P93*O$87 -> 734537.03 | Q57: =Q93*P$87 -> 799527.82 | S57: =IFERROR(RATE(MONTH($Q$3)-MONTH($I$3),0,-I57,Q57),"N/A") -> 0.12954211 | T57: =IFERROR(RATE(MONTH($Q$3)-MONTH($K$3),0,-K57,Q57),"N/A") -> 0.10802422
A58: Contraction | B58: =SUMIFS('data set'!$C:$C,'data set'!$E:$E,Model!$A58,'data set'!$B:$B,Model!B$3) -> 0 | C58: =SUMIFS('data set'!$C:$C,'data set'!$E:$E,Model!$A58,'data set'!$B:$B,Model!C$3) -> 0 | D58: =SUMIFS('data set'!$C:$C,'data set'!$E:$E,Model!$A58,'data set'!$B:$B,Model!D$3) -> 31236 | E58: =SUMIFS('data set'!$C:$C,'data set'!$E:$E,Model!$A58,'data set'!$B:$B,Model!E$3) -> 245712 | F58: =SUMIFS('data set'!$C:$C,'data set'!$E:$E,Model!$A58,'data set'!$B:$B,Model!F$3) -> 227472 | G58: =SUMIFS('data set'!$C:$C,'data set'!$E:$E,Model!$A58,'data set'!$B:$B,Model!G$3) -> 119220 | H58: =SUMIFS('data set'!$C:$C,'data set'!$E:$E,Model!$A58,'data set'!$B:$B,Model!H$3) -> 223116 | I58: =SUMIFS('data set'!$C:$C,'data set'!$E:$E,Model!$A58,'data set'!$B:$B,Model!I$3) -> 167832 | J58: =J94*I$87 -> 208521.18 | K58: =K94*J$87 -> 240324.83 | L58: =L94*K$87 -> 271777.61 | M58: =M94*L$87 -> 304700.39 | N58: =N94*M$87 -> 338463.51 | O58: =O94*N$87 -> 373143.58 | P58: =P94*O$87 -> 408577.35 | Q58: =Q94*P$87 -> 444727.69 | S58: =IFERROR(RATE(MONTH($Q$3)-MONTH($I$3),0,-I58,Q58),"N/A") -> 0.12954211 | T58: =IFERROR(RATE(MONTH($Q$3)-MONTH($K$3),0,-K58,Q58),"N/A") -> 0.10802422
A59: Old Team to New Team | B59: =SUMIFS('data set'!$C:$C,'data set'!$E:$E,Model!$A59,'data set'!$B:$B,Model!B$3) -> 0 | C59: =SUMIFS('data set'!$C:$C,'data set'!$E:$E,Model!$A59,'data set'!$B:$B,Model!C$3) -> 0 | D59: =SUMIFS('data set'!$C:$C,'data set'!$E:$E,Model!$A59,'data set'!$B:$B,Model!D$3) -> 0 | E59: =SUMIFS('data set'!$C:$C,'data set'!$E:$E,Model!$A59,'data set'!$B:$B,Model!E$3) -> 0 | F59: =SUMIFS('data set'!$C:$C,'data set'!$E:$E,Model!$A59,'data set'!$B:$B,Model!F$3) -> 0 | G59: =SUMIFS('data set'!$C:$C,'data set'!$E:$E,Model!$A59,'data set'!$B:$B,Model!G$3) -> 0 | H59: =SUMIFS('data set'!$C:$C,'data set'!$E:$E,Model!$A59,'data set'!$B:$B,Model!H$3) -> 0 | I59: =SUMIFS('data set'!$C:$C,'data set'!$E:$E,Model!$A59,'data set'!$B:$B,Model!I$3) -> 0 | J59: =J95*I$87 -> 0 | K59: =K95*J$87 -> 0 | L59: =L95*K$87 -> 0 | M59: =M95*L$87 -> 0 | N59: =N95*M$87 -> 0 | O59: =O95*N$87 -> 0 | P59: =P95*O$87 -> 0 | Q59: =Q95*P$87 -> 0 | S59: =IFERROR(RATE(MONTH($Q$3)-MONTH($I$3),0,-I59,Q59),"N/A") -> N/A | T59: =IFERROR(RATE(MONTH($Q$3)-MONTH($K$3),0,-K59,Q59),"N/A") -> N/A
A60: Churn-Failed Reactivation | B60: =SUMIFS('data set'!$C:$C,'data set'!$E:$E,Model!$A60,'data set'!$B:$B,Model!B$3) -> 0 | C60: =SUMIFS('data set'!$C:$C,'data set'!$E:$E,Model!$A60,'data set'!$B:$B,Model!C$3) -> 0 | D60: =SUMIFS('data set'!$C:$C,'data set'!$E:$E,Model!$A60,'data set'!$B:$B,Model!D$3) -> 0 | E60: =SUMIFS('data set'!$C:$C,'data set'!$E:$E,Model!$A60,'data set'!$B:$B,Model!E$3) -> 0 | F60: =SUMIFS('data set'!$C:$C,'data set'!$E:$E,Model!$A60,'data set'!$B:$B,Model!F$3) -> 0 | G60: =SUMIFS('data set'!$C:$C,'data set'!$E:$E,Model!$A60,'data set'!$B:$B,Model!G$3) -> 0 | H60: =SUMIFS('data set'!$C:$C,'data set'!$E:$E,Model!$A60,'data set'!$B:$B,Model!H$3) -> 0 | I60: =SUMIFS('data set'!$C:$C,'data set'!$E:$E,Model!$A60,'data set'!$B:$B,Model!I$3) -> 0 | J60: =J96*I$87 -> 0 | K60: =K96*J$87 -> 0 | L60: =L96*K$87 -> 0 | M60: =M96*L$87 -> 0 | N60: =N96*M$87 -> 0 | O60: =O96*N$87 -> 0 | P60: =P96*O$87 -> 0 | Q60: =Q96*P$87 -> 0 | S60: =IFERROR(RATE(MONTH($Q$3)-MONTH($I$3),0,-I60,Q60),"N/A") -> N/A | T60: =IFERROR(RATE(MONTH($Q$3)-MONTH($K$3),0,-K60,Q60),"N/A") -> N/A
A61: Churn | B61: =SUMIFS('data set'!$C:$C,'data set'!$E:$E,Model!$A61,'data set'!$B:$B,Model!B$3) -> 0 | C61: =SUMIFS('data set'!$C:$C,'data set'!$E:$E,Model!$A61,'data set'!$B:$B,Model!C$3) -> 9804 | D61: =SUMIFS('data set'!$C:$C,'data set'!$E:$E,Model!$A61,'data set'!$B:$B,Model!D$3) -> 1728 | E61: =SUMIFS('data set'!$C:$C,'data set'!$E:$E,Model!$A61,'data set'!$B:$B,Model!E$3) -> 14712 | F61: =SUMIFS('data set'!$C:$C,'data set'!$E:$E,Model!$A61,'data set'!$B:$B,Model!F$3) -> 0 | G61: =SUMIFS('data set'!$C:$C,'data set'!$E:$E,Model!$A61,'data set'!$B:$B,Model!G$3) -> 4752 | H61: =SUMIFS('data set'!$C:$C,'data set'!$E:$E,Model!$A61,'data set'!$B:$B,Model!H$3) -> 1440 | I61: =SUMIFS('data set'!$C:$C,'data set'!$E:$E,Model!$A61,'data set'!$B:$B,Model!I$3) -> 13584 | J61: =J12*J108 -> 11072 | K61: =K12*K108 -> 11072 | L61: =L12*L108 -> 11072 | M61: =M12*M108 -> 16608 | N61: =N12*N108 -> 16608 | O61: =O12*O108 -> 16608 | P61: =P12*P108 -> 22144 | Q61: =Q12*Q108 -> 22144 | S61: =IFERROR(RATE(MONTH($Q$3)-MONTH($I$3),0,-I61,Q61),"N/A") -> 0.062988461 | T61: =IFERROR(RATE(MONTH($Q$3)-MONTH($K$3),0,-K61,Q61),"N/A") -> 0.12246205
A62: Churn-Failed | B62: =SUMIFS('data set'!$C:$C,'data set'!$E:$E,Model!$A62,'data set'!$B:$B,Model!B$3) -> 0 | C62: =SUMIFS('data set'!$C:$C,'data set'!$E:$E,Model!$A62,'data set'!$B:$B,Model!C$3) -> 0 | D62: =SUMIFS('data set'!$C:$C,'data set'!$E:$E,Model!$A62,'data set'!$B:$B,Model!D$3) -> 1440 | E62: =SUMIFS('data set'!$C:$C,'data set'!$E:$E,Model!$A62,'data set'!$B:$B,Model!E$3) -> 0 | F62: =SUMIFS('data set'!$C:$C,'data set'!$E:$E,Model!$A62,'data set'!$B:$B,Model!F$3) -> 7380 | G62: =SUMIFS('data set'!$C:$C,'data set'!$E:$E,Model!$A62,'data set'!$B:$B,Model!G$3) -> 4320 | H62: =SUMIFS('data set'!$C:$C,'data set'!$E:$E,Model!$A62,'data set'!$B:$B,Model!H$3) -> 17412 | I62: =SUMIFS('data set'!$C:$C,'data set'!$E:$E,Model!$A62,'data set'!$B:$B,Model!I$3) -> 27996 | J62: =J13*J109 -> 6459.5 | K62: =K13*K109 -> 6459.5 | L62: =L13*L109 -> 6459.5 | M62: =M13*M109 -> 9689.25 | N62: =N13*N109 -> 9689.25 | O62: =O13*O109 -> 9689.25 | P62: =P13*P109 -> 12919 | Q62: =Q13*Q109 -> 12919 | S62: =IFERROR(RATE(MONTH($Q$3)-MONTH($I$3),0,-I62,Q62),"N/A") -> -0.09214474 | T62: =IFERROR(RATE(MONTH($Q$3)-MONTH($K$3),0,-K62,Q62),"N/A") -> 0.12246205
A63: Total Starting ARR | B63: =SUM(B54:B62) -> 0 | C63: =SUM(C54:C62) -> 11004 | D63: =SUM(D54:D62) -> 89592 | E63: =SUM(E54:E62) -> 441192 | F63: =SUM(F54:F62) -> 574176 | G63: =SUM(G54:G62) -> 594120 | H63: =SUM(H54:H62) -> 704832 | I63: =SUM(I54:I62) -> 843479 | ... Q63: =SUM(Q54:Q62) -> 2159965.8 | S63: =IFERROR(RATE(MONTH($Q$3)-MONTH($I$3),0,-I63,Q63),"N/A") -> 0.12472559 | T63: =IFERROR(RATE(MONTH($Q$3)-MONTH($K$3),0,-K63,Q63),"N/A") -> 0.10824842
A65: Revenue - Change in ARR
A66: New | B66: =SUMIFS('data set'!$F:$F,'data set'!$E:$E,Model!$A66,'data set'!$B:$B,Model!B$3) -> 11004 | C66: =SUMIFS('data set'!$F:$F,'data set'!$E:$E,Model!$A66,'data set'!$B:$B,Model!C$3) -> 81816 | D66: =SUMIFS('data set'!$F:$F,'data set'!$E:$E,Model!$A66,'data set'!$B:$B,Model!D$3) -> 320772 | E66: =SUMIFS('data set'!$F:$F,'data set'!$E:$E,Model!$A66,'data set'!$B:$B,Model!E$3) -> 195756 | F66: =SUMIFS('data set'!$F:$F,'data set'!$E:$E,Model!$A66,'data set'!$B:$B,Model!F$3) -> 80688 | G66: =SUMIFS('data set'!$F:$F,'data set'!$E:$E,Model!$A66,'data set'!$B:$B,Model!G$3) -> 130092 | H66: =SUMIFS('data set'!$F:$F,'data set'!$E:$E,Model!$A66,'data set'!$B:$B,Model!H$3) -> 173507 | I66: =SUMIFS('data set'!$F:$F,'data set'!$E:$E,Model!$A66,'data set'!$B:$B,Model!I$3) -> 177744 | J66: =J4*J123 -> 151986.56 | K66: =K4*K123 -> 156889.36 | L66: =L4*L123 -> 161792.15 | M66: =M4*M123 -> 166694.94 | N66: =N4*N123 -> 171597.73 | O66: =O4*O123 -> 176500.52 | P66: =P4*P123 -> 181403.32 | Q66: =Q4*Q123 -> 186306.11 | S66: =IFERROR(RATE(MONTH($Q$3)-MONTH($I$3),0,-I66,Q66),"N/A") -> 0.0058981707 | T66: =IFERROR(RATE(MONTH($Q$3)-MONTH($K$3),0,-K66,Q66),"N/A") -> 0.029055827
A67: Legacy to New Team | B67: =SUMIFS('data set'!$F:$F,'data set'!$E:$E,Model!$A67,'data set'!$B:$B,Model!B$3) -> 0 | C67: =SUMIFS('data set'!$F:$F,'data set'!$E:$E,Model!$A67,'data set'!$B:$B,Model!C$3) -> 3456 | D67: =SUMIFS('data set'!$F:$F,'data set'!$E:$E,Model!$A67,'data set'!$B:$B,Model!D$3) -> 38232 | E67: =SUMIFS('data set'!$F:$F,'data set'!$E:$E,Model!$A67,'data set'!$B:$B,Model!E$3) -> 18960 | F67: =SUMIFS('data set'!$F:$F,'data set'!$E:$E,Model!$A67,'data set'!$B:$B,Model!F$3) -> 20220 | G67: =SUMIFS('data set'!$F:$F,'data set'!$E:$E,Model!$A67,'data set'!$B:$B,Model!G$3) -> 3888 | H67: =SUMIFS('data set'!$F:$F,'data set'!$E:$E,Model!$A67,'data set'!$B:$B,Model!H$3) -> 1440 | I67: =SUMIFS('data set'!$F:$F,'data set'!$E:$E,Model!$A67,'data set'!$B:$B,Model!I$3) -> 0 | J67: =J5*J124 -> 7428 | K67: =K5*K124 -> 7428 | L67: =L5*L124 -> 7428 | M67: =M5*M124 -> 7428 | N67: =N5*N124 -> 7428 | O67: =O5*O124 -> 7428 | P67: =P5*P124 -> 7428 | Q67: =Q5*Q124 -> 7428 | S67: =IFERROR(RATE(MONTH($Q$3)-MONTH($I$3),0,-I67,Q67),"N/A") -> N/A | T67: =IFERROR(RATE(MONTH($Q$3)-MONTH($K$3),0,-K67,Q67),"N/A") -> 8.3301817e-15
A68: No Change | B68: =SUMIFS('data set'!$F:$F,'data set'!$E:$E,Model!$A68,'data set'!$B:$B,Model!B$3) -> 0 | C68: =SUMIFS('data set'!$F:$F,'data set'!$E:$E,Model!$A68,'data set'!$B:$B,Model!C$3) -> 0 | D68: =SUMIFS('data set'!$F:$F,'data set'!$E:$E,Model!$A68,'data set'!$B:$B,Model!D$3) -> 0 | E68: =SUMIFS('data set'!$F:$F,'data set'!$E:$E,Model!$A68,'data set'!$B:$B,Model!E$3) -> 0 | F68: =SUMIFS('data set'!$F:$F,'data set'!$E:$E,Model!$A68,'data set'!$B:$B,Model!F$3) -> 0 | G68: =SUMIFS('data set'!$F:$F,'data set'!$E:$E,Model!$A68,'data set'!$B:$B,Model!G$3) -> 0 | H68: =SUMIFS('data set'!$F:$F,'data set'!$E:$E,Model!$A68,'data set'!$B:$B,Model!H$3) -> 0 | I68: =SUMIFS('data set'!$F:$F,'data set'!$E:$E,Model!$A68,'data set'!$B:$B,Model!I$3) -> 0 | J68: =J6*J125 -> 0 | K68: =K6*K125 -> 0 | L68: =L6*L125 -> 0 | M68: =M6*M125 -> 0 | N68: =N6*N125 -> 0 | O68: =O6*O125 -> 0 | P68: =P6*P125 -> 0 | Q68: =Q6*Q125 -> 0 | S68: =IFERROR(RATE(MONTH($Q$3)-MONTH($I$3),0,-I68,Q68),"N/A") -> N/A | T68: =IFERROR(RATE(MONTH($Q$3)-MONTH($K$3),0,-K68,Q68),"N/A") -> N/A
A69: Expansion | B69: =SUMIFS('data set'!$F:$F,'data set'!$E:$E,Model!$A69,'data set'!$B:$B,Model!B$3) -> 0 | C69: =SUMIFS('data set'!$F:$F,'data set'!$E:$E,Model!$A69,'data set'!$B:$B,Model!C$3) -> 0 | D69: =SUMIFS('data set'!$F:$F,'data set'!$E:$E,Model!$A69,'data set'!$B:$B,Model!D$3) -> 16200 | E69: =SUMIFS('data set'!$F:$F,'data set'!$E:$E,Model!$A69,'data set'!$B:$B,Model!E$3) -> 82008 | F69: =SUMIFS('data set'!$F:$F,'data set'!$E:$E,Model!$A69,'data set'!$B:$B,Model!F$3) -> 73272 | G69: =SUMIFS('data set'!$F:$F,'data set'!$E:$E,Model!$A69,'data set'!$B:$B,Model!G$3) -> 98016 | H69: =SUMIFS('data set'!$F:$F,'data set'!$E:$E,Model!$A69,'data set'!$B:$B,Model!H$3) -> 68712 | I69: =SUMIFS('data set'!$F:$F,'data set'!$E:$E,Model!$A69,'data set'!$B:$B,Model!I$3) -> 112333 | J69: =J7*J126 -> 152296.03 | K69: =K7*K126 -> 176575.11 | L69: =L7*L126 -> 200854.19 | M69: =M7*M126 -> 225133.26 | N69: =N7*N126 -> 247205.15 | O69: =O7*O126 -> 271484.23 | P69: =P7*P126 -> 295763.31 | Q69: =Q7*Q126 -> 320042.39 | S69: =IFERROR(RATE(MONTH($Q$3)-MONTH($I$3),0,-I69,Q69),"N/A") -> 0.13982327 | T69: =IFERROR(RATE(MONTH($Q$3)-MONTH($K$3),0,-K69,Q69),"N/A") -> 0.10419642
A70: Contraction | B70: =SUMIFS('data set'!$F:$F,'data set'!$E:$E,Model!$A70,'data set'!$B:$B,Model!B$3) -> 0 | C70: =SUMIFS('data set'!$F:$F,'data set'!$E:$E,Model!$A70,'data set'!$B:$B,Model!C$3) -> 0 | D70: =SUMIFS('data set'!$F:$F,'data set'!$E:$E,Model!$A70,'data set'!$B:$B,Model!D$3) -> -8976 | E70: =SUMIFS('data set'!$F:$F,'data set'!$E:$E,Model!$A70,'data set'!$B:$B,Model!E$3) -> -143112 | F70: =SUMIFS('data set'!$F:$F,'data set'!$E:$E,Model!$A70,'data set'!$B:$B,Model!F$3) -> -118032 | G70: =SUMIFS('data set'!$F:$F,'data set'!$E:$E,Model!$A70,'data set'!$B:$B,Model!G$3) -> -54744 | H70: =SUMIFS('data set'!$F:$F,'data set'!$E:$E,Model!$A70,'data set'!$B:$B,Model!H$3) -> -43704 | I70: =SUMIFS('data set'!$F:$F,'data set'!$E:$E,Model!$A70,'data set'!$B:$B,Model!I$3) -> -45444 | J70: =J8*J127 -> -112013.25 | K70: =K8*K127 -> -128815.24 | L70: =L8*L127 -> -142816.9 | M70: =M8*M127 -> -159618.89 | N70: =N8*N127 -> -173620.54 | O70: =O8*O127 -> -190422.53 | P70: =P8*P127 -> -207224.52 | Q70: =Q8*Q127 -> -221226.17 | S70: =IFERROR(RATE(MONTH($Q$3)-MONTH($I$3),0,-I70,Q70),"N/A") -> 0.21876506 | T70: =IFERROR(RATE(MONTH($Q$3)-MONTH($K$3),0,-K70,Q70),"N/A") -> 0.094321361
A71: Old Team to New Team | B71: =SUMIFS('data set'!$F:$F,'data set'!$E:$E,Model!$A71,'data set'!$B:$B,Model!B$3) -> 0 | C71: =SUMIFS('data set'!$F:$F,'data set'!$E:$E,Model!$A71,'data set'!$B:$B,Model!C$3) -> 0 | D71: =SUMIFS('data set'!$F:$F,'data set'!$E:$E,Model!$A71,'data set'!$B:$B,Model!D$3) -> 0 | E71: =SUMIFS('data set'!$F:$F,'data set'!$E:$E,Model!$A71,'data set'!$B:$B,Model!E$3) -> 1200 | F71: =SUMIFS('data set'!$F:$F,'data set'!$E:$E,Model!$A71,'data set'!$B:$B,Model!F$3) -> 0 | G71: =SUMIFS('data set'!$F:$F,'data set'!$E:$E,Model!$A71,'data set'!$B:$B,Model!G$3) -> 3840 | H71: =SUMIFS('data set'!$F:$F,'data set'!$E:$E,Model!$A71,'data set'!$B:$B,Model!H$3) -> 0 | I71: =SUMIFS('data set'!$F:$F,'data set'!$E:$E,Model!$A71,'data set'!$B:$B,Model!I$3) -> 1440 | J71: =J9*J128 -> 1360 | K71: =K9*K128 -> 1360 | L71: =L9*L128 -> 1360 | M71: =M9*M128 -> 1360 | N71: =N9*N128 -> 1360 | O71: =O9*O128 -> 1360 | P71: =P9*P128 -> 1360 | Q71: =Q9*Q128 -> 1360 | S71: =IFERROR(RATE(MONTH($Q$3)-MONTH($I$3),0,-I71,Q71),"N/A") -> -0.0071193383 | T71: =IFERROR(RATE(MONTH($Q$3)-MONTH($K$3),0,-K71,Q71),"N/A") -> 8.3593552e-15
A72: Churn-Failed Reactivation | B72: =SUMIFS('data set'!$F:$F,'data set'!$E:$E,Model!$A72,'data set'!$B:$B,Model!B$3) -> 0 | C72: =SUMIFS('data set'!$F:$F,'data set'!$E:$E,Model!$A72,'data set'!$B:$B,Model!C$3) -> 0 | D72: =SUMIFS('data set'!$F:$F,'data set'!$E:$E,Model!$A72,'data set'!$B:$B,Model!D$3) -> 0 | E72: =SUMIFS('data set'!$F:$F,'data set'!$E:$E,Model!$A72,'data set'!$B:$B,Model!E$3) -> 0 | F72: =SUMIFS('data set'!$F:$F,'data set'!$E:$E,Model!$A72,'data set'!$B:$B,Model!F$3) -> 0 | G72: =SUMIFS('data set'!$F:$F,'data set'!$E:$E,Model!$A72,'data set'!$B:$B,Model!G$3) -> 1440 | H72: =SUMIFS('data set'!$F:$F,'data set'!$E:$E,Model!$A72,'data set'!$B:$B,Model!H$3) -> 2736 | I72: =SUMIFS('data set'!$F:$F,'data set'!$E:$E,Model!$A72,'data set'!$B:$B,Model!I$3) -> 0 | J72: =J10*J129 -> 10440 | K72: =K10*K129 -> 4176 | L72: =L10*L129 -> 4176 | M72: =M10*M129 -> 4176 | N72: =N10*N129 -> 4176 | O72: =O10*O129 -> 4176 | P72: =P10*P129 -> 4176 | Q72: =Q10*Q129 -> 6264 | S72: =IFERROR(RATE(MONTH($Q$3)-MONTH($I$3),0,-I72,Q72),"N/A") -> N/A | T72: =IFERROR(RATE(MONTH($Q$3)-MONTH($K$3),0,-K72,Q72),"N/A") -> 0.069913194
A73: Churn | B73: =SUMIFS('data set'!$F:$F,'data set'!$E:$E,Model!$A73,'data set'!$B:$B,Model!B$3) -> 0 | C73: =SUMIFS('data set'!$F:$F,'data set'!$E:$E,Model!$A73,'data set'!$B:$B,Model!C$3) -> -9804 | D73: =SUMIFS('data set'!$F:$F,'data set'!$E:$E,Model!$A73,'data set'!$B:$B,Model!D$3) -> -1728 | E73: =SUMIFS('data set'!$F:$F,'data set'!$E:$E,Model!$A73,'data set'!$B:$B,Model!E$3) -> -14712 | F73: =SUMIFS('data set'!$F:$F,'data set'!$E:$E,Model!$A73,'data set'!$B:$B,Model!F$3) -> 0 | G73: =SUMIFS('data set'!$F:$F,'data set'!$E:$E,Model!$A73,'data set'!$B:$B,Model!G$3) -> -4752 | H73: =SUMIFS('data set'!$F:$F,'data set'!$E:$E,Model!$A73,'data set'!$B:$B,Model!H$3) -> -1440 | I73: =SUMIFS('data set'!$F:$F,'data set'!$E:$E,Model!$A73,'data set'!$B:$B,Model!I$3) -> -13584 | J73: =J12*J130 -> -11072 | K73: =K12*K130 -> -11072 | L73: =L12*L130 -> -11072 | M73: =M12*M130 -> -16608 | N73: =N12*N130 -> -16608 | O73: =O12*O130 -> -16608 | P73: =P12*P130 -> -22144 | Q73: =Q12*Q130 -> -22144 | S73: =IFERROR(RATE(MONTH($Q$3)-MONTH($I$3),0,-I73,Q73),"N/A") -> 0.062988461 | T73: =IFERROR(RATE(MONTH($Q$3)-MONTH($K$3),0,-K73,Q73),"N/A") -> 0.12246205
A74: Churn-Failed | B74: =SUMIFS('data set'!$F:$F,'data set'!$E:$E,Model!$A74,'data set'!$B:$B,Model!B$3) -> 0 | C74: =SUMIFS('data set'!$F:$F,'data set'!$E:$E,Model!$A74,'data set'!$B:$B,Model!C$3) -> 0 | D74: =SUMIFS('data set'!$F:$F,'data set'!$E:$E,Model!$A74,'data set'!$B:$B,Model!D$3) -> -1440 | E74: =SUMIFS('data set'!$F:$F,'data set'!$E:$E,Model!$A74,'data set'!$B:$B,Model!E$3) -> 0 | F74: =SUMIFS('data set'!$F:$F,'data set'!$E:$E,Model!$A74,'data set'!$B:$B,Model!F$3) -> -7380 | G74: =SUMIFS('data set'!$F:$F,'data set'!$E:$E,Model!$A74,'data set'!$B:$B,Model!G$3) -> -4320 | H74: =SUMIFS('data set'!$F:$F,'data set'!$E:$E,Model!$A74,'data set'!$B:$B,Model!H$3) -> -17412 | I74: =SUMIFS('data set'!$F:$F,'data set'!$E:$E,Model!$A74,'data set'!$B:$B,Model!I$3) -> -27996 | J74: =J13*J131 -> -6459.5 | K74: =K13*K131 -> -6459.5 | L74: =L13*L131 -> -6459.5 | M74: =M13*M131 -> -9689.25 | N74: =N13*N131 -> -9689.25 | O74: =O13*O131 -> -9689.25 | P74: =P13*P131 -> -12919 | Q74: =Q13*Q131 -> -12919 | S74: =IFERROR(RATE(MONTH($Q$3)-MONTH($I$3),0,-I74,Q74),"N/A") -> -0.09214474 | T74: =IFERROR(RATE(MONTH($Q$3)-MONTH($K$3),0,-K74,Q74),"N/A") -> 0.12246205
A75: Total Change in ARR | B75: =SUM(B66:B74) -> 11004 | C75: =SUM(C66:C74) -> 75468 | D75: =SUM(D66:D74) -> 363060 | E75: =SUM(E66:E74) -> 140100 | F75: =SUM(F66:F74) -> 48768 | G75: =SUM(G66:G74) -> 173460 | H75: =SUM(H66:H74) -> 183839 | I75: =SUM(I66:I74) -> 204493 | ... Q75: =SUM(Q66:Q74) -> 265111.32 | S75: =IFERROR(RATE(MONTH($Q$3)-MONTH($I$3),0,-I75,Q75),"N/A") -> 0.032984318 | T75: =IFERROR(RATE(MONTH($Q$3)-MONTH($K$3),0,-K75,Q75),"N/A") -> 0.048021379
A77: Revenue - Ending ARR
A78: New | B78: =SUMIFS('data set'!$D:$D,'data set'!$E:$E,Model!$A78,'data set'!$B:$B,Model!B$3) -> 11004 | C78: =SUMIFS('data set'!$D:$D,'data set'!$E:$E,Model!$A78,'data set'!$B:$B,Model!C$3) -> 81816 | D78: =SUMIFS('data set'!$D:$D,'data set'!$E:$E,Model!$A78,'data set'!$B:$B,Model!D$3) -> 320772 | E78: =SUMIFS('data set'!$D:$D,'data set'!$E:$E,Model!$A78,'data set'!$B:$B,Model!E$3) -> 195756 | F78: =SUMIFS('data set'!$D:$D,'data set'!$E:$E,Model!$A78,'data set'!$B:$B,Model!F$3) -> 80688 | G78: =SUMIFS('data set'!$D:$D,'data set'!$E:$E,Model!$A78,'data set'!$B:$B,Model!G$3) -> 130092 | H78: =SUMIFS('data set'!$D:$D,'data set'!$E:$E,Model!$A78,'data set'!$B:$B,Model!H$3) -> 173507 | I78: =SUMIFS('data set'!$D:$D,'data set'!$E:$E,Model!$A78,'data set'!$B:$B,Model!I$3) -> 177744 | J78: =J54+J66 -> 151986.56 | K78: =K54+K66 -> 156889.36 | L78: =L54+L66 -> 161792.15 | M78: =M54+M66 -> 166694.94 | N78: =N54+N66 -> 171597.73 | O78: =O54+O66 -> 176500.52 | P78: =P54+P66 -> 181403.32 | Q78: =Q54+Q66 -> 186306.11 | S78: =IFERROR(RATE(MONTH($Q$3)-MONTH($I$3),0,-I78,Q78),"N/A") -> 0.0058981707 | T78: =IFERROR(RATE(MONTH($Q$3)-MONTH($K$3),0,-K78,Q78),"N/A") -> 0.029055827
A79: Legacy to New Team | B79: =SUMIFS('data set'!$D:$D,'data set'!$E:$E,Model!$A79,'data set'!$B:$B,Model!B$3) -> 0 | C79: =SUMIFS('data set'!$D:$D,'data set'!$E:$E,Model!$A79,'data set'!$B:$B,Model!C$3) -> 3456 | D79: =SUMIFS('data set'!$D:$D,'data set'!$E:$E,Model!$A79,'data set'!$B:$B,Model!D$3) -> 38232 | E79: =SUMIFS('data set'!$D:$D,'data set'!$E:$E,Model!$A79,'data set'!$B:$B,Model!E$3) -> 18960 | F79: =SUMIFS('data set'!$D:$D,'data set'!$E:$E,Model!$A79,'data set'!$B:$B,Model!F$3) -> 20220 | G79: =SUMIFS('data set'!$D:$D,'data set'!$E:$E,Model!$A79,'data set'!$B:$B,Model!G$3) -> 3888 | H79: =SUMIFS('data set'!$D:$D,'data set'!$E:$E,Model!$A79,'data set'!$B:$B,Model!H$3) -> 1440 | I79: =SUMIFS('data set'!$D:$D,'data set'!$E:$E,Model!$A79,'data set'!$B:$B,Model!I$3) -> 0 | J79: =J55+J67 -> 7428 | K79: =K55+K67 -> 7428 | L79: =L55+L67 -> 7428 | M79: =M55+M67 -> 7428 | N79: =N55+N67 -> 7428 | O79: =O55+O67 -> 7428 | P79: =P55+P67 -> 7428 | Q79: =Q55+Q67 -> 7428 | S79: =IFERROR(RATE(MONTH($Q$3)-MONTH($I$3),0,-I79,Q79),"N/A") -> N/A | T79: =IFERROR(RATE(MONTH($Q$3)-MONTH($K$3),0,-K79,Q79),"N/A") -> 8.3301817e-15
A80: No Change | B80: =SUMIFS('data set'!$D:$D,'data set'!$E:$E,Model!$A80,'data set'!$B:$B,Model!B$3) -> 0 | C80: =SUMIFS('data set'!$D:$D,'data set'!$E:$E,Model!$A80,'data set'!$B:$B,Model!C$3) -> 1200 | D80: =SUMIFS('data set'!$D:$D,'data set'!$E:$E,Model!$A80,'data set'!$B:$B,Model!D$3) -> 29520 | E80: =SUMIFS('data set'!$D:$D,'data set'!$E:$E,Model!$A80,'data set'!$B:$B,Model!E$3) -> 94128 | F80: =SUMIFS('data set'!$D:$D,'data set'!$E:$E,Model!$A80,'data set'!$B:$B,Model!F$3) -> 187908 | G80: =SUMIFS('data set'!$D:$D,'data set'!$E:$E,Model!$A80,'data set'!$B:$B,Model!G$3) -> 241536 | H80: =SUMIFS('data set'!$D:$D,'data set'!$E:$E,Model!$A80,'data set'!$B:$B,Model!H$3) -> 277992 | I80: =SUMIFS('data set'!$D:$D,'data set'!$E:$E,Model!$A80,'data set'!$B:$B,Model!I$3) -> 332340 | J80: =J56+J68 -> 412912.49 | K80: =K56+K68 -> 475889.9 | L80: =L56+L68 -> 538172.52 | M80: =M56+M68 -> 603366.03 | N80: =N56+N68 -> 670223.58 | O80: =O56+O68 -> 738896.85 | P80: =P56+P68 -> 809062.62 | Q80: =Q56+Q68 -> 880647.32 | S80: =IFERROR(RATE(MONTH($Q$3)-MONTH($I$3),0,-I80,Q80),"N/A") -> 0.12954211 | T80: =IFERROR(RATE(MONTH($Q$3)-MONTH($K$3),0,-K80,Q80),"N/A") -> 0.10802422
A81: Expansion | B81: =SUMIFS('data set'!$D:$D,'data set'!$E:$E,Model!$A81,'data set'!$B:$B,Model!B$3) -> 0 | C81: =SUMIFS('data set'!$D:$D,'data set'!$E:$E,Model!$A81,'data set'!$B:$B,Model!C$3) -> 0 | D81: =SUMIFS('data set'!$D:$D,'data set'!$E:$E,Model!$A81,'data set'!$B:$B,Model!D$3) -> 41868 | E81: =SUMIFS('data set'!$D:$D,'data set'!$E:$E,Model!$A81,'data set'!$B:$B,Model!E$3) -> 168648 | F81: =SUMIFS('data set'!$D:$D,'data set'!$E:$E,Model!$A81,'data set'!$B:$B,Model!F$3) -> 224688 | G81: =SUMIFS('data set'!$D:$D,'data set'!$E:$E,Model!$A81,'data set'!$B:$B,Model!G$3) -> 322308 | H81: =SUMIFS('data set'!$D:$D,'data set'!$E:$E,Model!$A81,'data set'!$B:$B,Model!H$3) -> 253584 | I81: =SUMIFS('data set'!$D:$D,'data set'!$E:$E,Model!$A81,'data set'!$B:$B,Model!I$3) -> 414060 | J81: =J57+J69 -> 527173.71 | K81: =K57+K69 -> 608629.13 | L81: =L57+L69 -> 689453.75 | M81: =M57+M69 -> 772921.14 | N81: =N57+N69 -> 855692.1 | O81: =O57+O69 -> 942318.71 | P81: =P57+P69 -> 1030300.3 | Q81: =Q57+Q69 -> 1119570.2 | S81: =IFERROR(RATE(MONTH($Q$3)-MONTH($I$3),0,-I81,Q81),"N/A") -> 0.13239647 | T81: =IFERROR(RATE(MONTH($Q$3)-MONTH($K$3),0,-K81,Q81),"N/A") -> 0.10692051
A82: Contraction | B82: =SUMIFS('data set'!$D:$D,'data set'!$E:$E,Model!$A82,'data set'!$B:$B,Model!B$3) -> 0 | C82: =SUMIFS('data set'!$D:$D,'data set'!$E:$E,Model!$A82,'data set'!$B:$B,Model!C$3) -> 0 | D82: =SUMIFS('data set'!$D:$D,'data set'!$E:$E,Model!$A82,'data set'!$B:$B,Model!D$3) -> 22260 | E82: =SUMIFS('data set'!$D:$D,'data set'!$E:$E,Model!$A82,'data set'!$B:$B,Model!E$3) -> 102600 | F82: =SUMIFS('data set'!$D:$D,'data set'!$E:$E,Model!$A82,'data set'!$B:$B,Model!F$3) -> 109440 | G82: =SUMIFS('data set'!$D:$D,'data set'!$E:$E,Model!$A82,'data set'!$B:$B,Model!G$3) -> 64476 | H82: =SUMIFS('data set'!$D:$D,'data set'!$E:$E,Model!$A82,'data set'!$B:$B,Model!H$3) -> 179412 | I82: =SUMIFS('data set'!$D:$D,'data set'!$E:$E,Model!$A82,'data set'!$B:$B,Model!I$3) -> 122388 | J82: =J58+J70 -> 96507.928 | K82: =K58+K70 -> 111509.59 | L82: =L58+L70 -> 128960.71 | M82: =M58+M70 -> 145081.5 | N82: =N58+N70 -> 164842.97 | O82: =O58+O70 -> 182721.05 | P82: =P58+P70 -> 201352.84 | Q82: =Q58+Q70 -> 223501.52 | S82: =IFERROR(RATE(MONTH($Q$3)-MONTH($I$3),0,-I82,Q82),"N/A") -> 0.078183559 | T82: =IFERROR(RATE(MONTH($Q$3)-MONTH($K$3),0,-K82,Q82),"N/A") -> 0.12286629
A83: Old Team to New Team | B83: =SUMIFS('data set'!$D:$D,'data set'!$E:$E,Model!$A83,'data set'!$B:$B,Model!B$3) -> 0 | C83: =SUMIFS('data set'!$D:$D,'data set'!$E:$E,Model!$A83,'data set'!$B:$B,Model!C$3) -> 0 | D83: =SUMIFS('data set'!$D:$D,'data set'!$E:$E,Model!$A83,'data set'!$B:$B,Model!D$3) -> 0 | E83: =SUMIFS('data set'!$D:$D,'data set'!$E:$E,Model!$A83,'data set'!$B:$B,Model!E$3) -> 1200 | F83: =SUMIFS('data set'!$D:$D,'data set'!$E:$E,Model!$A83,'data set'!$B:$B,Model!F$3) -> 0 | G83: =SUMIFS('data set'!$D:$D,'data set'!$E:$E,Model!$A83,'data set'!$B:$B,Model!G$3) -> 3840 | H83: =SUMIFS('data set'!$D:$D,'data set'!$E:$E,Model!$A83,'data set'!$B:$B,Model!H$3) -> 0 | I83: =SUMIFS('data set'!$D:$D,'data set'!$E:$E,Model!$A83,'data set'!$B:$B,Model!I$3) -> 1440 | J83: =J59+J71 -> 1360 | K83: =K59+K71 -> 1360 | L83: =L59+L71 -> 1360 | M83: =M59+M71 -> 1360 | N83: =N59+N71 -> 1360 | O83: =O59+O71 -> 1360 | P83: =P59+P71 -> 1360 | Q83: =Q59+Q71 -> 1360 | S83: =IFERROR(RATE(MONTH($Q$3)-MONTH($I$3),0,-I83,Q83),"N/A") -> -0.0071193383 | T83: =IFERROR(RATE(MONTH($Q$3)-MONTH($K$3),0,-K83,Q83),"N/A") -> 8.3593552e-15
A84: Churn-Failed Reactivation | B84: =SUMIFS('data set'!$D:$D,'data set'!$E:$E,Model!$A84,'data set'!$B:$B,Model!B$3) -> 0 | C84: =SUMIFS('data set'!$D:$D,'data set'!$E:$E,Model!$A84,'data set'!$B:$B,Model!C$3) -> 0 | D84: =SUMIFS('data set'!$D:$D,'data set'!$E:$E,Model!$A84,'data set'!$B:$B,Model!D$3) -> 0 | E84: =SUMIFS('data set'!$D:$D,'data set'!$E:$E,Model!$A84,'data set'!$B:$B,Model!E$3) -> 0 | F84: =SUMIFS('data set'!$D:$D,'data set'!$E:$E,Model!$A84,'data set'!$B:$B,Model!F$3) -> 0 | G84: =SUMIFS('data set'!$D:$D,'data set'!$E:$E,Model!$A84,'data set'!$B:$B,Model!G$3) -> 1440 | H84: =SUMIFS('data set'!$D:$D,'data set'!$E:$E,Model!$A84,'data set'!$B:$B,Model!H$3) -> 2736 | I84: =SUMIFS('data set'!$D:$D,'data set'!$E:$E,Model!$A84,'data set'!$B:$B,Model!I$3) -> 0 | J84: =J60+J72 -> 10440 | K84: =K60+K72 -> 4176 | L84: =L60+L72 -> 4176 | M84: =M60+M72 -> 4176 | N84: =N60+N72 -> 4176 | O84: =O60+O72 -> 4176 | P84: =P60+P72 -> 4176 | Q84: =Q60+Q72 -> 6264 | S84: =IFERROR(RATE(MONTH($Q$3)-MONTH($I$3),0,-I84,Q84),"N/A") -> N/A | T84: =IFERROR(RATE(MONTH($Q$3)-MONTH($K$3),0,-K84,Q84),"N/A") -> 0.069913194
A85: Churn | B85: =SUMIFS('data set'!$D:$D,'data set'!$E:$E,Model!$A85,'data set'!$B:$B,Model!B$3) -> 0 | C85: =SUMIFS('data set'!$D:$D,'data set'!$E:$E,Model!$A85,'data set'!$B:$B,Model!C$3) -> 0 | D85: =SUMIFS('data set'!$D:$D,'data set'!$E:$E,Model!$A85,'data set'!$B:$B,Model!D$3) -> 0 | E85: =SUMIFS('data set'!$D:$D,'data set'!$E:$E,Model!$A85,'data set'!$B:$B,Model!E$3) -> 0 | F85: =SUMIFS('data set'!$D:$D,'data set'!$E:$E,Model!$A85,'data set'!$B:$B,Model!F$3) -> 0 | G85: =SUMIFS('data set'!$D:$D,'data set'!$E:$E,Model!$A85,'data set'!$B:$B,Model!G$3) -> 0 | H85: =SUMIFS('data set'!$D:$D,'data set'!$E:$E,Model!$A85,'data set'!$B:$B,Model!H$3) -> 0 | I85: =SUMIFS('data set'!$D:$D,'data set'!$E:$E,Model!$A85,'data set'!$B:$B,Model!I$3) -> 0 | J85: =J61+J73 -> 0 | K85: =K61+K73 -> 0 | L85: =L61+L73 -> 0 | M85: =M61+M73 -> 0 | N85: =N61+N73 -> 0 | O85: =O61+O73 -> 0 | P85: =P61+P73 -> 0 | Q85: =Q61+Q73 -> 0 | S85: =IFERROR(RATE(MONTH($Q$3)-MONTH($I$3),0,-I85,Q85),"N/A") -> N/A | T85: =IFERROR(RATE(MONTH($Q$3)-MONTH($K$3),0,-K85,Q85),"N/A") -> N/A
A86: Churn-Failed | B86: =SUMIFS('data set'!$D:$D,'data set'!$E:$E,Model!$A86,'data set'!$B:$B,Model!B$3) -> 0 | C86: =SUMIFS('data set'!$D:$D,'data set'!$E:$E,Model!$A86,'data set'!$B:$B,Model!C$3) -> 0 | D86: =SUMIFS('data set'!$D:$D,'data set'!$E:$E,Model!$A86,'data set'!$B:$B,Model!D$3) -> 0 | E86: =SUMIFS('data set'!$D:$D,'data set'!$E:$E,Model!$A86,'data set'!$B:$B,Model!E$3) -> 0 | F86: =SUMIFS('data set'!$D:$D,'data set'!$E:$E,Model!$A86,'data set'!$B:$B,Model!F$3) -> 0 | G86: =SUMIFS('data set'!$D:$D,'data set'!$E:$E,Model!$A86,'data set'!$B:$B,Model!G$3) -> 0 | H86: =SUMIFS('data set'!$D:$D,'data set'!$E:$E,Model!$A86,'data set'!$B:$B,Model!H$3) -> 0 | I86: =SUMIFS('data set'!$D:$D,'data set'!$E:$E,Model!$A86,'data set'!$B:$B,Model!I$3) -> 0 | J86: =J62+J74 -> 0 | K86: =K62+K74 -> 0 | L86: =L62+L74 -> 0 | M86: =M62+M74 -> 0 | N86: =N62+N74 -> 0 | O86: =O62+O74 -> 0 | P86: =P62+P74 -> 0 | Q86: =Q62+Q74 -> 0 | S86: =IFERROR(RATE(MONTH($Q$3)-MONTH($I$3),0,-I86,Q86),"N/A") -> N/A | T86: =IFERROR(RATE(MONTH($Q$3)-MONTH($K$3),0,-K86,Q86),"N/A") -> N/A
A87: Total Ending ARR | B87: =SUM(B78:B86) -> 11004 | C87: =SUM(C78:C86) -> 86472 | D87: =SUM(D78:D86) -> 452652 | E87: =SUM(E78:E86) -> 581292 | F87: =SUM(F78:F86) -> 622944 | G87: =SUM(G78:G86) -> 767580 | H87: =SUM(H78:H86) -> 888671 | I87: =SUM(I78:I86) -> 1047972 | ... Q87: =SUM(Q78:Q86) -> 2425077.1 | S87: =IFERROR(RATE(MONTH($Q$3)-MONTH($I$3),0,-I87,Q87),"N/A") -> 0.11057268 | T87: =IFERROR(RATE(MONTH($Q$3)-MONTH($K$3),0,-K87,Q87),"N/A") -> 0.10040376
A89: % of Total - Starting Revenue
A90: New | C90: =IFERROR(C54/C$63,"0%") -> 0 | D90: =IFERROR(D54/D$63,"0%") -> 0 | E90: =IFERROR(E54/E$63,"0%") -> 0 | F90: =IFERROR(F54/F$63,"0%") -> 0 | G90: =IFERROR(G54/G$63,"0%") -> 0 | H90: =IFERROR(H54/H$63,"0%") -> 0 | I90: =IFERROR(I54/I$63,"0%") -> 0 | J90: =I90 -> 0 | K90: =J90 -> 0 | L90: =K90 -> 0 | M90: =L90 -> 0 | N90: =M90 -> 0 | O90: =N90 -> 0 | P90: =O90 -> 0 | Q90: =P90 -> 0 | S90: =IFERROR(RATE(MONTH($Q$3)-MONTH($I$3),0,-I90,Q90),"N/A") -> N/A | T90: =IFERROR(RATE(MONTH($Q$3)-MONTH($K$3),0,-K90,Q90),"N/A") -> N/A
A91: Legacy to New Team | C91: =IFERROR(C55/C$63,"0%") -> 0 | D91: =IFERROR(D55/D$63,"0%") -> 0 | E91: =IFERROR(E55/E$63,"0%") -> 0 | F91: =IFERROR(F55/F$63,"0%") -> 0 | G91: =IFERROR(G55/G$63,"0%") -> 0 | H91: =IFERROR(H55/H$63,"0%") -> 0 | I91: =IFERROR(I55/I$63,"0%") -> 0 | J91: =I91 -> 0 | K91: =J91 -> 0 | L91: =K91 -> 0 | M91: =L91 -> 0 | N91: =M91 -> 0 | O91: =N91 -> 0 | P91: =O91 -> 0 | Q91: =P91 -> 0 | S91: =IFERROR(RATE(MONTH($Q$3)-MONTH($I$3),0,-I91,Q91),"N/A") -> N/A | T91: =IFERROR(RATE(MONTH($Q$3)-MONTH($K$3),0,-K91,Q91),"N/A") -> N/A
A92: No Change | C92: =IFERROR(C56/C$63,"0%") -> 0.10905125 | D92: =IFERROR(D56/D$63,"0%") -> 0.3294937 | E92: =IFERROR(E56/E$63,"0%") -> 0.21334929 | F92: =IFERROR(F56/F$63,"0%") -> 0.32726551 | G92: =IFERROR(G56/G$63,"0%") -> 0.40654413 | H92: =IFERROR(H56/H$63,"0%") -> 0.39440888 | I92: =IFERROR(I56/I$63,"0%") -> 0.39401099 | J92: =I92 -> 0.39401099 | K92: =J92 -> 0.39401099 | L92: =K92 -> 0.39401099 | M92: =L92 -> 0.39401099 | N92: =M92 -> 0.39401099 | O92: =N92 -> 0.39401099 | P92: =O92 -> 0.39401099 | Q92: =P92 -> 0.39401099 | S92: =IFERROR(RATE(MONTH($Q$3)-MONTH($I$3),0,-I92,Q92),"N/A") -> 3.1899366e-12 | T92: =IFERROR(RATE(MONTH($Q$3)-MONTH($K$3),0,-K92,Q92),"N/A") -> 8.3714268e-15
A93: Expansion | C93: =IFERROR(C57/C$63,"0%") -> 0 | D93: =IFERROR(D57/D$63,"0%") -> 0.28649879 | E93: =IFERROR(E57/E$63,"0%") -> 0.19637709 | F93: =IFERROR(F57/F$63,"0%") -> 0.26371008 | G93: =IFERROR(G57/G$63,"0%") -> 0.37751969 | H93: =IFERROR(H57/H$63,"0%") -> 0.26229229 | I93: =IFERROR(I57/I$63,"0%") -> 0.35771726 | J93: =I93 -> 0.35771726 | K93: =J93 -> 0.35771726 | L93: =K93 -> 0.35771726 | M93: =L93 -> 0.35771726 | N93: =M93 -> 0.35771726 | O93: =N93 -> 0.35771726 | P93: =O93 -> 0.35771726 | Q93: =P93 -> 0.35771726 | S93: =IFERROR(RATE(MONTH($Q$3)-MONTH($I$3),0,-I93,Q93),"N/A") -> 3.1898873e-12 | T93: =IFERROR(RATE(MONTH($Q$3)-MONTH($K$3),0,-K93,Q93),"N/A") -> 8.3494423e-15
A94: Contraction | C94: =IFERROR(C58/C$63,"0%") -> 0 | D94: =IFERROR(D58/D$63,"0%") -> 0.3486472 | E94: =IFERROR(E58/E$63,"0%") -> 0.5569276 | F94: =IFERROR(F58/F$63,"0%") -> 0.39617121 | G94: =IFERROR(G58/G$63,"0%") -> 0.20066653 | H94: =IFERROR(H58/H$63,"0%") -> 0.31655203 | I94: =IFERROR(I58/I$63,"0%") -> 0.19897591 | J94: =I94 -> 0.19897591 | K94: =J94 -> 0.19897591 | L94: =K94 -> 0.19897591 | M94: =L94 -> 0.19897591 | N94: =M94 -> 0.19897591 | O94: =N94 -> 0.19897591 | P94: =O94 -> 0.19897591 | Q94: =P94 -> 0.19897591 | S94: =IFERROR(RATE(MONTH($Q$3)-MONTH($I$3),0,-I94,Q94),"N/A") -> 3.1897381e-12 | T94: =IFERROR(RATE(MONTH($Q$3)-MONTH($K$3),0,-K94,Q94),"N/A") -> 8.2716447e-15
A95: Old Team to New Team | C95: =IFERROR(C59/C$63,"0%") -> 0 | D95: =IFERROR(D59/D$63,"0%") -> 0 | E95: =IFERROR(E59/E$63,"0%") -> 0 | F95: =IFERROR(F59/F$63,"0%") -> 0 | G95: =IFERROR(G59/G$63,"0%") -> 0 | H95: =IFERROR(H59/H$63,"0%") -> 0 | I95: =IFERROR(I59/I$63,"0%") -> 0 | J95: =I95 -> 0 | K95: =J95 -> 0 | L95: =K95 -> 0 | M95: =L95 -> 0 | N95: =M95 -> 0 | O95: =N95 -> 0 | P95: =O95 -> 0 | Q95: =P95 -> 0 | S95: =IFERROR(RATE(MONTH($Q$3)-MONTH($I$3),0,-I95,Q95),"N/A") -> N/A | T95: =IFERROR(RATE(MONTH($Q$3)-MONTH($K$3),0,-K95,Q95),"N/A") -> N/A
A96: Churn-Failed Reactivation | C96: =IFERROR(C60/C$63,"0%") -> 0 | D96: =IFERROR(D60/D$63,"0%") -> 0 | E96: =IFERROR(E60/E$63,"0%") -> 0 | F96: =IFERROR(F60/F$63,"0%") -> 0 | G96: =IFERROR(G60/G$63,"0%") -> 0 | H96: =IFERROR(H60/H$63,"0%") -> 0 | I96: =IFERROR(I60/I$63,"0%") -> 0 | J96: =I96 -> 0 | K96: =J96 -> 0 | L96: =K96 -> 0 | M96: =L96 -> 0 | N96: =M96 -> 0 | O96: =N96 -> 0 | P96: =O96 -> 0 | Q96: =P96 -> 0 | S96: =IFERROR(RATE(MONTH($Q$3)-MONTH($I$3),0,-I96,Q96),"N/A") -> N/A | T96: =IFERROR(RATE(MONTH($Q$3)-MONTH($K$3),0,-K96,Q96),"N/A") -> N/A
A97: Churn | C97: =IFERROR(C61/C$63,"0%") -> 0.89094875 | D97: =IFERROR(D61/D$63,"0%") -> 0.019287436 | E97: =IFERROR(E61/E$63,"0%") -> 0.033346026 | F97: =IFERROR(F61/F$63,"0%") -> 0 | G97: =IFERROR(G61/G$63,"0%") -> 0.0079983842 | H97: =IFERROR(H61/H$63,"0%") -> 0.00204304 | I97: =IFERROR(I61/I$63,"0%") -> 0.016104728 | J97: =I97 -> 0.016104728 | K97: =J97 -> 0.016104728 | L97: =K97 -> 0.016104728 | M97: =L97 -> 0.016104728 | N97: =M97 -> 0.016104728 | O97: =N97 -> 0.016104728 | P97: =O97 -> 0.016104728 | Q97: =P97 -> 0.016104728 | S97: =IFERROR(RATE(MONTH($Q$3)-MONTH($I$3),0,-I97,Q97),"N/A") -> 3.1898158e-12 | T97: =IFERROR(RATE(MONTH($Q$3)-MONTH($K$3),0,-K97,Q97),"N/A") -> 8.3989937e-15
A98: Churn-Failed | C98: =IFERROR(C62/C$63,"0%") -> 0 | D98: =IFERROR(D62/D$63,"0%") -> 0.016072864 | E98: =IFERROR(E62/E$63,"0%") -> 0 | F98: =IFERROR(F62/F$63,"0%") -> 0.012853202 | G98: =IFERROR(G62/G$63,"0%") -> 0.0072712583 | H98: =IFERROR(H62/H$63,"0%") -> 0.024703759 | I98: =IFERROR(I62/I$63,"0%") -> 0.033191105 | J98: =I98 -> 0.033191105 | K98: =J98 -> 0.033191105 | L98: =K98 -> 0.033191105 | M98: =L98 -> 0.033191105 | N98: =M98 -> 0.033191105 | O98: =N98 -> 0.033191105 | P98: =O98 -> 0.033191105 | Q98: =P98 -> 0.033191105 | S98: =IFERROR(RATE(MONTH($Q$3)-MONTH($I$3),0,-I98,Q98),"N/A") -> 3.1898458e-12 | T98: =IFERROR(RATE(MONTH($Q$3)-MONTH($K$3),0,-K98,Q98),"N/A") -> 8.4407436e-15
A100: Average Per Customer (Starting ARR/Current # of Customers)
A101: New | B101: =IFERROR(B54/B4,"N/A") -> 0 | C101: =IFERROR(C54/C4,"N/A") -> 0 | D101: =IFERROR(D54/D4,"N/A") -> 0 | E101: =IFERROR(E54/E4,"N/A") -> 0 | F101: =IFERROR(F54/F4,"N/A") -> 0 | G101: =IFERROR(G54/G4,"N/A") -> 0 | H101: =IFERROR(H54/H4,"N/A") -> 0 | I101: =IFERROR(I54/I4,"N/A") -> 0 | J101: =AVERAGE(F101:I101) -> 0 | K101: =J101 -> 0 | L101: =K101 -> 0 | M101: =L101 -> 0 | N101: =M101 -> 0 | O101: =N101 -> 0 | P101: =O101 -> 0 | Q101: =P101 -> 0 | S101: =IFERROR(RATE(MONTH($Q$3)-MONTH($I$3),0,-I101,Q101),"N/A") -> N/A | T101: =IFERROR(RATE(MONTH($Q$3)-MONTH($K$3),0,-K101,Q101),"N/A") -> N/A
A102: Legacy to New Team | B102: =IFERROR(B55/B5,"N/A") -> N/A | C102: =IFERROR(C55/C5,"N/A") -> 0 | D102: =IFERROR(D55/D5,"N/A") -> 0 | E102: =IFERROR(E55/E5,"N/A") -> 0 | F102: =IFERROR(F55/F5,"N/A") -> 0 | G102: =IFERROR(G55/G5,"N/A") -> 0 | H102: =IFERROR(H55/H5,"N/A") -> 0 | I102: =IFERROR(I55/I5,"N/A") -> N/A | J102: =AVERAGE(F102:I102) -> 0 | K102: =J102 -> 0 | L102: =K102 -> 0 | M102: =L102 -> 0 | N102: =M102 -> 0 | O102: =N102 -> 0 | P102: =O102 -> 0 | Q102: =P102 -> 0 | S102: =IFERROR(RATE(MONTH($Q$3)-MONTH($I$3),0,-I102,Q102),"N/A") -> N/A | T102: =IFERROR(RATE(MONTH($Q$3)-MONTH($K$3),0,-K102,Q102),"N/A") -> N/A
A103: No Change | B103: =IFERROR(B56/B6,"N/A") -> N/A | C103: =IFERROR(C56/C6,"N/A") -> 1200 | D103: =IFERROR(D56/D6,"N/A") -> 1341.8182 | E103: =IFERROR(E56/E6,"N/A") -> 1404.8955 | F103: =IFERROR(F56/F6,"N/A") -> 1434.4122 | G103: =IFERROR(G56/G6,"N/A") -> 1429.2071 | H103: =IFERROR(H56/H6,"N/A") -> 1463.1158 | I103: =IFERROR(I56/I6,"N/A") -> 1490.3139 | J103: =AVERAGE(F103:I103) -> 1454.2623 | K103: =J103 -> 1454.2623 | L103: =K103 -> 1454.2623 | M103: =L103 -> 1454.2623 | N103: =M103 -> 1454.2623 | O103: =N103 -> 1454.2623 | P103: =O103 -> 1454.2623 | Q103: =P103 -> 1454.2623 | S103: =IFERROR(RATE(MONTH($Q$3)-MONTH($I$3),0,-I103,Q103),"N/A") -> -0.0030563251 | T103: =IFERROR(RATE(MONTH($Q$3)-MONTH($K$3),0,-K103,Q103),"N/A") -> 8.3827844e-15
A104: Expansion | B104: =IFERROR(B57/B7,"N/A") -> N/A | C104: =IFERROR(C57/C7,"N/A") -> N/A | D104: =IFERROR(D57/D7,"N/A") -> 5133.6 | E104: =IFERROR(E57/E7,"N/A") -> 6188.5714 | F104: =IFERROR(F57/F7,"N/A") -> 6309 | G104: =IFERROR(G57/G7,"N/A") -> 5097.5455 | H104: =IFERROR(H57/H7,"N/A") -> 4509.0732 | I104: =IFERROR(I57/I7,"N/A") -> 5028.7833 | J104: =AVERAGE(F104:I104) -> 5236.1005 | K104: =J104 -> 5236.1005 | L104: =K104 -> 5236.1005 | M104: =L104 -> 5236.1005 | N104: =M104 -> 5236.1005 | O104: =N104 -> 5236.1005 | P104: =O104 -> 5236.1005 | Q104: =P104 -> 5236.1005 | S104: =IFERROR(RATE(MONTH($Q$3)-MONTH($I$3),0,-I104,Q104),"N/A") -> 0.005062643 | T104: =IFERROR(RATE(MONTH($Q$3)-MONTH($K$3),0,-K104,Q104),"N/A") -> 8.2944462e-15
A105: Contraction | B105: =IFERROR(B58/B8,"N/A") -> N/A | C105: =IFERROR(C58/C8,"N/A") -> N/A | D105: =IFERROR(D58/D8,"N/A") -> 15618 | E105: =IFERROR(E58/E8,"N/A") -> 17550.857 | F105: =IFERROR(F58/F8,"N/A") -> 8748.9231 | G105: =IFERROR(G58/G8,"N/A") -> 8515.7143 | H105: =IFERROR(H58/H8,"N/A") -> 6562.2353 | I105: =IFERROR(I58/I8,"N/A") -> 5413.9355 | J105: =AVERAGE(F105:I105) -> 7310.202 | K105: =J105 -> 7310.202 | L105: =K105 -> 7310.202 | M105: =L105 -> 7310.202 | N105: =M105 -> 7310.202 | O105: =N105 -> 7310.202 | P105: =O105 -> 7310.202 | Q105: =P105 -> 7310.202 | S105: =IFERROR(RATE(MONTH($Q$3)-MONTH($I$3),0,-I105,Q105),"N/A") -> 0.038250235 | T105: =IFERROR(RATE(MONTH($Q$3)-MONTH($K$3),0,-K105,Q105),"N/A") -> 8.3007701e-15
A106: Old Team to New Team | B106: =IFERROR(B59/B9,"N/A") -> N/A | C106: =IFERROR(C59/C9,"N/A") -> N/A | D106: =IFERROR(D59/D9,"N/A") -> N/A | E106: =IFERROR(E59/E9,"N/A") -> 0 | F106: =IFERROR(F59/F9,"N/A") -> N/A | G106: =IFERROR(G59/G9,"N/A") -> 0 | H106: =IFERROR(H59/H9,"N/A") -> N/A | I106: =IFERROR(I59/I9,"N/A") -> 0 | J106: =AVERAGE(F106:I106) -> 0 | K106: =J106 -> 0 | L106: =K106 -> 0 | M106: =L106 -> 0 | N106: =M106 -> 0 | O106: =N106 -> 0 | P106: =O106 -> 0 | Q106: =P106 -> 0 | S106: =IFERROR(RATE(MONTH($Q$3)-MONTH($I$3),0,-I106,Q106),"N/A") -> N/A | T106: =IFERROR(RATE(MONTH($Q$3)-MONTH($K$3),0,-K106,Q106),"N/A") -> N/A
A107: Churn-Failed Reactivation | B107: =IFERROR(B60/B10,"N/A") -> N/A | C107: =IFERROR(C60/C10,"N/A") -> N/A | D107: =IFERROR(D60/D10,"N/A") -> N/A | E107: =IFERROR(E60/E10,"N/A") -> N/A | F107: =IFERROR(F60/F10,"N/A") -> N/A | G107: =IFERROR(G60/G10,"N/A") -> 0 | H107: =IFERROR(H60/H10,"N/A") -> 0 | I107: =IFERROR(I60/I10,"N/A") -> N/A | J107: =AVERAGE(F107:I107) -> 0 | K107: =J107 -> 0 | L107: =K107 -> 0 | M107: =L107 -> 0 | N107: =M107 -> 0 | O107: =N107 -> 0 | P107: =O107 -> 0 | Q107: =P107 -> 0 | S107: =IFERROR(RATE(MONTH($Q$3)-MONTH($I$3),0,-I107,Q107),"N/A") -> N/A | T107: =IFERROR(RATE(MONTH($Q$3)-MONTH($K$3),0,-K107,Q107),"N/A") -> N/A
A108: Churn | B108: =IFERROR(B61/B12,"N/A") -> N/A | C108: =IFERROR(C61/C12,"N/A") -> 9804 | D108: =IFERROR(D61/D12,"N/A") -> 1728 | E108: =IFERROR(E61/E12,"N/A") -> 4904 | F108: =IFERROR(F61/F12,"N/A") -> N/A | G108: =IFERROR(G61/G12,"N/A") -> 1584 | H108: =IFERROR(H61/H12,"N/A") -> 1440 | I108: =IFERROR(I61/I12,"N/A") -> 13584 | J108: =AVERAGE(F108:I108) -> 5536 | K108: =J108 -> 5536 | L108: =K108 -> 5536 | M108: =L108 -> 5536 | N108: =M108 -> 5536 | O108: =N108 -> 5536 | P108: =O108 -> 5536 | Q108: =P108 -> 5536 | S108: =IFERROR(RATE(MONTH($Q$3)-MONTH($I$3),0,-I108,Q108),"N/A") -> -0.10613681 | T108: =IFERROR(RATE(MONTH($Q$3)-MONTH($K$3),0,-K108,Q108),"N/A") -> 8.2719165e-15
A109: Churn-Failed | B109: =IFERROR(B62/B13,"N/A") -> N/A | C109: =IFERROR(C62/C13,"N/A") -> N/A | D109: =IFERROR(D62/D13,"N/A") -> 1440 | E109: =IFERROR(E62/E13,"N/A") -> N/A | F109: =IFERROR(F62/F13,"N/A") -> 2460 | G109: =IFERROR(G62/G13,"N/A") -> 1440 | H109: =IFERROR(H62/H13,"N/A") -> 4353 | I109: =IFERROR(I62/I13,"N/A") -> 4666 | J109: =AVERAGE(F109:I109) -> 3229.75 | K109: =J109 -> 3229.75 | L109: =K109 -> 3229.75 | M109: =L109 -> 3229.75 | N109: =M109 -> 3229.75 | O109: =N109 -> 3229.75 | P109: =O109 -> 3229.75 | Q109: =P109 -> 3229.75 | S109: =IFERROR(RATE(MONTH($Q$3)-MONTH($I$3),0,-I109,Q109),"N/A") -> -0.044945794 | T109: =IFERROR(RATE(MONTH($Q$3)-MONTH($K$3),0,-K109,Q109),"N/A") -> 8.3235745e-15
A111: Average Per Customer (Ending ARR/Current # of Customers)
...

Sheet data set
A1: workspace_id | B1: time_period | C1: start_arr | D1: end_arr | E1: change_type | F1: change_arr
A2: TCQZ2hkxWF | B2: 42979 | C2: 0 | D2: 1200 | E2: New | F2: 1200
A3: M59ojynAVJ | B3: 42979 | C3: 0 | D3: 9804 | E3: New | F3: 9804
A4: M59ojynAVJ | B4: 43009 | C4: 9804 | D4: 0 | E4: Churn | F4: -9804
A5: TCQZ2hkxWF | B5: 43009 | C5: 1200 | D5: 1200 | E5: No Change | F5: 0
A6: SCuDSME3Ff | B6: 43009 | C6: 0 | D6: 1200 | E6: New | F6: 1200
A7: RuFrFxGNyy | B7: 43009 | C7: 0 | D7: 1200 | E7: New | F7: 1200
A8: cEbVUyf5cJ | B8: 43009 | C8: 0 | D8: 1200 | E8: New | F8: 1200
A9: Lxvv14xXR7 | B9: 43009 | C9: 0 | D9: 1440 | E9: New | F9: 1440
A10: L2Br1vbRYT | B10: 43009 | C10: 0 | D10: 1440 | E10: New | F10: 1440
A11: W0oPZYASZG | B11: 43009 | C11: 0 | D11: 1440 | E11: New | F11: 1440
A12: Ik1cIiOBXS | B12: 43009 | C12: 0 | D12: 1440 | E12: New | F12: 1440
A13: fgJgxNEqgy | B13: 43009 | C13: 0 | D13: 1440 | E13: New | F13: 1440
... A1565: 9xnuq0cy33 | B1565: 43191 | C1565: 0 | D1565: 13368 | E1565: New | F1565: 13368

Sheet Growth_Analysis
A1: Linear Equations | B1: Varible | C1: Constant
A2: MoM Customer Growth | B2: 48.3 | C2: 228.5
A3: New | B3: -1.8 | C3: 68.5
A4: Expansion | B4: 10.78 | C4: -6.2
A5: Contraction | B5: 5.6 | C5: 0.7333
B8: Historical | J8: Projected
B9: =Model!B3 -> 42979 | C9: =Model!C3 -> 43009 | D9: =Model!D3 -> 43040 | E9: =Model!E3 -> 43070 | F9: =Model!F3 -> 43101 | G9: =Model!G3 -> 43132 | H9: =Model!H3 -> 43160 | I9: =Model!I3 -> 43191 | ... Q9: =Model!Q3 -> 43435
B10: 0 | C10: 0 | D10: 1 | E10: 2 | F10: 3 | G10: 4 | H10: 5 | I10: 6 | J10: 7 | K10: 8 | L10: 9 | M10: 10 | N10: 11 | O10: 12 | P10: 13 | Q10: 14
A11: MoM Customer growth | B11: =Model!B15 -> 2 | C11: =Model!C15 -> 27 | D11: =Model!D15 -> 93 | E11: =Model!E15 -> 182 | F11: =Model!F15 -> 234 | G11: =Model!G15 -> 277 | H11: =Model!H15 -> 323 | I11: =Model!I15 -> 372 | J11: =ROUND($B2*J$10+$C2,0) -> 567 | K11: =ROUND($B2*K$10+$C2,0) -> 615 | L11: =ROUND($B2*L$10+$C2,0) -> 663 | M11: =ROUND($B2*M$10+$C2,0) -> 712 | N11: =ROUND($B2*N$10+$C2,0) -> 760 | O11: =ROUND($B2*O$10+$C2,0) -> 808 | P11: =ROUND($B2*P$10+$C2,0) -> 856 | Q11: =ROUND($B2*Q$10+$C2,0) -> 905 | R11: Formula
A12: New (# of New Customers/ Total # of Customers) | B12: =Model!B4 -> 2 | C12: =Model!C4 -> 26 | D12: =Model!D4 -> 62 | E12: =Model!E4 -> 85 | F12: =Model!F4 -> 51 | G12: =Model!G4 -> 50 | H12: =Model!H4 -> 61 | I12: =Model!I4 -> 64 | J12: =ROUND($B3*J$10+$C3,0) -> 56 | K12: =ROUND($B3*K$10+$C3,0) -> 54 | L12: =ROUND($B3*L$10+$C3,0) -> 52 | M12: =ROUND($B3*M$10+$C3,0) -> 51 | N12: =ROUND($B3*N$10+$C3,0) -> 49 | O12: =ROUND($B3*O$10+$C3,0) -> 47 | P12: =ROUND($B3*P$10+$C3,0) -> 45 | Q12: =ROUND($B3*Q$10+$C3,0) -> 43 | R12: Constant
A13: Legacy to New Team | B13: =Model!B5 -> 0 | C13: =Model!C5 -> 1 | D13: =Model!D5 -> 4 | E13: =Model!E5 -> 4 | F13: =Model!F5 -> 5 | G13: =Model!G5 -> 2 | H13: =Model!H5 -> 1 | I13: =Model!I5 -> 0 | R13: Input Assumption
A14: Customers that remained same | B14: =Model!B6 -> 0 | C14: =Model!C6 -> 1 | D14: =Model!D6 -> 22 | E14: =Model!E6 -> 67 | F14: =Model!F6 -> 131 | G14: =Model!G6 -> 169 | H14: =Model!H6 -> 190 | I14: =Model!I6 -> 223 | R14: Formula
A15: Customers that Expand | B15: =Model!B7 -> 0 | C15: =Model!C7 -> 0 | D15: =Model!D7 -> 5 | E15: =Model!E7 -> 14 | F15: =Model!F7 -> 24 | G15: =Model!G7 -> 44 | H15: =Model!H7 -> 41 | I15: =Model!I7 -> 60 | J15: =ROUND($B4*J$10+$C4,0) -> 69 | K15: =ROUND($B4*K$10+$C4,0) -> 80 | L15: =ROUND($B4*L$10+$C4,0) -> 91 | M15: =ROUND($B4*M$10+$C4,0) -> 102 | N15: =ROUND($B4*N$10+$C4,0) -> 112 | O15: =ROUND($B4*O$10+$C4,0) -> 123 | P15: =ROUND($B4*P$10+$C4,0) -> 134 | Q15: =ROUND($B4*Q$10+$C4,0) -> 145 | R15: Linear Equation
A16: Customers that Contracted | B16: =Model!B8 -> 0 | C16: =Model!C8 -> 0 | D16: =Model!D8 -> 2 | E16: =Model!E8 -> 14 | F16: =Model!F8 -> 26 | G16: =Model!G8 -> 14 | H16: =Model!H8 -> 34 | I16: =Model!I8 -> 31 | J16: =ROUND($B5*J$10+$C5,0) -> 40 | K16: =ROUND($B5*K$10+$C5,0) -> 46 | L16: =ROUND($B5*L$10+$C5,0) -> 51 | M16: =ROUND($B5*M$10+$C5,0) -> 57 | N16: =ROUND($B5*N$10+$C5,0) -> 62 | O16: =ROUND($B5*O$10+$C5,0) -> 68 | P16: =ROUND($B5*P$10+$C5,0) -> 74 | Q16: =ROUND($B5*Q$10+$C5,0) -> 79 | R16: Linear Equation
A17: Old Team to New Team | B17: =Model!B9 -> 0 | C17: =Model!C9 -> 0 | D17: =Model!D9 -> 0 | E17: =Model!E9 -> 1 | F17: =Model!F9 -> 0 | G17: =Model!G9 -> 3 | H17: =Model!H9 -> 0 | I17: =Model!I9 -> 1 | R17: Input Assumption
A18: Failed Churn - Reactivition | B18: =Model!B10 -> 0 | C18: =Model!C10 -> 0 | D18: =Model!D10 -> 0 | E18: =Model!E10 -> 0 | F18: =Model!F10 -> 0 | G18: =Model!G10 -> 1 | H18: =Model!H10 -> 1 | I18: =Model!I10 -> 0 | R18: Input Assumption
A19: Churn | B19: =Model!B12 -> 0 | C19: =Model!C12 -> 1 | D19: =Model!D12 -> 1 | E19: =Model!E12 -> 3 | F19: =Model!F12 -> 0 | G19: =Model!G12 -> 3 | H19: =Model!H12 -> 1 | I19: =Model!I12 -> 1 | R19: Input Assumption
A20: Churn -Failed | B20: =Model!B13 -> 0 | C20: =Model!C13 -> 0 | D20: =Model!D13 -> 1 | E20: =Model!E13 -> 0 | F20: =Model!F13 -> 3 | G20: =Model!G13 -> 3 | H20: =Model!H13 -> 4 | I20: =Model!I13 -> 6 | R20: Input Assumption
A21: Churn | B21: =Model!B14 -> 0 | C21: =Model!C14 -> 1 | D21: =Model!D14 -> 2 | E21: =Model!E14 -> 3 | F21: =Model!F14 -> 3 | G21: =Model!G14 -> 6 | H21: =Model!H14 -> 5 | I21: =Model!I14 -> 7 | R21: Formula
A23: Linear Regression Analysis

Sheet Notes
A1: Legacy to New Team
A2: What's the difference between Churn, Churn - Failed, Churn - Reactiviation
A3: Old Team to New Team
A5: Churn means no longer a customer
A6: Churn Failed Reactivation is after Churn Failed - Still a customer
A7: Churn Failed is the same as churn
A8: Is there dropped data?
A9: Are there outliers?
A11: Questions
A12: 39NTHthWY3 is this an outlier?
A13: What do you mean by Net Expansion, is that overall ARR growth, or ARR growth due to expansion?
A15: Methodology 1
... A30: Removed client ID# 39NTHthWY3
